Workbook

Sheet Léame
A1: ROLES GOURMET · Calculadora de Costos, Merma y Precios
A2: Endulcora · Estudio Gastronómico — herramienta complementaria del eBook «Roles Gourmet: El Arte de la Masa Enriquecida»
B4: CÓMO USAR ESTE ARCHIVO
B5: Orden de trabajo | C5: 1) Actualiza precios en «1. Insumos» → 2) Revisa las cuatro masas en «2. Masas Base» → 3) Revisa «4. Costeo y Precios» → 4) Registra cada horneada en «5. Producción y Merma» → 5) Registra cada venta en «6. Ventas» → 6) Lee resultados en «8. Tablero».
B6: 1. Insumos | C6: Catálogo con los 133 insumos que aparecen en las 51 recetas y las 4 masas del libro. Escribe la presentación que compras y su precio; el costo por gramo, mililitro o pieza se calcula solo. Los precios vienen precargados como REFERENCIA (CDMX 2026) y debes reemplazarlos por los tuyos.
B7: 2. Masas Base | C7: Las cuatro fórmulas madre: 00A Masa Maestra Universal, 00B Masa Negra de Cacao, 00C Masa Salada y Umami, 00D Masa Madre. Cada lote rinde 12 roles. Aquí se calcula el costo de la masa, que después se suma a cada receta. Es la particularidad de este negocio: el rol se cotiza en dos capas, masa y relleno.
B8: 3. Rellenos y Cubiertas | C8: Las 341 líneas de relleno, glaseado y decoración de las 51 recetas, con su costo por lote.
B9: 4. Costeo y Precios | C9: El corazón del archivo. Suma masa + relleno, lo divide entre 12 roles, agrega empaque, energía, mano de obra y overhead, aplica la merma y calcula el precio sugerido para los cuatro canales del libro. Edita solo las columnas azules.
B10: 5. Producción y Merma | C10: Bitácora de cada horneada: roles buenos, roles fallidos, causa y costo real de lo perdido. En masa enriquecida y fermentada la merma se concentra en la fermentación y el armado.
B11: 6. Ventas | C11: Bitácora de ventas por pieza y canal, con comisiones de plataforma y utilidad neta automática.
B12: 7. Gastos Fijos | C12: Renta, servicios, publicidad y tu sueldo. De aquí salen el overhead por rol, el costo por hora y el punto de equilibrio.
B13: 8. Tablero | C13: Resumen del mes que elijas: ingresos, utilidad, margen, merma, ranking de recetas y avance hacia el punto de equilibrio.
B15: CÓDIGO DE COLORES
B16: Texto azul sobre fondo crema | C16: Celda que TÚ editas (dato de entrada). Es lo único que debes escribir.
B17: Texto azul sobre fondo amarillo | C17: Parámetro global o de mes. Cámbialo y todo el archivo se recalcula.
B18: Texto negro | C18: Resultado calculado por fórmula. No lo escribas a mano.
B19: Texto verde | C19: Resultado que viene de otra hoja del mismo archivo.
B20: Fondo crema claro | C20: Resultado destacado: costo unitario, precios sugeridos y KPI del tablero.
B22: LA LÓGICA DE COSTEO DE UN ROL
B23: Dos capas | C23: A diferencia de un pastel, un rol se costea en dos capas: (1) el lote de masa base, que rinde 12 roles y cuesta lo mismo para muchas recetas, y (2) el relleno y la cubierta, que es lo que cambia y lo que dispara el precio. Un Rol de Canela y un Rol Volcán de Pistache comparten exactamente la misma masa; lo que los separa es el relleno.
B25: AVISO IMPORTANTE
B26: Los precios precargados son de REFERENCIA (Ciudad de México, 2026). Cotiza con tus proveedores y sustitúyelos antes de fijar cualquier precio de venta.
B27: Seis recetas del Capítulo 9 son saladas (ajo y parmesano, pesto, queso azul, trufa, tocino y maple, stout y cheddar). Llevan queso, hongos o cárnicos y tienen vida útil más corta y requisitos de refrigeración distintos: revísalos en el capítulo de conservación del eBook antes de venderlos.
B28: Este archivo es una herramienta de costeo. Verifica los requisitos sanitarios y fiscales vigentes en tu localidad antes de comercializar.
B30: Endulcora · Estudio Gastronómico · Contacto e inscripciones a talleres: 5665271901

Sheet 1. Insumos
A1: 1 · CATÁLOGO DE INSUMOS
A2: Escribe la presentación que compras y su precio. El costo por unidad se recalcula solo y actualiza masas y recetas.
A4: Categoría | B4: Insumo | C4: Unidad base | D4: Cantidad de la presentación | E4: Precio de compra (MXN) | F4: Costo por unidad (MXN) | G4: Proveedor | H4: Última actualización | I4: Notas
A5: Harinas y secos | B5: Harina de fuerza (alto gluten) | C5: g | D5: 1000 | E5: 32 | F5: =IFERROR(E5/D5,0) -> 0.032 | I5: Precio de referencia — actualízalo
A6: Harinas y secos | B6: Harina de trigo todo uso | C6: g | D6: 1000 | E6: 26 | F6: =IFERROR(E6/D6,0) -> 0.026
A7: Harinas y secos | B7: Harina de almendra | C7: g | D7: 1000 | E7: 420 | F7: =IFERROR(E7/D7,0) -> 0.42
A8: Harinas y secos | B8: Fécula de maíz | C8: g | D8: 500 | E8: 32 | F8: =IFERROR(E8/D8,0) -> 0.064
A9: Harinas y secos | B9: Masa madre activa (cultivo propio) | C9: g | D9: 1000 | E9: 45 | F9: =IFERROR(E9/D9,0) -> 0.045
A10: Harinas y secos | B10: Galleta María o Graham | C10: g | D10: 500 | E10: 58 | F10: =IFERROR(E10/D10,0) -> 0.116
A11: Harinas y secos | B11: Galleta Lotus Biscoff | C11: g | D11: 250 | E11: 95 | F11: =IFERROR(E11/D11,0) -> 0.38
A12: Harinas y secos | B12: Galleta de barquillo | C12: g | D12: 250 | E12: 75 | F12: =IFERROR(E12/D12,0) -> 0.3
A13: Azúcares | B13: Azúcar refinada | C13: g | D13: 1000 | E13: 32 | F13: =IFERROR(E13/D13,0) -> 0.032
A14: Azúcares | B14: Azúcar glass | C14: g | D14: 1000 | E14: 45 | F14: =IFERROR(E14/D14,0) -> 0.045
A15: Azúcares | B15: Azúcar mascabado | C15: g | D15: 1000 | E15: 52 | F15: =IFERROR(E15/D15,0) -> 0.052
A16: Azúcares | B16: Piloncillo | C16: g | D16: 1000 | E16: 48 | F16: =IFERROR(E16/D16,0) -> 0.048
A17: Azúcares | B17: Miel de abeja | C17: g | D17: 500 | E17: 110 | F17: =IFERROR(E17/D17,0) -> 0.22
... A137: Aromáticos | B137: Pasta de miso blanco | C137: g | D137: 250 | E137: 190 | F137: =IFERROR(E137/D137,0) -> 0.76
A139: Fuente: promedio de mayoristas, tiendas de insumos de repostería y tiendas en línea de la Ciudad de México (referencia 2026, IVA incluido). Punto de partida, no cotización.

Sheet 2. Masas Base
A1: 2 · LAS CUATRO MASAS BASE
A2: Cada lote rinde 12 roles. El costo de la masa se suma automáticamente a cada receta de la hoja 4.
A4: Fórmula | B4: Masa | C4: Insumo | D4: Cantidad | E4: Unidad | F4: Costo por unidad (MXN) | G4: Costo del ingrediente (MXN) | H4: Descripción original del libro
A5: 00A | B5: Masa Maestra Universal (Estilo Brioche Ligero) | C5: Harina de fuerza (alto gluten) | D5: 500 | E5: g | F5: =IFERROR(INDEX('1. Insumos'!$F$5:$F$137,MATCH($C5,'1. Insumos'!$B$5:$B$137,0)),0) -> 0.032 | G5: =D5*F5 -> 16 | H5: 500 g Harina de fuerza (mínimo 12% a 14% de proteína)
A6: 00A | B6: Masa Maestra Universal (Estilo Brioche Ligero) | C6: Azúcar refinada | D6: 80 | E6: g | F6: =IFERROR(INDEX('1. Insumos'!$F$5:$F$137,MATCH($C6,'1. Insumos'!$B$5:$B$137,0)),0) -> 0.032 | G6: =D6*F6 -> 2.56 | H6: 80 g Azúcar refinada
A7: 00A | B7: Masa Maestra Universal (Estilo Brioche Ligero) | C7: Sal fina | D7: 10 | E7: g | F7: =IFERROR(INDEX('1. Insumos'!$F$5:$F$137,MATCH($C7,'1. Insumos'!$B$5:$B$137,0)),0) -> 0.022 | G7: =D7*F7 -> 0.22 | H7: 10 g Sal fina
A8: 00A | B8: Masa Maestra Universal (Estilo Brioche Ligero) | C8: Levadura seca instantánea | D8: 15 | E8: g | F8: =IFERROR(INDEX('1. Insumos'!$F$5:$F$137,MATCH($C8,'1. Insumos'!$B$5:$B$137,0)),0) -> 0.3 | G8: =D8*F8 -> 4.5 | H8: 15 g Levadura seca instantánea (o 45 g de levadura fresca)
A9: 00A | B9: Masa Maestra Universal (Estilo Brioche Ligero) | C9: Leche entera | D9: 200 | E9: ml | F9: =IFERROR(INDEX('1. Insumos'!$F$5:$F$137,MATCH($C9,'1. Insumos'!$B$5:$B$137,0)),0) -> 0.028 | G9: =D9*F9 -> 5.6 | H9: 200 ml Leche entera (tibia, a no más de 35 °C)
A10: 00A | B10: Masa Maestra Universal (Estilo Brioche Ligero) | C10: Huevo entero | D10: 2 | E10: pza | F10: =IFERROR(INDEX('1. Insumos'!$F$5:$F$137,MATCH($C10,'1. Insumos'!$B$5:$B$137,0)),0) -> 3.5 | G10: =D10*F10 -> 7 | H10: 2 pzas Huevo entero (a temperatura ambiente, aprox. 100 g)
A11: 00A | B11: Masa Maestra Universal (Estilo Brioche Ligero) | C11: Mantequilla sin sal | D11: 120 | E11: g | F11: =IFERROR(INDEX('1. Insumos'!$F$5:$F$137,MATCH($C11,'1. Insumos'!$B$5:$B$137,0)),0) -> 0.26 | G11: =D11*F11 -> 31.2 | H11: 120 g Mantequilla sin sal (fría, cortada en cubos pequeños)
A12: 00A | B12: Masa Maestra Universal (Estilo Brioche Ligero) | C12: Extracto de vainilla de Papantla | D12: 5 | E12: ml | F12: =IFERROR(INDEX('1. Insumos'!$F$5:$F$137,MATCH($C12,'1. Insumos'!$B$5:$B$137,0)),0) -> 1.28 | G12: =D12*F12 -> 6.4 | H12: 5 ml Extracto puro de vainilla
A13: 00D | B13: Variación Técnica: Masa Madre y Fermentación Salvaje | C13: Harina de fuerza (alto gluten) | D13: 450 | E13: g | F13: =IFERROR(INDEX('1. Insumos'!$F$5:$F$137,MATCH($C13,'1. Insumos'!$B$5:$B$137,0)),0) -> 0.032 | G13: =D13*F13 -> 14.4 | H13: 450 g Harina de fuerza
A14: 00D | B14: Variación Técnica: Masa Madre y Fermentación Salvaje | C14: Masa madre activa (cultivo propio) | D14: 150 | E14: g | F14: =IFERROR(INDEX('1. Insumos'!$F$5:$F$137,MATCH($C14,'1. Insumos'!$B$5:$B$137,0)),0) -> 0.045 | G14: =D14*F14 -> 6.75 | H14: 150 g Masa Madre activa (alimentada 4 horas antes, al 100% de hidratación)
A15: 00D | B15: Variación Técnica: Masa Madre y Fermentación Salvaje | C15: Azúcar refinada | D15: 60 | E15: g | F15: =IFERROR(INDEX('1. Insumos'!$F$5:$F$137,MATCH($C15,'1. Insumos'!$B$5:$B$137,0)),0) -> 0.032 | G15: =D15*F15 -> 1.92 | H15: 60 g Azúcar refinada
A16: 00D | B16: Variación Técnica: Masa Madre y Fermentación Salvaje | C16: Sal fina | D16: 10 | E16: g | F16: =IFERROR(INDEX('1. Insumos'!$F$5:$F$137,MATCH($C16,'1. Insumos'!$B$5:$B$137,0)),0) -> 0.022 | G16: =D16*F16 -> 0.22 | H16: 10 g Sal fina
... A51: 00C | B51: Variación Técnica: Masa Salada y Umami | C51: Mantequilla sin sal | D51: 120 | E51: g | F51: =IFERROR(INDEX('1. Insumos'!$F$5:$F$137,MATCH($C51,'1. Insumos'!$B$5:$B$137,0)),0) -> 0.26 | G51: =D51*F51 -> 31.2 | H51: 120 g Mantequilla sin sal (fría, cortada en cubos pequeños)
B53: COSTO POR LOTE DE MASA (12 roles)
B54: Fórmula | C54: Masa | D54: Costo del lote | E54: Costo por rol
B55: 00A | C55: Masa Maestra Universal (Estilo Brioche Ligero) | D55: =SUMIFS($G$5:$G$51,$A$5:$A$51,$B55) -> 73.48 | E55: =D55/12 -> 6.1233333
B56: 00B | C56: Variación Técnica: Masa Negra de Cacao Alcalino | D56: =SUMIFS($G$5:$G$51,$A$5:$A$51,$B56) -> 175.16 | E56: =D56/12 -> 14.596667
B57: 00C | C57: Variación Técnica: Masa Salada y Umami | D57: =SUMIFS($G$5:$G$51,$A$5:$A$51,$B57) -> 130.816 | E57: =D57/12 -> 10.901333
B58: 00D | C58: Variación Técnica: Masa Madre y Fermentación Salvaje | D58: =SUMIFS($G$5:$G$51,$A$5:$A$51,$B58) -> 65.97 | E58: =D58/12 -> 5.4975
B60: Las masas 00B y 00C son ajustes sobre la 00A descritos en el libro; aquí se desglosan completas para poder costearlas. La 00D lleva masa madre y cero levadura comercial.

Sheet 3. Rellenos y Cubiertas
A1: 3 · RELLENOS, GLASEADOS Y CUBIERTAS POR RECETA
A2: Todo lo que va sobre la masa. Ajusta la columna «Cantidad» solo si modificas la receta original.
A4: Nº | B4: Receta | C4: Insumo | D4: Cantidad | E4: Unidad | F4: Costo por unidad (MXN) | G4: Costo del ingrediente (MXN) | H4: Componente de la receta | I4: Descripción original del libro
A5: 1 | B5: Rol de Canela Clásico con Glaseado de Vainilla de Papantla | C5: Mantequilla sin sal | D5: 120 | E5: g | F5: =IFERROR(INDEX('1. Insumos'!$F$5:$F$137,MATCH($C5,'1. Insumos'!$B$5:$B$137,0)),0) -> 0.26 | G5: =D5*F5 -> 31.2 | H5: Para el Relleno de Canela | I5: 120 g Mantequilla sin sal (textura pomada, muy suave pero no derretida)
A6: 1 | B6: Rol de Canela Clásico con Glaseado de Vainilla de Papantla | C6: Azúcar mascabado | D6: 180 | E6: g | F6: =IFERROR(INDEX('1. Insumos'!$F$5:$F$137,MATCH($C6,'1. Insumos'!$B$5:$B$137,0)),0) -> 0.052 | G6: =D6*F6 -> 9.36 | H6: Para el Relleno de Canela | I6: 180 g Azúcar mascabado o morena (aporta humedad)
A7: 1 | B7: Rol de Canela Clásico con Glaseado de Vainilla de Papantla | C7: Canela en polvo (Ceilán) | D7: 25 | E7: g | F7: =IFERROR(INDEX('1. Insumos'!$F$5:$F$137,MATCH($C7,'1. Insumos'!$B$5:$B$137,0)),0) -> 0.72 | G7: =D7*F7 -> 18 | H7: Para el Relleno de Canela | I7: 25 g Canela en polvo (preferentemente variedad Ceilán)
A8: 1 | B8: Rol de Canela Clásico con Glaseado de Vainilla de Papantla | C8: Sal fina | D8: 2 | E8: g | F8: =IFERROR(INDEX('1. Insumos'!$F$5:$F$137,MATCH($C8,'1. Insumos'!$B$5:$B$137,0)),0) -> 0.022 | G8: =D8*F8 -> 0.044 | H8: Para el Relleno de Canela | I8: 2 g Sal fina
A9: 1 | B9: Rol de Canela Clásico con Glaseado de Vainilla de Papantla | C9: Queso crema original | D9: 150 | E9: g | F9: =IFERROR(INDEX('1. Insumos'!$F$5:$F$137,MATCH($C9,'1. Insumos'!$B$5:$B$137,0)),0) -> 0.19 | G9: =D9*F9 -> 28.5 | H9: Para el Glaseado de Vainilla de Papantla | I9: 150 g Queso crema original (a temperatura ambiente)
A10: 1 | B10: Rol de Canela Clásico con Glaseado de Vainilla de Papantla | C10: Mantequilla sin sal | D10: 60 | E10: g | F10: =IFERROR(INDEX('1. Insumos'!$F$5:$F$137,MATCH($C10,'1. Insumos'!$B$5:$B$137,0)),0) -> 0.26 | G10: =D10*F10 -> 15.6 | H10: Para el Glaseado de Vainilla de Papantla | I10: 60 g Mantequilla sin sal (pomada)
A11: 1 | B11: Rol de Canela Clásico con Glaseado de Vainilla de Papantla | C11: Azúcar glass | D11: 120 | E11: g | F11: =IFERROR(INDEX('1. Insumos'!$F$5:$F$137,MATCH($C11,'1. Insumos'!$B$5:$B$137,0)),0) -> 0.045 | G11: =D11*F11 -> 5.4 | H11: Para el Glaseado de Vainilla de Papantla | I11: 120 g Azúcar glass (cernida)
A12: 1 | B12: Rol de Canela Clásico con Glaseado de Vainilla de Papantla | C12: Extracto de vainilla de Papantla | D12: 10 | E12: ml | F12: =IFERROR(INDEX('1. Insumos'!$F$5:$F$137,MATCH($C12,'1. Insumos'!$B$5:$B$137,0)),0) -> 1.28 | G12: =D12*F12 -> 12.8 | H12: Para el Glaseado de Vainilla de Papantla | I12: 10 ml Extracto puro de vainilla de Papantla
A13: 1 | B13: Rol de Canela Clásico con Glaseado de Vainilla de Papantla | C13: Crema para batir (Nata 35% M.G.) | D13: 15 | E13: ml | F13: =IFERROR(INDEX('1. Insumos'!$F$5:$F$137,MATCH($C13,'1. Insumos'!$B$5:$B$137,0)),0) -> 0.13 | G13: =D13*F13 -> 1.95 | H13: Para el Glaseado de Vainilla de Papantla | I13: 15 ml Crema para batir o leche entera (solo para ajustar textura)
A14: 2 | B14: Rol de Doble Chocolate y Cocoa Alcalina | C14: Mantequilla sin sal | D14: 100 | E14: g | F14: =IFERROR(INDEX('1. Insumos'!$F$5:$F$137,MATCH($C14,'1. Insumos'!$B$5:$B$137,0)),0) -> 0.26 | G14: =D14*F14 -> 26 | H14: Para el Relleno de Doble Chocolate | I14: 100 g Mantequilla sin sal (pomada)
A15: 2 | B15: Rol de Doble Chocolate y Cocoa Alcalina | C15: Azúcar refinada | D15: 120 | E15: g | F15: =IFERROR(INDEX('1. Insumos'!$F$5:$F$137,MATCH($C15,'1. Insumos'!$B$5:$B$137,0)),0) -> 0.032 | G15: =D15*F15 -> 3.84 | H15: Para el Relleno de Doble Chocolate | I15: 120 g Azúcar refinada
A16: 2 | B16: Rol de Doble Chocolate y Cocoa Alcalina | C16: Cocoa alcalina en polvo | D16: 40 | E16: g | F16: =IFERROR(INDEX('1. Insumos'!$F$5:$F$137,MATCH($C16,'1. Insumos'!$B$5:$B$137,0)),0) -> 0.29 | G16: =D16*F16 -> 11.6 | H16: Para el Relleno de Doble Chocolate | I16: 40 g Cocoa alcalina en polvo (procesada en holandés)
... A345: 51 | B345: Rol de Earl Grey y Lavanda | C345: Limón amarillo | D345: 1 | E345: pza | F345: =IFERROR(INDEX('1. Insumos'!$F$5:$F$137,MATCH($C345,'1. Insumos'!$B$5:$B$137,0)),0) -> 6 | G345: =D345*F345 -> 6 | H345: Para el Glaseado de Bergamota o Limón | I345: Zumo de medio limón o esencia de bergamota

Sheet 4. Costeo y Precios
A1: 4 · COSTEO Y PRECIO DE VENTA POR ROL
A2: Edita solo las columnas azules: roles por lote, empaque, energía, minutos y % de merma. Todo lo demás se calcula.
A4: PARÁMETROS GLOBALES · márgenes recomendados por canal (Cap. 11 del eBook)
A5: Margen objetivo — Mostrador / pieza individual | C5: 0.6 | D5: Rango del libro: 55 % – 70 %
A6: Margen objetivo — Caja o charola de regalo | C6: 0.65 | D6: Rango del libro: 60 % – 75 %
A7: Margen objetivo — Cafetería y restaurante | C7: 0.5 | D7: Rango del libro: 45 % – 60 %
A8: Margen objetivo — Mayoreo / suscripción | C8: 0.4 | D8: Rango del libro: 35 % – 50 %
A9: Costo de mano de obra por hora (viene de Gastos Fijos) | C9: ='7. Gastos Fijos'!$C$24 -> 75
A10: Overhead por rol (viene de Gastos Fijos) | C10: ='7. Gastos Fijos'!$C$19 -> 10.611111
A11: % de merma por defecto | C11: 0.12 | D11: Principiante 15–25 % · Intermedio 8–15 % · Avanzado 3–8 %
A13: Nº | B13: Receta | C13: Masa | D13: Roles por lote | E13: Costo de la masa (lote) | F13: Costo del relleno (lote) | G13: Costo de insumos (lote) | H13: Insumos por rol | I13: Empaque | J13: Energía y consumibles | K13: Minutos por rol | L13: Mano de obra | M13: Overhead | N13: COSTO BASE | O13: % Merma | P13: COSTO TOTAL UNITARIO | Q13: PVP Mostrador | R13: Utilidad Mostrador | S13: PVP Caja regalo | T13: Utilidad Caja | U13: PVP Cafetería | V13: Utilidad Cafetería | W13: PVP Mayoreo | X13: Utilidad Mayoreo | Y13: Margen real Mostrador | Z13: Nivel y perfil
A14: 1 | B14: Rol de Canela Clásico con Glaseado de Vainilla de Papantla | C14: 00A | D14: 12 | E14: =IFERROR(INDEX('2. Masas Base'!$D$55:$D$58,MATCH($C14,'2. Masas Base'!$B$55:$B$58,0)),0) -> 73.48 | F14: =SUMIFS('3. Rellenos y Cubiertas'!$G$5:$G$345,'3. Rellenos y Cubiertas'!$A$5:$A$345,$A14) -> 122.854 | G14: =E14+F14 -> 196.334 | H14: =IFERROR(G14/D14,0) -> 16.361167 | I14: 9 | J14: 3 | K14: 5 | L14: =$C$9*K14/60 -> 6.25 | M14: =$C$10 -> 10.611111 | N14: =H14+I14+J14+L14+M14 -> 45.222278 | O14: =$C$11 -> 0.12 | P14: =IFERROR(N14/(1-O14),0) -> 51.388952 | Q14: =IFERROR(CEILING(P14/(1-$C$5),5),0) -> 130 | R14: =Q14-P14 -> 78.611048 | S14: =IFERROR(CEILING(P14/(1-$C$6),5),0) -> 150 | T14: =S14-P14 -> 98.611048 | U14: =IFERROR(CEILING(P14/(1-$C$7),5),0) -> 105 | V14: =U14-P14 -> 53.611048 | W14: =IFERROR(CEILING(P14/(1-$C$8),5),0) -> 90 | X14: =W14-P14 -> 38.611048 | Y14: =IFERROR(R14/Q14,0) -> 0.60470037 | Z14: Fácil · Dulce
A15: 2 | B15: Rol de Doble Chocolate y Cocoa Alcalina | C15: 00B | D15: 12 | E15: =IFERROR(INDEX('2. Masas Base'!$D$55:$D$58,MATCH($C15,'2. Masas Base'!$B$55:$B$58,0)),0) -> 175.16 | F15: =SUMIFS('3. Rellenos y Cubiertas'!$G$5:$G$345,'3. Rellenos y Cubiertas'!$A$5:$A$345,$A15) -> 156.34 | G15: =E15+F15 -> 331.5 | H15: =IFERROR(G15/D15,0) -> 27.625 | I15: 11 | J15: 4 | K15: 7 | L15: =$C$9*K15/60 -> 8.75 | M15: =$C$10 -> 10.611111 | N15: =H15+I15+J15+L15+M15 -> 61.986111 | O15: =$C$11 -> 0.12 | P15: =IFERROR(N15/(1-O15),0) -> 70.438763 | Q15: =IFERROR(CEILING(P15/(1-$C$5),5),0) -> 180 | R15: =Q15-P15 -> 109.56124 | S15: =IFERROR(CEILING(P15/(1-$C$6),5),0) -> 205 | T15: =S15-P15 -> 134.56124 | U15: =IFERROR(CEILING(P15/(1-$C$7),5),0) -> 145 | V15: =U15-P15 -> 74.561237 | W15: =IFERROR(CEILING(P15/(1-$C$8),5),0) -> 120 | X15: =W15-P15 -> 49.561237 | Y15: =IFERROR(R15/Q15,0) -> 0.60867354 | Z15: Intermedio · Dulce
A16: 3 | B16: Rol de Nuez Pecana y Caramelo Salado | C16: 00A | D16: 12 | E16: =IFERROR(INDEX('2. Masas Base'!$D$55:$D$58,MATCH($C16,'2. Masas Base'!$B$55:$B$58,0)),0) -> 73.48 | F16: =SUMIFS('3. Rellenos y Cubiertas'!$G$5:$G$345,'3. Rellenos y Cubiertas'!$A$5:$A$345,$A16) -> 153.6 | G16: =E16+F16 -> 227.08 | H16: =IFERROR(G16/D16,0) -> 18.923333 | I16: 11 | J16: 4 | K16: 7 | L16: =$C$9*K16/60 -> 8.75 | M16: =$C$10 -> 10.611111 | N16: =H16+I16+J16+L16+M16 -> 53.284444 | O16: =$C$11 -> 0.12 | P16: =IFERROR(N16/(1-O16),0) -> 60.550505 | Q16: =IFERROR(CEILING(P16/(1-$C$5),5),0) -> 155 | R16: =Q16-P16 -> 94.449495 | S16: =IFERROR(CEILING(P16/(1-$C$6),5),0) -> 175 | T16: =S16-P16 -> 114.44949 | U16: =IFERROR(CEILING(P16/(1-$C$7),5),0) -> 125 | V16: =U16-P16 -> 64.449495 | W16: =IFERROR(CEILING(P16/(1-$C$8),5),0) -> 105 | X16: =W16-P16 -> 44.449495 | Y16: =IFERROR(R16/Q16,0) -> 0.60935158 | Z16: Intermedio · Dulce
A17: 4 | B17: Rol de Manzana Canela y Streusel Crujiente | C17: 00A | D17: 12 | E17: =IFERROR(INDEX('2. Masas Base'!$D$55:$D$58,MATCH($C17,'2. Masas Base'!$B$55:$B$58,0)),0) -> 73.48 | F17: =SUMIFS('3. Rellenos y Cubiertas'!$G$5:$G$345,'3. Rellenos y Cubiertas'!$A$5:$A$345,$A17) -> 59.16 | G17: =E17+F17 -> 132.64 | H17: =IFERROR(G17/D17,0) -> 11.053333 | I17: 11 | J17: 4 | K17: 7 | L17: =$C$9*K17/60 -> 8.75 | M17: =$C$10 -> 10.611111 | N17: =H17+I17+J17+L17+M17 -> 45.414444 | O17: =$C$11 -> 0.12 | P17: =IFERROR(N17/(1-O17),0) -> 51.607323 | Q17: =IFERROR(CEILING(P17/(1-$C$5),5),0) -> 130 | R17: =Q17-P17 -> 78.392677 | S17: =IFERROR(CEILING(P17/(1-$C$6),5),0) -> 150 | T17: =S17-P17 -> 98.392677 | U17: =IFERROR(CEILING(P17/(1-$C$7),5),0) -> 105 | V17: =U17-P17 -> 53.392677 | W17: =IFERROR(CEILING(P17/(1-$C$8),5),0) -> 90 | X17: =W17-P17 -> 38.392677 | Y17: =IFERROR(R17/Q17,0) -> 0.60302059 | Z17: Intermedio · Dulce
A18: 5 | B18: Rol de Frutos Rojos y Queso Crema | C18: 00A | D18: 12 | E18: =IFERROR(INDEX('2. Masas Base'!$D$55:$D$58,MATCH($C18,'2. Masas Base'!$B$55:$B$58,0)),0) -> 73.48 | F18: =SUMIFS('3. Rellenos y Cubiertas'!$G$5:$G$345,'3. Rellenos y Cubiertas'!$A$5:$A$345,$A18) -> 324.42 | G18: =E18+F18 -> 397.9 | H18: =IFERROR(G18/D18,0) -> 33.158333 | I18: 11 | J18: 4 | K18: 7 | L18: =$C$9*K18/60 -> 8.75 | M18: =$C$10 -> 10.611111 | N18: =H18+I18+J18+L18+M18 -> 67.519444 | O18: =$C$11 -> 0.12 | P18: =IFERROR(N18/(1-O18),0) -> 76.726641 | Q18: =IFERROR(CEILING(P18/(1-$C$5),5),0) -> 195 | R18: =Q18-P18 -> 118.27336 | S18: =IFERROR(CEILING(P18/(1-$C$6),5),0) -> 220 | T18: =S18-P18 -> 143.27336 | U18: =IFERROR(CEILING(P18/(1-$C$7),5),0) -> 155 | V18: =U18-P18 -> 78.273359 | W18: =IFERROR(CEILING(P18/(1-$C$8),5),0) -> 130 | X18: =W18-P18 -> 53.273359 | Y18: =IFERROR(R18/Q18,0) -> 0.60653004 | Z18: Intermedio · Dulce
A19: 6 | B19: Rol de Almendra y Frangipane Clásico | C19: 00A | D19: 12 | E19: =IFERROR(INDEX('2. Masas Base'!$D$55:$D$58,MATCH($C19,'2. Masas Base'!$B$55:$B$58,0)),0) -> 73.48 | F19: =SUMIFS('3. Rellenos y Cubiertas'!$G$5:$G$345,'3. Rellenos y Cubiertas'!$A$5:$A$345,$A19) -> 126.01292 | G19: =E19+F19 -> 199.49292 | H19: =IFERROR(G19/D19,0) -> 16.62441 | I19: 11 | J19: 4 | K19: 7 | L19: =$C$9*K19/60 -> 8.75 | M19: =$C$10 -> 10.611111 | N19: =H19+I19+J19+L19+M19 -> 50.985521 | O19: =$C$11 -> 0.12 | P19: =IFERROR(N19/(1-O19),0) -> 57.938092 | Q19: =IFERROR(CEILING(P19/(1-$C$5),5),0) -> 145 | R19: =Q19-P19 -> 87.061908 | S19: =IFERROR(CEILING(P19/(1-$C$6),5),0) -> 170 | T19: =S19-P19 -> 112.06191 | U19: =IFERROR(CEILING(P19/(1-$C$7),5),0) -> 120 | V19: =U19-P19 -> 62.061908 | W19: =IFERROR(CEILING(P19/(1-$C$8),5),0) -> 100 | X19: =W19-P19 -> 42.061908 | Y19: =IFERROR(R19/Q19,0) -> 0.60042695 | Z19: Intermedio · Dulce
A20: 7 | B20: Rol de Limón y Semillas de Amapola | C20: 00A | D20: 12 | E20: =IFERROR(INDEX('2. Masas Base'!$D$55:$D$58,MATCH($C20,'2. Masas Base'!$B$55:$B$58,0)),0) -> 73.48 | F20: =SUMIFS('3. Rellenos y Cubiertas'!$G$5:$G$345,'3. Rellenos y Cubiertas'!$A$5:$A$345,$A20) -> 73.83 | G20: =E20+F20 -> 147.31 | H20: =IFERROR(G20/D20,0) -> 12.275833 | I20: 9 | J20: 3 | K20: 5 | L20: =$C$9*K20/60 -> 6.25 | M20: =$C$10 -> 10.611111 | N20: =H20+I20+J20+L20+M20 -> 41.136944 | O20: =$C$11 -> 0.12 | P20: =IFERROR(N20/(1-O20),0) -> 46.746528 | Q20: =IFERROR(CEILING(P20/(1-$C$5),5),0) -> 120 | R20: =Q20-P20 -> 73.253472 | S20: =IFERROR(CEILING(P20/(1-$C$6),5),0) -> 135 | T20: =S20-P20 -> 88.253472 | U20: =IFERROR(CEILING(P20/(1-$C$7),5),0) -> 95 | V20: =U20-P20 -> 48.253472 | W20: =IFERROR(CEILING(P20/(1-$C$8),5),0) -> 80 | X20: =W20-P20 -> 33.253472 | Y20: =IFERROR(R20/Q20,0) -> 0.6104456 | Z20: Fácil · Dulce
A21: 8 | B21: Rol de Zanahoria (Estilo Carrot Cake) | C21: 00A | D21: 12 | E21: =IFERROR(INDEX('2. Masas Base'!$D$55:$D$58,MATCH($C21,'2. Masas Base'!$B$55:$B$58,0)),0) -> 73.48 | F21: =SUMIFS('3. Rellenos y Cubiertas'!$G$5:$G$345,'3. Rellenos y Cubiertas'!$A$5:$A$345,$A21) -> 133.22 | G21: =E21+F21 -> 206.7 | H21: =IFERROR(G21/D21,0) -> 17.225 | I21: 11 | J21: 4 | K21: 7 | L21: =$C$9*K21/60 -> 8.75 | M21: =$C$10 -> 10.611111 | N21: =H21+I21+J21+L21+M21 -> 51.586111 | O21: =$C$11 -> 0.12 | P21: =IFERROR(N21/(1-O21),0) -> 58.620581 | Q21: =IFERROR(CEILING(P21/(1-$C$5),5),0) -> 150 | R21: =Q21-P21 -> 91.379419 | S21: =IFERROR(CEILING(P21/(1-$C$6),5),0) -> 170 | T21: =S21-P21 -> 111.37942 | U21: =IFERROR(CEILING(P21/(1-$C$7),5),0) -> 120 | V21: =U21-P21 -> 61.379419 | W21: =IFERROR(CEILING(P21/(1-$C$8),5),0) -> 100 | X21: =W21-P21 -> 41.379419 | Y21: =IFERROR(R21/Q21,0) -> 0.60919613 | Z21: Intermedio · Dulce
A22: 9 | B22: Rol de Dulce de Leche y Nuez Macadamia | C22: 00A | D22: 12 | E22: =IFERROR(INDEX('2. Masas Base'!$D$55:$D$58,MATCH($C22,'2. Masas Base'!$B$55:$B$58,0)),0) -> 73.48 | F22: =SUMIFS('3. Rellenos y Cubiertas'!$G$5:$G$345,'3. Rellenos y Cubiertas'!$A$5:$A$345,$A22) -> 203.64 | G22: =E22+F22 -> 277.12 | H22: =IFERROR(G22/D22,0) -> 23.093333 | I22: 9 | J22: 3 | K22: 5 | L22: =$C$9*K22/60 -> 6.25 | M22: =$C$10 -> 10.611111 | N22: =H22+I22+J22+L22+M22 -> 51.954444 | O22: =$C$11 -> 0.12 | P22: =IFERROR(N22/(1-O22),0) -> 59.039141 | Q22: =IFERROR(CEILING(P22/(1-$C$5),5),0) -> 150 | R22: =Q22-P22 -> 90.960859 | S22: =IFERROR(CEILING(P22/(1-$C$6),5),0) -> 170 | T22: =S22-P22 -> 110.96086 | U22: =IFERROR(CEILING(P22/(1-$C$7),5),0) -> 120 | V22: =U22-P22 -> 60.960859 | W22: =IFERROR(CEILING(P22/(1-$C$8),5),0) -> 100 | X22: =W22-P22 -> 40.960859 | Y22: =IFERROR(R22/Q22,0) -> 0.60640572 | Z22: Fácil · Dulce
A23: 10 | B23: Rol de Plátano Caramelizado y Nuez de Castilla | C23: 00A | D23: 12 | E23: =IFERROR(INDEX('2. Masas Base'!$D$55:$D$58,MATCH($C23,'2. Masas Base'!$B$55:$B$58,0)),0) -> 73.48 | F23: =SUMIFS('3. Rellenos y Cubiertas'!$G$5:$G$345,'3. Rellenos y Cubiertas'!$A$5:$A$345,$A23) -> 97.94 | G23: =E23+F23 -> 171.42 | H23: =IFERROR(G23/D23,0) -> 14.285 | I23: 11 | J23: 4 | K23: 7 | L23: =$C$9*K23/60 -> 8.75 | M23: =$C$10 -> 10.611111 | N23: =H23+I23+J23+L23+M23 -> 48.646111 | O23: =$C$11 -> 0.12 | P23: =IFERROR(N23/(1-O23),0) -> 55.279672 | Q23: =IFERROR(CEILING(P23/(1-$C$5),5),0) -> 140 | R23: =Q23-P23 -> 84.720328 | S23: =IFERROR(CEILING(P23/(1-$C$6),5),0) -> 160 | T23: =S23-P23 -> 104.72033 | U23: =IFERROR(CEILING(P23/(1-$C$7),5),0) -> 115 | V23: =U23-P23 -> 59.720328 | W23: =IFERROR(CEILING(P23/(1-$C$8),5),0) -> 95 | X23: =W23-P23 -> 39.720328 | Y23: =IFERROR(R23/Q23,0) -> 0.6051452 | Z23: Intermedio · Dulce
A24: 11 | B24: Rol Volcán de Crema de Avellana (Estilo Nutella) | C24: 00A | D24: 12 | E24: =IFERROR(INDEX('2. Masas Base'!$D$55:$D$58,MATCH($C24,'2. Masas Base'!$B$55:$B$58,0)),0) -> 73.48 | F24: =SUMIFS('3. Rellenos y Cubiertas'!$G$5:$G$345,'3. Rellenos y Cubiertas'!$A$5:$A$345,$A24) -> 120 | G24: =E24+F24 -> 193.48 | H24: =IFERROR(G24/D24,0) -> 16.123333 | I24: 11 | J24: 4 | K24: 7 | L24: =$C$9*K24/60 -> 8.75 | M24: =$C$10 -> 10.611111 | N24: =H24+I24+J24+L24+M24 -> 50.484444 | O24: =$C$11 -> 0.12 | P24: =IFERROR(N24/(1-O24),0) -> 57.368687 | Q24: =IFERROR(CEILING(P24/(1-$C$5),5),0) -> 145 | R24: =Q24-P24 -> 87.631313 | S24: =IFERROR(CEILING(P24/(1-$C$6),5),0) -> 165 | T24: =S24-P24 -> 107.63131 | U24: =IFERROR(CEILING(P24/(1-$C$7),5),0) -> 115 | V24: =U24-P24 -> 57.631313 | W24: =IFERROR(CEILING(P24/(1-$C$8),5),0) -> 100 | X24: =W24-P24 -> 42.631313 | Y24: =IFERROR(R24/Q24,0) -> 0.60435388 | Z24: Intermedio · Dulce
A25: 12 | B25: Rol Volcán de Pistache y Chocolate Blanco | C25: 00A | D25: 12 | E25: =IFERROR(INDEX('2. Masas Base'!$D$55:$D$58,MATCH($C25,'2. Masas Base'!$B$55:$B$58,0)),0) -> 73.48 | F25: =SUMIFS('3. Rellenos y Cubiertas'!$G$5:$G$345,'3. Rellenos y Cubiertas'!$A$5:$A$345,$A25) -> 296.8 | G25: =E25+F25 -> 370.28 | H25: =IFERROR(G25/D25,0) -> 30.856667 | I25: 11 | J25: 4 | K25: 7 | L25: =$C$9*K25/60 -> 8.75 | M25: =$C$10 -> 10.611111 | N25: =H25+I25+J25+L25+M25 -> 65.217778 | O25: =$C$11 -> 0.12 | P25: =IFERROR(N25/(1-O25),0) -> 74.111111 | Q25: =IFERROR(CEILING(P25/(1-$C$5),5),0) -> 190 | R25: =Q25-P25 -> 115.88889 | S25: =IFERROR(CEILING(P25/(1-$C$6),5),0) -> 215 | T25: =S25-P25 -> 140.88889 | U25: =IFERROR(CEILING(P25/(1-$C$7),5),0) -> 150 | V25: =U25-P25 -> 75.888889 | W25: =IFERROR(CEILING(P25/(1-$C$8),5),0) -> 125 | X25: =W25-P25 -> 50.888889 | Y25: =IFERROR(R25/Q25,0) -> 0.60994152 | Z25: Intermedio · Dulce
... A64: 51 | B64: Rol de Earl Grey y Lavanda | C64: 00A | D64: 12 | E64: =IFERROR(INDEX('2. Masas Base'!$D$55:$D$58,MATCH($C64,'2. Masas Base'!$B$55:$B$58,0)),0) -> 73.48 | F64: =SUMIFS('3. Rellenos y Cubiertas'!$G$5:$G$345,'3. Rellenos y Cubiertas'!$A$5:$A$345,$A64) -> 51.8 | G64: =E64+F64 -> 125.28 | H64: =IFERROR(G64/D64,0) -> 10.44 | I64: 9 | J64: 3 | K64: 5 | L64: =$C$9*K64/60 -> 6.25 | M64: =$C$10 -> 10.611111 | N64: =H64+I64+J64+L64+M64 -> 39.301111 | O64: =$C$11 -> 0.12 | P64: =IFERROR(N64/(1-O64),0) -> 44.660354 | Q64: =IFERROR(CEILING(P64/(1-$C$5),5),0) -> 115 | R64: =Q64-P64 -> 70.339646 | S64: =IFERROR(CEILING(P64/(1-$C$6),5),0) -> 130 | T64: =S64-P64 -> 85.339646 | U64: =IFERROR(CEILING(P64/(1-$C$7),5),0) -> 90 | V64: =U64-P64 -> 45.339646 | W64: =IFERROR(CEILING(P64/(1-$C$8),5),0) -> 75 | X64: =W64-P64 -> 30.339646 | Y64: =IFERROR(R64/Q64,0) -> 0.6116491 | Z64: Fácil · Dulce
B65: PROMEDIO DE LAS 51 RECETAS | E65: =AVERAGE(E14:E64) -> 84.935098 | F65: =AVERAGE(F14:F64) -> 130.13133 | G65: =AVERAGE(G14:G64) -> 215.06643 | H65: =AVERAGE(H14:H64) -> 17.922203 | N65: =AVERAGE(N14:N64) -> 51.577431 | P65: =AVERAGE(P14:P64) -> 58.610717 | Q65: =AVERAGE(Q14:Q64) -> 149.11765 | R65: =AVERAGE(R14:R64) -> 90.50693 | Y65: =AVERAGE(Y14:Y64) -> 0.60695441
B67: Supuestos de arranque escalados por dificultad: receta fácil → empaque $9, energía $3, 5 min por rol; intermedia → $11, $4, 7 min; avanzada → $14, $5, 10 min. Merma 12 % (nivel intermedio). Ajusta todo a tu operación real.
B68: La columna «Costo de la masa» viene de la hoja 2 según la fórmula base que pide cada receta; la columna «Costo del relleno» suma la hoja 3.

Sheet 5. Producción y Merma
A1: 5 · BITÁCORA DE PRODUCCIÓN Y MERMA
A2: Registra cada horneada. La hoja calcula tu merma real y cuánto dinero se fue a la basura.
A3: Roles buenos acumulados | D3: =SUM(F8:F207) -> 11
A4: Roles fallidos acumulados | D4: =SUM(G8:G207) -> 1
A5: % de merma real acumulada | D5: =IFERROR(D4/(D3+D4),0) -> 0.083333333
A6: Costo acumulado de la merma | D6: =SUM(K8:K207) -> 51.388952
A7: Fecha | B7: Lote | C7: Nº receta | D7: Receta | E7: Roles planeados | F7: Roles buenos | G7: Roles fallidos | H7: % merma real | I7: Causa principal | J7: Costo unitario | K7: Costo de la merma | L7: Notas
A8: 46235 | B8: L-2608-01 | C8: 1 | D8: =IFERROR(INDEX('4. Costeo y Precios'!$B$14:$B$64,MATCH($C8,'4. Costeo y Precios'!$A$14:$A$64,0)),"") -> Rol de Canela Clásico con Glaseado de Vainilla de Papantla | E8: 12 | F8: 11 | G8: 1 | H8: =IFERROR(G8/(F8+G8),"") -> 0.083333333 | I8: Fuga de relleno en el horneado | J8: =IFERROR(INDEX('4. Costeo y Precios'!$P$14:$P$64,MATCH($C8,'4. Costeo y Precios'!$A$14:$A$64,0)),0) -> 51.388952 | K8: =IF($C8="","",G8*J8) -> 51.388952 | L8: ← Fila de ejemplo: puedes borrarla
C9: 11 | D9: =IFERROR(INDEX('4. Costeo y Precios'!$B$14:$B$64,MATCH($C9,'4. Costeo y Precios'!$A$14:$A$64,0)),"") -> Rol Volcán de Crema de Avellana (Estilo Nutella) | H9: =IFERROR(G9/(F9+G9),"") | J9: =IFERROR(INDEX('4. Costeo y Precios'!$P$14:$P$64,MATCH($C9,'4. Costeo y Precios'!$A$14:$A$64,0)),0) -> 57.368687 | K9: =IF($C9="","",G9*J9) -> 0
C10: 42 | D10: =IFERROR(INDEX('4. Costeo y Precios'!$B$14:$B$64,MATCH($C10,'4. Costeo y Precios'!$A$14:$A$64,0)),"") -> Rol de Ajo Rostizado, Romero y Parmesano | H10: =IFERROR(G10/(F10+G10),"") | J10: =IFERROR(INDEX('4. Costeo y Precios'!$P$14:$P$64,MATCH($C10,'4. Costeo y Precios'!$A$14:$A$64,0)),0) -> 68.839899 | K10: =IF($C10="","",G10*J10) -> 0
D11: =IFERROR(INDEX('4. Costeo y Precios'!$B$14:$B$64,MATCH($C11,'4. Costeo y Precios'!$A$14:$A$64,0)),"") | H11: =IFERROR(G11/(F11+G11),"") | J11: =IFERROR(INDEX('4. Costeo y Precios'!$P$14:$P$64,MATCH($C11,'4. Costeo y Precios'!$A$14:$A$64,0)),0) -> 0 | K11: =IF($C11="","",G11*J11)
D12: =IFERROR(INDEX('4. Costeo y Precios'!$B$14:$B$64,MATCH($C12,'4. Costeo y Precios'!$A$14:$A$64,0)),"") | H12: =IFERROR(G12/(F12+G12),"") | J12: =IFERROR(INDEX('4. Costeo y Precios'!$P$14:$P$64,MATCH($C12,'4. Costeo y Precios'!$A$14:$A$64,0)),0) -> 0 | K12: =IF($C12="","",G12*J12)
D13: =IFERROR(INDEX('4. Costeo y Precios'!$B$14:$B$64,MATCH($C13,'4. Costeo y Precios'!$A$14:$A$64,0)),"") | H13: =IFERROR(G13/(F13+G13),"") | J13: =IFERROR(INDEX('4. Costeo y Precios'!$P$14:$P$64,MATCH($C13,'4. Costeo y Precios'!$A$14:$A$64,0)),0) -> 0 | K13: =IF($C13="","",G13*J13)
D14: =IFERROR(INDEX('4. Costeo y Precios'!$B$14:$B$64,MATCH($C14,'4. Costeo y Precios'!$A$14:$A$64,0)),"") | H14: =IFERROR(G14/(F14+G14),"") | J14: =IFERROR(INDEX('4. Costeo y Precios'!$P$14:$P$64,MATCH($C14,'4. Costeo y Precios'!$A$14:$A$64,0)),0) -> 0 | K14: =IF($C14="","",G14*J14)
D15: =IFERROR(INDEX('4. Costeo y Precios'!$B$14:$B$64,MATCH($C15,'4. Costeo y Precios'!$A$14:$A$64,0)),"") | H15: =IFERROR(G15/(F15+G15),"") | J15: =IFERROR(INDEX('4. Costeo y Precios'!$P$14:$P$64,MATCH($C15,'4. Costeo y Precios'!$A$14:$A$64,0)),0) -> 0 | K15: =IF($C15="","",G15*J15)
D16: =IFERROR(INDEX('4. Costeo y Precios'!$B$14:$B$64,MATCH($C16,'4. Costeo y Precios'!$A$14:$A$64,0)),"") | H16: =IFERROR(G16/(F16+G16),"") | J16: =IFERROR(INDEX('4. Costeo y Precios'!$P$14:$P$64,MATCH($C16,'4. Costeo y Precios'!$A$14:$A$64,0)),0) -> 0 | K16: =IF($C16="","",G16*J16)
D17: =IFERROR(INDEX('4. Costeo y Precios'!$B$14:$B$64,MATCH($C17,'4. Costeo y Precios'!$A$14:$A$64,0)),"") | H17: =IFERROR(G17/(F17+G17),"") | J17: =IFERROR(INDEX('4. Costeo y Precios'!$P$14:$P$64,MATCH($C17,'4. Costeo y Precios'!$A$14:$A$64,0)),0) -> 0 | K17: =IF($C17="","",G17*J17)
D18: =IFERROR(INDEX('4. Costeo y Precios'!$B$14:$B$64,MATCH($C18,'4. Costeo y Precios'!$A$14:$A$64,0)),"") | H18: =IFERROR(G18/(F18+G18),"") | J18: =IFERROR(INDEX('4. Costeo y Precios'!$P$14:$P$64,MATCH($C18,'4. Costeo y Precios'!$A$14:$A$64,0)),0) -> 0 | K18: =IF($C18="","",G18*J18)
D19: =IFERROR(INDEX('4. Costeo y Precios'!$B$14:$B$64,MATCH($C19,'4. Costeo y Precios'!$A$14:$A$64,0)),"") | H19: =IFERROR(G19/(F19+G19),"") | J19: =IFERROR(INDEX('4. Costeo y Precios'!$P$14:$P$64,MATCH($C19,'4. Costeo y Precios'!$A$14:$A$64,0)),0) -> 0 | K19: =IF($C19="","",G19*J19)
D20: =IFERROR(INDEX('4. Costeo y Precios'!$B$14:$B$64,MATCH($C20,'4. Costeo y Precios'!$A$14:$A$64,0)),"") | H20: =IFERROR(G20/(F20+G20),"") | J20: =IFERROR(INDEX('4. Costeo y Precios'!$P$14:$P$64,MATCH($C20,'4. Costeo y Precios'!$A$14:$A$64,0)),0) -> 0 | K20: =IF($C20="","",G20*J20)
D21: =IFERROR(INDEX('4. Costeo y Precios'!$B$14:$B$64,MATCH($C21,'4. Costeo y Precios'!$A$14:$A$64,0)),"") | H21: =IFERROR(G21/(F21+G21),"") | J21: =IFERROR(INDEX('4. Costeo y Precios'!$P$14:$P$64,MATCH($C21,'4. Costeo y Precios'!$A$14:$A$64,0)),0) -> 0 | K21: =IF($C21="","",G21*J21)
D22: =IFERROR(INDEX('4. Costeo y Precios'!$B$14:$B$64,MATCH($C22,'4. Costeo y Precios'!$A$14:$A$64,0)),"") | H22: =IFERROR(G22/(F22+G22),"") | J22: =IFERROR(INDEX('4. Costeo y Precios'!$P$14:$P$64,MATCH($C22,'4. Costeo y Precios'!$A$14:$A$64,0)),0) -> 0 | K22: =IF($C22="","",G22*J22)
... D207: =IFERROR(INDEX('4. Costeo y Precios'!$B$14:$B$64,MATCH($C207,'4. Costeo y Precios'!$A$14:$A$64,0)),"") | H207: =IFERROR(G207/(F207+G207),"") | J207: =IFERROR(INDEX('4. Costeo y Precios'!$P$14:$P$64,MATCH($C207,'4. Costeo y Precios'!$A$14:$A$64,0)),0) -> 0 | K207: =IF($C207="","",G207*J207)

Sheet 6. Ventas
A1: 6 · BITÁCORA DE VENTAS
A2: Una línea por venta. La utilidad neta descuenta el costo real y la comisión de plataforma.
A3: Roles vendidos acumulados | D3: =SUM(E8:E407) -> 26
A4: Ingreso total acumulado | D4: =SUM(G8:G407) -> 2490
A5: Utilidad neta total acumulada | D5: =SUM(L8:L407) -> 920.42475
A6: Margen neto promedio | D6: =IFERROR(D5/D4,0) -> 0.36964849
A7: Fecha | B7: Nº receta | C7: Receta | D7: Canal | E7: Roles | F7: Precio unitario | G7: Ingreso | H7: Costo unitario | I7: Costo total | J7: Comisión % | K7: Comisión $ | L7: Utilidad neta | M7: Margen % | N7: Cliente / Notas
A8: 46236 | B8: 1 | C8: =IFERROR(INDEX('4. Costeo y Precios'!$B$14:$B$64,MATCH($B8,'4. Costeo y Precios'!$A$14:$A$64,0)),"") -> Rol de Canela Clásico con Glaseado de Vainilla de Papantla | D8: Mostrador | E8: 8 | F8: 75 | G8: =IF($B8="","",E8*F8) -> 600 | H8: =IFERROR(INDEX('4. Costeo y Precios'!$P$14:$P$64,MATCH($B8,'4. Costeo y Precios'!$A$14:$A$64,0)),0) -> 51.388952 | I8: =IF($B8="","",E8*H8) -> 411.11162 | J8: 0 | K8: =IF($B8="","",G8*J8) -> 0 | L8: =IF($B8="","",G8-I8-K8) -> 188.88838 | M8: =IFERROR(L8/G8,"") -> 0.31481397 | N8: ← Fila de ejemplo: puedes borrarla
A9: 46237 | B9: 11 | C9: =IFERROR(INDEX('4. Costeo y Precios'!$B$14:$B$64,MATCH($B9,'4. Costeo y Precios'!$A$14:$A$64,0)),"") -> Rol Volcán de Crema de Avellana (Estilo Nutella) | D9: Caja de regalo | E9: 12 | F9: 110 | G9: =IF($B9="","",E9*F9) -> 1320 | H9: =IFERROR(INDEX('4. Costeo y Precios'!$P$14:$P$64,MATCH($B9,'4. Costeo y Precios'!$A$14:$A$64,0)),0) -> 57.368687 | I9: =IF($B9="","",E9*H9) -> 688.42424 | J9: 0 | K9: =IF($B9="","",G9*J9) -> 0 | L9: =IF($B9="","",G9-I9-K9) -> 631.57576 | M9: =IFERROR(L9/G9,"") -> 0.47846648
A10: 46238 | B10: 42 | C10: =IFERROR(INDEX('4. Costeo y Precios'!$B$14:$B$64,MATCH($B10,'4. Costeo y Precios'!$A$14:$A$64,0)),"") -> Rol de Ajo Rostizado, Romero y Parmesano | D10: Venta en línea | E10: 6 | F10: 95 | G10: =IF($B10="","",E10*F10) -> 570 | H10: =IFERROR(INDEX('4. Costeo y Precios'!$P$14:$P$64,MATCH($B10,'4. Costeo y Precios'!$A$14:$A$64,0)),0) -> 68.839899 | I10: =IF($B10="","",E10*H10) -> 413.03939 | J10: 0.1 | K10: =IF($B10="","",G10*J10) -> 57 | L10: =IF($B10="","",G10-I10-K10) -> 99.960606 | M10: =IFERROR(L10/G10,"") -> 0.17536948
C11: =IFERROR(INDEX('4. Costeo y Precios'!$B$14:$B$64,MATCH($B11,'4. Costeo y Precios'!$A$14:$A$64,0)),"") | G11: =IF($B11="","",E11*F11) | H11: =IFERROR(INDEX('4. Costeo y Precios'!$P$14:$P$64,MATCH($B11,'4. Costeo y Precios'!$A$14:$A$64,0)),0) -> 0 | I11: =IF($B11="","",E11*H11) | K11: =IF($B11="","",G11*J11) | L11: =IF($B11="","",G11-I11-K11) | M11: =IFERROR(L11/G11,"")
C12: =IFERROR(INDEX('4. Costeo y Precios'!$B$14:$B$64,MATCH($B12,'4. Costeo y Precios'!$A$14:$A$64,0)),"") | G12: =IF($B12="","",E12*F12) | H12: =IFERROR(INDEX('4. Costeo y Precios'!$P$14:$P$64,MATCH($B12,'4. Costeo y Precios'!$A$14:$A$64,0)),0) -> 0 | I12: =IF($B12="","",E12*H12) | K12: =IF($B12="","",G12*J12) | L12: =IF($B12="","",G12-I12-K12) | M12: =IFERROR(L12/G12,"")
C13: =IFERROR(INDEX('4. Costeo y Precios'!$B$14:$B$64,MATCH($B13,'4. Costeo y Precios'!$A$14:$A$64,0)),"") | G13: =IF($B13="","",E13*F13) | H13: =IFERROR(INDEX('4. Costeo y Precios'!$P$14:$P$64,MATCH($B13,'4. Costeo y Precios'!$A$14:$A$64,0)),0) -> 0 | I13: =IF($B13="","",E13*H13) | K13: =IF($B13="","",G13*J13) | L13: =IF($B13="","",G13-I13-K13) | M13: =IFERROR(L13/G13,"")
C14: =IFERROR(INDEX('4. Costeo y Precios'!$B$14:$B$64,MATCH($B14,'4. Costeo y Precios'!$A$14:$A$64,0)),"") | G14: =IF($B14="","",E14*F14) | H14: =IFERROR(INDEX('4. Costeo y Precios'!$P$14:$P$64,MATCH($B14,'4. Costeo y Precios'!$A$14:$A$64,0)),0) -> 0 | I14: =IF($B14="","",E14*H14) | K14: =IF($B14="","",G14*J14) | L14: =IF($B14="","",G14-I14-K14) | M14: =IFERROR(L14/G14,"")
C15: =IFERROR(INDEX('4. Costeo y Precios'!$B$14:$B$64,MATCH($B15,'4. Costeo y Precios'!$A$14:$A$64,0)),"") | G15: =IF($B15="","",E15*F15) | H15: =IFERROR(INDEX('4. Costeo y Precios'!$P$14:$P$64,MATCH($B15,'4. Costeo y Precios'!$A$14:$A$64,0)),0) -> 0 | I15: =IF($B15="","",E15*H15) | K15: =IF($B15="","",G15*J15) | L15: =IF($B15="","",G15-I15-K15) | M15: =IFERROR(L15/G15,"")
C16: =IFERROR(INDEX('4. Costeo y Precios'!$B$14:$B$64,MATCH($B16,'4. Costeo y Precios'!$A$14:$A$64,0)),"") | G16: =IF($B16="","",E16*F16) | H16: =IFERROR(INDEX('4. Costeo y Precios'!$P$14:$P$64,MATCH($B16,'4. Costeo y Precios'!$A$14:$A$64,0)),0) -> 0 | I16: =IF($B16="","",E16*H16) | K16: =IF($B16="","",G16*J16) | L16: =IF($B16="","",G16-I16-K16) | M16: =IFERROR(L16/G16,"")
C17: =IFERROR(INDEX('4. Costeo y Precios'!$B$14:$B$64,MATCH($B17,'4. Costeo y Precios'!$A$14:$A$64,0)),"") | G17: =IF($B17="","",E17*F17) | H17: =IFERROR(INDEX('4. Costeo y Precios'!$P$14:$P$64,MATCH($B17,'4. Costeo y Precios'!$A$14:$A$64,0)),0) -> 0 | I17: =IF($B17="","",E17*H17) | K17: =IF($B17="","",G17*J17) | L17: =IF($B17="","",G17-I17-K17) | M17: =IFERROR(L17/G17,"")
C18: =IFERROR(INDEX('4. Costeo y Precios'!$B$14:$B$64,MATCH($B18,'4. Costeo y Precios'!$A$14:$A$64,0)),"") | G18: =IF($B18="","",E18*F18) | H18: =IFERROR(INDEX('4. Costeo y Precios'!$P$14:$P$64,MATCH($B18,'4. Costeo y Precios'!$A$14:$A$64,0)),0) -> 0 | I18: =IF($B18="","",E18*H18) | K18: =IF($B18="","",G18*J18) | L18: =IF($B18="","",G18-I18-K18) | M18: =IFERROR(L18/G18,"")
C19: =IFERROR(INDEX('4. Costeo y Precios'!$B$14:$B$64,MATCH($B19,'4. Costeo y Precios'!$A$14:$A$64,0)),"") | G19: =IF($B19="","",E19*F19) | H19: =IFERROR(INDEX('4. Costeo y Precios'!$P$14:$P$64,MATCH($B19,'4. Costeo y Precios'!$A$14:$A$64,0)),0) -> 0 | I19: =IF($B19="","",E19*H19) | K19: =IF($B19="","",G19*J19) | L19: =IF($B19="","",G19-I19-K19) | M19: =IFERROR(L19/G19,"")
C20: =IFERROR(INDEX('4. Costeo y Precios'!$B$14:$B$64,MATCH($B20,'4. Costeo y Precios'!$A$14:$A$64,0)),"") | G20: =IF($B20="","",E20*F20) | H20: =IFERROR(INDEX('4. Costeo y Precios'!$P$14:$P$64,MATCH($B20,'4. Costeo y Precios'!$A$14:$A$64,0)),0) -> 0 | I20: =IF($B20="","",E20*H20) | K20: =IF($B20="","",G20*J20) | L20: =IF($B20="","",G20-I20-K20) | M20: =IFERROR(L20/G20,"")
C21: =IFERROR(INDEX('4. Costeo y Precios'!$B$14:$B$64,MATCH($B21,'4. Costeo y Precios'!$A$14:$A$64,0)),"") | G21: =IF($B21="","",E21*F21) | H21: =IFERROR(INDEX('4. Costeo y Precios'!$P$14:$P$64,MATCH($B21,'4. Costeo y Precios'!$A$14:$A$64,0)),0) -> 0 | I21: =IF($B21="","",E21*H21) | K21: =IF($B21="","",G21*J21) | L21: =IF($B21="","",G21-I21-K21) | M21: =IFERROR(L21/G21,"")
C22: =IFERROR(INDEX('4. Costeo y Precios'!$B$14:$B$64,MATCH($B22,'4. Costeo y Precios'!$A$14:$A$64,0)),"") | G22: =IF($B22="","",E22*F22) | H22: =IFERROR(INDEX('4. Costeo y Precios'!$P$14:$P$64,MATCH($B22,'4. Costeo y Precios'!$A$14:$A$64,0)),0) -> 0 | I22: =IF($B22="","",E22*H22) | K22: =IF($B22="","",G22*J22) | L22: =IF($B22="","",G22-I22-K22) | M22: =IFERROR(L22/G22,"")
... C407: =IFERROR(INDEX('4. Costeo y Precios'!$B$14:$B$64,MATCH($B407,'4. Costeo y Precios'!$A$14:$A$64,0)),"") | G407: =IF($B407="","",E407*F407) | H407: =IFERROR(INDEX('4. Costeo y Precios'!$P$14:$P$64,MATCH($B407,'4. Costeo y Precios'!$A$14:$A$64,0)),0) -> 0 | I407: =IF($B407="","",E407*H407) | K407: =IF($B407="","",G407*J407) | L407: =IF($B407="","",G407-I407-K407) | M407: =IFERROR(L407/G407,"")

Sheet 7. Gastos Fijos
A1: 7 · GASTOS FIJOS, MANO DE OBRA Y PUNTO DE EQUILIBRIO
A2: De aquí salen el overhead por rol y el costo por hora que usa la hoja de costeo.
B4: A · GASTOS FIJOS MENSUALES (MXN)
B5: Renta del espacio de producción | C5: 3000
B6: Luz, gas y agua | C6: 700
B7: Internet y telefonía | C7: 600
B8: Publicidad y anuncios pagados | C8: 1200
B9: Papelería, limpieza y consumibles generales | C9: 300
B10: Suscripciones y software (diseño, facturación) | C10: 200
B11: Transporte y repartos | C11: 500
B12: Depreciación de equipo (batidora, horno, cámara) | C12: 350
B13: Sueldos fijos de terceros | C13: 2000
B14: Otros gastos fijos | C14: 700
B15: TOTAL DE GASTOS FIJOS MENSUALES | C15: =SUM(C5:C14) -> 9550 | D15: Supuesto de arranque: obrador rentado de medio tiempo con cámara de fermentación. Si horneas desde casa, pon 0 en renta.
B17: B · OVERHEAD POR ROL
B18: Roles que produces al mes (estimado) | C18: 900
B19: Overhead prorrateado por rol | C19: =IFERROR($C$15/$C$18,0) -> 10.611111 | D19: Se enlaza automáticamente a la hoja «4. Costeo y Precios». 900 roles al mes son 75 lotes de masa.
B21: C · COSTO DE TU MANO DE OBRA
B22: Sueldo mensual que quieres cobrarte (MXN) | C22: 12000
B23: Horas de trabajo al mes | C23: 160
B24: Costo de mano de obra por hora | C24: =IFERROR($C$22/$C$23,0) -> 75 | D24: Ojo: la masa enriquecida tiene fermentación retardada de 8 a 12 horas, pero esas horas no son de trabajo activo. Cuenta solo el tiempo en que tus manos están ocupadas.
B26: D · PUNTO DE EQUILIBRIO
B27: Precio de venta promedio por rol | C27: =IFERROR(AVERAGE('4. Costeo y Precios'!$Q$14:$Q$64),0) -> 149.11765
B28: Costo total unitario promedio | C28: =IFERROR(AVERAGE('4. Costeo y Precios'!$P$14:$P$64),0) -> 58.610717
B29: Margen de contribución por rol | C29: =$C$27-$C$28 -> 90.50693
B30: ROLES QUE DEBES VENDER AL MES PARA NO PERDER | C30: =IFERROR(ROUNDUP($C$15/$C$29,0),0) -> 106
B31: Ingreso mensual de equilibrio | C31: =$C$30*$C$27 -> 15806.471
B32: Lotes de masa equivalentes | C32: =ROUNDUP($C$30/12,0) -> 9

Sheet 8. Tablero
A1: 8 · TABLERO DEL MES
A2: Escribe cualquier día del mes que quieras analizar y todo el tablero se actualiza.
B4: Mes a analizar (escribe cualquier fecha de ese mes) | C4: 46235
B5: Inicio del periodo | C5: =DATE(YEAR(C4),MONTH(C4),1) -> 46235
B6: Fin del periodo (exclusivo) | C6: =DATE(YEAR(C4),MONTH(C4)+1,1) -> 46266
B8: RESULTADOS DEL MES
B9: Roles vendidos | C9: =SUMIFS('6. Ventas'!$E$8:$E$407,'6. Ventas'!$A$8:$A$407,">="&$C$5,'6. Ventas'!$A$8:$A$407,"<"&$C$6) -> 26 | E9: Roles buenos producidos | F9: =SUMIFS('5. Producción y Merma'!$F$8:$F$207,'5. Producción y Merma'!$A$8:$A$207,">="&$C$5,'5. Producción y Merma'!$A$8:$A$207,"<"&$C$6) -> 11
B10: Ingreso del mes | C10: =SUMIFS('6. Ventas'!$G$8:$G$407,'6. Ventas'!$A$8:$A$407,">="&$C$5,'6. Ventas'!$A$8:$A$407,"<"&$C$6) -> 2490 | E10: Roles fallidos | F10: =SUMIFS('5. Producción y Merma'!$G$8:$G$207,'5. Producción y Merma'!$A$8:$A$207,">="&$C$5,'5. Producción y Merma'!$A$8:$A$207,"<"&$C$6) -> 1
B11: Costo de producto vendido | C11: =SUMIFS('6. Ventas'!$I$8:$I$407,'6. Ventas'!$A$8:$A$407,">="&$C$5,'6. Ventas'!$A$8:$A$407,"<"&$C$6) -> 1512.5753 | E11: % de merma del mes | F11: =IFERROR(F10/(F9+F10),0) -> 0.083333333
B12: Utilidad neta del mes | C12: =SUMIFS('6. Ventas'!$L$8:$L$407,'6. Ventas'!$A$8:$A$407,">="&$C$5,'6. Ventas'!$A$8:$A$407,"<"&$C$6) -> 920.42475 | E12: Dinero perdido en merma | F12: =SUMIFS('5. Producción y Merma'!$K$8:$K$207,'5. Producción y Merma'!$A$8:$A$207,">="&$C$5,'5. Producción y Merma'!$A$8:$A$207,"<"&$C$6) -> 51.388952
B13: Margen neto | C13: =IFERROR(C12/C10,0) -> 0.36964849 | E13: Merma como % del ingreso | F13: =IFERROR(F12/C10,0) -> 0.020638133
B14: Ticket promedio por rol | C14: =IFERROR(C10/C9,0) -> 95.769231 | E14: Punto de equilibrio (roles) | F14: ='7. Gastos Fijos'!$C$30 -> 106
B15: Utilidad después de gastos fijos | C15: =C12-'7. Gastos Fijos'!$C$15 -> -8629.5753 | E15: Avance hacia el equilibrio | F15: =IFERROR(C9/F14,0) -> 0.24528302
B18: VENTAS POR CANAL
B19: Canal | C19: Roles | E19: Ingreso | F19: Utilidad neta
B20: Mostrador | C20: =SUMIFS('6. Ventas'!$E$8:$E$407,'6. Ventas'!$A$8:$A$407,">="&$C$5,'6. Ventas'!$A$8:$A$407,"<"&$C$6,'6. Ventas'!$D$8:$D$407,$B20) -> 8 | E20: =SUMIFS('6. Ventas'!$G$8:$G$407,'6. Ventas'!$A$8:$A$407,">="&$C$5,'6. Ventas'!$A$8:$A$407,"<"&$C$6,'6. Ventas'!$D$8:$D$407,$B20) -> 600 | F20: =SUMIFS('6. Ventas'!$L$8:$L$407,'6. Ventas'!$A$8:$A$407,">="&$C$5,'6. Ventas'!$A$8:$A$407,"<"&$C$6,'6. Ventas'!$D$8:$D$407,$B20) -> 188.88838
B21: Caja de regalo | C21: =SUMIFS('6. Ventas'!$E$8:$E$407,'6. Ventas'!$A$8:$A$407,">="&$C$5,'6. Ventas'!$A$8:$A$407,"<"&$C$6,'6. Ventas'!$D$8:$D$407,$B21) -> 12 | E21: =SUMIFS('6. Ventas'!$G$8:$G$407,'6. Ventas'!$A$8:$A$407,">="&$C$5,'6. Ventas'!$A$8:$A$407,"<"&$C$6,'6. Ventas'!$D$8:$D$407,$B21) -> 1320 | F21: =SUMIFS('6. Ventas'!$L$8:$L$407,'6. Ventas'!$A$8:$A$407,">="&$C$5,'6. Ventas'!$A$8:$A$407,"<"&$C$6,'6. Ventas'!$D$8:$D$407,$B21) -> 631.57576
B22: Cafetería / restaurante | C22: =SUMIFS('6. Ventas'!$E$8:$E$407,'6. Ventas'!$A$8:$A$407,">="&$C$5,'6. Ventas'!$A$8:$A$407,"<"&$C$6,'6. Ventas'!$D$8:$D$407,$B22) -> 0 | E22: =SUMIFS('6. Ventas'!$G$8:$G$407,'6. Ventas'!$A$8:$A$407,">="&$C$5,'6. Ventas'!$A$8:$A$407,"<"&$C$6,'6. Ventas'!$D$8:$D$407,$B22) -> 0 | F22: =SUMIFS('6. Ventas'!$L$8:$L$407,'6. Ventas'!$A$8:$A$407,">="&$C$5,'6. Ventas'!$A$8:$A$407,"<"&$C$6,'6. Ventas'!$D$8:$D$407,$B22) -> 0
B23: Mayoreo / suscripción | C23: =SUMIFS('6. Ventas'!$E$8:$E$407,'6. Ventas'!$A$8:$A$407,">="&$C$5,'6. Ventas'!$A$8:$A$407,"<"&$C$6,'6. Ventas'!$D$8:$D$407,$B23) -> 0 | E23: =SUMIFS('6. Ventas'!$G$8:$G$407,'6. Ventas'!$A$8:$A$407,">="&$C$5,'6. Ventas'!$A$8:$A$407,"<"&$C$6,'6. Ventas'!$D$8:$D$407,$B23) -> 0 | F23: =SUMIFS('6. Ventas'!$L$8:$L$407,'6. Ventas'!$A$8:$A$407,">="&$C$5,'6. Ventas'!$A$8:$A$407,"<"&$C$6,'6. Ventas'!$D$8:$D$407,$B23) -> 0
B24: Taller | C24: =SUMIFS('6. Ventas'!$E$8:$E$407,'6. Ventas'!$A$8:$A$407,">="&$C$5,'6. Ventas'!$A$8:$A$407,"<"&$C$6,'6. Ventas'!$D$8:$D$407,$B24) -> 0 | E24: =SUMIFS('6. Ventas'!$G$8:$G$407,'6. Ventas'!$A$8:$A$407,">="&$C$5,'6. Ventas'!$A$8:$A$407,"<"&$C$6,'6. Ventas'!$D$8:$D$407,$B24) -> 0 | F24: =SUMIFS('6. Ventas'!$L$8:$L$407,'6. Ventas'!$A$8:$A$407,">="&$C$5,'6. Ventas'!$A$8:$A$407,"<"&$C$6,'6. Ventas'!$D$8:$D$407,$B24) -> 0
B25: Venta en línea | C25: =SUMIFS('6. Ventas'!$E$8:$E$407,'6. Ventas'!$A$8:$A$407,">="&$C$5,'6. Ventas'!$A$8:$A$407,"<"&$C$6,'6. Ventas'!$D$8:$D$407,$B25) -> 6 | E25: =SUMIFS('6. Ventas'!$G$8:$G$407,'6. Ventas'!$A$8:$A$407,">="&$C$5,'6. Ventas'!$A$8:$A$407,"<"&$C$6,'6. Ventas'!$D$8:$D$407,$B25) -> 570 | F25: =SUMIFS('6. Ventas'!$L$8:$L$407,'6. Ventas'!$A$8:$A$407,">="&$C$5,'6. Ventas'!$A$8:$A$407,"<"&$C$6,'6. Ventas'!$D$8:$D$407,$B25) -> 99.960606
B28: DESEMPEÑO POR RECETA (usa el filtro para ordenar)
A29: Nº | B29: Receta | C29: Roles | E29: Ingreso | F29: Utilidad neta
A30: 1 | B30: Rol de Canela Clásico con Glaseado de Vainilla de Papantla | C30: =SUMIFS('6. Ventas'!$E$8:$E$407,'6. Ventas'!$A$8:$A$407,">="&$C$5,'6. Ventas'!$A$8:$A$407,"<"&$C$6,'6. Ventas'!$B$8:$B$407,$A30) -> 8 | E30: =SUMIFS('6. Ventas'!$G$8:$G$407,'6. Ventas'!$A$8:$A$407,">="&$C$5,'6. Ventas'!$A$8:$A$407,"<"&$C$6,'6. Ventas'!$B$8:$B$407,$A30) -> 600 | F30: =SUMIFS('6. Ventas'!$L$8:$L$407,'6. Ventas'!$A$8:$A$407,">="&$C$5,'6. Ventas'!$A$8:$A$407,"<"&$C$6,'6. Ventas'!$B$8:$B$407,$A30) -> 188.88838
A31: 2 | B31: Rol de Doble Chocolate y Cocoa Alcalina | C31: =SUMIFS('6. Ventas'!$E$8:$E$407,'6. Ventas'!$A$8:$A$407,">="&$C$5,'6. Ventas'!$A$8:$A$407,"<"&$C$6,'6. Ventas'!$B$8:$B$407,$A31) -> 0 | E31: =SUMIFS('6. Ventas'!$G$8:$G$407,'6. Ventas'!$A$8:$A$407,">="&$C$5,'6. Ventas'!$A$8:$A$407,"<"&$C$6,'6. Ventas'!$B$8:$B$407,$A31) -> 0 | F31: =SUMIFS('6. Ventas'!$L$8:$L$407,'6. Ventas'!$A$8:$A$407,">="&$C$5,'6. Ventas'!$A$8:$A$407,"<"&$C$6,'6. Ventas'!$B$8:$B$407,$A31) -> 0
A32: 3 | B32: Rol de Nuez Pecana y Caramelo Salado | C32: =SUMIFS('6. Ventas'!$E$8:$E$407,'6. Ventas'!$A$8:$A$407,">="&$C$5,'6. Ventas'!$A$8:$A$407,"<"&$C$6,'6. Ventas'!$B$8:$B$407,$A32) -> 0 | E32: =SUMIFS('6. Ventas'!$G$8:$G$407,'6. Ventas'!$A$8:$A$407,">="&$C$5,'6. Ventas'!$A$8:$A$407,"<"&$C$6,'6. Ventas'!$B$8:$B$407,$A32) -> 0 | F32: =SUMIFS('6. Ventas'!$L$8:$L$407,'6. Ventas'!$A$8:$A$407,">="&$C$5,'6. Ventas'!$A$8:$A$407,"<"&$C$6,'6. Ventas'!$B$8:$B$407,$A32) -> 0
A33: 4 | B33: Rol de Manzana Canela y Streusel Crujiente | C33: =SUMIFS('6. Ventas'!$E$8:$E$407,'6. Ventas'!$A$8:$A$407,">="&$C$5,'6. Ventas'!$A$8:$A$407,"<"&$C$6,'6. Ventas'!$B$8:$B$407,$A33) -> 0 | E33: =SUMIFS('6. Ventas'!$G$8:$G$407,'6. Ventas'!$A$8:$A$407,">="&$C$5,'6. Ventas'!$A$8:$A$407,"<"&$C$6,'6. Ventas'!$B$8:$B$407,$A33) -> 0 | F33: =SUMIFS('6. Ventas'!$L$8:$L$407,'6. Ventas'!$A$8:$A$407,">="&$C$5,'6. Ventas'!$A$8:$A$407,"<"&$C$6,'6. Ventas'!$B$8:$B$407,$A33) -> 0
A34: 5 | B34: Rol de Frutos Rojos y Queso Crema | C34: =SUMIFS('6. Ventas'!$E$8:$E$407,'6. Ventas'!$A$8:$A$407,">="&$C$5,'6. Ventas'!$A$8:$A$407,"<"&$C$6,'6. Ventas'!$B$8:$B$407,$A34) -> 0 | E34: =SUMIFS('6. Ventas'!$G$8:$G$407,'6. Ventas'!$A$8:$A$407,">="&$C$5,'6. Ventas'!$A$8:$A$407,"<"&$C$6,'6. Ventas'!$B$8:$B$407,$A34) -> 0 | F34: =SUMIFS('6. Ventas'!$L$8:$L$407,'6. Ventas'!$A$8:$A$407,">="&$C$5,'6. Ventas'!$A$8:$A$407,"<"&$C$6,'6. Ventas'!$B$8:$B$407,$A34) -> 0
A35: 6 | B35: Rol de Almendra y Frangipane Clásico | C35: =SUMIFS('6. Ventas'!$E$8:$E$407,'6. Ventas'!$A$8:$A$407,">="&$C$5,'6. Ventas'!$A$8:$A$407,"<"&$C$6,'6. Ventas'!$B$8:$B$407,$A35) -> 0 | E35: =SUMIFS('6. Ventas'!$G$8:$G$407,'6. Ventas'!$A$8:$A$407,">="&$C$5,'6. Ventas'!$A$8:$A$407,"<"&$C$6,'6. Ventas'!$B$8:$B$407,$A35) -> 0 | F35: =SUMIFS('6. Ventas'!$L$8:$L$407,'6. Ventas'!$A$8:$A$407,">="&$C$5,'6. Ventas'!$A$8:$A$407,"<"&$C$6,'6. Ventas'!$B$8:$B$407,$A35) -> 0
A36: 7 | B36: Rol de Limón y Semillas de Amapola | C36: =SUMIFS('6. Ventas'!$E$8:$E$407,'6. Ventas'!$A$8:$A$407,">="&$C$5,'6. Ventas'!$A$8:$A$407,"<"&$C$6,'6. Ventas'!$B$8:$B$407,$A36) -> 0 | E36: =SUMIFS('6. Ventas'!$G$8:$G$407,'6. Ventas'!$A$8:$A$407,">="&$C$5,'6. Ventas'!$A$8:$A$407,"<"&$C$6,'6. Ventas'!$B$8:$B$407,$A36) -> 0 | F36: =SUMIFS('6. Ventas'!$L$8:$L$407,'6. Ventas'!$A$8:$A$407,">="&$C$5,'6. Ventas'!$A$8:$A$407,"<"&$C$6,'6. Ventas'!$B$8:$B$407,$A36) -> 0
A37: 8 | B37: Rol de Zanahoria (Estilo Carrot Cake) | C37: =SUMIFS('6. Ventas'!$E$8:$E$407,'6. Ventas'!$A$8:$A$407,">="&$C$5,'6. Ventas'!$A$8:$A$407,"<"&$C$6,'6. Ventas'!$B$8:$B$407,$A37) -> 0 | E37: =SUMIFS('6. Ventas'!$G$8:$G$407,'6. Ventas'!$A$8:$A$407,">="&$C$5,'6. Ventas'!$A$8:$A$407,"<"&$C$6,'6. Ventas'!$B$8:$B$407,$A37) -> 0 | F37: =SUMIFS('6. Ventas'!$L$8:$L$407,'6. Ventas'!$A$8:$A$407,">="&$C$5,'6. Ventas'!$A$8:$A$407,"<"&$C$6,'6. Ventas'!$B$8:$B$407,$A37) -> 0
A38: 9 | B38: Rol de Dulce de Leche y Nuez Macadamia | C38: =SUMIFS('6. Ventas'!$E$8:$E$407,'6. Ventas'!$A$8:$A$407,">="&$C$5,'6. Ventas'!$A$8:$A$407,"<"&$C$6,'6. Ventas'!$B$8:$B$407,$A38) -> 0 | E38: =SUMIFS('6. Ventas'!$G$8:$G$407,'6. Ventas'!$A$8:$A$407,">="&$C$5,'6. Ventas'!$A$8:$A$407,"<"&$C$6,'6. Ventas'!$B$8:$B$407,$A38) -> 0 | F38: =SUMIFS('6. Ventas'!$L$8:$L$407,'6. Ventas'!$A$8:$A$407,">="&$C$5,'6. Ventas'!$A$8:$A$407,"<"&$C$6,'6. Ventas'!$B$8:$B$407,$A38) -> 0
A39: 10 | B39: Rol de Plátano Caramelizado y Nuez de Castilla | C39: =SUMIFS('6. Ventas'!$E$8:$E$407,'6. Ventas'!$A$8:$A$407,">="&$C$5,'6. Ventas'!$A$8:$A$407,"<"&$C$6,'6. Ventas'!$B$8:$B$407,$A39) -> 0 | E39: =SUMIFS('6. Ventas'!$G$8:$G$407,'6. Ventas'!$A$8:$A$407,">="&$C$5,'6. Ventas'!$A$8:$A$407,"<"&$C$6,'6. Ventas'!$B$8:$B$407,$A39) -> 0 | F39: =SUMIFS('6. Ventas'!$L$8:$L$407,'6. Ventas'!$A$8:$A$407,">="&$C$5,'6. Ventas'!$A$8:$A$407,"<"&$C$6,'6. Ventas'!$B$8:$B$407,$A39) -> 0
A40: 11 | B40: Rol Volcán de Crema de Avellana (Estilo Nutella) | C40: =SUMIFS('6. Ventas'!$E$8:$E$407,'6. Ventas'!$A$8:$A$407,">="&$C$5,'6. Ventas'!$A$8:$A$407,"<"&$C$6,'6. Ventas'!$B$8:$B$407,$A40) -> 12 | E40: =SUMIFS('6. Ventas'!$G$8:$G$407,'6. Ventas'!$A$8:$A$407,">="&$C$5,'6. Ventas'!$A$8:$A$407,"<"&$C$6,'6. Ventas'!$B$8:$B$407,$A40) -> 1320 | F40: =SUMIFS('6. Ventas'!$L$8:$L$407,'6. Ventas'!$A$8:$A$407,">="&$C$5,'6. Ventas'!$A$8:$A$407,"<"&$C$6,'6. Ventas'!$B$8:$B$407,$A40) -> 631.57576
A41: 12 | B41: Rol Volcán de Pistache y Chocolate Blanco | C41: =SUMIFS('6. Ventas'!$E$8:$E$407,'6. Ventas'!$A$8:$A$407,">="&$C$5,'6. Ventas'!$A$8:$A$407,"<"&$C$6,'6. Ventas'!$B$8:$B$407,$A41) -> 0 | E41: =SUMIFS('6. Ventas'!$G$8:$G$407,'6. Ventas'!$A$8:$A$407,">="&$C$5,'6. Ventas'!$A$8:$A$407,"<"&$C$6,'6. Ventas'!$B$8:$B$407,$A41) -> 0 | F41: =SUMIFS('6. Ventas'!$L$8:$L$407,'6. Ventas'!$A$8:$A$407,">="&$C$5,'6. Ventas'!$A$8:$A$407,"<"&$C$6,'6. Ventas'!$B$8:$B$407,$A41) -> 0
... A80: 51 | B80: Rol de Earl Grey y Lavanda | C80: =SUMIFS('6. Ventas'!$E$8:$E$407,'6. Ventas'!$A$8:$A$407,">="&$C$5,'6. Ventas'!$A$8:$A$407,"<"&$C$6,'6. Ventas'!$B$8:$B$407,$A80) -> 0 | E80: =SUMIFS('6. Ventas'!$G$8:$G$407,'6. Ventas'!$A$8:$A$407,">="&$C$5,'6. Ventas'!$A$8:$A$407,"<"&$C$6,'6. Ventas'!$B$8:$B$407,$A80) -> 0 | F80: =SUMIFS('6. Ventas'!$L$8:$L$407,'6. Ventas'!$A$8:$A$407,">="&$C$5,'6. Ventas'!$A$8:$A$407,"<"&$C$6,'6. Ventas'!$B$8:$B$407,$A80) -> 0
