Workbook

Sheet LÉEME
A1: Tacos de Canasta · Del Sudado Tradicional a la Canasta de Autor
A2: Anexo 1 · Costeo, merma y precios · Endulcora · Estudio Gastronómico · En colaboración con Levent
A4: • | B4: Qué es: Hoja de costeo del eBook «Tacos de Canasta». Calcula el costo real de las 50 recetas y su precio por canal con tus propios precios.
A5: • | B5: Cómo se usa: 1) Insumos: captura presentación y precio que tú pagas. 2) Mi negocio: gastos fijos, sueldo, horas, merma y márgenes. 3) Recetas y precios: revisa costos y precios (se recalculan solos). 4) Registra lotes en Producción y ventas en Ventas. 5) Revisa el Tablero cada semana.
A6: • | B6: Celdas amarillas: Son las únicas que debes editar. Todo lo demás es fórmula: si la borras, se rompe el cálculo.
A7: • | B7: Modelo de costeo: Costo por unidad = Precio ÷ Presentación · Insumos del lote = Σ(cantidad × costo unitario) + aceite colorado · Insumos por pieza = lote ÷ piezas · Costo base = insumos + empaque + energía + mano de obra + gastos fijos · Costo total = Costo base ÷ (1 − merma) (se DIVIDE, no se suma) · Precio = Costo total ÷ (1 − margen), al peso siguiente.
A8: • | B8: Hojas: Insumos (catálogo editable) · Bases madre (9 aceites colorados y 6 guisados madre) · Ingredientes (cada línea del recetario normalizada, con el texto original del chef) · Mi negocio (supuestos) · Recetas y precios (hoja principal) · Producción (bitácora de lotes y merma) · Ventas (bitácora) · Tablero (resumen).
A9: • | B9: Unidades: Recetas 1–45: por taco (lote de 50 tacos, 25 g de guisado + 20 g de tortilla). Recetas 46–50 (salsas y deeps): por frasco de 250 g.
A10: • | B10: Equivalencias: Las piezas del recetario se convirtieron a gramos (diente de ajo 4 g, chile guajillo 10 g, ancho 15 g, pasilla 12 g, morita 5 g, laurel 0.3 g, tortilla 20 g, manteca 1 ml ≈ 0.92 g). Ver Anexo A del libro. Si tus piezas pesan distinto, corrige la cantidad en Ingredientes.
A11: • | B11: Advertencia: Los precios cargados son de referencia (mercado CDMX 2026), no cotizaciones. Los resultados son ilustrativos hasta que captures tus precios reales. No se promete ningún ingreso.
A12: • | B12: Créditos: Contenido y recetas: Chef Luis Alfonso Jiménez Cárdenas · Edición y costeo: Manuel Ramiro Justo Guzmán · Endulcora · Estudio Gastronómico, en colaboración con Levent · WhatsApp 56 6527 1901. Uso personal del comprador; prohibida su reventa o redistribución.
B14: Celda de ejemplo que sí puedes editar → | C14: 100

Sheet Insumos
A1: Insumos
A2: Captura la presentación que compras y lo que pagas. Precios de referencia CDMX 2026 (no son cotizaciones).
A4: ID | B4: Categoría | C4: Insumo | D4: Unidad | E4: Presentación | F4: Precio pagado | G4: Costo por unidad | H4: Usos | I4: Proveedor
A5: I-001 | B5: Maíz y tortilla | C5: Tortilla taquera de nixtamal (11 cm) | D5: g | E5: 1000 | F5: 30 | G5: =IFERROR(F5/E5,0) -> 0.03 | H5: =COUNTIF(Ingredientes!$D:$D,C5)+COUNTIF('Bases madre'!$C:$C,C5) -> 45
A6: I-002 | B6: Grasas | C6: Manteca de cerdo | D6: g | E6: 1000 | F6: 70 | G6: =IFERROR(F6/E6,0) -> 0.07 | H6: =COUNTIF(Ingredientes!$D:$D,C6)+COUNTIF('Bases madre'!$C:$C,C6) -> 37
A7: I-003 | B7: Grasas | C7: Aceite de maíz | D7: ml | E7: 1000 | F7: 48 | G7: =IFERROR(F7/E7,0) -> 0.048 | H7: =COUNTIF(Ingredientes!$D:$D,C7)+COUNTIF('Bases madre'!$C:$C,C7) -> 20
A8: I-004 | B8: Grasas | C8: Mantequilla sin sal | D8: g | E8: 1000 | F8: 330 | G8: =IFERROR(F8/E8,0) -> 0.33 | H8: =COUNTIF(Ingredientes!$D:$D,C8)+COUNTIF('Bases madre'!$C:$C,C8) -> 1
A9: I-005 | B9: Grasas | C9: Ghee (mantequilla clarificada) | D9: g | E9: 400 | F9: 190 | G9: =IFERROR(F9/E9,0) -> 0.475 | H9: =COUNTIF(Ingredientes!$D:$D,C9)+COUNTIF('Bases madre'!$C:$C,C9) -> 1
A10: I-006 | B10: Grasas | C10: Grasa de pato | D10: g | E10: 1000 | F10: 480 | G10: =IFERROR(F10/E10,0) -> 0.48 | H10: =COUNTIF(Ingredientes!$D:$D,C10)+COUNTIF('Bases madre'!$C:$C,C10) -> 1
A11: I-007 | B11: Cerdo | C11: Chicharrón prensado | D11: g | E11: 1000 | F11: 190 | G11: =IFERROR(F11/E11,0) -> 0.19 | H11: =COUNTIF(Ingredientes!$D:$D,C11)+COUNTIF('Bases madre'!$C:$C,C11) -> 2
A12: I-008 | B12: Cerdo | C12: Chicharrón de cerdo duro | D12: g | E12: 1000 | F12: 220 | G12: =IFERROR(F12/E12,0) -> 0.22 | H12: =COUNTIF(Ingredientes!$D:$D,C12)+COUNTIF('Bases madre'!$C:$C,C12) -> 2
A13: I-009 | B13: Cerdo | C13: Chicharrón carnoso norteño | D13: g | E13: 1000 | F13: 260 | G13: =IFERROR(F13/E13,0) -> 0.26 | H13: =COUNTIF(Ingredientes!$D:$D,C13)+COUNTIF('Bases madre'!$C:$C,C13) -> 1
A14: I-010 | B14: Cerdo | C14: Espaldilla de cerdo | D14: g | E14: 1000 | F14: 125 | G14: =IFERROR(F14/E14,0) -> 0.125 | H14: =COUNTIF(Ingredientes!$D:$D,C14)+COUNTIF('Bases madre'!$C:$C,C14) -> 4
A15: I-011 | B15: Cerdo | C15: Pierna de cerdo | D15: g | E15: 1000 | F15: 130 | G15: =IFERROR(F15/E15,0) -> 0.13 | H15: =COUNTIF(Ingredientes!$D:$D,C15)+COUNTIF('Bases madre'!$C:$C,C15) -> 3
A16: I-012 | B16: Cerdo | C16: Lomo de cerdo | D16: g | E16: 1000 | F16: 150 | G16: =IFERROR(F16/E16,0) -> 0.15 | H16: =COUNTIF(Ingredientes!$D:$D,C16)+COUNTIF('Bases madre'!$C:$C,C16) -> 1
... A108: I-104 | B108: Líquidos | C108: Agua purificada / caldo de cocción | D108: ml | E108: 20000 | F108: 40 | G108: =IFERROR(F108/E108,0) -> 0.002 | H108: =COUNTIF(Ingredientes!$D:$D,C108)+COUNTIF('Bases madre'!$C:$C,C108) -> 15

Sheet Bases madre
A1: Bases madre
A2: Nueve aceites colorados (fórmulas del chef) y seis guisados madre (clasificación de la edición). Capítulo 3 del libro.
A4: Código | B4: Aceite colorado | C4: Rendimiento (ml de grasa) | D4: Costo del lote | E4: Costo por ml | F4: Costo por taco (lote de 50) | G4: Recetas que lo usan | H4: Recetas
A5: AC-1 | B5: Aceite colorado de canasta (fórmula base) | C5: 250 | D5: =SUMIF($A$30:$A$87,A5,$G$30:$G$87) -> 29.82 | E5: =IFERROR(D5/C5,0) -> 0.11928 | F5: =D5/50 -> 0.5964 | G5: =COUNTIF('Recetas y precios'!$E:$E,A5) -> 5 | H5: 1–5
A6: AC-2 | B6: Con infusión de ajo y orégano | C6: 300 | D6: =SUMIF($A$30:$A$87,A6,$G$30:$G$87) -> 39.48 | E6: =IFERROR(D6/C6,0) -> 0.1316 | F6: =D6/50 -> 0.7896 | G6: =COUNTIF('Recetas y precios'!$E:$E,A6) -> 5 | H6: 6–10
A7: AC-3 | B7: Con cebolla cristalizada y laurel | C7: 250 | D7: =SUMIF($A$30:$A$87,A7,$G$30:$G$87) -> 25.96 | E7: =IFERROR(D7/C7,0) -> 0.10384 | F7: =D7/50 -> 0.5192 | G7: =COUNTIF('Recetas y precios'!$E:$E,A7) -> 5 | H7: 11–15
A8: AC-4 | B8: Con chile ancho y comino | C8: 300 | D8: =SUMIF($A$30:$A$87,A8,$G$30:$G$87) -> 36.58 | E8: =IFERROR(D8/C8,0) -> 0.12193333 | F8: =D8/50 -> 0.7316 | G8: =COUNTIF('Recetas y precios'!$E:$E,A8) -> 5 | H8: 16–20
A9: AC-5 | B9: Con chile morita y cebolla asada | C9: 300 | D9: =SUMIF($A$30:$A$87,A9,$G$30:$G$87) -> 35.22 | E9: =IFERROR(D9/C9,0) -> 0.1174 | F9: =D9/50 -> 0.7044 | G9: =COUNTIF('Recetas y precios'!$E:$E,A9) -> 5 | H9: 21–25
A10: AC-6 | B10: Con chile cascabel y pimienta gorda | C10: 300 | D10: =SUMIF($A$30:$A$87,A10,$G$30:$G$87) -> 35.77 | E10: =IFERROR(D10/C10,0) -> 0.11923333 | F10: =D10/50 -> 0.7154 | G10: =COUNTIF('Recetas y precios'!$E:$E,A10) -> 5 | H10: 26–30
A11: AC-7 | B11: Con chile pasilla, ajo y hoja de aguacate | C11: 300 | D11: =SUMIF($A$30:$A$87,A11,$G$30:$G$87) -> 37.68 | E11: =IFERROR(D11/C11,0) -> 0.1256 | F11: =D11/50 -> 0.7536 | G11: =COUNTIF('Recetas y precios'!$E:$E,A11) -> 5 | H11: 31–35
A12: AC-8 | B12: Con chile ancho, ajo y canela | C12: 300 | D12: =SUMIF($A$30:$A$87,A12,$G$30:$G$87) -> 44.29 | E12: =IFERROR(D12/C12,0) -> 0.14763333 | F12: =D12/50 -> 0.8858 | G12: =COUNTIF('Recetas y precios'!$E:$E,A12) -> 5 | H12: 36–40
A13: AC-9 | B13: Con chipotle meco y cáscara de mandarina | C13: 300 | D13: =SUMIF($A$30:$A$87,A13,$G$30:$G$87) -> 35.7 | E13: =IFERROR(D13/C13,0) -> 0.119 | F13: =D13/50 -> 0.714 | G13: =COUNTIF('Recetas y precios'!$E:$E,A13) -> 5 | H13: 41–45
A16: Código | B16: Guisado madre | C16: Clave de control de agua | D16: Nº recetas | F16: Insumos promedio por pieza
A17: G-1 | B17: Pasta de almidón | C17: Papa o frijol trabajados hasta formar una masa compacta que rueda en bloque. | D17: =COUNTIF('Recetas y precios'!$D:$D,A17) -> 8 | F17: =IFERROR(AVERAGEIF('Recetas y precios'!$D$5:$D$54,A17,'Recetas y precios'!$K$5:$K$54),0) -> 2.464525
A18: G-2 | B18: Adobo rojo de chiles secos | C18: Chiles secos hidratados, licuados, «chillados» en grasa y reducidos hasta película. | D18: =COUNTIF('Recetas y precios'!$D:$D,A18) -> 12 | F18: =IFERROR(AVERAGEIF('Recetas y precios'!$D$5:$D$54,A18,'Recetas y precios'!$K$5:$K$54),0) -> 5.669425
A19: G-3 | B19: Verde de tomatillo y pepita | C19: Tomatillo cocido o asado sin reventar; la pectina (o la pepita) amarra el guisado. | D19: =COUNTIF('Recetas y precios'!$D:$D,A19) -> 4 | F19: =IFERROR(AVERAGEIF('Recetas y precios'!$D$5:$D$54,A19,'Recetas y precios'!$K$5:$K$54),0) -> 4.6398
A20: G-4 | B20: Recaudo de jitomate | C20: Jitomate asado o crudo reducido a pasta que barniza carne o verdura. | D20: =COUNTIF('Recetas y precios'!$D:$D,A20) -> 9 | F20: =IFERROR(AVERAGEIF('Recetas y precios'!$D$5:$D$54,A20,'Recetas y precios'!$K$5:$K$54),0) -> 5.2736096
A21: G-5 | B21: Salteado seco de huerta | C21: Verdura, hongo o lácteo al que se le saca el agua antes de sazonar. | D21: =COUNTIF('Recetas y precios'!$D:$D,A21) -> 6 | F21: =IFERROR(AVERAGEIF('Recetas y precios'!$D$5:$D$54,A21,'Recetas y precios'!$K$5:$K$54),0) -> 4.1529
A22: G-6 | B22: Confitado y salteado cárnico | C22: Carne sellada o confitada en su grasa, picada fina y sin salsa libre. | D22: =COUNTIF('Recetas y precios'!$D:$D,A22) -> 6 | F22: =IFERROR(AVERAGEIF('Recetas y precios'!$D$5:$D$54,A22,'Recetas y precios'!$K$5:$K$54),0) -> 6.6399039
A23: S | B23: Acompañamientos de la canasta | C23: Salsas crudas y cocidas, encurtido y deeps que viajan fuera de la canasta. | D23: =COUNTIF('Recetas y precios'!$D:$D,A23) -> 5 | F23: =IFERROR(AVERAGEIF('Recetas y precios'!$D$5:$D$54,A23,'Recetas y precios'!$K$5:$K$54),0) -> 15.683513
A24: El guisado S (acompañamientos) se costea por frasco de 250 g.
A28: Fórmulas de los aceites colorados (edita cantidades en amarillo)
A29: Código | B29: Aceite | C29: Insumo | D29: Cantidad | E29: Unidad | F29: Costo unitario | G29: Costo | H29: Texto original del chef
A30: AC-1 | B30: Aceite colorado de canasta (fórmula base) | C30: Manteca de cerdo | D30: 230 | E30: g | F30: =IFERROR(VLOOKUP(C30,Insumos!$C$5:$G$108,5,FALSE()),0) -> 0.07 | G30: =D30*F30 -> 16.1 | H30: 250 ml Manteca de cerdo pura de cazo (o 150 ml manteca + 100 ml aceite de maíz)
A31: AC-1 | B31: Aceite colorado de canasta (fórmula base) | C31: Chile guajillo | D31: 40 | E31: g | F31: =IFERROR(VLOOKUP(C31,Insumos!$C$5:$G$108,5,FALSE()),0) -> 0.24 | G31: =D31*F31 -> 9.6 | H31: 4 Chiles guajillo secos limpios troceados (sin semillas)
A32: AC-1 | B32: Aceite colorado de canasta (fórmula base) | C32: Cebolla blanca | D32: 100 | E32: g | F32: =IFERROR(VLOOKUP(C32,Insumos!$C$5:$G$108,5,FALSE()),0) -> 0.028 | G32: =D32*F32 -> 2.8 | H32: 1/2 Cebolla blanca en rodajas gruesas
A33: AC-1 | B33: Aceite colorado de canasta (fórmula base) | C33: Ajo | D33: 12 | E33: g | F33: =IFERROR(VLOOKUP(C33,Insumos!$C$5:$G$108,5,FALSE()),0) -> 0.11 | G33: =D33*F33 -> 1.32 | H33: 3 Dientes de ajo con piel aplastados
A34: AC-2 | B34: Con infusión de ajo y orégano | C34: Manteca de cerdo | D34: 184 | E34: g | F34: =IFERROR(VLOOKUP(C34,Insumos!$C$5:$G$108,5,FALSE()),0) -> 0.07 | G34: =D34*F34 -> 12.88 | H34: 200 ml Manteca de cerdo limpia
A35: AC-2 | B35: Con infusión de ajo y orégano | C35: Aceite de maíz | D35: 100 | E35: ml | F35: =IFERROR(VLOOKUP(C35,Insumos!$C$5:$G$108,5,FALSE()),0) -> 0.048 | G35: =D35*F35 -> 4.8 | H35: 100 ml Aceite de maíz
A36: AC-2 | B36: Con infusión de ajo y orégano | C36: Chile guajillo | D36: 50 | E36: g | F36: =IFERROR(VLOOKUP(C36,Insumos!$C$5:$G$108,5,FALSE()),0) -> 0.24 | G36: =D36*F36 -> 12 | H36: 5 Chiles guajillo secos limpios troceados
A37: AC-2 | B37: Con infusión de ajo y orégano | C37: Chile ancho | D37: 15 | E37: g | F37: =IFERROR(VLOOKUP(C37,Insumos!$C$5:$G$108,5,FALSE()),0) -> 0.28 | G37: =D37*F37 -> 4.2 | H37: 1 Chile ancho limpio
A38: AC-2 | B38: Con infusión de ajo y orégano | C38: Ajo | D38: 20 | E38: g | F38: =IFERROR(VLOOKUP(C38,Insumos!$C$5:$G$108,5,FALSE()),0) -> 0.11 | G38: =D38*F38 -> 2.2 | H38: 5 Dientes de ajo machacados con cáscara
A39: AC-2 | B39: Con infusión de ajo y orégano | C39: Cebolla blanca | D39: 100 | E39: g | F39: =IFERROR(VLOOKUP(C39,Insumos!$C$5:$G$108,5,FALSE()),0) -> 0.028 | G39: =D39*F39 -> 2.8 | H39: 1/2 Cebolla en aros gruesos
A40: AC-2 | B40: Con infusión de ajo y orégano | C40: Orégano seco | D40: 2 | E40: g | F40: =IFERROR(VLOOKUP(C40,Insumos!$C$5:$G$108,5,FALSE()),0) -> 0.3 | G40: =D40*F40 -> 0.6 | H40: 2 g Orégano seco entero
A41: AC-3 | B41: Con cebolla cristalizada y laurel | C41: Aceite de maíz | D41: 250 | E41: ml | F41: =IFERROR(VLOOKUP(C41,Insumos!$C$5:$G$108,5,FALSE()),0) -> 0.048 | G41: =D41*F41 -> 12 | H41: 250 ml Aceite de maíz puro (o 150 ml aceite de maíz + 100 ml manteca de cerdo)
... A87: AC-9 | B87: Con chipotle meco y cáscara de mandarina | C87: Cáscara de naranja o mandarina | D87: 2 | E87: g | F87: =IFERROR(VLOOKUP(C87,Insumos!$C$5:$G$108,5,FALSE()),0) -> 0.03 | G87: =D87*F87 -> 0.06 | H87: 1 Tira delgada de piel de mandarina o naranja criolla sin albedo blanco (2 g)

Sheet Ingredientes
A1: Ingredientes
A2: Cada línea del recetario normalizada a un insumo del catálogo, con el texto original del chef al lado para auditarla.
A4: Nº | B4: Receta | C4: Texto original del chef | D4: Insumo | E4: Cantidad | F4: Unidad | G4: Costo unitario | H4: Costo
A5: 1 | B5: Papa Machacada Campesina con Cebolla Confitada al Comal | C5: 1,200 g Papa blanca (Alfa o Russet) lavada y con cáscara para cocción | D5: Papa blanca | E5: 1200 | F5: g | G5: =IFERROR(VLOOKUP(D5,Insumos!$C$5:$G$108,5,FALSE()),0) -> 0.03 | H5: =E5*G5 -> 36
A6: 1 | B6: Papa Machacada Campesina con Cebolla Confitada al Comal | C6: 120 g Manteca de cerdo pura de cazo (aporta sabor láctico y sella el almidón) | D6: Manteca de cerdo | E6: 120 | F6: g | G6: =IFERROR(VLOOKUP(D6,Insumos!$C$5:$G$108,5,FALSE()),0) -> 0.07 | H6: =E6*G6 -> 8.4
A7: 1 | B7: Papa Machacada Campesina con Cebolla Confitada al Comal | C7: 250 g Cebolla blanca picada en brunoise fina | D7: Cebolla blanca | E7: 250 | F7: g | G7: =IFERROR(VLOOKUP(D7,Insumos!$C$5:$G$108,5,FALSE()),0) -> 0.028 | H7: =E7*G7 -> 7
A8: 1 | B8: Papa Machacada Campesina con Cebolla Confitada al Comal | C8: 4 Dientes de ajo frescos picados finamente (15 g) | D8: Ajo | E8: 15 | F8: g | G8: =IFERROR(VLOOKUP(D8,Insumos!$C$5:$G$108,5,FALSE()),0) -> 0.11 | H8: =E8*G8 -> 1.65
A9: 1 | B9: Papa Machacada Campesina con Cebolla Confitada al Comal | C9: 18 g Sal de Colima fina | D9: Sal de mar fina (Colima) | E9: 18 | F9: g | G9: =IFERROR(VLOOKUP(D9,Insumos!$C$5:$G$108,5,FALSE()),0) -> 0.035 | H9: =E9*G9 -> 0.63
A10: 1 | B10: Papa Machacada Campesina con Cebolla Confitada al Comal | C10: 3 g Pimienta negra recién molida | D10: Pimienta negra | E10: 3 | F10: g | G10: =IFERROR(VLOOKUP(D10,Insumos!$C$5:$G$108,5,FALSE()),0) -> 0.45 | H10: =E10*G10 -> 1.35
A11: 1 | B11: Papa Machacada Campesina con Cebolla Confitada al Comal | C11: 2 g Comino entero recién molido en molcajete | D11: Comino | E11: 2 | F11: g | G11: =IFERROR(VLOOKUP(D11,Insumos!$C$5:$G$108,5,FALSE()),0) -> 0.38 | H11: =E11*G11 -> 0.76
A12: 1 | B12: Papa Machacada Campesina con Cebolla Confitada al Comal | C12: 50 Tortillas taqueras de maíz nixtamalizado (11 cm, 20 g c/u, temperatura de salida a 65°C) | D12: Tortilla taquera de nixtamal (11 cm) | E12: 1000 | F12: g | G12: =IFERROR(VLOOKUP(D12,Insumos!$C$5:$G$108,5,FALSE()),0) -> 0.03 | H12: =E12*G12 -> 30
A13: 2 | B13: Chicharrón Prensado al Guajillo y Laurel | C13: 700 g Chicharrón prensado de carnicería tradicional (en trozo, sin exceso de salitre) | D13: Chicharrón prensado | E13: 700 | F13: g | G13: =IFERROR(VLOOKUP(D13,Insumos!$C$5:$G$108,5,FALSE()),0) -> 0.19 | H13: =E13*G13 -> 133
A14: 2 | B14: Chicharrón Prensado al Guajillo y Laurel | C14: 6 Chiles guajillo secos desvenados y limpios (60 g) | D14: Chile guajillo | E14: 60 | F14: g | G14: =IFERROR(VLOOKUP(D14,Insumos!$C$5:$G$108,5,FALSE()),0) -> 0.24 | H14: =E14*G14 -> 14.4
A15: 2 | B15: Chicharrón Prensado al Guajillo y Laurel | C15: 2 Chiles anchos secos limpios (30 g, aportan dulzor y espesor) | D15: Chile ancho | E15: 30 | F15: g | G15: =IFERROR(VLOOKUP(D15,Insumos!$C$5:$G$108,5,FALSE()),0) -> 0.28 | H15: =E15*G15 -> 8.4
A16: 2 | B16: Chicharrón Prensado al Guajillo y Laurel | C16: 3 Dientes de ajo asados (12 g) | D16: Ajo | E16: 12 | F16: g | G16: =IFERROR(VLOOKUP(D16,Insumos!$C$5:$G$108,5,FALSE()),0) -> 0.11 | H16: =E16*G16 -> 1.32
... A500: 50 | B500: Deep de Chicharrón Prensado al Cilantro y Tomatillo Asado | C500: 50 ml Agua purificada | D500: Agua purificada / caldo de cocción | E500: 50 | F500: ml | G500: =IFERROR(VLOOKUP(D500,Insumos!$C$5:$G$108,5,FALSE()),0) -> 0.002 | H500: =E500*G500 -> 0.1

Sheet Mi negocio
A1: Mi negocio
A2: Los supuestos que mueven todo. Si estos números están mal, todos tus precios están mal.
B4: Gasto fijo mensual | C4: Monto | D4: Nota
B5: Renta de la cocina de producción | C5: 4000
B6: Luz y agua | C6: 650
B7: Teléfono e internet | C7: 400
B8: Publicidad y redes | C8: 800
B9: Cuotas, permisos y uso de piso | C9: 800
B10: Mantenimiento de bicicleta o transporte | C10: 600
B11: Limpieza y consumibles generales | C11: 500
B12: Depreciación de equipo (canastas, ollas, termómetros) | C12: 650
B13: Otros gastos fijos | C13: 600
B17: Total de gastos fijos | C17: =SUM(C5:C16) -> 9000
B19: Tacos (piezas) producidos al mes | C19: 6000 | D19: ≈ 250 tacos al día, 24 días.
B20: Gastos fijos por pieza (overhead) | C20: =IFERROR(C17/C19,0) -> 1.5 | D20: Se suma al costo de cada taco.
B21: Sueldo mensual que te pagas | C21: 15000
B22: Horas de trabajo al mes | C22: 200
B23: Costo de tu hora | C23: =IFERROR(C21/C22,0) -> 75 | D23: Mano de obra = minutos ÷ 60 × costo de la hora.
B24: % de merma por defecto | C24: 0.06 | D24: Tacos rotos, fallados o sobrantes. Compárala con tu merma real en el Tablero.
B25: Márgenes objetivo por canal
B26: Margen · Canasta en calle | C26: 0.5 | D26: Rango sugerido 45–55 %.
B27: Margen · Pedido de oficina / docena | C27: 0.6 | D27: Rango sugerido 55–65 %.
B28: Margen · Taquiza y eventos | C28: 0.66 | D28: Rango sugerido 62–70 %.
B29: Margen · Mayoreo a canasteros | C29: 0.3 | D29: Rango sugerido 25–35 %.

Sheet Recetas y precios
A1: Recetas y precios
A2: Hoja principal. Cambia un precio en Insumos y los 50 precios se recalculan solos.
A4: Nº | B4: Receta | C4: Capítulo | D4: Base | E4: Aceite | F4: Unidad de venta | G4: Piezas que rinde | H4: Aceite (ml) | I4: Costo aceite | J4: Otros insumos | K4: Insumos por pieza | L4: Empaque | M4: Energía | N4: Minutos por pieza | O4: Mano de obra | P4: Gastos fijos | Q4: Costo base | R4: Merma propia | S4: Merma aplicada | T4: COSTO TOTAL | U4: PVP calle | V4: PVP oficina | W4: PVP taquiza | X4: PVP mayoreo | Y4: Utilidad calle | Z4: Margen real calle
A5: 1 | B5: Papa Machacada Campesina con Cebolla Confitada al Comal | C5: Cap. 6 · Guisados de raíz | D5: G-1 | E5: AC-1 | F5: taco | G5: 50 | H5: 250 | I5: =IF(E5="",0,H5*VLOOKUP(E5,'Bases madre'!$A$5:$E$13,5,FALSE())) -> 29.82 | J5: =SUMIF(Ingredientes!$A$5:$A$500,A5,Ingredientes!$H$5:$H$500) -> 85.79 | K5: =IFERROR((I5+J5)/G5,0) -> 2.3122 | L5: 0.6 | M5: 0.35 | N5: 1 | O5: =N5/60*'Mi negocio'!$C$23 -> 1.25 | P5: ='Mi negocio'!$C$20 -> 1.5 | Q5: =K5+L5+M5+O5+P5 -> 6.0122 | S5: =IF(R5="",'Mi negocio'!$C$24,R5) -> 0.06 | T5: =IFERROR(Q5/(1-S5),0) -> 6.3959574 | U5: =IFERROR(CEILING(ROUND(T5/(1-'Mi negocio'!$C$26),6),1),0) -> 13 | V5: =IFERROR(CEILING(ROUND(T5/(1-'Mi negocio'!$C$27),6),1),0) -> 16 | W5: =IFERROR(CEILING(ROUND(T5/(1-'Mi negocio'!$C$28),6),1),0) -> 19 | X5: =IFERROR(CEILING(ROUND(T5/(1-'Mi negocio'!$C$29),6),1),0) -> 10 | Y5: =U5-T5 -> 6.6040426 | Z5: =IFERROR(Y5/U5,0) -> 0.50800327
A6: 2 | B6: Chicharrón Prensado al Guajillo y Laurel | C6: Cap. 6 · Guisados de raíz | D6: G-2 | E6: AC-1 | F6: taco | G6: 50 | H6: 250 | I6: =IF(E6="",0,H6*VLOOKUP(E6,'Bases madre'!$A$5:$E$13,5,FALSE())) -> 29.82 | J6: =SUMIF(Ingredientes!$A$5:$A$500,A6,Ingredientes!$H$5:$H$500) -> 193.88 | K6: =IFERROR((I6+J6)/G6,0) -> 4.474 | L6: 0.6 | M6: 0.35 | N6: 1 | O6: =N6/60*'Mi negocio'!$C$23 -> 1.25 | P6: ='Mi negocio'!$C$20 -> 1.5 | Q6: =K6+L6+M6+O6+P6 -> 8.174 | S6: =IF(R6="",'Mi negocio'!$C$24,R6) -> 0.06 | T6: =IFERROR(Q6/(1-S6),0) -> 8.6957447 | U6: =IFERROR(CEILING(ROUND(T6/(1-'Mi negocio'!$C$26),6),1),0) -> 18 | V6: =IFERROR(CEILING(ROUND(T6/(1-'Mi negocio'!$C$27),6),1),0) -> 22 | W6: =IFERROR(CEILING(ROUND(T6/(1-'Mi negocio'!$C$28),6),1),0) -> 26 | X6: =IFERROR(CEILING(ROUND(T6/(1-'Mi negocio'!$C$29),6),1),0) -> 13 | Y6: =U6-T6 -> 9.3042553 | Z6: =IFERROR(Y6/U6,0) -> 0.51690307
A7: 3 | B7: Frijoles Refritos con Hoja de Aguacate y Manteca Quemada | C7: Cap. 6 · Guisados de raíz | D7: G-1 | E7: AC-1 | F7: taco | G7: 50 | H7: 250 | I7: =IF(E7="",0,H7*VLOOKUP(E7,'Bases madre'!$A$5:$E$13,5,FALSE())) -> 29.82 | J7: =SUMIF(Ingredientes!$A$5:$A$500,A7,Ingredientes!$H$5:$H$500) -> 60.55 | K7: =IFERROR((I7+J7)/G7,0) -> 1.8074 | L7: 0.6 | M7: 0.35 | N7: 1 | O7: =N7/60*'Mi negocio'!$C$23 -> 1.25 | P7: ='Mi negocio'!$C$20 -> 1.5 | Q7: =K7+L7+M7+O7+P7 -> 5.5074 | S7: =IF(R7="",'Mi negocio'!$C$24,R7) -> 0.06 | T7: =IFERROR(Q7/(1-S7),0) -> 5.8589362 | U7: =IFERROR(CEILING(ROUND(T7/(1-'Mi negocio'!$C$26),6),1),0) -> 12 | V7: =IFERROR(CEILING(ROUND(T7/(1-'Mi negocio'!$C$27),6),1),0) -> 15 | W7: =IFERROR(CEILING(ROUND(T7/(1-'Mi negocio'!$C$28),6),1),0) -> 18 | X7: =IFERROR(CEILING(ROUND(T7/(1-'Mi negocio'!$C$29),6),1),0) -> 9 | Y7: =U7-T7 -> 6.1410638 | Z7: =IFERROR(Y7/U7,0) -> 0.51175532
A8: 4 | B8: Adobo de Cerdo Deshebrado al Chile Ancho y Comino | C8: Cap. 6 · Guisados de raíz | D8: G-2 | E8: AC-1 | F8: taco | G8: 50 | H8: 250 | I8: =IF(E8="",0,H8*VLOOKUP(E8,'Bases madre'!$A$5:$E$13,5,FALSE())) -> 29.82 | J8: =SUMIF(Ingredientes!$A$5:$A$500,A8,Ingredientes!$H$5:$H$500) -> 215.99 | K8: =IFERROR((I8+J8)/G8,0) -> 4.9162 | L8: 0.6 | M8: 0.35 | N8: 1.4 | O8: =N8/60*'Mi negocio'!$C$23 -> 1.75 | P8: ='Mi negocio'!$C$20 -> 1.5 | Q8: =K8+L8+M8+O8+P8 -> 9.1162 | S8: =IF(R8="",'Mi negocio'!$C$24,R8) -> 0.06 | T8: =IFERROR(Q8/(1-S8),0) -> 9.6980851 | U8: =IFERROR(CEILING(ROUND(T8/(1-'Mi negocio'!$C$26),6),1),0) -> 20 | V8: =IFERROR(CEILING(ROUND(T8/(1-'Mi negocio'!$C$27),6),1),0) -> 25 | W8: =IFERROR(CEILING(ROUND(T8/(1-'Mi negocio'!$C$28),6),1),0) -> 29 | X8: =IFERROR(CEILING(ROUND(T8/(1-'Mi negocio'!$C$29),6),1),0) -> 14 | Y8: =U8-T8 -> 10.301915 | Z8: =IFERROR(Y8/U8,0) -> 0.51509574
A9: 5 | B9: Picadillo Tradicional de Res con Cubos de Zanahoria y Papa | C9: Cap. 6 · Guisados de raíz | D9: G-4 | E9: AC-1 | F9: taco | G9: 50 | H9: 250 | I9: =IF(E9="",0,H9*VLOOKUP(E9,'Bases madre'!$A$5:$E$13,5,FALSE())) -> 29.82 | J9: =SUMIF(Ingredientes!$A$5:$A$500,A9,Ingredientes!$H$5:$H$500) -> 181.82 | K9: =IFERROR((I9+J9)/G9,0) -> 4.2328 | L9: 0.6 | M9: 0.35 | N9: 1.4 | O9: =N9/60*'Mi negocio'!$C$23 -> 1.75 | P9: ='Mi negocio'!$C$20 -> 1.5 | Q9: =K9+L9+M9+O9+P9 -> 8.4328 | S9: =IF(R9="",'Mi negocio'!$C$24,R9) -> 0.06 | T9: =IFERROR(Q9/(1-S9),0) -> 8.9710638 | U9: =IFERROR(CEILING(ROUND(T9/(1-'Mi negocio'!$C$26),6),1),0) -> 18 | V9: =IFERROR(CEILING(ROUND(T9/(1-'Mi negocio'!$C$27),6),1),0) -> 23 | W9: =IFERROR(CEILING(ROUND(T9/(1-'Mi negocio'!$C$28),6),1),0) -> 27 | X9: =IFERROR(CEILING(ROUND(T9/(1-'Mi negocio'!$C$29),6),1),0) -> 13 | Y9: =U9-T9 -> 9.0289362 | Z9: =IFERROR(Y9/U9,0) -> 0.50160757
A10: 6 | B10: Chicharrón en Salsa Verde Cocida con Tomatillo y Cilantro | C10: Cap. 6 · Guisados de raíz | D10: G-3 | E10: AC-2 | F10: taco | G10: 50 | H10: 300 | I10: =IF(E10="",0,H10*VLOOKUP(E10,'Bases madre'!$A$5:$E$13,5,FALSE())) -> 39.48 | J10: =SUMIF(Ingredientes!$A$5:$A$500,A10,Ingredientes!$H$5:$H$500) -> 150.21 | K10: =IFERROR((I10+J10)/G10,0) -> 3.7938 | L10: 0.6 | M10: 0.35 | N10: 1 | O10: =N10/60*'Mi negocio'!$C$23 -> 1.25 | P10: ='Mi negocio'!$C$20 -> 1.5 | Q10: =K10+L10+M10+O10+P10 -> 7.4938 | S10: =IF(R10="",'Mi negocio'!$C$24,R10) -> 0.06 | T10: =IFERROR(Q10/(1-S10),0) -> 7.9721277 | U10: =IFERROR(CEILING(ROUND(T10/(1-'Mi negocio'!$C$26),6),1),0) -> 16 | V10: =IFERROR(CEILING(ROUND(T10/(1-'Mi negocio'!$C$27),6),1),0) -> 20 | W10: =IFERROR(CEILING(ROUND(T10/(1-'Mi negocio'!$C$28),6),1),0) -> 24 | X10: =IFERROR(CEILING(ROUND(T10/(1-'Mi negocio'!$C$29),6),1),0) -> 12 | Y10: =U10-T10 -> 8.0278723 | Z10: =IFERROR(Y10/U10,0) -> 0.50174202
A11: 7 | B11: Tinga Tradicional de Pollo al Chipotle Meco y Cebolla Pluma | C11: Cap. 6 · Guisados de raíz | D11: G-4 | E11: AC-2 | F11: taco | G11: 50 | H11: 300 | I11: =IF(E11="",0,H11*VLOOKUP(E11,'Bases madre'!$A$5:$E$13,5,FALSE())) -> 39.48 | J11: =SUMIF(Ingredientes!$A$5:$A$500,A11,Ingredientes!$H$5:$H$500) -> 176.52 | K11: =IFERROR((I11+J11)/G11,0) -> 4.32 | L11: 0.6 | M11: 0.35 | N11: 1.4 | O11: =N11/60*'Mi negocio'!$C$23 -> 1.75 | P11: ='Mi negocio'!$C$20 -> 1.5 | Q11: =K11+L11+M11+O11+P11 -> 8.52 | S11: =IF(R11="",'Mi negocio'!$C$24,R11) -> 0.06 | T11: =IFERROR(Q11/(1-S11),0) -> 9.0638298 | U11: =IFERROR(CEILING(ROUND(T11/(1-'Mi negocio'!$C$26),6),1),0) -> 19 | V11: =IFERROR(CEILING(ROUND(T11/(1-'Mi negocio'!$C$27),6),1),0) -> 23 | W11: =IFERROR(CEILING(ROUND(T11/(1-'Mi negocio'!$C$28),6),1),0) -> 27 | X11: =IFERROR(CEILING(ROUND(T11/(1-'Mi negocio'!$C$29),6),1),0) -> 13 | Y11: =U11-T11 -> 9.9361702 | Z11: =IFERROR(Y11/U11,0) -> 0.52295633
A12: 8 | B12: Frijol Negro Refrito con Chorizo y Chile de Árbol Frito | C12: Cap. 6 · Guisados de raíz | D12: G-1 | E12: AC-2 | F12: taco | G12: 50 | H12: 300 | I12: =IF(E12="",0,H12*VLOOKUP(E12,'Bases madre'!$A$5:$E$13,5,FALSE())) -> 39.48 | J12: =SUMIF(Ingredientes!$A$5:$A$500,A12,Ingredientes!$H$5:$H$500) -> 94.9 | K12: =IFERROR((I12+J12)/G12,0) -> 2.6876 | L12: 0.6 | M12: 0.35 | N12: 1 | O12: =N12/60*'Mi negocio'!$C$23 -> 1.25 | P12: ='Mi negocio'!$C$20 -> 1.5 | Q12: =K12+L12+M12+O12+P12 -> 6.3876 | S12: =IF(R12="",'Mi negocio'!$C$24,R12) -> 0.06 | T12: =IFERROR(Q12/(1-S12),0) -> 6.7953191 | U12: =IFERROR(CEILING(ROUND(T12/(1-'Mi negocio'!$C$26),6),1),0) -> 14 | V12: =IFERROR(CEILING(ROUND(T12/(1-'Mi negocio'!$C$27),6),1),0) -> 17 | W12: =IFERROR(CEILING(ROUND(T12/(1-'Mi negocio'!$C$28),6),1),0) -> 20 | X12: =IFERROR(CEILING(ROUND(T12/(1-'Mi negocio'!$C$29),6),1),0) -> 10 | Y12: =U12-T12 -> 7.2046809 | Z12: =IFERROR(Y12/U12,0) -> 0.51462006
A13: 9 | B13: Alambre Tradicional de Res con Tocino, Morro y Cebolla Asada | C13: Cap. 6 · Guisados de raíz | D13: G-6 | E13: AC-2 | F13: taco | G13: 50 | H13: 300 | I13: =IF(E13="",0,H13*VLOOKUP(E13,'Bases madre'!$A$5:$E$13,5,FALSE())) -> 39.48 | J13: =SUMIF(Ingredientes!$A$5:$A$500,A13,Ingredientes!$H$5:$H$500) -> 216.30103 | K13: =IFERROR((I13+J13)/G13,0) -> 5.1156207 | L13: 0.6 | M13: 0.35 | N13: 1.4 | O13: =N13/60*'Mi negocio'!$C$23 -> 1.75 | P13: ='Mi negocio'!$C$20 -> 1.5 | Q13: =K13+L13+M13+O13+P13 -> 9.3156207 | S13: =IF(R13="",'Mi negocio'!$C$24,R13) -> 0.06 | T13: =IFERROR(Q13/(1-S13),0) -> 9.9102348 | U13: =IFERROR(CEILING(ROUND(T13/(1-'Mi negocio'!$C$26),6),1),0) -> 20 | V13: =IFERROR(CEILING(ROUND(T13/(1-'Mi negocio'!$C$27),6),1),0) -> 25 | W13: =IFERROR(CEILING(ROUND(T13/(1-'Mi negocio'!$C$28),6),1),0) -> 30 | X13: =IFERROR(CEILING(ROUND(T13/(1-'Mi negocio'!$C$29),6),1),0) -> 15 | Y13: =U13-T13 -> 10.089765 | Z13: =IFERROR(Y13/U13,0) -> 0.50448826
A14: 10 | B14: Papas con Longaniza Tradicional de Toluca y Laurel | C14: Cap. 6 · Guisados de raíz | D14: G-1 | E14: AC-2 | F14: taco | G14: 50 | H14: 300 | I14: =IF(E14="",0,H14*VLOOKUP(E14,'Bases madre'!$A$5:$E$13,5,FALSE())) -> 39.48 | J14: =SUMIF(Ingredientes!$A$5:$A$500,A14,Ingredientes!$H$5:$H$500) -> 134.46 | K14: =IFERROR((I14+J14)/G14,0) -> 3.4788 | L14: 0.6 | M14: 0.35 | N14: 1 | O14: =N14/60*'Mi negocio'!$C$23 -> 1.25 | P14: ='Mi negocio'!$C$20 -> 1.5 | Q14: =K14+L14+M14+O14+P14 -> 7.1788 | S14: =IF(R14="",'Mi negocio'!$C$24,R14) -> 0.06 | T14: =IFERROR(Q14/(1-S14),0) -> 7.6370213 | U14: =IFERROR(CEILING(ROUND(T14/(1-'Mi negocio'!$C$26),6),1),0) -> 16 | V14: =IFERROR(CEILING(ROUND(T14/(1-'Mi negocio'!$C$27),6),1),0) -> 20 | W14: =IFERROR(CEILING(ROUND(T14/(1-'Mi negocio'!$C$28),6),1),0) -> 23 | X14: =IFERROR(CEILING(ROUND(T14/(1-'Mi negocio'!$C$29),6),1),0) -> 11 | Y14: =U14-T14 -> 8.3629787 | Z14: =IFERROR(Y14/U14,0) -> 0.52268617
A15: 11 | B15: Frijol Negro Refrito con Hoja Santa Fresca (Acuyo) y Cebolla Morada | C15: Cap. 7 · Huerta, campo y frijoles | D15: G-1 | E15: AC-3 | F15: taco | G15: 50 | H15: 250 | I15: =IF(E15="",0,H15*VLOOKUP(E15,'Bases madre'!$A$5:$E$13,5,FALSE())) -> 25.96 | J15: =SUMIF(Ingredientes!$A$5:$A$500,A15,Ingredientes!$H$5:$H$500) -> 69.67 | K15: =IFERROR((I15+J15)/G15,0) -> 1.9126 | L15: 0.6 | M15: 0.35 | N15: 1 | O15: =N15/60*'Mi negocio'!$C$23 -> 1.25 | P15: ='Mi negocio'!$C$20 -> 1.5 | Q15: =K15+L15+M15+O15+P15 -> 5.6126 | S15: =IF(R15="",'Mi negocio'!$C$24,R15) -> 0.06 | T15: =IFERROR(Q15/(1-S15),0) -> 5.9708511 | U15: =IFERROR(CEILING(ROUND(T15/(1-'Mi negocio'!$C$26),6),1),0) -> 12 | V15: =IFERROR(CEILING(ROUND(T15/(1-'Mi negocio'!$C$27),6),1),0) -> 15 | W15: =IFERROR(CEILING(ROUND(T15/(1-'Mi negocio'!$C$28),6),1),0) -> 18 | X15: =IFERROR(CEILING(ROUND(T15/(1-'Mi negocio'!$C$29),6),1),0) -> 9 | Y15: =U15-T15 -> 6.0291489 | Z15: =IFERROR(Y15/U15,0) -> 0.50242908
A16: 12 | B16: Tinga de Setas al Chipotle Meco y Cebolla Caramelizada | C16: Cap. 7 · Huerta, campo y frijoles | D16: G-4 | E16: AC-3 | F16: taco | G16: 50 | H16: 250 | I16: =IF(E16="",0,H16*VLOOKUP(E16,'Bases madre'!$A$5:$E$13,5,FALSE())) -> 25.96 | J16: =SUMIF(Ingredientes!$A$5:$A$500,A16,Ingredientes!$H$5:$H$500) -> 174.52 | K16: =IFERROR((I16+J16)/G16,0) -> 4.0096 | L16: 0.6 | M16: 0.35 | N16: 1.4 | O16: =N16/60*'Mi negocio'!$C$23 -> 1.75 | P16: ='Mi negocio'!$C$20 -> 1.5 | Q16: =K16+L16+M16+O16+P16 -> 8.2096 | S16: =IF(R16="",'Mi negocio'!$C$24,R16) -> 0.06 | T16: =IFERROR(Q16/(1-S16),0) -> 8.733617 | U16: =IFERROR(CEILING(ROUND(T16/(1-'Mi negocio'!$C$26),6),1),0) -> 18 | V16: =IFERROR(CEILING(ROUND(T16/(1-'Mi negocio'!$C$27),6),1),0) -> 22 | W16: =IFERROR(CEILING(ROUND(T16/(1-'Mi negocio'!$C$28),6),1),0) -> 26 | X16: =IFERROR(CEILING(ROUND(T16/(1-'Mi negocio'!$C$29),6),1),0) -> 13 | Y16: =U16-T16 -> 9.266383 | Z16: =IFERROR(Y16/U16,0) -> 0.51479905
... A49: 45 | B49: Hongos Silvestres Salteados con Quelite Cenizo y Requesón de Rancho | C49: Cap. 10 · Contemporáneos, deeps y salsas | D49: G-5 | E49: AC-9 | F49: taco | G49: 50 | H49: 300 | I49: =IF(E49="",0,H49*VLOOKUP(E49,'Bases madre'!$A$5:$E$13,5,FALSE())) -> 35.7 | J49: =SUMIF(Ingredientes!$A$5:$A$500,A49,Ingredientes!$H$5:$H$500) -> 307.96 | K49: =IFERROR((I49+J49)/G49,0) -> 6.8732 | L49: 0.6 | M49: 0.35 | N49: 1.4 | O49: =N49/60*'Mi negocio'!$C$23 -> 1.75 | P49: ='Mi negocio'!$C$20 -> 1.5 | Q49: =K49+L49+M49+O49+P49 -> 11.0732 | S49: =IF(R49="",'Mi negocio'!$C$24,R49) -> 0.06 | T49: =IFERROR(Q49/(1-S49),0) -> 11.78 | U49: =IFERROR(CEILING(ROUND(T49/(1-'Mi negocio'!$C$26),6),1),0) -> 24 | V49: =IFERROR(CEILING(ROUND(T49/(1-'Mi negocio'!$C$27),6),1),0) -> 30 | W49: =IFERROR(CEILING(ROUND(T49/(1-'Mi negocio'!$C$28),6),1),0) -> 35 | X49: =IFERROR(CEILING(ROUND(T49/(1-'Mi negocio'!$C$29),6),1),0) -> 17 | Y49: =U49-T49 -> 12.22 | Z49: =IFERROR(Y49/U49,0) -> 0.50916667
A50: 46 | B50: Salsa Cruda de Aguacate Taquera y Tomatillo Verde | C50: Cap. 10 · Contemporáneos, deeps y salsas | D50: S | F50: frasco 250 g | G50: 3.8 | H50: 0 | I50: =IF(E50="",0,H50*VLOOKUP(E50,'Bases madre'!$A$5:$E$13,5,FALSE())) -> 0 | J50: =SUMIF(Ingredientes!$A$5:$A$500,A50,Ingredientes!$H$5:$H$500) -> 49.08 | K50: =IFERROR((I50+J50)/G50,0) -> 12.915789 | L50: 9 | M50: 1.5 | N50: 6 | O50: =N50/60*'Mi negocio'!$C$23 -> 7.5 | P50: ='Mi negocio'!$C$20 -> 1.5 | Q50: =K50+L50+M50+O50+P50 -> 32.415789 | S50: =IF(R50="",'Mi negocio'!$C$24,R50) -> 0.06 | T50: =IFERROR(Q50/(1-S50),0) -> 34.484882 | U50: =IFERROR(CEILING(ROUND(T50/(1-'Mi negocio'!$C$26),6),1),0) -> 69 | V50: =IFERROR(CEILING(ROUND(T50/(1-'Mi negocio'!$C$27),6),1),0) -> 87 | W50: =IFERROR(CEILING(ROUND(T50/(1-'Mi negocio'!$C$28),6),1),0) -> 102 | X50: =IFERROR(CEILING(ROUND(T50/(1-'Mi negocio'!$C$29),6),1),0) -> 50 | Y50: =U50-T50 -> 34.515118 | Z50: =IFERROR(Y50/U50,0) -> 0.5002191
A51: 47 | B51: Salsa Roja Cocida de Chile Morita Tatemado y Xoconostle | C51: Cap. 10 · Contemporáneos, deeps y salsas | D51: S | F51: frasco 250 g | G51: 3.6 | H51: 0 | I51: =IF(E51="",0,H51*VLOOKUP(E51,'Bases madre'!$A$5:$E$13,5,FALSE())) -> 0 | J51: =SUMIF(Ingredientes!$A$5:$A$500,A51,Ingredientes!$H$5:$H$500) -> 41.54 | K51: =IFERROR((I51+J51)/G51,0) -> 11.538889 | L51: 9 | M51: 1.5 | N51: 6 | O51: =N51/60*'Mi negocio'!$C$23 -> 7.5 | P51: ='Mi negocio'!$C$20 -> 1.5 | Q51: =K51+L51+M51+O51+P51 -> 31.038889 | S51: =IF(R51="",'Mi negocio'!$C$24,R51) -> 0.06 | T51: =IFERROR(Q51/(1-S51),0) -> 33.020095 | U51: =IFERROR(CEILING(ROUND(T51/(1-'Mi negocio'!$C$26),6),1),0) -> 67 | V51: =IFERROR(CEILING(ROUND(T51/(1-'Mi negocio'!$C$27),6),1),0) -> 83 | W51: =IFERROR(CEILING(ROUND(T51/(1-'Mi negocio'!$C$28),6),1),0) -> 98 | X51: =IFERROR(CEILING(ROUND(T51/(1-'Mi negocio'!$C$29),6),1),0) -> 48 | Y51: =U51-T51 -> 33.979905 | Z51: =IFERROR(Y51/U51,0) -> 0.50716277
A52: 48 | B52: Cebollitas Encurtidas con Chile Habanero Naranja y Orégano Yucateco | C52: Cap. 10 · Contemporáneos, deeps y salsas | D52: S | F52: frasco 250 g | G52: 3.2 | H52: 0 | I52: =IF(E52="",0,H52*VLOOKUP(E52,'Bases madre'!$A$5:$E$13,5,FALSE())) -> 0 | J52: =SUMIF(Ingredientes!$A$5:$A$500,A52,Ingredientes!$H$5:$H$500) -> 37.89 | K52: =IFERROR((I52+J52)/G52,0) -> 11.840625 | L52: 9 | M52: 1.5 | N52: 6 | O52: =N52/60*'Mi negocio'!$C$23 -> 7.5 | P52: ='Mi negocio'!$C$20 -> 1.5 | Q52: =K52+L52+M52+O52+P52 -> 31.340625 | S52: =IF(R52="",'Mi negocio'!$C$24,R52) -> 0.06 | T52: =IFERROR(Q52/(1-S52),0) -> 33.34109 | U52: =IFERROR(CEILING(ROUND(T52/(1-'Mi negocio'!$C$26),6),1),0) -> 67 | V52: =IFERROR(CEILING(ROUND(T52/(1-'Mi negocio'!$C$27),6),1),0) -> 84 | W52: =IFERROR(CEILING(ROUND(T52/(1-'Mi negocio'!$C$28),6),1),0) -> 99 | X52: =IFERROR(CEILING(ROUND(T52/(1-'Mi negocio'!$C$29),6),1),0) -> 48 | Y52: =U52-T52 -> 33.65891 | Z52: =IFERROR(Y52/U52,0) -> 0.50237178
A53: 49 | B53: Deep de Frijol Maneado con Manteca de Cerdo y Chile Pasilla | C53: Cap. 10 · Contemporáneos, deeps y salsas | D53: S | F53: frasco 250 g | G53: 4.2 | H53: 0 | I53: =IF(E53="",0,H53*VLOOKUP(E53,'Bases madre'!$A$5:$E$13,5,FALSE())) -> 0 | J53: =SUMIF(Ingredientes!$A$5:$A$500,A53,Ingredientes!$H$5:$H$500) -> 45.59 | K53: =IFERROR((I53+J53)/G53,0) -> 10.854762 | L53: 9 | M53: 1.5 | N53: 6 | O53: =N53/60*'Mi negocio'!$C$23 -> 7.5 | P53: ='Mi negocio'!$C$20 -> 1.5 | Q53: =K53+L53+M53+O53+P53 -> 30.354762 | S53: =IF(R53="",'Mi negocio'!$C$24,R53) -> 0.06 | T53: =IFERROR(Q53/(1-S53),0) -> 32.2923 | U53: =IFERROR(CEILING(ROUND(T53/(1-'Mi negocio'!$C$26),6),1),0) -> 65 | V53: =IFERROR(CEILING(ROUND(T53/(1-'Mi negocio'!$C$27),6),1),0) -> 81 | W53: =IFERROR(CEILING(ROUND(T53/(1-'Mi negocio'!$C$28),6),1),0) -> 95 | X53: =IFERROR(CEILING(ROUND(T53/(1-'Mi negocio'!$C$29),6),1),0) -> 47 | Y53: =U53-T53 -> 32.7077 | Z53: =IFERROR(Y53/U53,0) -> 0.50319539
A54: 50 | B54: Deep de Chicharrón Prensado al Cilantro y Tomatillo Asado | C54: Cap. 10 · Contemporáneos, deeps y salsas | D54: S | F54: frasco 250 g | G54: 4 | H54: 0 | I54: =IF(E54="",0,H54*VLOOKUP(E54,'Bases madre'!$A$5:$E$13,5,FALSE())) -> 0 | J54: =SUMIF(Ingredientes!$A$5:$A$500,A54,Ingredientes!$H$5:$H$500) -> 125.07 | K54: =IFERROR((I54+J54)/G54,0) -> 31.2675 | L54: 9 | M54: 1.5 | N54: 6 | O54: =N54/60*'Mi negocio'!$C$23 -> 7.5 | P54: ='Mi negocio'!$C$20 -> 1.5 | Q54: =K54+L54+M54+O54+P54 -> 50.7675 | S54: =IF(R54="",'Mi negocio'!$C$24,R54) -> 0.06 | T54: =IFERROR(Q54/(1-S54),0) -> 54.007979 | U54: =IFERROR(CEILING(ROUND(T54/(1-'Mi negocio'!$C$26),6),1),0) -> 109 | V54: =IFERROR(CEILING(ROUND(T54/(1-'Mi negocio'!$C$27),6),1),0) -> 136 | W54: =IFERROR(CEILING(ROUND(T54/(1-'Mi negocio'!$C$28),6),1),0) -> 159 | X54: =IFERROR(CEILING(ROUND(T54/(1-'Mi negocio'!$C$29),6),1),0) -> 78 | Y54: =U54-T54 -> 54.992021 | Z54: =IFERROR(Y54/U54,0) -> 0.50451396
B56: Recetas 1–45 por taco; 46–50 por frasco de 250 g. Deja «Merma propia» vacía para usar la merma por defecto de Mi negocio.

Sheet Producción
A1: Producción y merma
A2: Una fila por lote. La primera fila es un ejemplo: sobrescríbela.
A4: Fecha | B4: Lote | C4: Nº receta | D4: Receta | E4: Planeadas | F4: Buenas | G4: Falladas | H4: % merma | I4: Costo total unitario | J4: Costo de la merma | K4: Causa principal | L4: Notas
A5: 46300 | B5: L-2610-01 | C5: 1 | D5: =IF(C5="","",IFERROR(VLOOKUP(C5,'Recetas y precios'!$A$5:$B$54,2,FALSE()),"")) -> Papa Machacada Campesina con Cebolla Confitada al Comal | E5: 50 | F5: 48 | G5: 2 | H5: =IF((F5+G5)>0,G5/(F5+G5),"") -> 0.04 | I5: =IF(C5="",0,IFERROR(VLOOKUP(C5,'Recetas y precios'!$A$5:$T$54,20,FALSE()),0)) -> 6.3959574 | J5: =G5*I5 -> 12.791915 | K5: Tortilla rota o desfondada | L5: Fila de ejemplo
D6: =IF(C6="","",IFERROR(VLOOKUP(C6,'Recetas y precios'!$A$5:$B$54,2,FALSE()),"")) | H6: =IF((F6+G6)>0,G6/(F6+G6),"") | I6: =IF(C6="",0,IFERROR(VLOOKUP(C6,'Recetas y precios'!$A$5:$T$54,20,FALSE()),0)) -> 0 | J6: =G6*I6 -> 0
D7: =IF(C7="","",IFERROR(VLOOKUP(C7,'Recetas y precios'!$A$5:$B$54,2,FALSE()),"")) | H7: =IF((F7+G7)>0,G7/(F7+G7),"") | I7: =IF(C7="",0,IFERROR(VLOOKUP(C7,'Recetas y precios'!$A$5:$T$54,20,FALSE()),0)) -> 0 | J7: =G7*I7 -> 0
D8: =IF(C8="","",IFERROR(VLOOKUP(C8,'Recetas y precios'!$A$5:$B$54,2,FALSE()),"")) | H8: =IF((F8+G8)>0,G8/(F8+G8),"") | I8: =IF(C8="",0,IFERROR(VLOOKUP(C8,'Recetas y precios'!$A$5:$T$54,20,FALSE()),0)) -> 0 | J8: =G8*I8 -> 0
D9: =IF(C9="","",IFERROR(VLOOKUP(C9,'Recetas y precios'!$A$5:$B$54,2,FALSE()),"")) | H9: =IF((F9+G9)>0,G9/(F9+G9),"") | I9: =IF(C9="",0,IFERROR(VLOOKUP(C9,'Recetas y precios'!$A$5:$T$54,20,FALSE()),0)) -> 0 | J9: =G9*I9 -> 0
D10: =IF(C10="","",IFERROR(VLOOKUP(C10,'Recetas y precios'!$A$5:$B$54,2,FALSE()),"")) | H10: =IF((F10+G10)>0,G10/(F10+G10),"") | I10: =IF(C10="",0,IFERROR(VLOOKUP(C10,'Recetas y precios'!$A$5:$T$54,20,FALSE()),0)) -> 0 | J10: =G10*I10 -> 0
D11: =IF(C11="","",IFERROR(VLOOKUP(C11,'Recetas y precios'!$A$5:$B$54,2,FALSE()),"")) | H11: =IF((F11+G11)>0,G11/(F11+G11),"") | I11: =IF(C11="",0,IFERROR(VLOOKUP(C11,'Recetas y precios'!$A$5:$T$54,20,FALSE()),0)) -> 0 | J11: =G11*I11 -> 0
D12: =IF(C12="","",IFERROR(VLOOKUP(C12,'Recetas y precios'!$A$5:$B$54,2,FALSE()),"")) | H12: =IF((F12+G12)>0,G12/(F12+G12),"") | I12: =IF(C12="",0,IFERROR(VLOOKUP(C12,'Recetas y precios'!$A$5:$T$54,20,FALSE()),0)) -> 0 | J12: =G12*I12 -> 0
D13: =IF(C13="","",IFERROR(VLOOKUP(C13,'Recetas y precios'!$A$5:$B$54,2,FALSE()),"")) | H13: =IF((F13+G13)>0,G13/(F13+G13),"") | I13: =IF(C13="",0,IFERROR(VLOOKUP(C13,'Recetas y precios'!$A$5:$T$54,20,FALSE()),0)) -> 0 | J13: =G13*I13 -> 0
D14: =IF(C14="","",IFERROR(VLOOKUP(C14,'Recetas y precios'!$A$5:$B$54,2,FALSE()),"")) | H14: =IF((F14+G14)>0,G14/(F14+G14),"") | I14: =IF(C14="",0,IFERROR(VLOOKUP(C14,'Recetas y precios'!$A$5:$T$54,20,FALSE()),0)) -> 0 | J14: =G14*I14 -> 0
D15: =IF(C15="","",IFERROR(VLOOKUP(C15,'Recetas y precios'!$A$5:$B$54,2,FALSE()),"")) | H15: =IF((F15+G15)>0,G15/(F15+G15),"") | I15: =IF(C15="",0,IFERROR(VLOOKUP(C15,'Recetas y precios'!$A$5:$T$54,20,FALSE()),0)) -> 0 | J15: =G15*I15 -> 0
D16: =IF(C16="","",IFERROR(VLOOKUP(C16,'Recetas y precios'!$A$5:$B$54,2,FALSE()),"")) | H16: =IF((F16+G16)>0,G16/(F16+G16),"") | I16: =IF(C16="",0,IFERROR(VLOOKUP(C16,'Recetas y precios'!$A$5:$T$54,20,FALSE()),0)) -> 0 | J16: =G16*I16 -> 0
D17: =IF(C17="","",IFERROR(VLOOKUP(C17,'Recetas y precios'!$A$5:$B$54,2,FALSE()),"")) | H17: =IF((F17+G17)>0,G17/(F17+G17),"") | I17: =IF(C17="",0,IFERROR(VLOOKUP(C17,'Recetas y precios'!$A$5:$T$54,20,FALSE()),0)) -> 0 | J17: =G17*I17 -> 0
... D304: =IF(C304="","",IFERROR(VLOOKUP(C304,'Recetas y precios'!$A$5:$B$54,2,FALSE()),"")) | H304: =IF((F304+G304)>0,G304/(F304+G304),"") | I304: =IF(C304="",0,IFERROR(VLOOKUP(C304,'Recetas y precios'!$A$5:$T$54,20,FALSE()),0)) -> 0 | J304: =G304*I304 -> 0

Sheet Ventas
A1: Ventas
A2: Una fila por venta. La primera fila es un ejemplo: sobrescríbela.
A4: Fecha | B4: Nº receta | C4: Receta | D4: Canal | E4: Piezas | F4: Precio unitario | G4: Ingreso | H4: Costo total | I4: Comisión % | J4: Comisión $ | K4: Utilidad neta | L4: Margen | M4: Cliente o nota
A5: 46300 | B5: 1 | C5: =IF(B5="","",IFERROR(VLOOKUP(B5,'Recetas y precios'!$A$5:$B$54,2,FALSE()),"")) -> Papa Machacada Campesina con Cebolla Confitada al Comal | D5: Canasta en calle | E5: 40 | F5: 13 | G5: =E5*F5 -> 520 | H5: =IF(B5="",0,E5*IFERROR(VLOOKUP(B5,'Recetas y precios'!$A$5:$T$54,20,FALSE()),0)) -> 255.8383 | I5: 0 | J5: =G5*I5 -> 0 | K5: =G5-H5-J5 -> 264.1617 | L5: =IF(G5>0,K5/G5,"") -> 0.50800327 | M5: Fila de ejemplo
C6: =IF(B6="","",IFERROR(VLOOKUP(B6,'Recetas y precios'!$A$5:$B$54,2,FALSE()),"")) | G6: =E6*F6 -> 0 | H6: =IF(B6="",0,E6*IFERROR(VLOOKUP(B6,'Recetas y precios'!$A$5:$T$54,20,FALSE()),0)) -> 0 | J6: =G6*I6 -> 0 | K6: =G6-H6-J6 -> 0 | L6: =IF(G6>0,K6/G6,"")
C7: =IF(B7="","",IFERROR(VLOOKUP(B7,'Recetas y precios'!$A$5:$B$54,2,FALSE()),"")) | G7: =E7*F7 -> 0 | H7: =IF(B7="",0,E7*IFERROR(VLOOKUP(B7,'Recetas y precios'!$A$5:$T$54,20,FALSE()),0)) -> 0 | J7: =G7*I7 -> 0 | K7: =G7-H7-J7 -> 0 | L7: =IF(G7>0,K7/G7,"")
C8: =IF(B8="","",IFERROR(VLOOKUP(B8,'Recetas y precios'!$A$5:$B$54,2,FALSE()),"")) | G8: =E8*F8 -> 0 | H8: =IF(B8="",0,E8*IFERROR(VLOOKUP(B8,'Recetas y precios'!$A$5:$T$54,20,FALSE()),0)) -> 0 | J8: =G8*I8 -> 0 | K8: =G8-H8-J8 -> 0 | L8: =IF(G8>0,K8/G8,"")
C9: =IF(B9="","",IFERROR(VLOOKUP(B9,'Recetas y precios'!$A$5:$B$54,2,FALSE()),"")) | G9: =E9*F9 -> 0 | H9: =IF(B9="",0,E9*IFERROR(VLOOKUP(B9,'Recetas y precios'!$A$5:$T$54,20,FALSE()),0)) -> 0 | J9: =G9*I9 -> 0 | K9: =G9-H9-J9 -> 0 | L9: =IF(G9>0,K9/G9,"")
C10: =IF(B10="","",IFERROR(VLOOKUP(B10,'Recetas y precios'!$A$5:$B$54,2,FALSE()),"")) | G10: =E10*F10 -> 0 | H10: =IF(B10="",0,E10*IFERROR(VLOOKUP(B10,'Recetas y precios'!$A$5:$T$54,20,FALSE()),0)) -> 0 | J10: =G10*I10 -> 0 | K10: =G10-H10-J10 -> 0 | L10: =IF(G10>0,K10/G10,"")
C11: =IF(B11="","",IFERROR(VLOOKUP(B11,'Recetas y precios'!$A$5:$B$54,2,FALSE()),"")) | G11: =E11*F11 -> 0 | H11: =IF(B11="",0,E11*IFERROR(VLOOKUP(B11,'Recetas y precios'!$A$5:$T$54,20,FALSE()),0)) -> 0 | J11: =G11*I11 -> 0 | K11: =G11-H11-J11 -> 0 | L11: =IF(G11>0,K11/G11,"")
C12: =IF(B12="","",IFERROR(VLOOKUP(B12,'Recetas y precios'!$A$5:$B$54,2,FALSE()),"")) | G12: =E12*F12 -> 0 | H12: =IF(B12="",0,E12*IFERROR(VLOOKUP(B12,'Recetas y precios'!$A$5:$T$54,20,FALSE()),0)) -> 0 | J12: =G12*I12 -> 0 | K12: =G12-H12-J12 -> 0 | L12: =IF(G12>0,K12/G12,"")
C13: =IF(B13="","",IFERROR(VLOOKUP(B13,'Recetas y precios'!$A$5:$B$54,2,FALSE()),"")) | G13: =E13*F13 -> 0 | H13: =IF(B13="",0,E13*IFERROR(VLOOKUP(B13,'Recetas y precios'!$A$5:$T$54,20,FALSE()),0)) -> 0 | J13: =G13*I13 -> 0 | K13: =G13-H13-J13 -> 0 | L13: =IF(G13>0,K13/G13,"")
C14: =IF(B14="","",IFERROR(VLOOKUP(B14,'Recetas y precios'!$A$5:$B$54,2,FALSE()),"")) | G14: =E14*F14 -> 0 | H14: =IF(B14="",0,E14*IFERROR(VLOOKUP(B14,'Recetas y precios'!$A$5:$T$54,20,FALSE()),0)) -> 0 | J14: =G14*I14 -> 0 | K14: =G14-H14-J14 -> 0 | L14: =IF(G14>0,K14/G14,"")
C15: =IF(B15="","",IFERROR(VLOOKUP(B15,'Recetas y precios'!$A$5:$B$54,2,FALSE()),"")) | G15: =E15*F15 -> 0 | H15: =IF(B15="",0,E15*IFERROR(VLOOKUP(B15,'Recetas y precios'!$A$5:$T$54,20,FALSE()),0)) -> 0 | J15: =G15*I15 -> 0 | K15: =G15-H15-J15 -> 0 | L15: =IF(G15>0,K15/G15,"")
C16: =IF(B16="","",IFERROR(VLOOKUP(B16,'Recetas y precios'!$A$5:$B$54,2,FALSE()),"")) | G16: =E16*F16 -> 0 | H16: =IF(B16="",0,E16*IFERROR(VLOOKUP(B16,'Recetas y precios'!$A$5:$T$54,20,FALSE()),0)) -> 0 | J16: =G16*I16 -> 0 | K16: =G16-H16-J16 -> 0 | L16: =IF(G16>0,K16/G16,"")
C17: =IF(B17="","",IFERROR(VLOOKUP(B17,'Recetas y precios'!$A$5:$B$54,2,FALSE()),"")) | G17: =E17*F17 -> 0 | H17: =IF(B17="",0,E17*IFERROR(VLOOKUP(B17,'Recetas y precios'!$A$5:$T$54,20,FALSE()),0)) -> 0 | J17: =G17*I17 -> 0 | K17: =G17-H17-J17 -> 0 | L17: =IF(G17>0,K17/G17,"")
... C504: =IF(B504="","",IFERROR(VLOOKUP(B504,'Recetas y precios'!$A$5:$B$54,2,FALSE()),"")) | G504: =E504*F504 -> 0 | H504: =IF(B504="",0,E504*IFERROR(VLOOKUP(B504,'Recetas y precios'!$A$5:$T$54,20,FALSE()),0)) -> 0 | J504: =G504*I504 -> 0 | K504: =G504-H504-J504 -> 0 | L504: =IF(G504>0,K504/G504,"")

Sheet Tablero
A1: Tablero
A2: Resumen automático de Ventas y Producción. No se edita.
B3: Ventas | E3: Canal | F3: Ingreso | G3: Piezas
B4: Ingreso acumulado | C4: =SUM(Ventas!G5:G504) -> 520 | E4: Canasta en calle | F4: =SUMIF(Ventas!$D$5:$D$504,E4,Ventas!$G$5:$G$504) -> 520 | G4: =SUMIF(Ventas!$D$5:$D$504,E4,Ventas!$E$5:$E$504) -> 40
B5: Piezas vendidas | C5: =SUM(Ventas!E5:E504) -> 40 | E5: Pedido de oficina / docena | F5: =SUMIF(Ventas!$D$5:$D$504,E5,Ventas!$G$5:$G$504) -> 0 | G5: =SUMIF(Ventas!$D$5:$D$504,E5,Ventas!$E$5:$E$504) -> 0
B6: Costo de lo vendido | C6: =SUM(Ventas!H5:H504) -> 255.8383 | E6: Taquiza y eventos | F6: =SUMIF(Ventas!$D$5:$D$504,E6,Ventas!$G$5:$G$504) -> 0 | G6: =SUMIF(Ventas!$D$5:$D$504,E6,Ventas!$E$5:$E$504) -> 0
B7: Comisiones | C7: =SUM(Ventas!J5:J504) -> 0 | E7: Mayoreo a canasteros | F7: =SUMIF(Ventas!$D$5:$D$504,E7,Ventas!$G$5:$G$504) -> 0 | G7: =SUMIF(Ventas!$D$5:$D$504,E7,Ventas!$E$5:$E$504) -> 0
B8: Utilidad neta (antes de gastos fijos) | C8: =SUM(Ventas!K5:K504) -> 264.1617 | E8: Venta directa | F8: =SUMIF(Ventas!$D$5:$D$504,E8,Ventas!$G$5:$G$504) -> 0 | G8: =SUMIF(Ventas!$D$5:$D$504,E8,Ventas!$E$5:$E$504) -> 0
B9: Margen neto | C9: =IFERROR(C8/C4,0) -> 0.50800327
B10: Utilidad después de gastos fijos | C10: =C8-'Mi negocio'!C17 -> -8735.8383
B11: Producción y merma | E11: Base madre | F11: Recetas | G11: Insumos prom.
B12: Piezas buenas producidas | C12: =SUM(Producción!F5:F304) -> 48 | E12: G-1 · Pasta de almidón | F12: ='Bases madre'!D17 -> 8 | G12: ='Bases madre'!F17 -> 2.464525
B13: Piezas falladas | C13: =SUM(Producción!G5:G304) -> 2 | E13: G-2 · Adobo rojo de chiles secos | F13: ='Bases madre'!D18 -> 12 | G13: ='Bases madre'!F18 -> 5.669425
B14: Merma real | C14: =IFERROR(C13/(C12+C13),0) -> 0.04 | E14: G-3 · Verde de tomatillo y pepita | F14: ='Bases madre'!D19 -> 4 | G14: ='Bases madre'!F19 -> 4.6398
B15: Merma supuesta | C15: ='Mi negocio'!$C$24 -> 0.06 | E15: G-4 · Recaudo de jitomate | F15: ='Bases madre'!D20 -> 9 | G15: ='Bases madre'!F20 -> 5.2736096
B16: Dinero perdido en merma | C16: =SUM(Producción!J5:J304) -> 12.791915 | E16: G-5 · Salteado seco de huerta | F16: ='Bases madre'!D21 -> 6 | G16: ='Bases madre'!F21 -> 4.1529
B17: Punto de equilibrio | E17: G-6 · Confitado y salteado cárnico | F17: ='Bases madre'!D22 -> 6 | G17: ='Bases madre'!F22 -> 6.6399039
B18: Precio promedio de calle (tacos 1–45) | C18: =AVERAGEIF('Recetas y precios'!$F$5:$F$54,"taco",'Recetas y precios'!$U$5:$U$54) -> 19.711111 | E18: S · Acompañamientos de la canasta | F18: ='Bases madre'!D23 -> 5 | G18: ='Bases madre'!F23 -> 15.683513
B19: Costo total promedio (tacos 1–45) | C19: =AVERAGEIF('Recetas y precios'!$F$5:$F$54,"taco",'Recetas y precios'!$T$5:$T$54) -> 9.6224068
B20: Margen de contribución por taco | C20: =C18-C19 -> 10.088704
B21: Gastos fijos del mes | C21: ='Mi negocio'!C17 -> 9000
B22: PUNTO DE EQUILIBRIO (tacos al mes) | C22: =IFERROR(ROUNDUP(C21/C20,0),0) -> 893
B23: Avance contra el punto de equilibrio | C23: =IFERROR(C5/C22,0) -> 0.044792833
B26: Endulcora · Estudio Gastronómico · En colaboración con Levent · Tacos de Canasta · Anexo 1
