Workbook

Sheet Léame
A1: TAMALES DE MÉXICO · Calculadora de Costos, Merma y Precios
A2: Endulcora · Estudio Gastronómico — herramienta complementaria del eBook «Tamales de México: Ruta Regional»
B4: CÓMO USAR ESTE ARCHIVO
B5: Orden de trabajo | C5: 1) Actualiza precios en «1. Insumos» → 2) Revisa «3. Costeo y Precios» → 3) Registra cada producción en «4. Producción y Merma» → 4) Registra cada venta en «5. Ventas» → 5) Lee resultados en «7. Tablero».
B6: 1. Insumos | C6: Catálogo con los 89 insumos que aparecen en las 51 recetas del libro, de todas las regiones del país. Escribe la presentación que compras y su precio; el costo por gramo, ml o pieza se calcula solo. Los precios vienen precargados como REFERENCIA orientativa (CDMX 2026) y debes reemplazarlos por los tuyos.
B7: 2. Recetas | C7: Las 51 formulaciones del libro ya cargadas, con sus 498 líneas de ingredientes. Jala el costo del catálogo y calcula el costo de insumos DEL LOTE COMPLETO. No necesitas tocar esta hoja salvo que quieras ajustar gramajes.
B8: 3. Costeo y Precios | C8: El corazón del archivo. Divide el costo del lote entre las piezas que rinde, suma empaque + energía + mano de obra + overhead, aplica la merma y calcula el precio de venta sugerido para los cuatro canales del libro. Edita solo las celdas azules.
B9: 4. Producción y Merma | C9: Bitácora de cada lote: piezas buenas, piezas falladas, causa y costo real de lo que se perdió. Te dice si tu % de merma supuesto es el verdadero.
B10: 5. Ventas | C10: Bitácora de ventas por pieza y canal, con comisiones de plataforma y utilidad neta automática.
B11: 6. Gastos Fijos | C11: Renta, gas, publicidad y tu sueldo. De aquí salen el overhead por pieza, el costo por hora de mano de obra y el punto de equilibrio.
B12: 7. Tablero | C12: Resumen del mes que elijas: ingresos, utilidad, margen, merma, ranking de recetas y avance hacia el punto de equilibrio.
B13: CÓDIGO DE COLORES
B14: Texto azul sobre fondo claro | C14: Celda que TÚ editas (dato de entrada). Es lo único que debes escribir.
B15: Texto negro | C15: Celda calculada por fórmula. No la sobreescribas o romperás el archivo.
B16: Fondo crema | C16: Encabezado o subtotal.
B17: IMPORTANTE
B18: Cada receta rinde lo suyo | C18: A diferencia de un recetario de una sola región, aquí el rendimiento varía de 8 piezas (mucbipollo yucateco) a 20 (tamalitos de dedo de Nuevo León). Los gramajes de la hoja «2. Recetas» son POR LOTE completo, tal como aparecen en el eBook, y la hoja de costeo divide entre las piezas reales de cada fórmula para darte el costo unitario. La columna «Piezas por lote» ya viene cargada receta por receta.
B19: Los precios son referencia | C19: Los precios precargados son orientativos y NO son una cotización. Reemplázalos con tus precios reales de compra antes de tomar cualquier decisión de venta.
B20: Sin promesa de resultados | C20: Esta herramienta calcula costos y precios sugeridos. No promete ingresos ni resultados de negocio garantizados.
B21: Créditos | C21: Recetas y contenido técnico: Chef Luis Alfonso Jiménez Cárdenas · Edición: Manuel Ramiro Justo Guzmán · Endulcora · Estudio Gastronómico · WhatsApp 56 6527 1901

Sheet 1. Insumos
A1: 1 · CATÁLOGO DE INSUMOS
A2: Escribe la presentación que compras y su precio. El costo por unidad se recalcula solo y actualiza las 51 recetas.
A4: Categoría | B4: Insumo | C4: Unidad base | D4: Cantidad de la presentación | E4: Precio de compra (MXN) | F4: Costo por unidad (MXN) | G4: Proveedor | I4: Nota
A5: Caldos y fondos | B5: Agua | C5: ml | D5: 1000 | E5: 1 | F5: =IFERROR(E5/D5,0) -> 0.001 | I5: Precio de referencia CDMX 2026 — actualízalo con tu precio real
A6: Caldos y fondos | B6: Caldo de cerdo | C6: ml | D6: 1000 | E6: 32 | F6: =IFERROR(E6/D6,0) -> 0.032
A7: Caldos y fondos | B7: Caldo de frijol | C7: ml | D7: 1000 | E7: 18 | F7: =IFERROR(E7/D7,0) -> 0.018
A8: Caldos y fondos | B8: Caldo de pescado o marisco | C8: ml | D8: 1000 | E8: 38 | F8: =IFERROR(E8/D8,0) -> 0.038
A9: Caldos y fondos | B9: Caldo de pollo | C9: ml | D9: 1000 | E9: 30 | F9: =IFERROR(E9/D9,0) -> 0.03
A10: Carnes | B10: Barbacoa de borrego | C10: g | D10: 1000 | E10: 420 | F10: =IFERROR(E10/D10,0) -> 0.42
A11: Carnes | B11: Carne molida de res | C11: g | D11: 1000 | E11: 190 | F11: =IFERROR(E11/D11,0) -> 0.19
A12: Carnes | B12: Conejo | C12: g | D12: 1000 | E12: 290 | F12: =IFERROR(E12/D12,0) -> 0.29
A13: Carnes | B13: Costilla de cerdo | C13: g | D13: 1000 | E13: 175 | F13: =IFERROR(E13/D13,0) -> 0.175
A14: Carnes | B14: Falda de res | C14: g | D14: 1000 | E14: 210 | F14: =IFERROR(E14/D14,0) -> 0.21
A15: Carnes | B15: Pollo de rancho | C15: g | D15: 1000 | E15: 165 | F15: =IFERROR(E15/D15,0) -> 0.165
A16: Carnes | B16: Pulpa de cerdo | C16: g | D16: 1000 | E16: 185 | F16: =IFERROR(E16/D16,0) -> 0.185
A17: Chiles secos | B17: Chile ancho seco | C17: pza | D17: 30 | E17: 70 | F17: =IFERROR(E17/D17,0) -> 2.3333333
... A93: Quelites y hongos | B93: Hoja de chepil (chipilín) fresca | C93: g | D93: 250 | E93: 55 | F93: =IFERROR(E93/D93,0) -> 0.22

Sheet 2. Recetas
A1: 2 · RECETAS (LISTA DE MATERIALES)
A2: Las 51 formulaciones del eBook. Las cantidades son POR LOTE completo, según el rendimiento de cada receta. Ajusta la columna «Cantidad» solo si modificas la receta original.
A4: Nº | B4: Receta | C4: Insumo | D4: Cantidad | E4: Unidad | F4: Costo por unidad (MXN) | G4: Costo del ingrediente (MXN) | H4: Como aparece en el eBook
A5: 1 | B5: Baja California: Tamal Estilo Tijuana de Carne de Res Adobada en Hoja de Maíz | C5: Masa de maíz nixtamalizado fresca de molino | D5: 1000 | E5: g | F5: =IFERROR(INDEX('1. Insumos'!$F$5:$F$93,MATCH($C5,'1. Insumos'!$B$5:$B$93,0)),0) -> 0.032 | G5: =D5*F5 -> 32 | H5: Masa de maíz nixtamalizado de molienda media
A6: 1 | B6: Baja California: Tamal Estilo Tijuana de Carne de Res Adobada en Hoja de Maíz | C6: Manteca de cerdo criollo lavada | D6: 270 | E6: g | F6: =IFERROR(INDEX('1. Insumos'!$F$5:$F$93,MATCH($C6,'1. Insumos'!$B$5:$B$93,0)),0) -> 0.145 | G6: =D6*F6 -> 39.15 | H6: Manteca de cerdo criollo
A7: 1 | B7: Baja California: Tamal Estilo Tijuana de Carne de Res Adobada en Hoja de Maíz | C7: Caldo de pollo | D7: 250 | E7: ml | F7: =IFERROR(INDEX('1. Insumos'!$F$5:$F$93,MATCH($C7,'1. Insumos'!$B$5:$B$93,0)),0) -> 0.03 | G7: =D7*F7 -> 7.5 | H7: Caldo de res concentrado (tibio y desgrasado)
A8: 1 | B8: Baja California: Tamal Estilo Tijuana de Carne de Res Adobada en Hoja de Maíz | C8: Preparación derivada de la misma receta (sin costo adicional) | D8: 50 | E8: ml | F8: =IFERROR(INDEX('1. Insumos'!$F$5:$F$93,MATCH($C8,'1. Insumos'!$B$5:$B$93,0)),0) -> 0 | G8: =D8*F8 -> 0 | H8: Adobo colado de la carne (para teñir y sazonar la masa)
A9: 1 | B9: Baja California: Tamal Estilo Tijuana de Carne de Res Adobada en Hoja de Maíz | C9: Sal de grano | D9: 16 | E9: g | F9: =IFERROR(INDEX('1. Insumos'!$F$5:$F$93,MATCH($C9,'1. Insumos'!$B$5:$B$93,0)),0) -> 0.025 | G9: =D9*F9 -> 0.4 | H9: Sal fina
A10: 1 | B10: Baja California: Tamal Estilo Tijuana de Carne de Res Adobada en Hoja de Maíz | C10: Polvo para hornear | D10: 5 | E10: g | F10: =IFERROR(INDEX('1. Insumos'!$F$5:$F$93,MATCH($C10,'1. Insumos'!$B$5:$B$93,0)),0) -> 0.175 | G10: =D10*F10 -> 0.875 | H10: Polvo para hornear
A11: 1 | B11: Baja California: Tamal Estilo Tijuana de Carne de Res Adobada en Hoja de Maíz | C11: Falda de res | D11: 500 | E11: g | F11: =IFERROR(INDEX('1. Insumos'!$F$5:$F$93,MATCH($C11,'1. Insumos'!$B$5:$B$93,0)),0) -> 0.21 | G11: =D11*F11 -> 105 | H11: Falda o pescuezo de res cocido suave con ajo y cebolla, deshebrado fino
A12: 1 | B12: Baja California: Tamal Estilo Tijuana de Carne de Res Adobada en Hoja de Maíz | C12: Chile ancho seco | D12: 5 | E12: pza | F12: =IFERROR(INDEX('1. Insumos'!$F$5:$F$93,MATCH($C12,'1. Insumos'!$B$5:$B$93,0)),0) -> 2.3333333 | G12: =D12*F12 -> 11.666667 | H12: Chiles anchos desvenados y tostados
A13: 1 | B13: Baja California: Tamal Estilo Tijuana de Carne de Res Adobada en Hoja de Maíz | C13: Chile guajillo seco | D13: 3 | E13: pza | F13: =IFERROR(INDEX('1. Insumos'!$F$5:$F$93,MATCH($C13,'1. Insumos'!$B$5:$B$93,0)),0) -> 1.5 | G13: =D13*F13 -> 4.5 | H13: Chiles guajillos tostados
A14: 1 | B14: Baja California: Tamal Estilo Tijuana de Carne de Res Adobada en Hoja de Maíz | C14: Ajo | D14: 3 | E14: pza | F14: =IFERROR(INDEX('1. Insumos'!$F$5:$F$93,MATCH($C14,'1. Insumos'!$B$5:$B$93,0)),0) -> 0.875 | G14: =D14*F14 -> 2.625 | H14: Dientes de ajo asados
A15: 1 | B15: Baja California: Tamal Estilo Tijuana de Carne de Res Adobada en Hoja de Maíz | C15: Cebolla blanca | D15: 0.25 | E15: pza | F15: =IFERROR(INDEX('1. Insumos'!$F$5:$F$93,MATCH($C15,'1. Insumos'!$B$5:$B$93,0)),0) -> 3.75 | G15: =D15*F15 -> 0.9375 | H15: Cebolla blanca asada
A16: 1 | B16: Baja California: Tamal Estilo Tijuana de Carne de Res Adobada en Hoja de Maíz | C16: Orégano seco oaxaqueño | D16: 2 | E16: g | F16: =IFERROR(INDEX('1. Insumos'!$F$5:$F$93,MATCH($C16,'1. Insumos'!$B$5:$B$93,0)),0) -> 0.6 | G16: =D16*F16 -> 1.2 | H16: Orégano seco
... A502: 51 | B502: Quintana Roo: Tamal Caribeño de Mariscos en Achiote y Habanero Tatemado | C502: Aceite de maíz | D502: 25 | E502: ml | F502: =IFERROR(INDEX('1. Insumos'!$F$5:$F$93,MATCH($C502,'1. Insumos'!$B$5:$B$93,0)),0) -> 0.065 | G502: =D502*F502 -> 1.625 | H502: Aceite de coco neutro o manteca

Sheet 3. Costeo y Precios
A1: 3 · COSTEO Y PRECIO DE VENTA POR RECETA
A2: Edita solo las celdas azules: piezas por lote, empaque, energía, minutos de trabajo y % de merma. Todo lo demás se calcula.
A4: PARÁMETROS GLOBALES · márgenes recomendados por canal (Cap. 15.3 del eBook)
A5: Margen objetivo — Menudeo por pieza | C5: 0.5 | D5: Rango del libro: 45 % – 55 %
A6: Margen objetivo — Docena por encargo | C6: 0.42 | D6: Rango del libro: 38 % – 48 %
A7: Margen objetivo — Evento y banquete | C7: 0.55 | D7: Rango del libro: 50 % – 62 %
A8: Margen objetivo — Mayoreo / reventa | C8: 0.3 | D8: Rango del libro: 25 % – 35 %
A9: Costo de mano de obra por hora (viene de Gastos Fijos) | C9: ='6. Gastos Fijos'!$C$24 -> 75
A10: Overhead por pieza (viene de Gastos Fijos) | C10: ='6. Gastos Fijos'!$C$19 -> 7.15
A11: % de merma por defecto | C11: 0.12 | D11: Principiante 15–25 % · Intermedio 8–15 % · Avanzado 3–8 %
A13: Nº | B13: Receta | C13: Piezas por lote | D13: Costo de insumos del lote | E13: Costo de insumos por pieza | F13: Empaque | G13: Energía y consumibles | H13: Minutos por pieza | I13: Mano de obra | J13: Overhead | K13: COSTO BASE | L13: % Merma | M13: COSTO TOTAL UNITARIO | N13: PVP Menudeo | O13: Utilidad Menudeo | P13: PVP Docena | Q13: Utilidad Docena | R13: PVP Evento | S13: Utilidad Evento | T13: PVP Mayoreo | U13: Utilidad Mayoreo | V13: Margen real Menudeo
A14: 1 | B14: Baja California: Tamal Estilo Tijuana de Carne de Res Adobada en Hoja de Maíz | C14: 14 | D14: =SUMIFS('2. Recetas'!$G$5:$G$502,'2. Recetas'!$A$5:$A$502,$A14) -> 217.25417 | E14: =IFERROR(D14/C14,0) -> 15.518155 | F14: 5 | G14: 3 | H14: 5 | I14: =$C$9*H14/60 -> 6.25 | J14: =$C$10 -> 7.15 | K14: =E14+F14+G14+I14+J14 -> 36.918155 | L14: =$C$11 -> 0.12 | M14: =IFERROR(K14/(1-L14),0) -> 41.952449 | N14: =IFERROR(CEILING(M14/(1-$C$5),5),0) -> 85 | O14: =N14-M14 -> 43.047551 | P14: =IFERROR(CEILING(M14/(1-$C$6),5),0) -> 75 | Q14: =P14-M14 -> 33.047551 | R14: =IFERROR(CEILING(M14/(1-$C$7),5),0) -> 95 | S14: =R14-M14 -> 53.047551 | T14: =IFERROR(CEILING(M14/(1-$C$8),5),0) -> 60 | U14: =T14-M14 -> 18.047551 | V14: =IFERROR(O14/N14,0) -> 0.50644178
A15: 2 | B15: Baja California Sur: Tamal Sudcaliforniano de Res, Cerdo, Aceitunas y Pasas | C15: 14 | D15: =SUMIFS('2. Recetas'!$G$5:$G$502,'2. Recetas'!$A$5:$A$502,$A15) -> 286.87833 | E15: =IFERROR(D15/C15,0) -> 20.49131 | F15: 5 | G15: 3 | H15: 5 | I15: =$C$9*H15/60 -> 6.25 | J15: =$C$10 -> 7.15 | K15: =E15+F15+G15+I15+J15 -> 41.89131 | L15: =$C$11 -> 0.12 | M15: =IFERROR(K15/(1-L15),0) -> 47.603761 | N15: =IFERROR(CEILING(M15/(1-$C$5),5),0) -> 100 | O15: =N15-M15 -> 52.396239 | P15: =IFERROR(CEILING(M15/(1-$C$6),5),0) -> 85 | Q15: =P15-M15 -> 37.396239 | R15: =IFERROR(CEILING(M15/(1-$C$7),5),0) -> 110 | S15: =R15-M15 -> 62.396239 | T15: =IFERROR(CEILING(M15/(1-$C$8),5),0) -> 70 | U15: =T15-M15 -> 22.396239 | V15: =IFERROR(O15/N15,0) -> 0.52396239
A16: 3 | B16: Sonora: Tamal de Chile Colorado con Puerco Deshebrado | C16: 15 | D16: =SUMIFS('2. Recetas'!$G$5:$G$502,'2. Recetas'!$A$5:$A$502,$A16) -> 288.99167 | E16: =IFERROR(D16/C16,0) -> 19.266111 | F16: 5 | G16: 3 | H16: 5 | I16: =$C$9*H16/60 -> 6.25 | J16: =$C$10 -> 7.15 | K16: =E16+F16+G16+I16+J16 -> 40.666111 | L16: =$C$11 -> 0.12 | M16: =IFERROR(K16/(1-L16),0) -> 46.21149 | N16: =IFERROR(CEILING(M16/(1-$C$5),5),0) -> 95 | O16: =N16-M16 -> 48.78851 | P16: =IFERROR(CEILING(M16/(1-$C$6),5),0) -> 80 | Q16: =P16-M16 -> 33.78851 | R16: =IFERROR(CEILING(M16/(1-$C$7),5),0) -> 105 | S16: =R16-M16 -> 58.78851 | T16: =IFERROR(CEILING(M16/(1-$C$8),5),0) -> 70 | U16: =T16-M16 -> 23.78851 | V16: =IFERROR(O16/N16,0) -> 0.51356326
A17: 4 | B17: Chihuahua: Tamal Norteño de Chile Pasado con Queso Menonita y Res | C17: 14 | D17: =SUMIFS('2. Recetas'!$G$5:$G$502,'2. Recetas'!$A$5:$A$502,$A17) -> 273.68333 | E17: =IFERROR(D17/C17,0) -> 19.54881 | F17: 5 | G17: 3 | H17: 5 | I17: =$C$9*H17/60 -> 6.25 | J17: =$C$10 -> 7.15 | K17: =E17+F17+G17+I17+J17 -> 40.94881 | L17: =$C$11 -> 0.12 | M17: =IFERROR(K17/(1-L17),0) -> 46.532738 | N17: =IFERROR(CEILING(M17/(1-$C$5),5),0) -> 95 | O17: =N17-M17 -> 48.467262 | P17: =IFERROR(CEILING(M17/(1-$C$6),5),0) -> 85 | Q17: =P17-M17 -> 38.467262 | R17: =IFERROR(CEILING(M17/(1-$C$7),5),0) -> 105 | S17: =R17-M17 -> 58.467262 | T17: =IFERROR(CEILING(M17/(1-$C$8),5),0) -> 70 | U17: =T17-M17 -> 23.467262 | V17: =IFERROR(O17/N17,0) -> 0.5101817
A18: 5 | B18: Coahuila: Tamal de Costilla de Puerco en Salsa Verde de Tomatillo y Serrano | C18: 15 | D18: =SUMIFS('2. Recetas'!$G$5:$G$502,'2. Recetas'!$A$5:$A$502,$A18) -> 190.80833 | E18: =IFERROR(D18/C18,0) -> 12.720556 | F18: 5 | G18: 3 | H18: 5 | I18: =$C$9*H18/60 -> 6.25 | J18: =$C$10 -> 7.15 | K18: =E18+F18+G18+I18+J18 -> 34.120556 | L18: =$C$11 -> 0.12 | M18: =IFERROR(K18/(1-L18),0) -> 38.773359 | N18: =IFERROR(CEILING(M18/(1-$C$5),5),0) -> 80 | O18: =N18-M18 -> 41.226641 | P18: =IFERROR(CEILING(M18/(1-$C$6),5),0) -> 70 | Q18: =P18-M18 -> 31.226641 | R18: =IFERROR(CEILING(M18/(1-$C$7),5),0) -> 90 | S18: =R18-M18 -> 51.226641 | T18: =IFERROR(CEILING(M18/(1-$C$8),5),0) -> 60 | U18: =T18-M18 -> 21.226641 | V18: =IFERROR(O18/N18,0) -> 0.51533302
A19: 6 | B19: Nuevo León: Tamal Norteño "De Dedo" de Picadillo Ranchero con Chile Ancho | C19: 20 | D19: =SUMIFS('2. Recetas'!$G$5:$G$502,'2. Recetas'!$A$5:$A$502,$A19) -> 180.20833 | E19: =IFERROR(D19/C19,0) -> 9.0104167 | F19: 5 | G19: 3 | H19: 5 | I19: =$C$9*H19/60 -> 6.25 | J19: =$C$10 -> 7.15 | K19: =E19+F19+G19+I19+J19 -> 30.410417 | L19: =$C$11 -> 0.12 | M19: =IFERROR(K19/(1-L19),0) -> 34.557292 | N19: =IFERROR(CEILING(M19/(1-$C$5),5),0) -> 70 | O19: =N19-M19 -> 35.442708 | P19: =IFERROR(CEILING(M19/(1-$C$6),5),0) -> 60 | Q19: =P19-M19 -> 25.442708 | R19: =IFERROR(CEILING(M19/(1-$C$7),5),0) -> 80 | S19: =R19-M19 -> 45.442708 | T19: =IFERROR(CEILING(M19/(1-$C$8),5),0) -> 50 | U19: =T19-M19 -> 15.442708 | V19: =IFERROR(O19/N19,0) -> 0.5063244
A20: 7 | B20: Tamaulipas: Tamal de Puerco en Salsa de Chile Cascabel y Comino | C20: 15 | D20: =SUMIFS('2. Recetas'!$G$5:$G$502,'2. Recetas'!$A$5:$A$502,$A20) -> 197.225 | E20: =IFERROR(D20/C20,0) -> 13.148333 | F20: 5 | G20: 3 | H20: 5 | I20: =$C$9*H20/60 -> 6.25 | J20: =$C$10 -> 7.15 | K20: =E20+F20+G20+I20+J20 -> 34.548333 | L20: =$C$11 -> 0.12 | M20: =IFERROR(K20/(1-L20),0) -> 39.25947 | N20: =IFERROR(CEILING(M20/(1-$C$5),5),0) -> 80 | O20: =N20-M20 -> 40.74053 | P20: =IFERROR(CEILING(M20/(1-$C$6),5),0) -> 70 | Q20: =P20-M20 -> 30.74053 | R20: =IFERROR(CEILING(M20/(1-$C$7),5),0) -> 90 | S20: =R20-M20 -> 50.74053 | T20: =IFERROR(CEILING(M20/(1-$C$8),5),0) -> 60 | U20: =T20-M20 -> 20.74053 | V20: =IFERROR(O20/N20,0) -> 0.50925663
A21: 8 | B21: Sinaloa: Tamal Barbón de Escuinapa (Camarones Enteros con Barbas) | C21: 12 | D21: =SUMIFS('2. Recetas'!$G$5:$G$502,'2. Recetas'!$A$5:$A$502,$A21) -> 280.975 | E21: =IFERROR(D21/C21,0) -> 23.414583 | F21: 5 | G21: 3 | H21: 5 | I21: =$C$9*H21/60 -> 6.25 | J21: =$C$10 -> 7.15 | K21: =E21+F21+G21+I21+J21 -> 44.814583 | L21: =$C$11 -> 0.12 | M21: =IFERROR(K21/(1-L21),0) -> 50.925663 | N21: =IFERROR(CEILING(M21/(1-$C$5),5),0) -> 105 | O21: =N21-M21 -> 54.074337 | P21: =IFERROR(CEILING(M21/(1-$C$6),5),0) -> 90 | Q21: =P21-M21 -> 39.074337 | R21: =IFERROR(CEILING(M21/(1-$C$7),5),0) -> 115 | S21: =R21-M21 -> 64.074337 | T21: =IFERROR(CEILING(M21/(1-$C$8),5),0) -> 75 | U21: =T21-M21 -> 24.074337 | V21: =IFERROR(O21/N21,0) -> 0.51499369
A22: 9 | B22: Sinaloa / Sonora: Tamal Tonto de Masa con Chile Colorado (Para Caldos) | C22: 16 | D22: =SUMIFS('2. Recetas'!$G$5:$G$502,'2. Recetas'!$A$5:$A$502,$A22) -> 89.5 | E22: =IFERROR(D22/C22,0) -> 5.59375 | F22: 5 | G22: 3 | H22: 5 | I22: =$C$9*H22/60 -> 6.25 | J22: =$C$10 -> 7.15 | K22: =E22+F22+G22+I22+J22 -> 26.99375 | L22: =$C$11 -> 0.12 | M22: =IFERROR(K22/(1-L22),0) -> 30.674716 | N22: =IFERROR(CEILING(M22/(1-$C$5),5),0) -> 65 | O22: =N22-M22 -> 34.325284 | P22: =IFERROR(CEILING(M22/(1-$C$6),5),0) -> 55 | Q22: =P22-M22 -> 24.325284 | R22: =IFERROR(CEILING(M22/(1-$C$7),5),0) -> 70 | S22: =R22-M22 -> 39.325284 | T22: =IFERROR(CEILING(M22/(1-$C$8),5),0) -> 45 | U22: =T22-M22 -> 14.325284 | V22: =IFERROR(O22/N22,0) -> 0.52808129
A23: 10 | B23: Michoacán: Corundas Michoacanas Triangulares en Hoja de Caña | C23: 16 | D23: =SUMIFS('2. Recetas'!$G$5:$G$502,'2. Recetas'!$A$5:$A$502,$A23) -> 179.7625 | E23: =IFERROR(D23/C23,0) -> 11.235156 | F23: 5 | G23: 3 | H23: 5 | I23: =$C$9*H23/60 -> 6.25 | J23: =$C$10 -> 7.15 | K23: =E23+F23+G23+I23+J23 -> 32.635156 | L23: =$C$11 -> 0.12 | M23: =IFERROR(K23/(1-L23),0) -> 37.085405 | N23: =IFERROR(CEILING(M23/(1-$C$5),5),0) -> 75 | O23: =N23-M23 -> 37.914595 | P23: =IFERROR(CEILING(M23/(1-$C$6),5),0) -> 65 | Q23: =P23-M23 -> 27.914595 | R23: =IFERROR(CEILING(M23/(1-$C$7),5),0) -> 85 | S23: =R23-M23 -> 47.914595 | T23: =IFERROR(CEILING(M23/(1-$C$8),5),0) -> 55 | U23: =T23-M23 -> 17.914595 | V23: =IFERROR(O23/N23,0) -> 0.50552794
A24: 11 | B24: Michoacán: Uchepos Tradicionales de Elote Tierno con Mantequilla | C24: 14 | D24: =SUMIFS('2. Recetas'!$G$5:$G$502,'2. Recetas'!$A$5:$A$502,$A24) -> 212.29 | E24: =IFERROR(D24/C24,0) -> 15.163571 | F24: 5 | G24: 3 | H24: 5 | I24: =$C$9*H24/60 -> 6.25 | J24: =$C$10 -> 7.15 | K24: =E24+F24+G24+I24+J24 -> 36.563571 | L24: =$C$11 -> 0.12 | M24: =IFERROR(K24/(1-L24),0) -> 41.549513 | N24: =IFERROR(CEILING(M24/(1-$C$5),5),0) -> 85 | O24: =N24-M24 -> 43.450487 | P24: =IFERROR(CEILING(M24/(1-$C$6),5),0) -> 75 | Q24: =P24-M24 -> 33.450487 | R24: =IFERROR(CEILING(M24/(1-$C$7),5),0) -> 95 | S24: =R24-M24 -> 53.450487 | T24: =IFERROR(CEILING(M24/(1-$C$8),5),0) -> 60 | U24: =T24-M24 -> 18.450487 | V24: =IFERROR(O24/N24,0) -> 0.5111822
A25: 12 | B25: Jalisco: Tamal Tapatío de Lomo de Cerdo en Mole Dulce de Chile Ancho | C25: 14 | D25: =SUMIFS('2. Recetas'!$G$5:$G$502,'2. Recetas'!$A$5:$A$502,$A25) -> 227.27 | E25: =IFERROR(D25/C25,0) -> 16.233571 | F25: 5 | G25: 3 | H25: 5 | I25: =$C$9*H25/60 -> 6.25 | J25: =$C$10 -> 7.15 | K25: =E25+F25+G25+I25+J25 -> 37.633571 | L25: =$C$11 -> 0.12 | M25: =IFERROR(K25/(1-L25),0) -> 42.765422 | N25: =IFERROR(CEILING(M25/(1-$C$5),5),0) -> 90 | O25: =N25-M25 -> 47.234578 | P25: =IFERROR(CEILING(M25/(1-$C$6),5),0) -> 75 | Q25: =P25-M25 -> 32.234578 | R25: =IFERROR(CEILING(M25/(1-$C$7),5),0) -> 100 | S25: =R25-M25 -> 57.234578 | T25: =IFERROR(CEILING(M25/(1-$C$8),5),0) -> 65 | U25: =T25-M25 -> 22.234578 | V25: =IFERROR(O25/N25,0) -> 0.52482864
... A64: 51 | B64: Quintana Roo: Tamal Caribeño de Mariscos en Achiote y Habanero Tatemado | C64: 12 | D64: =SUMIFS('2. Recetas'!$G$5:$G$502,'2. Recetas'!$A$5:$A$502,$A64) -> 280.25 | E64: =IFERROR(D64/C64,0) -> 23.354167 | F64: 5 | G64: 3 | H64: 5 | I64: =$C$9*H64/60 -> 6.25 | J64: =$C$10 -> 7.15 | K64: =E64+F64+G64+I64+J64 -> 44.754167 | L64: =$C$11 -> 0.12 | M64: =IFERROR(K64/(1-L64),0) -> 50.857008 | N64: =IFERROR(CEILING(M64/(1-$C$5),5),0) -> 105 | O64: =N64-M64 -> 54.142992 | P64: =IFERROR(CEILING(M64/(1-$C$6),5),0) -> 90 | Q64: =P64-M64 -> 39.142992 | R64: =IFERROR(CEILING(M64/(1-$C$7),5),0) -> 115 | S64: =R64-M64 -> 64.142992 | T64: =IFERROR(CEILING(M64/(1-$C$8),5),0) -> 75 | U64: =T64-M64 -> 24.142992 | V64: =IFERROR(O64/N64,0) -> 0.51564755

Sheet 4. Producción y Merma
A1: 4 · BITÁCORA DE PRODUCCIÓN Y MERMA
A2: Registra cada lote. La hoja calcula tu merma real y cuánto dinero se fue a la basura.
A3: Piezas buenas acumuladas | D3: =SUM(F8:F207) -> 56
A4: Piezas falladas acumuladas | D4: =SUM(G8:G207) -> 4
A5: % de merma real acumulada | D5: =IFERROR(D4/(D3+D4),0) -> 0.066666667
A6: Costo acumulado de la merma | D6: =SUM(K8:K207) -> 190.54505
A7: Fecha | B7: Lote | C7: Nº receta | D7: Receta | E7: Piezas planeadas | F7: Piezas buenas | G7: Piezas falladas | H7: % merma real | I7: Causa principal | J7: Costo unitario | K7: Costo de la merma | L7: Notas
A8: 46235 | B8: L-2608-01 | C8: 1 | D8: =IFERROR(INDEX('3. Costeo y Precios'!$B$14:$B$64,MATCH($C8,'3. Costeo y Precios'!$A$14:$A$64,0)),"") -> Baja California: Tamal Estilo Tijuana de Carne de Res Adobada en Hoja de Maíz | E8: 24 | F8: 22 | G8: 2 | H8: =IFERROR(G8/(F8+G8),"") -> 0.083333333 | I8: Tamal abierto en la vaporera | J8: =IFERROR(INDEX('3. Costeo y Precios'!$M$14:$M$64,MATCH($C8,'3. Costeo y Precios'!$A$14:$A$64,0)),0) -> 41.952449 | K8: =IF($C8="","",G8*J8) -> 83.904897
A9: 46237 | B9: L-2608-02 | C9: 19 | D9: =IFERROR(INDEX('3. Costeo y Precios'!$B$14:$B$64,MATCH($C9,'3. Costeo y Precios'!$A$14:$A$64,0)),"") -> San Luis Potosí: Zacahuil Huasteco Tradicional de Masa Martajada (Porción Individual Estandarizada) | E9: 36 | F9: 34 | G9: 2 | H9: =IFERROR(G9/(F9+G9),"") -> 0.055555556 | I9: Masa cruda al centro | J9: =IFERROR(INDEX('3. Costeo y Precios'!$M$14:$M$64,MATCH($C9,'3. Costeo y Precios'!$A$14:$A$64,0)),0) -> 53.320076 | K9: =IF($C9="","",G9*J9) -> 106.64015
D10: =IFERROR(INDEX('3. Costeo y Precios'!$B$14:$B$64,MATCH($C10,'3. Costeo y Precios'!$A$14:$A$64,0)),"") | H10: =IFERROR(G10/(F10+G10),"") | J10: =IFERROR(INDEX('3. Costeo y Precios'!$M$14:$M$64,MATCH($C10,'3. Costeo y Precios'!$A$14:$A$64,0)),0) -> 0 | K10: =IF($C10="","",G10*J10)
D11: =IFERROR(INDEX('3. Costeo y Precios'!$B$14:$B$64,MATCH($C11,'3. Costeo y Precios'!$A$14:$A$64,0)),"") | H11: =IFERROR(G11/(F11+G11),"") | J11: =IFERROR(INDEX('3. Costeo y Precios'!$M$14:$M$64,MATCH($C11,'3. Costeo y Precios'!$A$14:$A$64,0)),0) -> 0 | K11: =IF($C11="","",G11*J11)
D12: =IFERROR(INDEX('3. Costeo y Precios'!$B$14:$B$64,MATCH($C12,'3. Costeo y Precios'!$A$14:$A$64,0)),"") | H12: =IFERROR(G12/(F12+G12),"") | J12: =IFERROR(INDEX('3. Costeo y Precios'!$M$14:$M$64,MATCH($C12,'3. Costeo y Precios'!$A$14:$A$64,0)),0) -> 0 | K12: =IF($C12="","",G12*J12)
D13: =IFERROR(INDEX('3. Costeo y Precios'!$B$14:$B$64,MATCH($C13,'3. Costeo y Precios'!$A$14:$A$64,0)),"") | H13: =IFERROR(G13/(F13+G13),"") | J13: =IFERROR(INDEX('3. Costeo y Precios'!$M$14:$M$64,MATCH($C13,'3. Costeo y Precios'!$A$14:$A$64,0)),0) -> 0 | K13: =IF($C13="","",G13*J13)
D14: =IFERROR(INDEX('3. Costeo y Precios'!$B$14:$B$64,MATCH($C14,'3. Costeo y Precios'!$A$14:$A$64,0)),"") | H14: =IFERROR(G14/(F14+G14),"") | J14: =IFERROR(INDEX('3. Costeo y Precios'!$M$14:$M$64,MATCH($C14,'3. Costeo y Precios'!$A$14:$A$64,0)),0) -> 0 | K14: =IF($C14="","",G14*J14)
D15: =IFERROR(INDEX('3. Costeo y Precios'!$B$14:$B$64,MATCH($C15,'3. Costeo y Precios'!$A$14:$A$64,0)),"") | H15: =IFERROR(G15/(F15+G15),"") | J15: =IFERROR(INDEX('3. Costeo y Precios'!$M$14:$M$64,MATCH($C15,'3. Costeo y Precios'!$A$14:$A$64,0)),0) -> 0 | K15: =IF($C15="","",G15*J15)
D16: =IFERROR(INDEX('3. Costeo y Precios'!$B$14:$B$64,MATCH($C16,'3. Costeo y Precios'!$A$14:$A$64,0)),"") | H16: =IFERROR(G16/(F16+G16),"") | J16: =IFERROR(INDEX('3. Costeo y Precios'!$M$14:$M$64,MATCH($C16,'3. Costeo y Precios'!$A$14:$A$64,0)),0) -> 0 | K16: =IF($C16="","",G16*J16)
D17: =IFERROR(INDEX('3. Costeo y Precios'!$B$14:$B$64,MATCH($C17,'3. Costeo y Precios'!$A$14:$A$64,0)),"") | H17: =IFERROR(G17/(F17+G17),"") | J17: =IFERROR(INDEX('3. Costeo y Precios'!$M$14:$M$64,MATCH($C17,'3. Costeo y Precios'!$A$14:$A$64,0)),0) -> 0 | K17: =IF($C17="","",G17*J17)
D18: =IFERROR(INDEX('3. Costeo y Precios'!$B$14:$B$64,MATCH($C18,'3. Costeo y Precios'!$A$14:$A$64,0)),"") | H18: =IFERROR(G18/(F18+G18),"") | J18: =IFERROR(INDEX('3. Costeo y Precios'!$M$14:$M$64,MATCH($C18,'3. Costeo y Precios'!$A$14:$A$64,0)),0) -> 0 | K18: =IF($C18="","",G18*J18)
D19: =IFERROR(INDEX('3. Costeo y Precios'!$B$14:$B$64,MATCH($C19,'3. Costeo y Precios'!$A$14:$A$64,0)),"") | H19: =IFERROR(G19/(F19+G19),"") | J19: =IFERROR(INDEX('3. Costeo y Precios'!$M$14:$M$64,MATCH($C19,'3. Costeo y Precios'!$A$14:$A$64,0)),0) -> 0 | K19: =IF($C19="","",G19*J19)
D20: =IFERROR(INDEX('3. Costeo y Precios'!$B$14:$B$64,MATCH($C20,'3. Costeo y Precios'!$A$14:$A$64,0)),"") | H20: =IFERROR(G20/(F20+G20),"") | J20: =IFERROR(INDEX('3. Costeo y Precios'!$M$14:$M$64,MATCH($C20,'3. Costeo y Precios'!$A$14:$A$64,0)),0) -> 0 | K20: =IF($C20="","",G20*J20)
D21: =IFERROR(INDEX('3. Costeo y Precios'!$B$14:$B$64,MATCH($C21,'3. Costeo y Precios'!$A$14:$A$64,0)),"") | H21: =IFERROR(G21/(F21+G21),"") | J21: =IFERROR(INDEX('3. Costeo y Precios'!$M$14:$M$64,MATCH($C21,'3. Costeo y Precios'!$A$14:$A$64,0)),0) -> 0 | K21: =IF($C21="","",G21*J21)
... D207: =IFERROR(INDEX('3. Costeo y Precios'!$B$14:$B$64,MATCH($C207,'3. Costeo y Precios'!$A$14:$A$64,0)),"") | H207: =IFERROR(G207/(F207+G207),"") | J207: =IFERROR(INDEX('3. Costeo y Precios'!$M$14:$M$64,MATCH($C207,'3. Costeo y Precios'!$A$14:$A$64,0)),0) -> 0 | K207: =IF($C207="","",G207*J207)

Sheet 5. Ventas
A1: 5 · BITÁCORA DE VENTAS
A2: Una línea por venta. La utilidad neta descuenta el costo real y la comisión de plataforma.
A3: Piezas vendidas acumuladas | D3: =SUM(E8:E407) -> 96
A4: Ingreso total acumulado | D4: =SUM(G8:G407) -> 9660
A5: Utilidad neta total acumulada | D5: =SUM(L8:L407) -> 5821.7752
A6: Margen neto promedio | D6: =IFERROR(D5/D4,0) -> 0.60266824
A7: Fecha | B7: Nº receta | C7: Receta | D7: Canal | E7: Piezas | F7: Precio unitario | G7: Ingreso | H7: Costo unitario | I7: Costo total | J7: Comisión % | K7: Comisión $ | L7: Utilidad neta | M7: Margen % | N7: Cliente / Notas
A8: 46236 | B8: 1 | C8: =IFERROR(INDEX('3. Costeo y Precios'!$B$14:$B$64,MATCH($B8,'3. Costeo y Precios'!$A$14:$A$64,0)),"") -> Baja California: Tamal Estilo Tijuana de Carne de Res Adobada en Hoja de Maíz | D8: Menudeo por pieza | E8: 12 | F8: 95 | G8: =IF($B8="","",E8*F8) -> 1140 | H8: =IFERROR(INDEX('3. Costeo y Precios'!$M$14:$M$64,MATCH($B8,'3. Costeo y Precios'!$A$14:$A$64,0)),0) -> 41.952449 | I8: =IF($B8="","",E8*H8) -> 503.42938 | K8: =IF($B8="","",G8*J8) -> 0 | L8: =IF($B8="","",G8-I8-K8) -> 636.57062 | M8: =IFERROR(L8/G8,"") -> 0.55839528
A9: 46238 | B9: 19 | C9: =IFERROR(INDEX('3. Costeo y Precios'!$B$14:$B$64,MATCH($B9,'3. Costeo y Precios'!$A$14:$A$64,0)),"") -> San Luis Potosí: Zacahuil Huasteco Tradicional de Masa Martajada (Porción Individual Estandarizada) | D9: Docena por encargo | E9: 24 | F9: 80 | G9: =IF($B9="","",E9*F9) -> 1920 | H9: =IFERROR(INDEX('3. Costeo y Precios'!$M$14:$M$64,MATCH($B9,'3. Costeo y Precios'!$A$14:$A$64,0)),0) -> 53.320076 | I9: =IF($B9="","",E9*H9) -> 1279.6818 | K9: =IF($B9="","",G9*J9) -> 0 | L9: =IF($B9="","",G9-I9-K9) -> 640.31818 | M9: =IFERROR(L9/G9,"") -> 0.33349905
A10: 46242 | B10: 35 | C10: =IFERROR(INDEX('3. Costeo y Precios'!$B$14:$B$64,MATCH($B10,'3. Costeo y Precios'!$A$14:$A$64,0)),"") -> Morelos: Tamal de Frijol con Manteca y Flor de Tzompantle (Colorín) | D10: Evento y banquete | E10: 60 | F10: 110 | G10: =IF($B10="","",E10*F10) -> 6600 | H10: =IFERROR(INDEX('3. Costeo y Precios'!$M$14:$M$64,MATCH($B10,'3. Costeo y Precios'!$A$14:$A$64,0)),0) -> 34.251894 | I10: =IF($B10="","",E10*H10) -> 2055.1136 | K10: =IF($B10="","",G10*J10) -> 0 | L10: =IF($B10="","",G10-I10-K10) -> 4544.8864 | M10: =IFERROR(L10/G10,"") -> 0.68861915
C11: =IFERROR(INDEX('3. Costeo y Precios'!$B$14:$B$64,MATCH($B11,'3. Costeo y Precios'!$A$14:$A$64,0)),"") | G11: =IF($B11="","",E11*F11) | H11: =IFERROR(INDEX('3. Costeo y Precios'!$M$14:$M$64,MATCH($B11,'3. Costeo y Precios'!$A$14:$A$64,0)),0) -> 0 | I11: =IF($B11="","",E11*H11) | K11: =IF($B11="","",G11*J11) | L11: =IF($B11="","",G11-I11-K11) | M11: =IFERROR(L11/G11,"")
C12: =IFERROR(INDEX('3. Costeo y Precios'!$B$14:$B$64,MATCH($B12,'3. Costeo y Precios'!$A$14:$A$64,0)),"") | G12: =IF($B12="","",E12*F12) | H12: =IFERROR(INDEX('3. Costeo y Precios'!$M$14:$M$64,MATCH($B12,'3. Costeo y Precios'!$A$14:$A$64,0)),0) -> 0 | I12: =IF($B12="","",E12*H12) | K12: =IF($B12="","",G12*J12) | L12: =IF($B12="","",G12-I12-K12) | M12: =IFERROR(L12/G12,"")
C13: =IFERROR(INDEX('3. Costeo y Precios'!$B$14:$B$64,MATCH($B13,'3. Costeo y Precios'!$A$14:$A$64,0)),"") | G13: =IF($B13="","",E13*F13) | H13: =IFERROR(INDEX('3. Costeo y Precios'!$M$14:$M$64,MATCH($B13,'3. Costeo y Precios'!$A$14:$A$64,0)),0) -> 0 | I13: =IF($B13="","",E13*H13) | K13: =IF($B13="","",G13*J13) | L13: =IF($B13="","",G13-I13-K13) | M13: =IFERROR(L13/G13,"")
C14: =IFERROR(INDEX('3. Costeo y Precios'!$B$14:$B$64,MATCH($B14,'3. Costeo y Precios'!$A$14:$A$64,0)),"") | G14: =IF($B14="","",E14*F14) | H14: =IFERROR(INDEX('3. Costeo y Precios'!$M$14:$M$64,MATCH($B14,'3. Costeo y Precios'!$A$14:$A$64,0)),0) -> 0 | I14: =IF($B14="","",E14*H14) | K14: =IF($B14="","",G14*J14) | L14: =IF($B14="","",G14-I14-K14) | M14: =IFERROR(L14/G14,"")
C15: =IFERROR(INDEX('3. Costeo y Precios'!$B$14:$B$64,MATCH($B15,'3. Costeo y Precios'!$A$14:$A$64,0)),"") | G15: =IF($B15="","",E15*F15) | H15: =IFERROR(INDEX('3. Costeo y Precios'!$M$14:$M$64,MATCH($B15,'3. Costeo y Precios'!$A$14:$A$64,0)),0) -> 0 | I15: =IF($B15="","",E15*H15) | K15: =IF($B15="","",G15*J15) | L15: =IF($B15="","",G15-I15-K15) | M15: =IFERROR(L15/G15,"")
C16: =IFERROR(INDEX('3. Costeo y Precios'!$B$14:$B$64,MATCH($B16,'3. Costeo y Precios'!$A$14:$A$64,0)),"") | G16: =IF($B16="","",E16*F16) | H16: =IFERROR(INDEX('3. Costeo y Precios'!$M$14:$M$64,MATCH($B16,'3. Costeo y Precios'!$A$14:$A$64,0)),0) -> 0 | I16: =IF($B16="","",E16*H16) | K16: =IF($B16="","",G16*J16) | L16: =IF($B16="","",G16-I16-K16) | M16: =IFERROR(L16/G16,"")
C17: =IFERROR(INDEX('3. Costeo y Precios'!$B$14:$B$64,MATCH($B17,'3. Costeo y Precios'!$A$14:$A$64,0)),"") | G17: =IF($B17="","",E17*F17) | H17: =IFERROR(INDEX('3. Costeo y Precios'!$M$14:$M$64,MATCH($B17,'3. Costeo y Precios'!$A$14:$A$64,0)),0) -> 0 | I17: =IF($B17="","",E17*H17) | K17: =IF($B17="","",G17*J17) | L17: =IF($B17="","",G17-I17-K17) | M17: =IFERROR(L17/G17,"")
C18: =IFERROR(INDEX('3. Costeo y Precios'!$B$14:$B$64,MATCH($B18,'3. Costeo y Precios'!$A$14:$A$64,0)),"") | G18: =IF($B18="","",E18*F18) | H18: =IFERROR(INDEX('3. Costeo y Precios'!$M$14:$M$64,MATCH($B18,'3. Costeo y Precios'!$A$14:$A$64,0)),0) -> 0 | I18: =IF($B18="","",E18*H18) | K18: =IF($B18="","",G18*J18) | L18: =IF($B18="","",G18-I18-K18) | M18: =IFERROR(L18/G18,"")
C19: =IFERROR(INDEX('3. Costeo y Precios'!$B$14:$B$64,MATCH($B19,'3. Costeo y Precios'!$A$14:$A$64,0)),"") | G19: =IF($B19="","",E19*F19) | H19: =IFERROR(INDEX('3. Costeo y Precios'!$M$14:$M$64,MATCH($B19,'3. Costeo y Precios'!$A$14:$A$64,0)),0) -> 0 | I19: =IF($B19="","",E19*H19) | K19: =IF($B19="","",G19*J19) | L19: =IF($B19="","",G19-I19-K19) | M19: =IFERROR(L19/G19,"")
C20: =IFERROR(INDEX('3. Costeo y Precios'!$B$14:$B$64,MATCH($B20,'3. Costeo y Precios'!$A$14:$A$64,0)),"") | G20: =IF($B20="","",E20*F20) | H20: =IFERROR(INDEX('3. Costeo y Precios'!$M$14:$M$64,MATCH($B20,'3. Costeo y Precios'!$A$14:$A$64,0)),0) -> 0 | I20: =IF($B20="","",E20*H20) | K20: =IF($B20="","",G20*J20) | L20: =IF($B20="","",G20-I20-K20) | M20: =IFERROR(L20/G20,"")
C21: =IFERROR(INDEX('3. Costeo y Precios'!$B$14:$B$64,MATCH($B21,'3. Costeo y Precios'!$A$14:$A$64,0)),"") | G21: =IF($B21="","",E21*F21) | H21: =IFERROR(INDEX('3. Costeo y Precios'!$M$14:$M$64,MATCH($B21,'3. Costeo y Precios'!$A$14:$A$64,0)),0) -> 0 | I21: =IF($B21="","",E21*H21) | K21: =IF($B21="","",G21*J21) | L21: =IF($B21="","",G21-I21-K21) | M21: =IFERROR(L21/G21,"")
C22: =IFERROR(INDEX('3. Costeo y Precios'!$B$14:$B$64,MATCH($B22,'3. Costeo y Precios'!$A$14:$A$64,0)),"") | G22: =IF($B22="","",E22*F22) | H22: =IFERROR(INDEX('3. Costeo y Precios'!$M$14:$M$64,MATCH($B22,'3. Costeo y Precios'!$A$14:$A$64,0)),0) -> 0 | I22: =IF($B22="","",E22*H22) | K22: =IF($B22="","",G22*J22) | L22: =IF($B22="","",G22-I22-K22) | M22: =IFERROR(L22/G22,"")
... C407: =IFERROR(INDEX('3. Costeo y Precios'!$B$14:$B$64,MATCH($B407,'3. Costeo y Precios'!$A$14:$A$64,0)),"") | G407: =IF($B407="","",E407*F407) | H407: =IFERROR(INDEX('3. Costeo y Precios'!$M$14:$M$64,MATCH($B407,'3. Costeo y Precios'!$A$14:$A$64,0)),0) -> 0 | I407: =IF($B407="","",E407*H407) | K407: =IF($B407="","",G407*J407) | L407: =IF($B407="","",G407-I407-K407) | M407: =IFERROR(L407/G407,"")

Sheet 6. Gastos Fijos
A1: 6 · GASTOS FIJOS, MANO DE OBRA Y PUNTO DE EQUILIBRIO
A2: De aquí salen el overhead por pieza y el costo por hora que usa la hoja de costeo.
B4: A · GASTOS FIJOS MENSUALES (MXN)
B5: Renta del espacio de producción | C5: 2500
B6: Gas de la vaporera y servicios | C6: 900
B7: Internet y telefonía | C7: 600
B8: Publicidad y anuncios pagados | C8: 1000
B9: Papelería, limpieza y consumibles generales | C9: 250
B10: Suscripciones y software (diseño, facturación) | C10: 200
B11: Transporte y repartos | C11: 400
B12: Depreciación de equipo (vaporera, congelador) | C12: 150
B13: Sueldos fijos de terceros | C13: 1000
B14: Otros gastos fijos | C14: 150
B15: TOTAL DE GASTOS FIJOS AL MES | C15: =SUM(C5:C14) -> 7150
B17: B · OVERHEAD POR PIEZA
B18: Piezas que produces al mes (estimado) | C18: 1000
B19: Overhead prorrateado por pieza | C19: =IFERROR($C$15/$C$18,0) -> 7.15 | D19: Se enlaza automáticamente a la hoja «3. Costeo y Precios».
B21: C · COSTO DE TU MANO DE OBRA
B22: Sueldo mensual que quieres cobrarte (MXN) | C22: 12000
B23: Horas de trabajo al mes | C23: 160
B24: Costo de mano de obra por hora | C24: =IFERROR($C$22/$C$23,0) -> 75
B26: D · PUNTO DE EQUILIBRIO
B27: Precio de venta promedio por pieza | C27: =IFERROR(AVERAGE('3. Costeo y Precios'!$N$14:$N$64),0) -> 90.686275 | D27: Promedio del PVP sugerido del canal Menudeo por pieza.
B28: Costo total unitario promedio | C28: =IFERROR(AVERAGE('3. Costeo y Precios'!$M$14:$M$64),0) -> 44.148049
B29: Margen de contribución por pieza | C29: =$C$27-$C$28 -> 46.538225
B30: PIEZAS QUE DEBES VENDER AL MES PARA NO PERDER | C30: =IFERROR(ROUNDUP($C$15/$C$29,0),0) -> 154
B31: Ingreso mensual de equilibrio | C31: =$C$30*$C$27 -> 13965.686

Sheet 7. Tablero
A1: 7 · TABLERO DEL MES
A2: Escribe cualquier día del mes que quieras analizar y todo el tablero se actualiza.
B4: Mes a analizar (escribe cualquier fecha de ese mes) | C4: 46235
B5: Inicio del periodo | C5: =DATE(YEAR(C4),MONTH(C4),1) -> 46235
B6: Fin del periodo (exclusivo) | C6: =DATE(YEAR(C4),MONTH(C4)+1,1) -> 46266
B8: PRODUCCIÓN Y MERMA DEL MES
B9: Piezas vendidas | C9: =SUMIFS('5. Ventas'!$E$8:$E$407,'5. Ventas'!$A$8:$A$407,">="&$C$5,'5. Ventas'!$A$8:$A$407,"<"&$C$6) -> 96 | E9: Piezas buenas producidas | F9: =SUMIFS('4. Producción y Merma'!$F$8:$F$207,'4. Producción y Merma'!$A$8:$A$207,">="&$C$5,'4. Producción y Merma'!$A$8:$A$207,"<"&$C$6) -> 56
B10: Ingreso del mes | C10: =SUMIFS('5. Ventas'!$G$8:$G$407,'5. Ventas'!$A$8:$A$407,">="&$C$5,'5. Ventas'!$A$8:$A$407,"<"&$C$6) -> 9660 | E10: Piezas falladas | F10: =SUMIFS('4. Producción y Merma'!$G$8:$G$207,'4. Producción y Merma'!$A$8:$A$207,">="&$C$5,'4. Producción y Merma'!$A$8:$A$207,"<"&$C$6) -> 4
B11: Costo de producto vendido | C11: =SUMIFS('5. Ventas'!$I$8:$I$407,'5. Ventas'!$A$8:$A$407,">="&$C$5,'5. Ventas'!$A$8:$A$407,"<"&$C$6) -> 3838.2248 | E11: % de merma del mes | F11: =IFERROR(F10/(F9+F10),0) -> 0.066666667
B12: Utilidad neta del mes | C12: =SUMIFS('5. Ventas'!$L$8:$L$407,'5. Ventas'!$A$8:$A$407,">="&$C$5,'5. Ventas'!$A$8:$A$407,"<"&$C$6) -> 5821.7752 | E12: Dinero perdido en merma | F12: =SUMIFS('4. Producción y Merma'!$K$8:$K$207,'4. Producción y Merma'!$A$8:$A$207,">="&$C$5,'4. Producción y Merma'!$A$8:$A$207,"<"&$C$6) -> 190.54505
B13: Margen neto | C13: =IFERROR(C12/C10,0) -> 0.60266824 | E13: Merma como % del ingreso | F13: =IFERROR(F12/C10,0) -> 0.01972516
B14: Ticket promedio por pieza | C14: =IFERROR(C10/C9,0) -> 100.625 | E14: Punto de equilibrio (piezas) | F14: ='6. Gastos Fijos'!$C$30 -> 154
B15: Avance al punto de equilibrio | C15: =IFERROR(C9/F14,0) -> 0.62337662
B16: Utilidad después de gastos fijos | C16: =C12-'6. Gastos Fijos'!$C$15 -> -1328.2248
B18: VENTAS POR CANAL
B19: Canal | C19: Piezas | E19: Ingreso | F19: Utilidad neta
B20: Menudeo por pieza | C20: =SUMIFS('5. Ventas'!$E$8:$E$407,'5. Ventas'!$A$8:$A$407,">="&$C$5,'5. Ventas'!$A$8:$A$407,"<"&$C$6,'5. Ventas'!$D$8:$D$407,$B20) -> 12 | E20: =SUMIFS('5. Ventas'!$G$8:$G$407,'5. Ventas'!$A$8:$A$407,">="&$C$5,'5. Ventas'!$A$8:$A$407,"<"&$C$6,'5. Ventas'!$D$8:$D$407,$B20) -> 1140 | F20: =SUMIFS('5. Ventas'!$L$8:$L$407,'5. Ventas'!$A$8:$A$407,">="&$C$5,'5. Ventas'!$A$8:$A$407,"<"&$C$6,'5. Ventas'!$D$8:$D$407,$B20) -> 636.57062
B21: Docena por encargo | C21: =SUMIFS('5. Ventas'!$E$8:$E$407,'5. Ventas'!$A$8:$A$407,">="&$C$5,'5. Ventas'!$A$8:$A$407,"<"&$C$6,'5. Ventas'!$D$8:$D$407,$B21) -> 24 | E21: =SUMIFS('5. Ventas'!$G$8:$G$407,'5. Ventas'!$A$8:$A$407,">="&$C$5,'5. Ventas'!$A$8:$A$407,"<"&$C$6,'5. Ventas'!$D$8:$D$407,$B21) -> 1920 | F21: =SUMIFS('5. Ventas'!$L$8:$L$407,'5. Ventas'!$A$8:$A$407,">="&$C$5,'5. Ventas'!$A$8:$A$407,"<"&$C$6,'5. Ventas'!$D$8:$D$407,$B21) -> 640.31818
B22: Evento y banquete | C22: =SUMIFS('5. Ventas'!$E$8:$E$407,'5. Ventas'!$A$8:$A$407,">="&$C$5,'5. Ventas'!$A$8:$A$407,"<"&$C$6,'5. Ventas'!$D$8:$D$407,$B22) -> 60 | E22: =SUMIFS('5. Ventas'!$G$8:$G$407,'5. Ventas'!$A$8:$A$407,">="&$C$5,'5. Ventas'!$A$8:$A$407,"<"&$C$6,'5. Ventas'!$D$8:$D$407,$B22) -> 6600 | F22: =SUMIFS('5. Ventas'!$L$8:$L$407,'5. Ventas'!$A$8:$A$407,">="&$C$5,'5. Ventas'!$A$8:$A$407,"<"&$C$6,'5. Ventas'!$D$8:$D$407,$B22) -> 4544.8864
B23: Mayoreo / reventa | C23: =SUMIFS('5. Ventas'!$E$8:$E$407,'5. Ventas'!$A$8:$A$407,">="&$C$5,'5. Ventas'!$A$8:$A$407,"<"&$C$6,'5. Ventas'!$D$8:$D$407,$B23) -> 0 | E23: =SUMIFS('5. Ventas'!$G$8:$G$407,'5. Ventas'!$A$8:$A$407,">="&$C$5,'5. Ventas'!$A$8:$A$407,"<"&$C$6,'5. Ventas'!$D$8:$D$407,$B23) -> 0 | F23: =SUMIFS('5. Ventas'!$L$8:$L$407,'5. Ventas'!$A$8:$A$407,">="&$C$5,'5. Ventas'!$A$8:$A$407,"<"&$C$6,'5. Ventas'!$D$8:$D$407,$B23) -> 0
B24: Temporada | C24: =SUMIFS('5. Ventas'!$E$8:$E$407,'5. Ventas'!$A$8:$A$407,">="&$C$5,'5. Ventas'!$A$8:$A$407,"<"&$C$6,'5. Ventas'!$D$8:$D$407,$B24) -> 0 | E24: =SUMIFS('5. Ventas'!$G$8:$G$407,'5. Ventas'!$A$8:$A$407,">="&$C$5,'5. Ventas'!$A$8:$A$407,"<"&$C$6,'5. Ventas'!$D$8:$D$407,$B24) -> 0 | F24: =SUMIFS('5. Ventas'!$L$8:$L$407,'5. Ventas'!$A$8:$A$407,">="&$C$5,'5. Ventas'!$A$8:$A$407,"<"&$C$6,'5. Ventas'!$D$8:$D$407,$B24) -> 0
B25: Venta en línea | C25: =SUMIFS('5. Ventas'!$E$8:$E$407,'5. Ventas'!$A$8:$A$407,">="&$C$5,'5. Ventas'!$A$8:$A$407,"<"&$C$6,'5. Ventas'!$D$8:$D$407,$B25) -> 0 | E25: =SUMIFS('5. Ventas'!$G$8:$G$407,'5. Ventas'!$A$8:$A$407,">="&$C$5,'5. Ventas'!$A$8:$A$407,"<"&$C$6,'5. Ventas'!$D$8:$D$407,$B25) -> 0 | F25: =SUMIFS('5. Ventas'!$L$8:$L$407,'5. Ventas'!$A$8:$A$407,">="&$C$5,'5. Ventas'!$A$8:$A$407,"<"&$C$6,'5. Ventas'!$D$8:$D$407,$B25) -> 0
B28: DESEMPEÑO POR RECETA
A29: Nº | B29: Receta | C29: Piezas | E29: Ingreso | F29: Utilidad neta
A30: 1 | B30: Baja California: Tamal Estilo Tijuana de Carne de Res Adobada en Hoja de Maíz | C30: =SUMIFS('5. Ventas'!$E$8:$E$407,'5. Ventas'!$A$8:$A$407,">="&$C$5,'5. Ventas'!$A$8:$A$407,"<"&$C$6,'5. Ventas'!$B$8:$B$407,$A30) -> 12 | E30: =SUMIFS('5. Ventas'!$G$8:$G$407,'5. Ventas'!$A$8:$A$407,">="&$C$5,'5. Ventas'!$A$8:$A$407,"<"&$C$6,'5. Ventas'!$B$8:$B$407,$A30) -> 1140 | F30: =SUMIFS('5. Ventas'!$L$8:$L$407,'5. Ventas'!$A$8:$A$407,">="&$C$5,'5. Ventas'!$A$8:$A$407,"<"&$C$6,'5. Ventas'!$B$8:$B$407,$A30) -> 636.57062
A31: 2 | B31: Baja California Sur: Tamal Sudcaliforniano de Res, Cerdo, Aceitunas y Pasas | C31: =SUMIFS('5. Ventas'!$E$8:$E$407,'5. Ventas'!$A$8:$A$407,">="&$C$5,'5. Ventas'!$A$8:$A$407,"<"&$C$6,'5. Ventas'!$B$8:$B$407,$A31) -> 0 | E31: =SUMIFS('5. Ventas'!$G$8:$G$407,'5. Ventas'!$A$8:$A$407,">="&$C$5,'5. Ventas'!$A$8:$A$407,"<"&$C$6,'5. Ventas'!$B$8:$B$407,$A31) -> 0 | F31: =SUMIFS('5. Ventas'!$L$8:$L$407,'5. Ventas'!$A$8:$A$407,">="&$C$5,'5. Ventas'!$A$8:$A$407,"<"&$C$6,'5. Ventas'!$B$8:$B$407,$A31) -> 0
A32: 3 | B32: Sonora: Tamal de Chile Colorado con Puerco Deshebrado | C32: =SUMIFS('5. Ventas'!$E$8:$E$407,'5. Ventas'!$A$8:$A$407,">="&$C$5,'5. Ventas'!$A$8:$A$407,"<"&$C$6,'5. Ventas'!$B$8:$B$407,$A32) -> 0 | E32: =SUMIFS('5. Ventas'!$G$8:$G$407,'5. Ventas'!$A$8:$A$407,">="&$C$5,'5. Ventas'!$A$8:$A$407,"<"&$C$6,'5. Ventas'!$B$8:$B$407,$A32) -> 0 | F32: =SUMIFS('5. Ventas'!$L$8:$L$407,'5. Ventas'!$A$8:$A$407,">="&$C$5,'5. Ventas'!$A$8:$A$407,"<"&$C$6,'5. Ventas'!$B$8:$B$407,$A32) -> 0
A33: 4 | B33: Chihuahua: Tamal Norteño de Chile Pasado con Queso Menonita y Res | C33: =SUMIFS('5. Ventas'!$E$8:$E$407,'5. Ventas'!$A$8:$A$407,">="&$C$5,'5. Ventas'!$A$8:$A$407,"<"&$C$6,'5. Ventas'!$B$8:$B$407,$A33) -> 0 | E33: =SUMIFS('5. Ventas'!$G$8:$G$407,'5. Ventas'!$A$8:$A$407,">="&$C$5,'5. Ventas'!$A$8:$A$407,"<"&$C$6,'5. Ventas'!$B$8:$B$407,$A33) -> 0 | F33: =SUMIFS('5. Ventas'!$L$8:$L$407,'5. Ventas'!$A$8:$A$407,">="&$C$5,'5. Ventas'!$A$8:$A$407,"<"&$C$6,'5. Ventas'!$B$8:$B$407,$A33) -> 0
A34: 5 | B34: Coahuila: Tamal de Costilla de Puerco en Salsa Verde de Tomatillo y Serrano | C34: =SUMIFS('5. Ventas'!$E$8:$E$407,'5. Ventas'!$A$8:$A$407,">="&$C$5,'5. Ventas'!$A$8:$A$407,"<"&$C$6,'5. Ventas'!$B$8:$B$407,$A34) -> 0 | E34: =SUMIFS('5. Ventas'!$G$8:$G$407,'5. Ventas'!$A$8:$A$407,">="&$C$5,'5. Ventas'!$A$8:$A$407,"<"&$C$6,'5. Ventas'!$B$8:$B$407,$A34) -> 0 | F34: =SUMIFS('5. Ventas'!$L$8:$L$407,'5. Ventas'!$A$8:$A$407,">="&$C$5,'5. Ventas'!$A$8:$A$407,"<"&$C$6,'5. Ventas'!$B$8:$B$407,$A34) -> 0
A35: 6 | B35: Nuevo León: Tamal Norteño "De Dedo" de Picadillo Ranchero con Chile Ancho | C35: =SUMIFS('5. Ventas'!$E$8:$E$407,'5. Ventas'!$A$8:$A$407,">="&$C$5,'5. Ventas'!$A$8:$A$407,"<"&$C$6,'5. Ventas'!$B$8:$B$407,$A35) -> 0 | E35: =SUMIFS('5. Ventas'!$G$8:$G$407,'5. Ventas'!$A$8:$A$407,">="&$C$5,'5. Ventas'!$A$8:$A$407,"<"&$C$6,'5. Ventas'!$B$8:$B$407,$A35) -> 0 | F35: =SUMIFS('5. Ventas'!$L$8:$L$407,'5. Ventas'!$A$8:$A$407,">="&$C$5,'5. Ventas'!$A$8:$A$407,"<"&$C$6,'5. Ventas'!$B$8:$B$407,$A35) -> 0
A36: 7 | B36: Tamaulipas: Tamal de Puerco en Salsa de Chile Cascabel y Comino | C36: =SUMIFS('5. Ventas'!$E$8:$E$407,'5. Ventas'!$A$8:$A$407,">="&$C$5,'5. Ventas'!$A$8:$A$407,"<"&$C$6,'5. Ventas'!$B$8:$B$407,$A36) -> 0 | E36: =SUMIFS('5. Ventas'!$G$8:$G$407,'5. Ventas'!$A$8:$A$407,">="&$C$5,'5. Ventas'!$A$8:$A$407,"<"&$C$6,'5. Ventas'!$B$8:$B$407,$A36) -> 0 | F36: =SUMIFS('5. Ventas'!$L$8:$L$407,'5. Ventas'!$A$8:$A$407,">="&$C$5,'5. Ventas'!$A$8:$A$407,"<"&$C$6,'5. Ventas'!$B$8:$B$407,$A36) -> 0
A37: 8 | B37: Sinaloa: Tamal Barbón de Escuinapa (Camarones Enteros con Barbas) | C37: =SUMIFS('5. Ventas'!$E$8:$E$407,'5. Ventas'!$A$8:$A$407,">="&$C$5,'5. Ventas'!$A$8:$A$407,"<"&$C$6,'5. Ventas'!$B$8:$B$407,$A37) -> 0 | E37: =SUMIFS('5. Ventas'!$G$8:$G$407,'5. Ventas'!$A$8:$A$407,">="&$C$5,'5. Ventas'!$A$8:$A$407,"<"&$C$6,'5. Ventas'!$B$8:$B$407,$A37) -> 0 | F37: =SUMIFS('5. Ventas'!$L$8:$L$407,'5. Ventas'!$A$8:$A$407,">="&$C$5,'5. Ventas'!$A$8:$A$407,"<"&$C$6,'5. Ventas'!$B$8:$B$407,$A37) -> 0
A38: 9 | B38: Sinaloa / Sonora: Tamal Tonto de Masa con Chile Colorado (Para Caldos) | C38: =SUMIFS('5. Ventas'!$E$8:$E$407,'5. Ventas'!$A$8:$A$407,">="&$C$5,'5. Ventas'!$A$8:$A$407,"<"&$C$6,'5. Ventas'!$B$8:$B$407,$A38) -> 0 | E38: =SUMIFS('5. Ventas'!$G$8:$G$407,'5. Ventas'!$A$8:$A$407,">="&$C$5,'5. Ventas'!$A$8:$A$407,"<"&$C$6,'5. Ventas'!$B$8:$B$407,$A38) -> 0 | F38: =SUMIFS('5. Ventas'!$L$8:$L$407,'5. Ventas'!$A$8:$A$407,">="&$C$5,'5. Ventas'!$A$8:$A$407,"<"&$C$6,'5. Ventas'!$B$8:$B$407,$A38) -> 0
A39: 10 | B39: Michoacán: Corundas Michoacanas Triangulares en Hoja de Caña | C39: =SUMIFS('5. Ventas'!$E$8:$E$407,'5. Ventas'!$A$8:$A$407,">="&$C$5,'5. Ventas'!$A$8:$A$407,"<"&$C$6,'5. Ventas'!$B$8:$B$407,$A39) -> 0 | E39: =SUMIFS('5. Ventas'!$G$8:$G$407,'5. Ventas'!$A$8:$A$407,">="&$C$5,'5. Ventas'!$A$8:$A$407,"<"&$C$6,'5. Ventas'!$B$8:$B$407,$A39) -> 0 | F39: =SUMIFS('5. Ventas'!$L$8:$L$407,'5. Ventas'!$A$8:$A$407,">="&$C$5,'5. Ventas'!$A$8:$A$407,"<"&$C$6,'5. Ventas'!$B$8:$B$407,$A39) -> 0
A40: 11 | B40: Michoacán: Uchepos Tradicionales de Elote Tierno con Mantequilla | C40: =SUMIFS('5. Ventas'!$E$8:$E$407,'5. Ventas'!$A$8:$A$407,">="&$C$5,'5. Ventas'!$A$8:$A$407,"<"&$C$6,'5. Ventas'!$B$8:$B$407,$A40) -> 0 | E40: =SUMIFS('5. Ventas'!$G$8:$G$407,'5. Ventas'!$A$8:$A$407,">="&$C$5,'5. Ventas'!$A$8:$A$407,"<"&$C$6,'5. Ventas'!$B$8:$B$407,$A40) -> 0 | F40: =SUMIFS('5. Ventas'!$L$8:$L$407,'5. Ventas'!$A$8:$A$407,">="&$C$5,'5. Ventas'!$A$8:$A$407,"<"&$C$6,'5. Ventas'!$B$8:$B$407,$A40) -> 0
A41: 12 | B41: Jalisco: Tamal Tapatío de Lomo de Cerdo en Mole Dulce de Chile Ancho | C41: =SUMIFS('5. Ventas'!$E$8:$E$407,'5. Ventas'!$A$8:$A$407,">="&$C$5,'5. Ventas'!$A$8:$A$407,"<"&$C$6,'5. Ventas'!$B$8:$B$407,$A41) -> 0 | E41: =SUMIFS('5. Ventas'!$G$8:$G$407,'5. Ventas'!$A$8:$A$407,">="&$C$5,'5. Ventas'!$A$8:$A$407,"<"&$C$6,'5. Ventas'!$B$8:$B$407,$A41) -> 0 | F41: =SUMIFS('5. Ventas'!$L$8:$L$407,'5. Ventas'!$A$8:$A$407,">="&$C$5,'5. Ventas'!$A$8:$A$407,"<"&$C$6,'5. Ventas'!$B$8:$B$407,$A41) -> 0
... A80: 51 | B80: Quintana Roo: Tamal Caribeño de Mariscos en Achiote y Habanero Tatemado | C80: =SUMIFS('5. Ventas'!$E$8:$E$407,'5. Ventas'!$A$8:$A$407,">="&$C$5,'5. Ventas'!$A$8:$A$407,"<"&$C$6,'5. Ventas'!$B$8:$B$407,$A80) -> 0 | E80: =SUMIFS('5. Ventas'!$G$8:$G$407,'5. Ventas'!$A$8:$A$407,">="&$C$5,'5. Ventas'!$A$8:$A$407,"<"&$C$6,'5. Ventas'!$B$8:$B$407,$A80) -> 0 | F80: =SUMIFS('5. Ventas'!$L$8:$L$407,'5. Ventas'!$A$8:$A$407,">="&$C$5,'5. Ventas'!$A$8:$A$407,"<"&$C$6,'5. Ventas'!$B$8:$B$407,$A80) -> 0
