Workbook

Sheet Léame
A1: VELAS COMESTIBLES · Calculadora de Costos, Merma y Precios
A2: Endulcora · Estudio Gastronómico — herramienta complementaria del eBook «Velas Comestibles: El Arte de Derretir Sabores»
B4: CÓMO USAR ESTE ARCHIVO
B5: Orden de trabajo | C5: 1) Actualiza precios en «1. Insumos» → 2) Revisa «3. Costeo y Precios» → 3) Registra cada producción en «4. Producción y Merma» → 4) Registra cada venta en «5. Ventas» → 5) Lee resultados en «7. Tablero».
B6: 1. Insumos | C6: Catálogo con los 106 insumos que aparecen en las 50 recetas del libro. Escribe la presentación que compras y su precio; el costo por gramo/ml se calcula solo. Los precios vienen precargados como REFERENCIA orientativa (CDMX 2026) y debes reemplazarlos por los tuyos.
B7: 2. Recetas | C7: Las 50 formulaciones del libro ya cargadas, con sus 271 líneas de ingredientes. Jala el costo del catálogo y calcula el costo de insumos de cada vela. No necesitas tocar esta hoja salvo que quieras ajustar gramajes.
B8: 3. Costeo y Precios | C8: El corazón del archivo. Suma insumos + empaque + energía + mano de obra + overhead, aplica la merma y calcula el precio de venta sugerido para los cuatro canales del libro. Edita solo las columnas azules.
B9: 4. Producción y Merma | C9: Bitácora de cada lote: piezas buenas, piezas falladas, causa y costo real de lo que se perdió. Te dice si tu % de merma supuesto es el verdadero.
B10: 5. Ventas | C10: Bitácora de ventas por pieza y canal, con comisiones de plataforma y utilidad neta automática.
B11: 6. Gastos Fijos | C11: Renta, servicios, publicidad y tu sueldo. De aquí salen el overhead por pieza, el costo por hora de mano de obra y el punto de equilibrio.
B12: 7. Tablero | C12: Resumen del mes que elijas: ingresos, utilidad, margen, merma, ranking de recetas y avance hacia el punto de equilibrio.
B13: CÓDIGO DE COLORES
B14: Texto azul sobre fondo crema | C14: Celda que TÚ editas (dato de entrada). Es lo único que debes escribir.
B15: Texto negro | C15: Fórmula automática. No la borres.
B16: Texto verde | C16: Dato que viene de otra hoja del mismo archivo.
B17: Fondo amarillo | C17: Supuesto clave: revísalo antes de fijar precios.
B18: FÓRMULAS QUE USA (Cap. 10 del libro)
B19: Costo por unidad | C19: Precio de compra ÷ Cantidad de la presentación
B20: Costo de insumos | C20: Suma de (cantidad × costo por gramo) de cada ingrediente
B21: Costo base | C21: Insumos + Empaque + Energía + Mano de obra + Overhead
B22: Costo total unitario | C22: Costo base ÷ (1 − % merma) ← se divide, no se suma
B23: Precio de venta (PVP) | C23: Costo total ÷ (1 − margen objetivo)
B24: Utilidad por pieza | C24: PVP − Costo total unitario
B25: Punto de equilibrio | C25: Gastos fijos ÷ (Precio promedio − Costo total unitario promedio)
B26: ADVERTENCIAS
B27: Precios de referencia | C27: Los precios precargados en «1. Insumos» son estimaciones de mercado, NO cotizaciones. Actualízalos con tus tickets reales antes de tomar cualquier decisión de precio.
B28: Merma por nivel | C28: Principiante 15–25 % · Intermedio 8–15 % · Avanzado 3–8 %. El archivo arranca en 15 %.
B29: Revisión estacional | C29: Mantequilla, chocolate y empaque cambian de precio. Recostea al menos cada temporada.
B31: Endulcora · Estudio Gastronómico
B32: Contenido: Chef Luis Alfonso Jiménez Cárdenas · Edición: Manuel Ramiro Justo Guzmán · WhatsApp 5665271901

Sheet 1. Insumos
A1: 1 · CATÁLOGO DE INSUMOS
A2: Escribe la presentación que compras y su precio. El costo por unidad se recalcula solo y actualiza las 50 recetas.
A4: Categoría | B4: Insumo | C4: Unidad base | D4: Cantidad de la presentación | E4: Precio de compra (MXN) | F4: Costo por unidad (MXN) | G4: Proveedor | H4: Última actualización | I4: Notas
A5: Aceites | B5: Aceite de ajonjolí tostado | C5: ml | D5: 250 | E5: 120 | F5: =IFERROR(E5/D5,0) -> 0.48 | I5: Precio de referencia — actualízalo
A6: Aceites | B6: Aceite de oliva virgen extra | C6: ml | D6: 500 | E6: 165 | F6: =IFERROR(E6/D6,0) -> 0.33
A7: Aromáticos premium | B7: Aceite de trufa negra | C7: ml | D7: 100 | E7: 290 | F7: =IFERROR(E7/D7,0) -> 2.9
A8: Aromáticos premium | B8: Carpaccio de trufa negra finamente picado | C8: g | D8: 50 | E8: 460 | F8: =IFERROR(E8/D8,0) -> 9.2
A9: Aromáticos premium | B9: Flores de lavanda culinaria | C9: g | D9: 50 | E9: 150 | F9: =IFERROR(E9/D9,0) -> 3
A10: Aromáticos premium | B10: Frambuesa liofilizada | C10: g | D10: 50 | E10: 175 | F10: =IFERROR(E10/D10,0) -> 3.5
A11: Aromáticos premium | B11: Granos de café tostado | C11: g | D11: 250 | E11: 145 | F11: =IFERROR(E11/D11,0) -> 0.58
A12: Aromáticos premium | B12: Pétalos de rosa comestibles | C12: g | D12: 20 | E12: 140 | F12: =IFERROR(E12/D12,0) -> 7
A13: Aromáticos premium | B13: Té Matcha de grado culinario alto | C13: g | D13: 100 | E13: 340 | F13: =IFERROR(E13/D13,0) -> 3.4
A14: Aromáticos premium | B14: Vaina de vainilla de Papantla | C14: pza | D14: 5 | E14: 320 | F14: =IFERROR(E14/D14,0) -> 64
A15: Chiles | B15: Chile ancho seco | C15: g | D15: 100 | E15: 45 | F15: =IFERROR(E15/D15,0) -> 0.45
A16: Chiles | B16: Chile chipotle seco | C16: g | D16: 100 | E16: 60 | F16: =IFERROR(E16/D16,0) -> 0.6
A17: Chiles | B17: Chile de árbol seco quebrado | C17: g | D17: 100 | E17: 45 | F17: =IFERROR(E17/D17,0) -> 0.45
... A110: Semillas | B110: Semillas de cilantro | C110: g | D110: 100 | E110: 45 | F110: =IFERROR(E110/D110,0) -> 0.45
B112: Supuesto: los precios cargados son estimaciones de mercado minorista en CDMX (2026) provistas como punto de partida, no cotizaciones de proveedor. Fuente: estimación del preparador de la hoja. Sustitúyelos por tus tickets reales.

Sheet 2. Recetas
A1: 2 · RECETAS (LISTA DE MATERIALES)
A2: Las 50 formulaciones del eBook. Ajusta la columna «Cantidad» solo si modificas la receta original.
A4: Nº | B4: Receta | C4: Insumo | D4: Cantidad | E4: Unidad | F4: Costo por unidad (MXN) | G4: Costo del ingrediente (MXN) | H4: Descripción original del libro
A5: 1 | B5: Vela de Mantequilla de Ajo Rostizado y Romero Fresco | C5: Mantequilla sin sal | D5: 250 | E5: g | F5: {=IFERROR(INDEX('1. Insumos'!$F$5:$F$110,MATCH($C5,'1. Insumos'!$B$5:$B$110,0)),0)} -> 0.22 | G5: =D5*F5 -> 55 | H5: Mantequilla sin sal (mín. 82 % materia grasa)
A6: 1 | B6: Vela de Mantequilla de Ajo Rostizado y Romero Fresco | C6: Puré de ajo rostizado | D6: 40 | E6: g | F6: {=IFERROR(INDEX('1. Insumos'!$F$5:$F$110,MATCH($C6,'1. Insumos'!$B$5:$B$110,0)),0)} -> 0.26 | G6: =D6*F6 -> 10.4 | H6: Puré de ajo rostizado (~1 cabeza grande)
A7: 1 | B7: Vela de Mantequilla de Ajo Rostizado y Romero Fresco | C7: Aceite de oliva virgen extra | D7: 15 | E7: ml | F7: {=IFERROR(INDEX('1. Insumos'!$F$5:$F$110,MATCH($C7,'1. Insumos'!$B$5:$B$110,0)),0)} -> 0.33 | G7: =D7*F7 -> 4.95 | H7: Aceite de oliva virgen extra (para rostizar)
A8: 1 | B8: Vela de Mantequilla de Ajo Rostizado y Romero Fresco | C8: Romero fresco | D8: 6 | E8: g | F8: {=IFERROR(INDEX('1. Insumos'!$F$5:$F$110,MATCH($C8,'1. Insumos'!$B$5:$B$110,0)),0)} -> 0.56 | G8: =D8*F8 -> 3.36 | H8: Romero fresco, finamente picado y sin tallo
A9: 1 | B9: Vela de Mantequilla de Ajo Rostizado y Romero Fresco | C9: Sal en escamas | D9: 4 | E9: g | F9: {=IFERROR(INDEX('1. Insumos'!$F$5:$F$110,MATCH($C9,'1. Insumos'!$B$5:$B$110,0)),0)} -> 0.76 | G9: =D9*F9 -> 3.04 | H9: Sal de mar en escamas
A10: 1 | B10: Vela de Mantequilla de Ajo Rostizado y Romero Fresco | C10: Pabilo de algodón orgánico puro | D10: 1 | E10: pza | F10: {=IFERROR(INDEX('1. Insumos'!$F$5:$F$110,MATCH($C10,'1. Insumos'!$B$5:$B$110,0)),0)} -> 3.6 | G10: =D10*F10 -> 3.6 | H10: Pabilo de algodón orgánico puro
A11: 2 | B11: Vela de Mantequilla a las Finas Hierbas (Tomillo, Orégano, Salvia) | C11: Mantequilla sin sal | D11: 250 | E11: g | F11: {=IFERROR(INDEX('1. Insumos'!$F$5:$F$110,MATCH($C11,'1. Insumos'!$B$5:$B$110,0)),0)} -> 0.22 | G11: =D11*F11 -> 55 | H11: Mantequilla sin sal (mín. 82 %)
A12: 2 | B12: Vela de Mantequilla a las Finas Hierbas (Tomillo, Orégano, Salvia) | C12: Tomillo fresco | D12: 3 | E12: g | F12: {=IFERROR(INDEX('1. Insumos'!$F$5:$F$110,MATCH($C12,'1. Insumos'!$B$5:$B$110,0)),0)} -> 0.56 | G12: =D12*F12 -> 1.68 | H12: Tomillo fresco (solo hojas, picadas)
A13: 2 | B13: Vela de Mantequilla a las Finas Hierbas (Tomillo, Orégano, Salvia) | C13: Orégano fresco | D13: 3 | E13: g | F13: {=IFERROR(INDEX('1. Insumos'!$F$5:$F$110,MATCH($C13,'1. Insumos'!$B$5:$B$110,0)),0)} -> 0.56 | G13: =D13*F13 -> 1.68 | H13: Orégano fresco (finamente picado)
A14: 2 | B14: Vela de Mantequilla a las Finas Hierbas (Tomillo, Orégano, Salvia) | C14: Salvia fresca | D14: 4 | E14: g | F14: {=IFERROR(INDEX('1. Insumos'!$F$5:$F$110,MATCH($C14,'1. Insumos'!$B$5:$B$110,0)),0)} -> 0.64 | G14: =D14*F14 -> 2.56 | H14: Salvia fresca (finamente picada)
A15: 2 | B15: Vela de Mantequilla a las Finas Hierbas (Tomillo, Orégano, Salvia) | C15: Sal fina | D15: 4 | E15: g | F15: {=IFERROR(INDEX('1. Insumos'!$F$5:$F$110,MATCH($C15,'1. Insumos'!$B$5:$B$110,0)),0)} -> 0.025 | G15: =D15*F15 -> 0.1 | H15: Sal fina de mesa
A16: 2 | B16: Vela de Mantequilla a las Finas Hierbas (Tomillo, Orégano, Salvia) | C16: Pabilo de algodón orgánico puro | D16: 1 | E16: pza | F16: {=IFERROR(INDEX('1. Insumos'!$F$5:$F$110,MATCH($C16,'1. Insumos'!$B$5:$B$110,0)),0)} -> 3.6 | G16: =D16*F16 -> 3.6 | H16: Pabilo de algodón orgánico puro
... A275: 50 | B275: Vela Vegana Estilo Ghee con Especias Chai | C275: Pabilo de algodón orgánico puro | D275: 1 | E275: pza | F275: {=IFERROR(INDEX('1. Insumos'!$F$5:$F$110,MATCH($C275,'1. Insumos'!$B$5:$B$110,0)),0)} -> 3.6 | G275: =D275*F275 -> 3.6 | H275: Pabilo de algodón orgánico puro

Sheet 3. Costeo y Precios
A1: 3 · COSTEO Y PRECIO DE VENTA POR RECETA
A2: Edita solo las columnas azules: empaque, energía, minutos de trabajo y % de merma. Todo lo demás se calcula.
A4: PARÁMETROS GLOBALES · márgenes recomendados por canal (Cap. 10.3 del eBook)
A5: Margen objetivo — Regalo gourmet (menudeo) | C5: 0.6 | D5: Rango del libro: 55 % – 70 %
A6: Margen objetivo — Restaurante (platillo de firma) | C6: 0.7 | D6: Rango del libro: 65 % – 80 %
A7: Margen objetivo — Recuerdo de evento personalizado | C7: 0.65 | D7: Rango del libro: 55 % – 75 %
A8: Margen objetivo — Mayoreo / banquete (volumen) | C8: 0.4 | D8: Rango del libro: 35 % – 50 %
A9: Costo de mano de obra por hora (viene de Gastos Fijos) | C9: ='6. Gastos Fijos'!$C$24 -> 75
A10: Overhead por pieza (viene de Gastos Fijos) | C10: ='6. Gastos Fijos'!$C$19 -> 35.75
A11: % de merma por defecto | C11: 0.15 | D11: Principiante 15–25 % · Intermedio 8–15 % · Avanzado 3–8 %
A13: Nº | B13: Receta | C13: Costo de insumos | D13: Empaque | E13: Energía y consumibles | F13: Minutos por pieza | G13: Mano de obra | H13: Overhead | I13: COSTO BASE | J13: % Merma | K13: COSTO TOTAL UNITARIO | L13: PVP Regalo gourmet | M13: Utilidad Regalo | N13: PVP Restaurante | O13: Utilidad Restaurante | P13: PVP Recuerdo de evento | Q13: Utilidad Evento | R13: PVP Mayoreo / banquete | S13: Utilidad Mayoreo | T13: Margen real Regalo
A14: 1 | B14: Vela de Mantequilla de Ajo Rostizado y Romero Fresco | C14: =SUMIFS('2. Recetas'!$G$5:$G$275,'2. Recetas'!$A$5:$A$275,$A14) -> 80.35 | D14: 18 | E14: 4 | F14: 8 | G14: =$C$9*F14/60 -> 10 | H14: =$C$10 -> 35.75 | I14: =C14+D14+E14+G14+H14 -> 148.1 | J14: =$C$11 -> 0.15 | K14: =IFERROR(I14/(1-J14),0) -> 174.23529 | L14: =IFERROR(CEILING(K14/(1-$C$5),10),0) -> 440 | M14: =L14-K14 -> 265.76471 | N14: =IFERROR(CEILING(K14/(1-$C$6),10),0) -> 590 | O14: =N14-K14 -> 415.76471 | P14: =IFERROR(CEILING(K14/(1-$C$7),10),0) -> 500 | Q14: =P14-K14 -> 325.76471 | R14: =IFERROR(CEILING(K14/(1-$C$8),10),0) -> 300 | S14: =R14-K14 -> 125.76471 | T14: =IFERROR(M14/L14,0) -> 0.6040107
A15: 2 | B15: Vela de Mantequilla a las Finas Hierbas (Tomillo, Orégano, Salvia) | C15: =SUMIFS('2. Recetas'!$G$5:$G$275,'2. Recetas'!$A$5:$A$275,$A15) -> 64.62 | D15: 18 | E15: 4 | F15: 8 | G15: =$C$9*F15/60 -> 10 | H15: =$C$10 -> 35.75 | I15: =C15+D15+E15+G15+H15 -> 132.37 | J15: =$C$11 -> 0.15 | K15: =IFERROR(I15/(1-J15),0) -> 155.72941 | L15: =IFERROR(CEILING(K15/(1-$C$5),10),0) -> 390 | M15: =L15-K15 -> 234.27059 | N15: =IFERROR(CEILING(K15/(1-$C$6),10),0) -> 520 | O15: =N15-K15 -> 364.27059 | P15: =IFERROR(CEILING(K15/(1-$C$7),10),0) -> 450 | Q15: =P15-K15 -> 294.27059 | R15: =IFERROR(CEILING(K15/(1-$C$8),10),0) -> 260 | S15: =R15-K15 -> 104.27059 | T15: =IFERROR(M15/L15,0) -> 0.60069382
A16: 3 | B16: Vela de Mantequilla de Trufa Negra y Sal en Escamas | C16: =SUMIFS('2. Recetas'!$G$5:$G$275,'2. Recetas'!$A$5:$A$275,$A16) -> 214.14 | D16: 18 | E16: 4 | F16: 8 | G16: =$C$9*F16/60 -> 10 | H16: =$C$10 -> 35.75 | I16: =C16+D16+E16+G16+H16 -> 281.89 | J16: =$C$11 -> 0.15 | K16: =IFERROR(I16/(1-J16),0) -> 331.63529 | L16: =IFERROR(CEILING(K16/(1-$C$5),10),0) -> 830 | M16: =L16-K16 -> 498.36471 | N16: =IFERROR(CEILING(K16/(1-$C$6),10),0) -> 1110 | O16: =N16-K16 -> 778.36471 | P16: =IFERROR(CEILING(K16/(1-$C$7),10),0) -> 950 | Q16: =P16-K16 -> 618.36471 | R16: =IFERROR(CEILING(K16/(1-$C$8),10),0) -> 560 | S16: =R16-K16 -> 228.36471 | T16: =IFERROR(M16/L16,0) -> 0.6004394
A17: 4 | B17: Vela de Mantequilla de Tomate Deshidratado y Albahaca | C17: =SUMIFS('2. Recetas'!$G$5:$G$275,'2. Recetas'!$A$5:$A$275,$A17) -> 81.9 | D17: 18 | E17: 4 | F17: 8 | G17: =$C$9*F17/60 -> 10 | H17: =$C$10 -> 35.75 | I17: =C17+D17+E17+G17+H17 -> 149.65 | J17: =$C$11 -> 0.15 | K17: =IFERROR(I17/(1-J17),0) -> 176.05882 | L17: =IFERROR(CEILING(K17/(1-$C$5),10),0) -> 450 | M17: =L17-K17 -> 273.94118 | N17: =IFERROR(CEILING(K17/(1-$C$6),10),0) -> 590 | O17: =N17-K17 -> 413.94118 | P17: =IFERROR(CEILING(K17/(1-$C$7),10),0) -> 510 | Q17: =P17-K17 -> 333.94118 | R17: =IFERROR(CEILING(K17/(1-$C$8),10),0) -> 300 | S17: =R17-K17 -> 123.94118 | T17: =IFERROR(M17/L17,0) -> 0.60875817
A18: 5 | B18: Vela de Mantequilla de Chile de Árbol, Limón y Sal de Mar | C18: =SUMIFS('2. Recetas'!$G$5:$G$275,'2. Recetas'!$A$5:$A$275,$A18) -> 61.45 | D18: 18 | E18: 4 | F18: 8 | G18: =$C$9*F18/60 -> 10 | H18: =$C$10 -> 35.75 | I18: =C18+D18+E18+G18+H18 -> 129.2 | J18: =$C$11 -> 0.15 | K18: =IFERROR(I18/(1-J18),0) -> 152 | L18: =IFERROR(CEILING(K18/(1-$C$5),10),0) -> 380 | M18: =L18-K18 -> 228 | N18: =IFERROR(CEILING(K18/(1-$C$6),10),0) -> 510 | O18: =N18-K18 -> 358 | P18: =IFERROR(CEILING(K18/(1-$C$7),10),0) -> 440 | Q18: =P18-K18 -> 288 | R18: =IFERROR(CEILING(K18/(1-$C$8),10),0) -> 260 | S18: =R18-K18 -> 108 | T18: =IFERROR(M18/L18,0) -> 0.6
A19: 6 | B19: Vela de Mantequilla de Cebolla Caramelizada al Balsámico | C19: =SUMIFS('2. Recetas'!$G$5:$G$275,'2. Recetas'!$A$5:$A$275,$A19) -> 64.475 | D19: 18 | E19: 4 | F19: 8 | G19: =$C$9*F19/60 -> 10 | H19: =$C$10 -> 35.75 | I19: =C19+D19+E19+G19+H19 -> 132.225 | J19: =$C$11 -> 0.15 | K19: =IFERROR(I19/(1-J19),0) -> 155.55882 | L19: =IFERROR(CEILING(K19/(1-$C$5),10),0) -> 390 | M19: =L19-K19 -> 234.44118 | N19: =IFERROR(CEILING(K19/(1-$C$6),10),0) -> 520 | O19: =N19-K19 -> 364.44118 | P19: =IFERROR(CEILING(K19/(1-$C$7),10),0) -> 450 | Q19: =P19-K19 -> 294.44118 | R19: =IFERROR(CEILING(K19/(1-$C$8),10),0) -> 260 | S19: =R19-K19 -> 104.44118 | T19: =IFERROR(M19/L19,0) -> 0.60113122
A20: 7 | B20: Vela de Mantequilla de Cilantro, Jalapeño y Ralladura de Limón Verde | C20: =SUMIFS('2. Recetas'!$G$5:$G$275,'2. Recetas'!$A$5:$A$275,$A20) -> 61.36 | D20: 18 | E20: 4 | F20: 8 | G20: =$C$9*F20/60 -> 10 | H20: =$C$10 -> 35.75 | I20: =C20+D20+E20+G20+H20 -> 129.11 | J20: =$C$11 -> 0.15 | K20: =IFERROR(I20/(1-J20),0) -> 151.89412 | L20: =IFERROR(CEILING(K20/(1-$C$5),10),0) -> 380 | M20: =L20-K20 -> 228.10588 | N20: =IFERROR(CEILING(K20/(1-$C$6),10),0) -> 510 | O20: =N20-K20 -> 358.10588 | P20: =IFERROR(CEILING(K20/(1-$C$7),10),0) -> 440 | Q20: =P20-K20 -> 288.10588 | R20: =IFERROR(CEILING(K20/(1-$C$8),10),0) -> 260 | S20: =R20-K20 -> 108.10588 | T20: =IFERROR(M20/L20,0) -> 0.60027864
A21: 8 | B21: Vela de Mantequilla de Pimienta Negra Quebrada y Parmesano | C21: =SUMIFS('2. Recetas'!$G$5:$G$275,'2. Recetas'!$A$5:$A$275,$A21) -> 86.65 | D21: 18 | E21: 4 | F21: 8 | G21: =$C$9*F21/60 -> 10 | H21: =$C$10 -> 35.75 | I21: =C21+D21+E21+G21+H21 -> 154.4 | J21: =$C$11 -> 0.15 | K21: =IFERROR(I21/(1-J21),0) -> 181.64706 | L21: =IFERROR(CEILING(K21/(1-$C$5),10),0) -> 460 | M21: =L21-K21 -> 278.35294 | N21: =IFERROR(CEILING(K21/(1-$C$6),10),0) -> 610 | O21: =N21-K21 -> 428.35294 | P21: =IFERROR(CEILING(K21/(1-$C$7),10),0) -> 520 | Q21: =P21-K21 -> 338.35294 | R21: =IFERROR(CEILING(K21/(1-$C$8),10),0) -> 310 | S21: =R21-K21 -> 128.35294 | T21: =IFERROR(M21/L21,0) -> 0.60511509
A22: 9 | B22: Vela de Mantequilla de Tocino Ahumado y Miel de Maple | C22: =SUMIFS('2. Recetas'!$G$5:$G$275,'2. Recetas'!$A$5:$A$275,$A22) -> 75.3 | D22: 18 | E22: 4 | F22: 8 | G22: =$C$9*F22/60 -> 10 | H22: =$C$10 -> 35.75 | I22: =C22+D22+E22+G22+H22 -> 143.05 | J22: =$C$11 -> 0.15 | K22: =IFERROR(I22/(1-J22),0) -> 168.29412 | L22: =IFERROR(CEILING(K22/(1-$C$5),10),0) -> 430 | M22: =L22-K22 -> 261.70588 | N22: =IFERROR(CEILING(K22/(1-$C$6),10),0) -> 570 | O22: =N22-K22 -> 401.70588 | P22: =IFERROR(CEILING(K22/(1-$C$7),10),0) -> 490 | Q22: =P22-K22 -> 321.70588 | R22: =IFERROR(CEILING(K22/(1-$C$8),10),0) -> 290 | S22: =R22-K22 -> 121.70588 | T22: =IFERROR(M22/L22,0) -> 0.60861833
A23: 10 | B23: Vela de Mantequilla de Queso Azul y Nuez Picada | C23: =SUMIFS('2. Recetas'!$G$5:$G$275,'2. Recetas'!$A$5:$A$275,$A23) -> 85.5 | D23: 18 | E23: 4 | F23: 8 | G23: =$C$9*F23/60 -> 10 | H23: =$C$10 -> 35.75 | I23: =C23+D23+E23+G23+H23 -> 153.25 | J23: =$C$11 -> 0.15 | K23: =IFERROR(I23/(1-J23),0) -> 180.29412 | L23: =IFERROR(CEILING(K23/(1-$C$5),10),0) -> 460 | M23: =L23-K23 -> 279.70588 | N23: =IFERROR(CEILING(K23/(1-$C$6),10),0) -> 610 | O23: =N23-K23 -> 429.70588 | P23: =IFERROR(CEILING(K23/(1-$C$7),10),0) -> 520 | Q23: =P23-K23 -> 339.70588 | R23: =IFERROR(CEILING(K23/(1-$C$8),10),0) -> 310 | S23: =R23-K23 -> 129.70588 | T23: =IFERROR(M23/L23,0) -> 0.60805627
A24: 11 | B24: Vela de Mantequilla de Miso Blanco y Ajonjolí Tostado | C24: =SUMIFS('2. Recetas'!$G$5:$G$275,'2. Recetas'!$A$5:$A$275,$A24) -> 65.26 | D24: 18 | E24: 4 | F24: 8 | G24: =$C$9*F24/60 -> 10 | H24: =$C$10 -> 35.75 | I24: =C24+D24+E24+G24+H24 -> 133.01 | J24: =$C$11 -> 0.15 | K24: =IFERROR(I24/(1-J24),0) -> 156.48235 | L24: =IFERROR(CEILING(K24/(1-$C$5),10),0) -> 400 | M24: =L24-K24 -> 243.51765 | N24: =IFERROR(CEILING(K24/(1-$C$6),10),0) -> 530 | O24: =N24-K24 -> 373.51765 | P24: =IFERROR(CEILING(K24/(1-$C$7),10),0) -> 450 | Q24: =P24-K24 -> 293.51765 | R24: =IFERROR(CEILING(K24/(1-$C$8),10),0) -> 270 | S24: =R24-K24 -> 113.51765 | T24: =IFERROR(M24/L24,0) -> 0.60879412
A25: 12 | B25: Vela de Mantequilla de Pimentón de la Vera (Dulce y Picante) | C25: =SUMIFS('2. Recetas'!$G$5:$G$275,'2. Recetas'!$A$5:$A$275,$A25) -> 65.98 | D25: 18 | E25: 4 | F25: 8 | G25: =$C$9*F25/60 -> 10 | H25: =$C$10 -> 35.75 | I25: =C25+D25+E25+G25+H25 -> 133.73 | J25: =$C$11 -> 0.15 | K25: =IFERROR(I25/(1-J25),0) -> 157.32941 | L25: =IFERROR(CEILING(K25/(1-$C$5),10),0) -> 400 | M25: =L25-K25 -> 242.67059 | N25: =IFERROR(CEILING(K25/(1-$C$6),10),0) -> 530 | O25: =N25-K25 -> 372.67059 | P25: =IFERROR(CEILING(K25/(1-$C$7),10),0) -> 450 | Q25: =P25-K25 -> 292.67059 | R25: =IFERROR(CEILING(K25/(1-$C$8),10),0) -> 270 | S25: =R25-K25 -> 112.67059 | T25: =IFERROR(M25/L25,0) -> 0.60667647
... A63: 50 | B63: Vela Vegana Estilo Ghee con Especias Chai | C63: =SUMIFS('2. Recetas'!$G$5:$G$275,'2. Recetas'!$A$5:$A$275,$A63) -> 128.95 | D63: 18 | E63: 4 | F63: 8 | G63: =$C$9*F63/60 -> 10 | H63: =$C$10 -> 35.75 | I63: =C63+D63+E63+G63+H63 -> 196.7 | J63: =$C$11 -> 0.15 | K63: =IFERROR(I63/(1-J63),0) -> 231.41176 | L63: =IFERROR(CEILING(K63/(1-$C$5),10),0) -> 580 | M63: =L63-K63 -> 348.58824 | N63: =IFERROR(CEILING(K63/(1-$C$6),10),0) -> 780 | O63: =N63-K63 -> 548.58824 | P63: =IFERROR(CEILING(K63/(1-$C$7),10),0) -> 670 | Q63: =P63-K63 -> 438.58824 | R63: =IFERROR(CEILING(K63/(1-$C$8),10),0) -> 390 | S63: =R63-K63 -> 158.58824 | T63: =IFERROR(M63/L63,0) -> 0.6010142
B64: PROMEDIO DE LAS 50 RECETAS | C64: =AVERAGE(C14:C63) -> 112.13317 | I64: =AVERAGE(I14:I63) -> 179.88317 | K64: =AVERAGE(K14:K63) -> 211.62725 | L64: =AVERAGE(L14:L63) -> 533.8 | M64: =AVERAGE(M14:M63) -> 322.17275 | T64: =AVERAGE(T14:T63) -> 0.60395017
B66: Supuestos de arranque tomados del ejemplo del Capítulo 10: empaque $18 y energía $4 por pieza, 8 minutos de trabajo por vela, merma 15 % (nivel intermedio). Los costos de insumo salen de precios de mercado actuales, por lo que serán más altos que los del ejemplo didáctico del libro. Ajusta todo a tu operación real.

Sheet 4. Producción y Merma
A1: 4 · BITÁCORA DE PRODUCCIÓN Y MERMA
A2: Registra cada lote. La hoja calcula tu merma real y cuánto dinero se fue a la basura.
A3: Piezas buenas acumuladas | D3: =SUM(F8:F207) -> 10
A4: Piezas falladas acumuladas | D4: =SUM(G8:G207) -> 2
A5: % de merma real acumulada | D5: =IFERROR(D4/(D3+D4),0) -> 0.16666667
A6: Costo acumulado de la merma | D6: =SUM(K8:K207) -> 348.47059
A7: Fecha | B7: Lote | C7: Nº receta | D7: Receta | E7: Piezas planeadas | F7: Piezas buenas | G7: Piezas falladas | H7: % merma real | I7: Causa principal | J7: Costo unitario | K7: Costo de la merma | L7: Notas
A8: 46235 | B8: L-2608-01 | C8: 1 | D8: {=IFERROR(INDEX('3. Costeo y Precios'!$B$14:$B$63,MATCH($C8,'3. Costeo y Precios'!$A$14:$A$63,0)),"")} -> Vela de Mantequilla de Ajo Rostizado y Romero Fresco | E8: 12 | F8: 10 | G8: 2 | H8: =IFERROR(G8/(F8+G8),"") -> 0.16666667 | I8: Mecha descentrada | J8: {=IFERROR(INDEX('3. Costeo y Precios'!$K$14:$K$63,MATCH($C8,'3. Costeo y Precios'!$A$14:$A$63,0)),0)} -> 174.23529 | K8: =IF($C8="","",G8*J8) -> 348.47059 | L8: ← Fila de ejemplo: puedes borrarla
C9: 23 | D9: {=IFERROR(INDEX('3. Costeo y Precios'!$B$14:$B$63,MATCH($C9,'3. Costeo y Precios'!$A$14:$A$63,0)),"")} -> Vela de Manteca de Cerdo con Especias de Chorizo | H9: =IFERROR(G9/(F9+G9),"") | J9: {=IFERROR(INDEX('3. Costeo y Precios'!$K$14:$K$63,MATCH($C9,'3. Costeo y Precios'!$A$14:$A$63,0)),0)} -> 124.70588 | K9: =IF($C9="","",G9*J9) -> 0
C10: 5 | D10: {=IFERROR(INDEX('3. Costeo y Precios'!$B$14:$B$63,MATCH($C10,'3. Costeo y Precios'!$A$14:$A$63,0)),"")} -> Vela de Mantequilla de Chile de Árbol, Limón y Sal de Mar | H10: =IFERROR(G10/(F10+G10),"") | J10: {=IFERROR(INDEX('3. Costeo y Precios'!$K$14:$K$63,MATCH($C10,'3. Costeo y Precios'!$A$14:$A$63,0)),0)} -> 152 | K10: =IF($C10="","",G10*J10) -> 0
D11: {=IFERROR(INDEX('3. Costeo y Precios'!$B$14:$B$63,MATCH($C11,'3. Costeo y Precios'!$A$14:$A$63,0)),"")} | H11: =IFERROR(G11/(F11+G11),"") | J11: {=IFERROR(INDEX('3. Costeo y Precios'!$K$14:$K$63,MATCH($C11,'3. Costeo y Precios'!$A$14:$A$63,0)),0)} -> 0 | K11: =IF($C11="","",G11*J11)
D12: {=IFERROR(INDEX('3. Costeo y Precios'!$B$14:$B$63,MATCH($C12,'3. Costeo y Precios'!$A$14:$A$63,0)),"")} | H12: =IFERROR(G12/(F12+G12),"") | J12: {=IFERROR(INDEX('3. Costeo y Precios'!$K$14:$K$63,MATCH($C12,'3. Costeo y Precios'!$A$14:$A$63,0)),0)} -> 0 | K12: =IF($C12="","",G12*J12)
D13: {=IFERROR(INDEX('3. Costeo y Precios'!$B$14:$B$63,MATCH($C13,'3. Costeo y Precios'!$A$14:$A$63,0)),"")} | H13: =IFERROR(G13/(F13+G13),"") | J13: {=IFERROR(INDEX('3. Costeo y Precios'!$K$14:$K$63,MATCH($C13,'3. Costeo y Precios'!$A$14:$A$63,0)),0)} -> 0 | K13: =IF($C13="","",G13*J13)
D14: {=IFERROR(INDEX('3. Costeo y Precios'!$B$14:$B$63,MATCH($C14,'3. Costeo y Precios'!$A$14:$A$63,0)),"")} | H14: =IFERROR(G14/(F14+G14),"") | J14: {=IFERROR(INDEX('3. Costeo y Precios'!$K$14:$K$63,MATCH($C14,'3. Costeo y Precios'!$A$14:$A$63,0)),0)} -> 0 | K14: =IF($C14="","",G14*J14)
D15: {=IFERROR(INDEX('3. Costeo y Precios'!$B$14:$B$63,MATCH($C15,'3. Costeo y Precios'!$A$14:$A$63,0)),"")} | H15: =IFERROR(G15/(F15+G15),"") | J15: {=IFERROR(INDEX('3. Costeo y Precios'!$K$14:$K$63,MATCH($C15,'3. Costeo y Precios'!$A$14:$A$63,0)),0)} -> 0 | K15: =IF($C15="","",G15*J15)
D16: {=IFERROR(INDEX('3. Costeo y Precios'!$B$14:$B$63,MATCH($C16,'3. Costeo y Precios'!$A$14:$A$63,0)),"")} | H16: =IFERROR(G16/(F16+G16),"") | J16: {=IFERROR(INDEX('3. Costeo y Precios'!$K$14:$K$63,MATCH($C16,'3. Costeo y Precios'!$A$14:$A$63,0)),0)} -> 0 | K16: =IF($C16="","",G16*J16)
D17: {=IFERROR(INDEX('3. Costeo y Precios'!$B$14:$B$63,MATCH($C17,'3. Costeo y Precios'!$A$14:$A$63,0)),"")} | H17: =IFERROR(G17/(F17+G17),"") | J17: {=IFERROR(INDEX('3. Costeo y Precios'!$K$14:$K$63,MATCH($C17,'3. Costeo y Precios'!$A$14:$A$63,0)),0)} -> 0 | K17: =IF($C17="","",G17*J17)
D18: {=IFERROR(INDEX('3. Costeo y Precios'!$B$14:$B$63,MATCH($C18,'3. Costeo y Precios'!$A$14:$A$63,0)),"")} | H18: =IFERROR(G18/(F18+G18),"") | J18: {=IFERROR(INDEX('3. Costeo y Precios'!$K$14:$K$63,MATCH($C18,'3. Costeo y Precios'!$A$14:$A$63,0)),0)} -> 0 | K18: =IF($C18="","",G18*J18)
D19: {=IFERROR(INDEX('3. Costeo y Precios'!$B$14:$B$63,MATCH($C19,'3. Costeo y Precios'!$A$14:$A$63,0)),"")} | H19: =IFERROR(G19/(F19+G19),"") | J19: {=IFERROR(INDEX('3. Costeo y Precios'!$K$14:$K$63,MATCH($C19,'3. Costeo y Precios'!$A$14:$A$63,0)),0)} -> 0 | K19: =IF($C19="","",G19*J19)
D20: {=IFERROR(INDEX('3. Costeo y Precios'!$B$14:$B$63,MATCH($C20,'3. Costeo y Precios'!$A$14:$A$63,0)),"")} | H20: =IFERROR(G20/(F20+G20),"") | J20: {=IFERROR(INDEX('3. Costeo y Precios'!$K$14:$K$63,MATCH($C20,'3. Costeo y Precios'!$A$14:$A$63,0)),0)} -> 0 | K20: =IF($C20="","",G20*J20)
D21: {=IFERROR(INDEX('3. Costeo y Precios'!$B$14:$B$63,MATCH($C21,'3. Costeo y Precios'!$A$14:$A$63,0)),"")} | H21: =IFERROR(G21/(F21+G21),"") | J21: {=IFERROR(INDEX('3. Costeo y Precios'!$K$14:$K$63,MATCH($C21,'3. Costeo y Precios'!$A$14:$A$63,0)),0)} -> 0 | K21: =IF($C21="","",G21*J21)
D22: {=IFERROR(INDEX('3. Costeo y Precios'!$B$14:$B$63,MATCH($C22,'3. Costeo y Precios'!$A$14:$A$63,0)),"")} | H22: =IFERROR(G22/(F22+G22),"") | J22: {=IFERROR(INDEX('3. Costeo y Precios'!$K$14:$K$63,MATCH($C22,'3. Costeo y Precios'!$A$14:$A$63,0)),0)} -> 0 | K22: =IF($C22="","",G22*J22)
... D207: {=IFERROR(INDEX('3. Costeo y Precios'!$B$14:$B$63,MATCH($C207,'3. Costeo y Precios'!$A$14:$A$63,0)),"")} | H207: =IFERROR(G207/(F207+G207),"") | J207: {=IFERROR(INDEX('3. Costeo y Precios'!$K$14:$K$63,MATCH($C207,'3. Costeo y Precios'!$A$14:$A$63,0)),0)} -> 0 | K207: =IF($C207="","",G207*J207)

Sheet 5. Ventas
A1: 5 · BITÁCORA DE VENTAS
A2: Una línea por venta. La utilidad neta descuenta el costo real y la comisión de plataforma.
A3: Piezas vendidas acumuladas | D3: =SUM(E8:E407) -> 24
A4: Ingreso total acumulado | D4: =SUM(G8:G407) -> 24280
A5: Utilidad neta total acumulada | D5: =SUM(L8:L407) -> 20416.647
A6: Margen neto promedio | D6: =IFERROR(D5/D4,0) -> 0.84088332
A7: Fecha | B7: Nº receta | C7: Receta | D7: Canal | E7: Piezas | F7: Precio unitario | G7: Ingreso | H7: Costo unitario | I7: Costo total | J7: Comisión % | K7: Comisión $ | L7: Utilidad neta | M7: Margen % | N7: Cliente / Notas
A8: 46236 | B8: 1 | C8: {=IFERROR(INDEX('3. Costeo y Precios'!$B$14:$B$63,MATCH($B8,'3. Costeo y Precios'!$A$14:$A$63,0)),"")} -> Vela de Mantequilla de Ajo Rostizado y Romero Fresco | D8: Regalo gourmet | E8: 4 | F8: 320 | G8: =IF($B8="","",E8*F8) -> 1280 | H8: {=IFERROR(INDEX('3. Costeo y Precios'!$K$14:$K$63,MATCH($B8,'3. Costeo y Precios'!$A$14:$A$63,0)),0)} -> 174.23529 | I8: =IF($B8="","",E8*H8) -> 696.94118 | J8: 0.1 | K8: =IF($B8="","",G8*J8) -> 128 | L8: =IF($B8="","",G8-I8-K8) -> 455.05882 | M8: =IFERROR(L8/G8,"") -> 0.35551471 | N8: ← Fila de ejemplo: puedes borrarla
B9: 5 | C9: {=IFERROR(INDEX('3. Costeo y Precios'!$B$14:$B$63,MATCH($B9,'3. Costeo y Precios'!$A$14:$A$63,0)),"")} -> Vela de Mantequilla de Chile de Árbol, Limón y Sal de Mar | E9: 5 | F9: 1000 | G9: =IF($B9="","",E9*F9) -> 5000 | H9: {=IFERROR(INDEX('3. Costeo y Precios'!$K$14:$K$63,MATCH($B9,'3. Costeo y Precios'!$A$14:$A$63,0)),0)} -> 152 | I9: =IF($B9="","",E9*H9) -> 760 | K9: =IF($B9="","",G9*J9) -> 0 | L9: =IF($B9="","",G9-I9-K9) -> 4240 | M9: =IFERROR(L9/G9,"") -> 0.848
B10: 7 | C10: {=IFERROR(INDEX('3. Costeo y Precios'!$B$14:$B$63,MATCH($B10,'3. Costeo y Precios'!$A$14:$A$63,0)),"")} -> Vela de Mantequilla de Cilantro, Jalapeño y Ralladura de Limón Verde | E10: 15 | F10: 1200 | G10: =IF($B10="","",E10*F10) -> 18000 | H10: {=IFERROR(INDEX('3. Costeo y Precios'!$K$14:$K$63,MATCH($B10,'3. Costeo y Precios'!$A$14:$A$63,0)),0)} -> 151.89412 | I10: =IF($B10="","",E10*H10) -> 2278.4118 | K10: =IF($B10="","",G10*J10) -> 0 | L10: =IF($B10="","",G10-I10-K10) -> 15721.588 | M10: =IFERROR(L10/G10,"") -> 0.87342157
C11: {=IFERROR(INDEX('3. Costeo y Precios'!$B$14:$B$63,MATCH($B11,'3. Costeo y Precios'!$A$14:$A$63,0)),"")} | G11: =IF($B11="","",E11*F11) | H11: {=IFERROR(INDEX('3. Costeo y Precios'!$K$14:$K$63,MATCH($B11,'3. Costeo y Precios'!$A$14:$A$63,0)),0)} -> 0 | I11: =IF($B11="","",E11*H11) | K11: =IF($B11="","",G11*J11) | L11: =IF($B11="","",G11-I11-K11) | M11: =IFERROR(L11/G11,"")
C12: {=IFERROR(INDEX('3. Costeo y Precios'!$B$14:$B$63,MATCH($B12,'3. Costeo y Precios'!$A$14:$A$63,0)),"")} | G12: =IF($B12="","",E12*F12) | H12: {=IFERROR(INDEX('3. Costeo y Precios'!$K$14:$K$63,MATCH($B12,'3. Costeo y Precios'!$A$14:$A$63,0)),0)} -> 0 | I12: =IF($B12="","",E12*H12) | K12: =IF($B12="","",G12*J12) | L12: =IF($B12="","",G12-I12-K12) | M12: =IFERROR(L12/G12,"")
C13: {=IFERROR(INDEX('3. Costeo y Precios'!$B$14:$B$63,MATCH($B13,'3. Costeo y Precios'!$A$14:$A$63,0)),"")} | G13: =IF($B13="","",E13*F13) | H13: {=IFERROR(INDEX('3. Costeo y Precios'!$K$14:$K$63,MATCH($B13,'3. Costeo y Precios'!$A$14:$A$63,0)),0)} -> 0 | I13: =IF($B13="","",E13*H13) | K13: =IF($B13="","",G13*J13) | L13: =IF($B13="","",G13-I13-K13) | M13: =IFERROR(L13/G13,"")
C14: {=IFERROR(INDEX('3. Costeo y Precios'!$B$14:$B$63,MATCH($B14,'3. Costeo y Precios'!$A$14:$A$63,0)),"")} | G14: =IF($B14="","",E14*F14) | H14: {=IFERROR(INDEX('3. Costeo y Precios'!$K$14:$K$63,MATCH($B14,'3. Costeo y Precios'!$A$14:$A$63,0)),0)} -> 0 | I14: =IF($B14="","",E14*H14) | K14: =IF($B14="","",G14*J14) | L14: =IF($B14="","",G14-I14-K14) | M14: =IFERROR(L14/G14,"")
C15: {=IFERROR(INDEX('3. Costeo y Precios'!$B$14:$B$63,MATCH($B15,'3. Costeo y Precios'!$A$14:$A$63,0)),"")} | G15: =IF($B15="","",E15*F15) | H15: {=IFERROR(INDEX('3. Costeo y Precios'!$K$14:$K$63,MATCH($B15,'3. Costeo y Precios'!$A$14:$A$63,0)),0)} -> 0 | I15: =IF($B15="","",E15*H15) | K15: =IF($B15="","",G15*J15) | L15: =IF($B15="","",G15-I15-K15) | M15: =IFERROR(L15/G15,"")
C16: {=IFERROR(INDEX('3. Costeo y Precios'!$B$14:$B$63,MATCH($B16,'3. Costeo y Precios'!$A$14:$A$63,0)),"")} | G16: =IF($B16="","",E16*F16) | H16: {=IFERROR(INDEX('3. Costeo y Precios'!$K$14:$K$63,MATCH($B16,'3. Costeo y Precios'!$A$14:$A$63,0)),0)} -> 0 | I16: =IF($B16="","",E16*H16) | K16: =IF($B16="","",G16*J16) | L16: =IF($B16="","",G16-I16-K16) | M16: =IFERROR(L16/G16,"")
C17: {=IFERROR(INDEX('3. Costeo y Precios'!$B$14:$B$63,MATCH($B17,'3. Costeo y Precios'!$A$14:$A$63,0)),"")} | G17: =IF($B17="","",E17*F17) | H17: {=IFERROR(INDEX('3. Costeo y Precios'!$K$14:$K$63,MATCH($B17,'3. Costeo y Precios'!$A$14:$A$63,0)),0)} -> 0 | I17: =IF($B17="","",E17*H17) | K17: =IF($B17="","",G17*J17) | L17: =IF($B17="","",G17-I17-K17) | M17: =IFERROR(L17/G17,"")
C18: {=IFERROR(INDEX('3. Costeo y Precios'!$B$14:$B$63,MATCH($B18,'3. Costeo y Precios'!$A$14:$A$63,0)),"")} | G18: =IF($B18="","",E18*F18) | H18: {=IFERROR(INDEX('3. Costeo y Precios'!$K$14:$K$63,MATCH($B18,'3. Costeo y Precios'!$A$14:$A$63,0)),0)} -> 0 | I18: =IF($B18="","",E18*H18) | K18: =IF($B18="","",G18*J18) | L18: =IF($B18="","",G18-I18-K18) | M18: =IFERROR(L18/G18,"")
C19: {=IFERROR(INDEX('3. Costeo y Precios'!$B$14:$B$63,MATCH($B19,'3. Costeo y Precios'!$A$14:$A$63,0)),"")} | G19: =IF($B19="","",E19*F19) | H19: {=IFERROR(INDEX('3. Costeo y Precios'!$K$14:$K$63,MATCH($B19,'3. Costeo y Precios'!$A$14:$A$63,0)),0)} -> 0 | I19: =IF($B19="","",E19*H19) | K19: =IF($B19="","",G19*J19) | L19: =IF($B19="","",G19-I19-K19) | M19: =IFERROR(L19/G19,"")
C20: {=IFERROR(INDEX('3. Costeo y Precios'!$B$14:$B$63,MATCH($B20,'3. Costeo y Precios'!$A$14:$A$63,0)),"")} | G20: =IF($B20="","",E20*F20) | H20: {=IFERROR(INDEX('3. Costeo y Precios'!$K$14:$K$63,MATCH($B20,'3. Costeo y Precios'!$A$14:$A$63,0)),0)} -> 0 | I20: =IF($B20="","",E20*H20) | K20: =IF($B20="","",G20*J20) | L20: =IF($B20="","",G20-I20-K20) | M20: =IFERROR(L20/G20,"")
C21: {=IFERROR(INDEX('3. Costeo y Precios'!$B$14:$B$63,MATCH($B21,'3. Costeo y Precios'!$A$14:$A$63,0)),"")} | G21: =IF($B21="","",E21*F21) | H21: {=IFERROR(INDEX('3. Costeo y Precios'!$K$14:$K$63,MATCH($B21,'3. Costeo y Precios'!$A$14:$A$63,0)),0)} -> 0 | I21: =IF($B21="","",E21*H21) | K21: =IF($B21="","",G21*J21) | L21: =IF($B21="","",G21-I21-K21) | M21: =IFERROR(L21/G21,"")
C22: {=IFERROR(INDEX('3. Costeo y Precios'!$B$14:$B$63,MATCH($B22,'3. Costeo y Precios'!$A$14:$A$63,0)),"")} | G22: =IF($B22="","",E22*F22) | H22: {=IFERROR(INDEX('3. Costeo y Precios'!$K$14:$K$63,MATCH($B22,'3. Costeo y Precios'!$A$14:$A$63,0)),0)} -> 0 | I22: =IF($B22="","",E22*H22) | K22: =IF($B22="","",G22*J22) | L22: =IF($B22="","",G22-I22-K22) | M22: =IFERROR(L22/G22,"")
... C407: {=IFERROR(INDEX('3. Costeo y Precios'!$B$14:$B$63,MATCH($B407,'3. Costeo y Precios'!$A$14:$A$63,0)),"")} | G407: =IF($B407="","",E407*F407) | H407: {=IFERROR(INDEX('3. Costeo y Precios'!$K$14:$K$63,MATCH($B407,'3. Costeo y Precios'!$A$14:$A$63,0)),0)} -> 0 | I407: =IF($B407="","",E407*H407) | K407: =IF($B407="","",G407*J407) | L407: =IF($B407="","",G407-I407-K407) | M407: =IFERROR(L407/G407,"")

Sheet 6. Gastos Fijos
A1: 6 · GASTOS FIJOS, MANO DE OBRA Y PUNTO DE EQUILIBRIO
A2: De aquí salen el overhead por pieza y el costo por hora que usa la hoja de costeo.
B4: A · GASTOS FIJOS MENSUALES (MXN)
B5: Renta del espacio de producción | C5: 2500
B6: Luz, gas y agua | C6: 200
B7: Internet y telefonía | C7: 600
B8: Publicidad y anuncios pagados | C8: 1000
B9: Papelería, limpieza y consumibles generales | C9: 200
B10: Suscripciones y software (diseño, facturación) | C10: 200
B11: Transporte y repartos | C11: 200
B12: Depreciación de equipo | C12: 50
B13: Sueldos fijos de terceros | C13: 1500
B14: Otros gastos fijos | C14: 700
B15: TOTAL DE GASTOS FIJOS MENSUALES | C15: =SUM(C5:C14) -> 7150 | D15: Supuesto: arranque desde casa, sin renta (Cap. 10 del eBook usa ~$2,000 de gastos fijos y 200 piezas = $10 de overhead por vela). Sustituye por tus cifras reales.
B17: B · OVERHEAD POR PIEZA
B18: Piezas que produces al mes (estimado) | C18: 200
B19: Overhead prorrateado por pieza | C19: =IFERROR($C$15/$C$18,0) -> 35.75 | D19: Se enlaza automáticamente a la hoja «3. Costeo y Precios».
B21: C · COSTO DE TU MANO DE OBRA
B22: Sueldo mensual que quieres cobrarte (MXN) | C22: 12000
B23: Horas de trabajo al mes | C23: 160
B24: Costo de mano de obra por hora | C24: =IFERROR($C$22/$C$23,0) -> 75
B26: D · PUNTO DE EQUILIBRIO
B27: Precio de venta promedio por pieza | C27: =IFERROR(AVERAGE('3. Costeo y Precios'!$L$14:$L$63),0) -> 533.8 | D27: Promedio del PVP sugerido de canal Regalo gourmet.
B28: Costo total unitario promedio | C28: =IFERROR(AVERAGE('3. Costeo y Precios'!$K$14:$K$63),0) -> 211.62725
B29: Margen de contribución por pieza | C29: =$C$27-$C$28 -> 322.17275
B30: PIEZAS QUE DEBES VENDER AL MES PARA NO PERDER | C30: =IFERROR(ROUNDUP($C$15/$C$29,0),0) -> 23
B31: Ingreso mensual de equilibrio | C31: =$C$30*$C$27 -> 12277.4

Sheet 7. Tablero
A1: 7 · TABLERO DEL MES
A2: Escribe cualquier día del mes que quieras analizar y todo el tablero se actualiza.
B4: Mes a analizar (escribe cualquier fecha de ese mes) | C4: 46235
B5: Inicio del periodo | C5: =DATE(YEAR(C4),MONTH(C4),1) -> 46235
B6: Fin del periodo (exclusivo) | C6: =DATE(YEAR(C4),MONTH(C4)+1,1) -> 46266
B8: PRODUCCIÓN Y MERMA DEL MES
B9: Piezas vendidas | C9: =SUMIFS('5. Ventas'!$E$8:$E$407,'5. Ventas'!$A$8:$A$407,">="&$C$5,'5. Ventas'!$A$8:$A$407,"<"&$C$6) -> 4 | E9: Piezas buenas producidas | F9: =SUMIFS('4. Producción y Merma'!$F$8:$F$207,'4. Producción y Merma'!$A$8:$A$207,">="&$C$5,'4. Producción y Merma'!$A$8:$A$207,"<"&$C$6) -> 10
B10: Ingreso del mes | C10: =SUMIFS('5. Ventas'!$G$8:$G$407,'5. Ventas'!$A$8:$A$407,">="&$C$5,'5. Ventas'!$A$8:$A$407,"<"&$C$6) -> 1280 | E10: Piezas falladas | F10: =SUMIFS('4. Producción y Merma'!$G$8:$G$207,'4. Producción y Merma'!$A$8:$A$207,">="&$C$5,'4. Producción y Merma'!$A$8:$A$207,"<"&$C$6) -> 2
B11: Costo de producto vendido | C11: =SUMIFS('5. Ventas'!$I$8:$I$407,'5. Ventas'!$A$8:$A$407,">="&$C$5,'5. Ventas'!$A$8:$A$407,"<"&$C$6) -> 696.94118 | E11: % de merma del mes | F11: =IFERROR(F10/(F9+F10),0) -> 0.16666667
B12: Utilidad neta del mes | C12: =SUMIFS('5. Ventas'!$L$8:$L$407,'5. Ventas'!$A$8:$A$407,">="&$C$5,'5. Ventas'!$A$8:$A$407,"<"&$C$6) -> 455.05882 | E12: Dinero perdido en merma | F12: =SUMIFS('4. Producción y Merma'!$K$8:$K$207,'4. Producción y Merma'!$A$8:$A$207,">="&$C$5,'4. Producción y Merma'!$A$8:$A$207,"<"&$C$6) -> 348.47059
B13: Margen neto | C13: =IFERROR(C12/C10,0) -> 0.35551471 | E13: Merma como % del ingreso | F13: =IFERROR(F12/C10,0) -> 0.27224265
B14: Ticket promedio por pieza | C14: =IFERROR(C10/C9,0) -> 320 | E14: Punto de equilibrio (piezas) | F14: ='6. Gastos Fijos'!$C$30 -> 23
B15: Utilidad después de gastos fijos | C15: =C12-'6. Gastos Fijos'!$C$15 -> -6694.9412 | E15: Avance hacia el equilibrio | F15: =IFERROR(C9/F14,0) -> 0.17391304
B18: VENTAS POR CANAL
B19: Canal | C19: Piezas | E19: Ingreso | F19: Utilidad neta
B20: Regalo gourmet | C20: =SUMIFS('5. Ventas'!$E$8:$E$407,'5. Ventas'!$A$8:$A$407,">="&$C$5,'5. Ventas'!$A$8:$A$407,"<"&$C$6,'5. Ventas'!$D$8:$D$407,$B20) -> 4 | E20: =SUMIFS('5. Ventas'!$G$8:$G$407,'5. Ventas'!$A$8:$A$407,">="&$C$5,'5. Ventas'!$A$8:$A$407,"<"&$C$6,'5. Ventas'!$D$8:$D$407,$B20) -> 1280 | F20: =SUMIFS('5. Ventas'!$L$8:$L$407,'5. Ventas'!$A$8:$A$407,">="&$C$5,'5. Ventas'!$A$8:$A$407,"<"&$C$6,'5. Ventas'!$D$8:$D$407,$B20) -> 455.05882
B21: Restaurante | C21: =SUMIFS('5. Ventas'!$E$8:$E$407,'5. Ventas'!$A$8:$A$407,">="&$C$5,'5. Ventas'!$A$8:$A$407,"<"&$C$6,'5. Ventas'!$D$8:$D$407,$B21) -> 0 | E21: =SUMIFS('5. Ventas'!$G$8:$G$407,'5. Ventas'!$A$8:$A$407,">="&$C$5,'5. Ventas'!$A$8:$A$407,"<"&$C$6,'5. Ventas'!$D$8:$D$407,$B21) -> 0 | F21: =SUMIFS('5. Ventas'!$L$8:$L$407,'5. Ventas'!$A$8:$A$407,">="&$C$5,'5. Ventas'!$A$8:$A$407,"<"&$C$6,'5. Ventas'!$D$8:$D$407,$B21) -> 0
B22: Recuerdo de evento | C22: =SUMIFS('5. Ventas'!$E$8:$E$407,'5. Ventas'!$A$8:$A$407,">="&$C$5,'5. Ventas'!$A$8:$A$407,"<"&$C$6,'5. Ventas'!$D$8:$D$407,$B22) -> 0 | E22: =SUMIFS('5. Ventas'!$G$8:$G$407,'5. Ventas'!$A$8:$A$407,">="&$C$5,'5. Ventas'!$A$8:$A$407,"<"&$C$6,'5. Ventas'!$D$8:$D$407,$B22) -> 0 | F22: =SUMIFS('5. Ventas'!$L$8:$L$407,'5. Ventas'!$A$8:$A$407,">="&$C$5,'5. Ventas'!$A$8:$A$407,"<"&$C$6,'5. Ventas'!$D$8:$D$407,$B22) -> 0
B23: Mayoreo / banquete | C23: =SUMIFS('5. Ventas'!$E$8:$E$407,'5. Ventas'!$A$8:$A$407,">="&$C$5,'5. Ventas'!$A$8:$A$407,"<"&$C$6,'5. Ventas'!$D$8:$D$407,$B23) -> 0 | E23: =SUMIFS('5. Ventas'!$G$8:$G$407,'5. Ventas'!$A$8:$A$407,">="&$C$5,'5. Ventas'!$A$8:$A$407,"<"&$C$6,'5. Ventas'!$D$8:$D$407,$B23) -> 0 | F23: =SUMIFS('5. Ventas'!$L$8:$L$407,'5. Ventas'!$A$8:$A$407,">="&$C$5,'5. Ventas'!$A$8:$A$407,"<"&$C$6,'5. Ventas'!$D$8:$D$407,$B23) -> 0
B24: Taller | C24: =SUMIFS('5. Ventas'!$E$8:$E$407,'5. Ventas'!$A$8:$A$407,">="&$C$5,'5. Ventas'!$A$8:$A$407,"<"&$C$6,'5. Ventas'!$D$8:$D$407,$B24) -> 0 | E24: =SUMIFS('5. Ventas'!$G$8:$G$407,'5. Ventas'!$A$8:$A$407,">="&$C$5,'5. Ventas'!$A$8:$A$407,"<"&$C$6,'5. Ventas'!$D$8:$D$407,$B24) -> 0 | F24: =SUMIFS('5. Ventas'!$L$8:$L$407,'5. Ventas'!$A$8:$A$407,">="&$C$5,'5. Ventas'!$A$8:$A$407,"<"&$C$6,'5. Ventas'!$D$8:$D$407,$B24) -> 0
B25: Venta directa | C25: =SUMIFS('5. Ventas'!$E$8:$E$407,'5. Ventas'!$A$8:$A$407,">="&$C$5,'5. Ventas'!$A$8:$A$407,"<"&$C$6,'5. Ventas'!$D$8:$D$407,$B25) -> 0 | E25: =SUMIFS('5. Ventas'!$G$8:$G$407,'5. Ventas'!$A$8:$A$407,">="&$C$5,'5. Ventas'!$A$8:$A$407,"<"&$C$6,'5. Ventas'!$D$8:$D$407,$B25) -> 0 | F25: =SUMIFS('5. Ventas'!$L$8:$L$407,'5. Ventas'!$A$8:$A$407,">="&$C$5,'5. Ventas'!$A$8:$A$407,"<"&$C$6,'5. Ventas'!$D$8:$D$407,$B25) -> 0
B28: DESEMPEÑO POR RECETA (usa el filtro para ordenar)
A29: Nº | B29: Receta | C29: Piezas | E29: Ingreso | F29: Utilidad neta
A30: 1 | B30: Vela de Mantequilla de Ajo Rostizado y Romero Fresco | C30: =SUMIFS('5. Ventas'!$E$8:$E$407,'5. Ventas'!$A$8:$A$407,">="&$C$5,'5. Ventas'!$A$8:$A$407,"<"&$C$6,'5. Ventas'!$B$8:$B$407,$A30) -> 4 | E30: =SUMIFS('5. Ventas'!$G$8:$G$407,'5. Ventas'!$A$8:$A$407,">="&$C$5,'5. Ventas'!$A$8:$A$407,"<"&$C$6,'5. Ventas'!$B$8:$B$407,$A30) -> 1280 | F30: =SUMIFS('5. Ventas'!$L$8:$L$407,'5. Ventas'!$A$8:$A$407,">="&$C$5,'5. Ventas'!$A$8:$A$407,"<"&$C$6,'5. Ventas'!$B$8:$B$407,$A30) -> 455.05882
A31: 2 | B31: Vela de Mantequilla a las Finas Hierbas (Tomillo, Orégano, Salvia) | C31: =SUMIFS('5. Ventas'!$E$8:$E$407,'5. Ventas'!$A$8:$A$407,">="&$C$5,'5. Ventas'!$A$8:$A$407,"<"&$C$6,'5. Ventas'!$B$8:$B$407,$A31) -> 0 | E31: =SUMIFS('5. Ventas'!$G$8:$G$407,'5. Ventas'!$A$8:$A$407,">="&$C$5,'5. Ventas'!$A$8:$A$407,"<"&$C$6,'5. Ventas'!$B$8:$B$407,$A31) -> 0 | F31: =SUMIFS('5. Ventas'!$L$8:$L$407,'5. Ventas'!$A$8:$A$407,">="&$C$5,'5. Ventas'!$A$8:$A$407,"<"&$C$6,'5. Ventas'!$B$8:$B$407,$A31) -> 0
A32: 3 | B32: Vela de Mantequilla de Trufa Negra y Sal en Escamas | C32: =SUMIFS('5. Ventas'!$E$8:$E$407,'5. Ventas'!$A$8:$A$407,">="&$C$5,'5. Ventas'!$A$8:$A$407,"<"&$C$6,'5. Ventas'!$B$8:$B$407,$A32) -> 0 | E32: =SUMIFS('5. Ventas'!$G$8:$G$407,'5. Ventas'!$A$8:$A$407,">="&$C$5,'5. Ventas'!$A$8:$A$407,"<"&$C$6,'5. Ventas'!$B$8:$B$407,$A32) -> 0 | F32: =SUMIFS('5. Ventas'!$L$8:$L$407,'5. Ventas'!$A$8:$A$407,">="&$C$5,'5. Ventas'!$A$8:$A$407,"<"&$C$6,'5. Ventas'!$B$8:$B$407,$A32) -> 0
A33: 4 | B33: Vela de Mantequilla de Tomate Deshidratado y Albahaca | C33: =SUMIFS('5. Ventas'!$E$8:$E$407,'5. Ventas'!$A$8:$A$407,">="&$C$5,'5. Ventas'!$A$8:$A$407,"<"&$C$6,'5. Ventas'!$B$8:$B$407,$A33) -> 0 | E33: =SUMIFS('5. Ventas'!$G$8:$G$407,'5. Ventas'!$A$8:$A$407,">="&$C$5,'5. Ventas'!$A$8:$A$407,"<"&$C$6,'5. Ventas'!$B$8:$B$407,$A33) -> 0 | F33: =SUMIFS('5. Ventas'!$L$8:$L$407,'5. Ventas'!$A$8:$A$407,">="&$C$5,'5. Ventas'!$A$8:$A$407,"<"&$C$6,'5. Ventas'!$B$8:$B$407,$A33) -> 0
A34: 5 | B34: Vela de Mantequilla de Chile de Árbol, Limón y Sal de Mar | C34: =SUMIFS('5. Ventas'!$E$8:$E$407,'5. Ventas'!$A$8:$A$407,">="&$C$5,'5. Ventas'!$A$8:$A$407,"<"&$C$6,'5. Ventas'!$B$8:$B$407,$A34) -> 0 | E34: =SUMIFS('5. Ventas'!$G$8:$G$407,'5. Ventas'!$A$8:$A$407,">="&$C$5,'5. Ventas'!$A$8:$A$407,"<"&$C$6,'5. Ventas'!$B$8:$B$407,$A34) -> 0 | F34: =SUMIFS('5. Ventas'!$L$8:$L$407,'5. Ventas'!$A$8:$A$407,">="&$C$5,'5. Ventas'!$A$8:$A$407,"<"&$C$6,'5. Ventas'!$B$8:$B$407,$A34) -> 0
A35: 6 | B35: Vela de Mantequilla de Cebolla Caramelizada al Balsámico | C35: =SUMIFS('5. Ventas'!$E$8:$E$407,'5. Ventas'!$A$8:$A$407,">="&$C$5,'5. Ventas'!$A$8:$A$407,"<"&$C$6,'5. Ventas'!$B$8:$B$407,$A35) -> 0 | E35: =SUMIFS('5. Ventas'!$G$8:$G$407,'5. Ventas'!$A$8:$A$407,">="&$C$5,'5. Ventas'!$A$8:$A$407,"<"&$C$6,'5. Ventas'!$B$8:$B$407,$A35) -> 0 | F35: =SUMIFS('5. Ventas'!$L$8:$L$407,'5. Ventas'!$A$8:$A$407,">="&$C$5,'5. Ventas'!$A$8:$A$407,"<"&$C$6,'5. Ventas'!$B$8:$B$407,$A35) -> 0
A36: 7 | B36: Vela de Mantequilla de Cilantro, Jalapeño y Ralladura de Limón Verde | C36: =SUMIFS('5. Ventas'!$E$8:$E$407,'5. Ventas'!$A$8:$A$407,">="&$C$5,'5. Ventas'!$A$8:$A$407,"<"&$C$6,'5. Ventas'!$B$8:$B$407,$A36) -> 0 | E36: =SUMIFS('5. Ventas'!$G$8:$G$407,'5. Ventas'!$A$8:$A$407,">="&$C$5,'5. Ventas'!$A$8:$A$407,"<"&$C$6,'5. Ventas'!$B$8:$B$407,$A36) -> 0 | F36: =SUMIFS('5. Ventas'!$L$8:$L$407,'5. Ventas'!$A$8:$A$407,">="&$C$5,'5. Ventas'!$A$8:$A$407,"<"&$C$6,'5. Ventas'!$B$8:$B$407,$A36) -> 0
A37: 8 | B37: Vela de Mantequilla de Pimienta Negra Quebrada y Parmesano | C37: =SUMIFS('5. Ventas'!$E$8:$E$407,'5. Ventas'!$A$8:$A$407,">="&$C$5,'5. Ventas'!$A$8:$A$407,"<"&$C$6,'5. Ventas'!$B$8:$B$407,$A37) -> 0 | E37: =SUMIFS('5. Ventas'!$G$8:$G$407,'5. Ventas'!$A$8:$A$407,">="&$C$5,'5. Ventas'!$A$8:$A$407,"<"&$C$6,'5. Ventas'!$B$8:$B$407,$A37) -> 0 | F37: =SUMIFS('5. Ventas'!$L$8:$L$407,'5. Ventas'!$A$8:$A$407,">="&$C$5,'5. Ventas'!$A$8:$A$407,"<"&$C$6,'5. Ventas'!$B$8:$B$407,$A37) -> 0
A38: 9 | B38: Vela de Mantequilla de Tocino Ahumado y Miel de Maple | C38: =SUMIFS('5. Ventas'!$E$8:$E$407,'5. Ventas'!$A$8:$A$407,">="&$C$5,'5. Ventas'!$A$8:$A$407,"<"&$C$6,'5. Ventas'!$B$8:$B$407,$A38) -> 0 | E38: =SUMIFS('5. Ventas'!$G$8:$G$407,'5. Ventas'!$A$8:$A$407,">="&$C$5,'5. Ventas'!$A$8:$A$407,"<"&$C$6,'5. Ventas'!$B$8:$B$407,$A38) -> 0 | F38: =SUMIFS('5. Ventas'!$L$8:$L$407,'5. Ventas'!$A$8:$A$407,">="&$C$5,'5. Ventas'!$A$8:$A$407,"<"&$C$6,'5. Ventas'!$B$8:$B$407,$A38) -> 0
A39: 10 | B39: Vela de Mantequilla de Queso Azul y Nuez Picada | C39: =SUMIFS('5. Ventas'!$E$8:$E$407,'5. Ventas'!$A$8:$A$407,">="&$C$5,'5. Ventas'!$A$8:$A$407,"<"&$C$6,'5. Ventas'!$B$8:$B$407,$A39) -> 0 | E39: =SUMIFS('5. Ventas'!$G$8:$G$407,'5. Ventas'!$A$8:$A$407,">="&$C$5,'5. Ventas'!$A$8:$A$407,"<"&$C$6,'5. Ventas'!$B$8:$B$407,$A39) -> 0 | F39: =SUMIFS('5. Ventas'!$L$8:$L$407,'5. Ventas'!$A$8:$A$407,">="&$C$5,'5. Ventas'!$A$8:$A$407,"<"&$C$6,'5. Ventas'!$B$8:$B$407,$A39) -> 0
A40: 11 | B40: Vela de Mantequilla de Miso Blanco y Ajonjolí Tostado | C40: =SUMIFS('5. Ventas'!$E$8:$E$407,'5. Ventas'!$A$8:$A$407,">="&$C$5,'5. Ventas'!$A$8:$A$407,"<"&$C$6,'5. Ventas'!$B$8:$B$407,$A40) -> 0 | E40: =SUMIFS('5. Ventas'!$G$8:$G$407,'5. Ventas'!$A$8:$A$407,">="&$C$5,'5. Ventas'!$A$8:$A$407,"<"&$C$6,'5. Ventas'!$B$8:$B$407,$A40) -> 0 | F40: =SUMIFS('5. Ventas'!$L$8:$L$407,'5. Ventas'!$A$8:$A$407,">="&$C$5,'5. Ventas'!$A$8:$A$407,"<"&$C$6,'5. Ventas'!$B$8:$B$407,$A40) -> 0
A41: 12 | B41: Vela de Mantequilla de Pimentón de la Vera (Dulce y Picante) | C41: =SUMIFS('5. Ventas'!$E$8:$E$407,'5. Ventas'!$A$8:$A$407,">="&$C$5,'5. Ventas'!$A$8:$A$407,"<"&$C$6,'5. Ventas'!$B$8:$B$407,$A41) -> 0 | E41: =SUMIFS('5. Ventas'!$G$8:$G$407,'5. Ventas'!$A$8:$A$407,">="&$C$5,'5. Ventas'!$A$8:$A$407,"<"&$C$6,'5. Ventas'!$B$8:$B$407,$A41) -> 0 | F41: =SUMIFS('5. Ventas'!$L$8:$L$407,'5. Ventas'!$A$8:$A$407,">="&$C$5,'5. Ventas'!$A$8:$A$407,"<"&$C$6,'5. Ventas'!$B$8:$B$407,$A41) -> 0
... A79: 50 | B79: Vela Vegana Estilo Ghee con Especias Chai | C79: =SUMIFS('5. Ventas'!$E$8:$E$407,'5. Ventas'!$A$8:$A$407,">="&$C$5,'5. Ventas'!$A$8:$A$407,"<"&$C$6,'5. Ventas'!$B$8:$B$407,$A79) -> 0 | E79: =SUMIFS('5. Ventas'!$G$8:$G$407,'5. Ventas'!$A$8:$A$407,">="&$C$5,'5. Ventas'!$A$8:$A$407,"<"&$C$6,'5. Ventas'!$B$8:$B$407,$A79) -> 0 | F79: =SUMIFS('5. Ventas'!$L$8:$L$407,'5. Ventas'!$A$8:$A$407,">="&$C$5,'5. Ventas'!$A$8:$A$407,"<"&$C$6,'5. Ventas'!$B$8:$B$407,$A79) -> 0
