Workbook

Sheet LÉEME
A1: Pastelería Científica para Diabéticos · Anexo 1 · Costeo, merma y precios
A2: Endulcora · Estudio Gastronómico — En colaboración con Levent
A4: Celdas amarillas = editables. Todo lo demás son fórmulas.
A5: 1. Captura tus precios reales en «Insumos». Los 49 precios se recalculan solos.
A6: 2. Ajusta gastos fijos, sueldo, merma y márgenes en «Mi negocio».
A7: 3. Revisa costos y PVP por canal en «Recetas y precios».
A8: 4. Planea en «Producción» y registra en «Ventas»; el «Tablero» resume.
A9: Modelo: Costo total = Costo base ÷ (1 − merma) · PVP = Costo total ÷ (1 − margen), redondeado al peso hacia arriba.
A10: Precios de referencia CDMX 2026, ilustrativos. No son cotización.

Sheet Insumos
A1: ID | B1: Insumo | C1: Categoría | D1: Unidad | E1: Cantidad comprada | F1: Precio de compra | G1: Costo por unidad
A2: ALU | B2: Alulosa cristalina | C2: Edulcorantes | D2: g | E2: 1000 | F2: 420 | G2: =IFERROR(F2/E2,0)
A3: ALUP | B3: Alulosa pulverizada | C3: Edulcorantes | D3: g | E3: 1000 | F3: 450 | G3: =IFERROR(F3/E3,0)
A4: ALUJ | B4: Jarabe de alulosa | C4: Edulcorantes | D4: g | E4: 500 | F4: 260 | G4: =IFERROR(F4/E4,0)
A5: ERG | B5: Eritritol granulado | C5: Edulcorantes | D5: g | E5: 1000 | F5: 220 | G5: =IFERROR(F5/E5,0)
A6: ERP | B6: Eritritol pulverizado (glas) | C6: Edulcorantes | D6: g | E6: 1000 | F6: 250 | G6: =IFERROR(F6/E6,0)
A7: ERM | B7: Eritritol con fruto del monje | C7: Edulcorantes | D7: g | E7: 800 | F7: 330 | G7: =IFERROR(F7/E7,0)
A8: EST | B8: Estevia pura (Reb M) | C8: Edulcorantes | D8: g | E8: 50 | F8: 190 | G8: =IFERROR(F8/E8,0)
A9: INU | B9: Inulina (achicoria o agave) | C9: Edulcorantes | D9: g | E9: 500 | F9: 180 | G9: =IFERROR(F9/E9,0)
A10: HAL | B10: Harina de almendra fina sin piel | C10: Harinas y fibras | D10: g | E10: 1000 | F10: 380 | G10: =IFERROR(F10/E10,0)
A11: HCO | B11: Harina de coco desgrasada | C11: Harinas y fibras | D11: g | E11: 1000 | F11: 160 | G11: =IFERROR(F11/E11,0)
A12: HAV | B12: Harina de avellana | C12: Harinas y fibras | D12: g | E12: 1000 | F12: 520 | G12: =IFERROR(F12/E12,0)
A13: HPE | B13: Harina de nuez pecana | C13: Harinas y fibras | D13: g | E13: 1000 | F13: 480 | G13: =IFERROR(F13/E13,0)
... A87: AGU | B87: Agua purificada | C87: Otros | D87: ml | E87: 20000 | F87: 45 | G87: =IFERROR(F87/E87,0)
A88: SUB1 | B88: Base B-1 Bizcocho (sub-receta) | C88: Sub-recetas | D88: g | E88: 1 | F88: =VLOOKUP("B1",'Bases madre'!$A:$F,6,FALSE) | G88: =IFERROR(F88/E88,0)
A89: SUB2 | B89: Base B-2 Sablée (sub-receta) | C89: Sub-recetas | D89: g | E89: 1 | F89: =VLOOKUP("B2",'Bases madre'!$A:$F,6,FALSE) | G89: =IFERROR(F89/E89,0)

Sheet Bases madre
A1: Base | B1: Nombre | C1: Costo lote | D1: Rendimiento (g) | E1: Costo por kg | F1: Costo por g
A2: B1 | B2: Bizcocho de almendra | C2: =SUMIF($A$12:$A$63,A2,$E$12:$E$63) | D2: 1300 | E2: =C2/D2*1000 | F2: =C2/D2
A3: B2 | B3: Masa sablée de almendra | C3: =SUMIF($A$12:$A$63,A3,$E$12:$E$63) | D3: 540 | E3: =C3/D3*1000 | F3: =C3/D3
A4: B3 | B4: Crema de yemas y lácteos cuajados | C4: =SUMIF($A$12:$A$63,A4,$E$12:$E$63) | D4: 800 | E4: =C4/D4*1000 | F4: =C4/D4
A5: B4 | B5: Aparato de queso crema | C5: =SUMIF($A$12:$A$63,A5,$E$12:$E$63) | D5: 1600 | E5: =C5/D5*1000 | F5: =C5/D5
A6: B5 | B6: Ganache de chocolate sin azúcar | C6: =SUMIF($A$12:$A$63,A6,$E$12:$E$63) | D6: 520 | E6: =C6/D6*1000 | F6: =C6/D6
A7: B6 | B7: Caramelo de alulosa | C7: =SUMIF($A$12:$A$63,A7,$E$12:$E$63) | D7: 350 | E7: =C7/D7*1000 | F7: =C7/D7
A8: B7 | B8: Masa levada sin gluten | C8: =SUMIF($A$12:$A$63,A8,$E$12:$E$63) | D8: 560 | E8: =C8/D8*1000 | F8: =C8/D8
A11: Base | B11: Insumo ID | C11: Insumo | D11: Cantidad | E11: Costo línea
A12: B1 | B12: HAL | C12: =VLOOKUP(B12,Insumos!$A:$G,2,FALSE) | D12: 300 | E12: =D12*VLOOKUP(B12,Insumos!$A:$G,7,FALSE)
A13: B1 | B13: HCO | C13: =VLOOKUP(B13,Insumos!$A:$G,2,FALSE) | D13: 35 | E13: =D13*VLOOKUP(B13,Insumos!$A:$G,7,FALSE)
A14: B1 | B14: FBA | C14: =VLOOKUP(B14,Insumos!$A:$G,2,FALSE) | D14: 40 | E14: =D14*VLOOKUP(B14,Insumos!$A:$G,7,FALSE)
A15: B1 | B15: ALU | C15: =VLOOKUP(B15,Insumos!$A:$G,2,FALSE) | D15: 220 | E15: =D15*VLOOKUP(B15,Insumos!$A:$G,7,FALSE)
A16: B1 | B16: ERP | C16: =VLOOKUP(B16,Insumos!$A:$G,2,FALSE) | D16: 80 | E16: =D16*VLOOKUP(B16,Insumos!$A:$G,7,FALSE)
A17: B1 | B17: MAN | C17: =VLOOKUP(B17,Insumos!$A:$G,2,FALSE) | D17: 180 | E17: =D17*VLOOKUP(B17,Insumos!$A:$G,7,FALSE)
A18: B1 | B18: HUE | C18: =VLOOKUP(B18,Insumos!$A:$G,2,FALSE) | D18: 250 | E18: =D18*VLOOKUP(B18,Insumos!$A:$G,7,FALSE)
A19: B1 | B19: LAL | C19: =VLOOKUP(B19,Insumos!$A:$G,2,FALSE) | D19: 200 | E19: =D19*VLOOKUP(B19,Insumos!$A:$G,7,FALSE)
A20: B1 | B20: PPH | C20: =VLOOKUP(B20,Insumos!$A:$G,2,FALSE) | D20: 8 | E20: =D20*VLOOKUP(B20,Insumos!$A:$G,7,FALSE)
A21: B1 | B21: XAN | C21: =VLOOKUP(B21,Insumos!$A:$G,2,FALSE) | D21: 4 | E21: =D21*VLOOKUP(B21,Insumos!$A:$G,7,FALSE)
A22: B1 | B22: SAL | C22: =VLOOKUP(B22,Insumos!$A:$G,2,FALSE) | D22: 3 | E22: =D22*VLOOKUP(B22,Insumos!$A:$G,7,FALSE)
A23: B1 | B23: VAE | C23: =VLOOKUP(B23,Insumos!$A:$G,2,FALSE) | D23: 10 | E23: =D23*VLOOKUP(B23,Insumos!$A:$G,7,FALSE)
... A62: B7 | B62: HUE | C62: =VLOOKUP(B62,Insumos!$A:$G,2,FALSE) | D62: 100 | E62: =D62*VLOOKUP(B62,Insumos!$A:$G,7,FALSE)

Sheet Ingredientes
A1: Receta | B1: Texto original del chef | C1: Insumo ID | D1: Insumo | E1: Cantidad | F1: Unidad | G1: Costo línea | H1: Nota
A2: 1 | B2: 300 g Harina de almendra ultrafina sin piel (tamizada) | C2: HAL | D2: =VLOOKUP(C2,Insumos!$A:$G,2,FALSE) | E2: 300 | F2: g | G2: =E2*VLOOKUP(C2,Insumos!$A:$G,7,FALSE)
A3: 1 | B3: 35 g Harina de coco desgrasada pura | C3: HCO | D3: =VLOOKUP(C3,Insumos!$A:$G,2,FALSE) | E3: 35 | F3: g | G3: =E3*VLOOKUP(C3,Insumos!$A:$G,7,FALSE)
A4: 1 | B4: 40 g Fibra de bambú insoluble o almidón resistente RS4 | C4: FBA | D4: =VLOOKUP(C4,Insumos!$A:$G,2,FALSE) | E4: 40 | F4: g | G4: =E4*VLOOKUP(C4,Insumos!$A:$G,7,FALSE)
A5: 1 | B5: 25 g Cacao puro en polvo (10-12% materia grasa, desgrasado natural) | C5: CAN | D5: =VLOOKUP(C5,Insumos!$A:$G,2,FALSE) | E5: 25 | F5: g | G5: =E5*VLOOKUP(C5,Insumos!$A:$G,7,FALSE)
A6: 1 | B6: 8 g Bicarbonato de sodio puro | C6: BIC | D6: =VLOOKUP(C6,Insumos!$A:$G,2,FALSE) | E6: 8 | F6: g | G6: =E6*VLOOKUP(C6,Insumos!$A:$G,7,FALSE)
A7: 1 | B7: 4 g Goma xantana grado alimenticio | C7: XAN | D7: =VLOOKUP(C7,Insumos!$A:$G,2,FALSE) | E7: 4 | F7: g | G7: =E7*VLOOKUP(C7,Insumos!$A:$G,7,FALSE)
A8: 1 | B8: 3 g Sal marina fina | C8: SAL | D8: =VLOOKUP(C8,Insumos!$A:$G,2,FALSE) | E8: 3 | F8: g | G8: =E8*VLOOKUP(C8,Insumos!$A:$G,7,FALSE)
A9: 1 | B9: 220 ml Leche de almendra pura sin azúcar (0carbohidratos) | C9: LAL | D9: =VLOOKUP(C9,Insumos!$A:$G,2,FALSE) | E9: 220 | F9: ml | G9: =E9*VLOOKUP(C9,Insumos!$A:$G,7,FALSE)
A10: 1 | B10: 25 ml Vinagre de sidra de manzana o vinagre blanco destilado | C10: VIN | D10: =VLOOKUP(C10,Insumos!$A:$G,2,FALSE) | E10: 25 | F10: ml | G10: =E10*VLOOKUP(C10,Insumos!$A:$G,7,FALSE)
A11: 1 | B11: 15 ml Extracto concentrado de vainilla Bourbon pura | C11: VAE | D11: =VLOOKUP(C11,Insumos!$A:$G,2,FALSE) | E11: 15 | F11: ml | G11: =E11*VLOOKUP(C11,Insumos!$A:$G,7,FALSE)
A12: 1 | B12: 8 g Colorante rojo carmín hidrosoluble (rojo allura / carmín cochinilla) | C12: COL | D12: =VLOOKUP(C12,Insumos!$A:$G,2,FALSE) | E12: 8 | F12: g | G12: =E12*VLOOKUP(C12,Insumos!$A:$G,7,FALSE)
A13: 1 | B13: 180 g Mantequilla de vaca sin sal (82 % MG) a temperatura ambiente (20 °C ) | C13: MAN | D13: =VLOOKUP(C13,Insumos!$A:$G,2,FALSE) | E13: 180 | F13: g | G13: =E13*VLOOKUP(C13,Insumos!$A:$G,7,FALSE)
... A34: 2 | B34: 4 g Pectina de bajo metoxilo (LM Pectin, gelifica con iones de calcio) | C34: PEC | D34: =VLOOKUP(C34,Insumos!$A:$G,2,FALSE) | E34: 4 | F34: g | G34: =E34*VLOOKUP(C34,Insumos!$A:$G,7,FALSE)
A35: 2 | B35: 10 ml Zumo de limón criollo | C35: LIM | D35: =VLOOKUP(C35,Insumos!$A:$G,2,FALSE) | E35: 0.25 | F35: pz | G35: =E35*VLOOKUP(C35,Insumos!$A:$G,7,FALSE) | H35: Jugo convertido a piezas (limón ≈ 40 ml, naranja ≈ 80 ml)
A36: 2 | B36: 600 ml Crema para batir pasteurizada de vaca (35 % grasa butírica, fría a 2 °C) | C36: CRE | D36: =VLOOKUP(C36,Insumos!$A:$G,2,FALSE) | E36: 600 | F36: ml | G36: =E36*VLOOKUP(C36,Insumos!$A:$G,7,FALSE)
A37: 2 | B37: 60 g Eritritol pulverizado con fruto del monje (tamizado fino) | C37: ERM | D37: =VLOOKUP(C37,Insumos!$A:$G,2,FALSE) | E37: 60 | F37: g | G37: =E37*VLOOKUP(C37,Insumos!$A:$G,7,FALSE)
A38: 2 | B38: 10 ml Extracto puro natural de vainilla | C38: VAE | D38: =VLOOKUP(C38,Insumos!$A:$G,2,FALSE) | E38: 10 | F38: ml | G38: =E38*VLOOKUP(C38,Insumos!$A:$G,7,FALSE)
A39: 2 | B39: 80 g Cobertura de chocolate amargo 100% cacao puro rallado en virutas | C39: CH100 | D39: =VLOOKUP(C39,Insumos!$A:$G,2,FALSE) | E39: 80 | F39: g | G39: =E39*VLOOKUP(C39,Insumos!$A:$G,7,FALSE)
A40: 3 | B40: 280 g Harina de almendra fina sin piel | C40: HAL | D40: =VLOOKUP(C40,Insumos!$A:$G,2,FALSE) | E40: 280 | F40: g | G40: =E40*VLOOKUP(C40,Insumos!$A:$G,7,FALSE)
A41: 3 | B41: 40 g Harina de coco desgrasada pura | C41: HCO | D41: =VLOOKUP(C41,Insumos!$A:$G,2,FALSE) | E41: 40 | F41: g | G41: =E41*VLOOKUP(C41,Insumos!$A:$G,7,FALSE)
A42: 3 | B42: 30 g Harina de linaza dorada micronizada (aporta emulgentes y retiene agua) | C42: HLI | D42: =VLOOKUP(C42,Insumos!$A:$G,2,FALSE) | E42: 30 | F42: g | G42: =E42*VLOOKUP(C42,Insumos!$A:$G,7,FALSE)
A43: 3 | B43: 8 g Canela de Ceilán pura en polvo | C43: CAP | D43: =VLOOKUP(C43,Insumos!$A:$G,2,FALSE) | E43: 8 | F43: g | G43: =E43*VLOOKUP(C43,Insumos!$A:$G,7,FALSE)
A44: 3 | B44: 3 g Jengibre en polvo micronizado | C44: ESP | D44: =VLOOKUP(C44,Insumos!$A:$G,2,FALSE) | E44: 3 | F44: g | G44: =E44*VLOOKUP(C44,Insumos!$A:$G,7,FALSE)
A45: 3 | B45: 1 g Nuez moscada recién rallada | C45: ESP | D45: =VLOOKUP(C45,Insumos!$A:$G,2,FALSE) | E45: 1 | F45: g | G45: =E45*VLOOKUP(C45,Insumos!$A:$G,7,FALSE)
A46: 3 | B46: 8 g Polvo para hornear doble acción | C46: PPH | D46: =VLOOKUP(C46,Insumos!$A:$G,2,FALSE) | E46: 8 | F46: g | G46: =E46*VLOOKUP(C46,Insumos!$A:$G,7,FALSE)
A47: 3 | B47: 5 g Bicarbonato de sodio | C47: BIC | D47: =VLOOKUP(C47,Insumos!$A:$G,2,FALSE) | E47: 5 | F47: g | G47: =E47*VLOOKUP(C47,Insumos!$A:$G,7,FALSE)
... A76: 4 | B76: 30 g Mantequilla sin sal | C76: MAN | D76: =VLOOKUP(C76,Insumos!$A:$G,2,FALSE) | E76: 30 | F76: g | G76: =E76*VLOOKUP(C76,Insumos!$A:$G,7,FALSE)
A77: 4 | B77: Avellanas tostadas enteras para decorar la corona | C77: AVE | D77: =VLOOKUP(C77,Insumos!$A:$G,2,FALSE) | E77: 30 | F77: g | G77: =E77*VLOOKUP(C77,Insumos!$A:$G,7,FALSE) | H77: Cantidad estimada (al gusto en el original)
A78: 5 | B78: 150 g Harina de almendra fina pura | C78: HAL | D78: =VLOOKUP(C78,Insumos!$A:$G,2,FALSE) | E78: 150 | F78: g | G78: =E78*VLOOKUP(C78,Insumos!$A:$G,7,FALSE)
A79: 5 | B79: 120 g Alulosa pulverizada micronizada | C79: ALUP | D79: =VLOOKUP(C79,Insumos!$A:$G,2,FALSE) | E79: 120 | F79: g | G79: =E79*VLOOKUP(C79,Insumos!$A:$G,7,FALSE)
A80: 5 | B80: 4 Huevos enteros L (200 g) | C80: HUE | D80: =VLOOKUP(C80,Insumos!$A:$G,2,FALSE) | E80: 200 | F80: g | G80: =E80*VLOOKUP(C80,Insumos!$A:$G,7,FALSE)
A81: 5 | B81: 4 Claras de huevo (140 g) | C81: CLA | D81: =VLOOKUP(C81,Insumos!$A:$G,2,FALSE) | E81: 140 | F81: g | G81: =E81*VLOOKUP(C81,Insumos!$A:$G,7,FALSE)
A82: 5 | B82: 30 g Eritritol granulado (para montar las claras) | C82: ERG | D82: =VLOOKUP(C82,Insumos!$A:$G,2,FALSE) | E82: 30 | F82: g | G82: =E82*VLOOKUP(C82,Insumos!$A:$G,7,FALSE)
A83: 5 | B83: 30 g Mantequilla sin sal derretida tibia | C83: MAN | D83: =VLOOKUP(C83,Insumos!$A:$G,2,FALSE) | E83: 30 | F83: g | G83: =E83*VLOOKUP(C83,Insumos!$A:$G,7,FALSE)
A84: 5 | B84: 2 g Goma xantana | C84: XAN | D84: =VLOOKUP(C84,Insumos!$A:$G,2,FALSE) | E84: 2 | F84: g | G84: =E84*VLOOKUP(C84,Insumos!$A:$G,7,FALSE)
A85: 5 | B85: 1 g Sal fina | C85: SAL | D85: =VLOOKUP(C85,Insumos!$A:$G,2,FALSE) | E85: 1 | F85: g | G85: =E85*VLOOKUP(C85,Insumos!$A:$G,7,FALSE)
A86: 5 | B86: 150 ml Café espresso intenso recién extraído (de grano arábica) | C86: CAF | D86: =VLOOKUP(C86,Insumos!$A:$G,2,FALSE) | E86: 150 | F86: ml | G86: =E86*VLOOKUP(C86,Insumos!$A:$G,7,FALSE)
A87: 5 | B87: 70 g Alulosa cristalina | C87: ALU | D87: =VLOOKUP(C87,Insumos!$A:$G,2,FALSE) | E87: 70 | F87: g | G87: =E87*VLOOKUP(C87,Insumos!$A:$G,7,FALSE)
A88: 5 | B88: 15 ml Extracto concentrado natural de café | C88: EXT | D88: =VLOOKUP(C88,Insumos!$A:$G,2,FALSE) | E88: 15 | F88: ml | G88: =E88*VLOOKUP(C88,Insumos!$A:$G,7,FALSE)
A89: 5 | B89: 4 Yemas de huevo fresco (80 g) | C89: YEM | D89: =VLOOKUP(C89,Insumos!$A:$G,2,FALSE) | E89: 80 | F89: g | G89: =E89*VLOOKUP(C89,Insumos!$A:$G,7,FALSE)
... A108: 6 | B108: 350 ml Crema para batir pasteurizada de vaca (35 % materia grasa) | C108: CRE | D108: =VLOOKUP(C108,Insumos!$A:$G,2,FALSE) | E108: 350 | F108: ml | G108: =E108*VLOOKUP(C108,Insumos!$A:$G,7,FALSE)
A109: 6 | B109: 250 g "Leche condensada" keto (leche evaporada cocida a fuego lento con 120 g de alulosa y 20 g de mantequilla hasta espesar) | C109: LEV2 | D109: =VLOOKUP(C109,Insumos!$A:$G,2,FALSE) | E109: 300 | F109: ml | G109: =E109*VLOOKUP(C109,Insumos!$A:$G,7,FALSE) | H109: Leche condensada keto desglosada: leche evaporada estimada para reducir a 250 g
A110: 6 | B110: 250 g "Leche condensada" keto (leche evaporada cocida a fuego lento con 120 g de alulosa y 20 g de mantequilla hasta espesar) | C110: ALU | D110: =VLOOKUP(C110,Insumos!$A:$G,2,FALSE) | E110: 120 | F110: g | G110: =E110*VLOOKUP(C110,Insumos!$A:$G,7,FALSE) | H110: Ídem
A111: 6 | B111: 250 g "Leche condensada" keto (leche evaporada cocida a fuego lento con 120 g de alulosa y 20 g de mantequilla hasta espesar) | C111: MAN | D111: =VLOOKUP(C111,Insumos!$A:$G,2,FALSE) | E111: 20 | F111: g | G111: =E111*VLOOKUP(C111,Insumos!$A:$G,7,FALSE) | H111: Ídem
A112: 6 | B112: 15 ml Ron añejo destilado o extracto natural de ron (opcional, 0azúcar) | C112: LIC | D112: =VLOOKUP(C112,Insumos!$A:$G,2,FALSE) | E112: 15 | F112: ml | G112: =E112*VLOOKUP(C112,Insumos!$A:$G,7,FALSE)
A113: 6 | B113: 5 ml Extracto concentrado de vainilla | C113: VAE | D113: =VLOOKUP(C113,Insumos!$A:$G,2,FALSE) | E113: 5 | F113: ml | G113: =E113*VLOOKUP(C113,Insumos!$A:$G,7,FALSE)
A114: 6 | B114: 4 Claras de huevo fresco (140 g) | C114: CLA | D114: =VLOOKUP(C114,Insumos!$A:$G,2,FALSE) | E114: 140 | F114: g | G114: =E114*VLOOKUP(C114,Insumos!$A:$G,7,FALSE)
A115: 6 | B115: 160 g Alulosa pura cristalina | C115: ALU | D115: =VLOOKUP(C115,Insumos!$A:$G,2,FALSE) | E115: 160 | F115: g | G115: =E115*VLOOKUP(C115,Insumos!$A:$G,7,FALSE)
A116: 6 | B116: 40 g Eritritol pulverizado (para rigidizar la corona de merengue) | C116: ERP | D116: =VLOOKUP(C116,Insumos!$A:$G,2,FALSE) | E116: 40 | F116: g | G116: =E116*VLOOKUP(C116,Insumos!$A:$G,7,FALSE)
A117: 6 | B117: 2 g Cremor tártaro | C117: CRT | D117: =VLOOKUP(C117,Insumos!$A:$G,2,FALSE) | E117: 2 | F117: g | G117: =E117*VLOOKUP(C117,Insumos!$A:$G,7,FALSE)
A118: 6 | B118: Canela de Ceilán en polvo para espolvorear la superficie | C118: CAP | D118: =VLOOKUP(C118,Insumos!$A:$G,2,FALSE) | E118: 1 | F118: g | G118: =E118*VLOOKUP(C118,Insumos!$A:$G,7,FALSE) | H118: Cantidad estimada (al gusto en el original)
A119: 7 | B119: 4 Claras de huevo L (140 g) | C119: CLA | D119: =VLOOKUP(C119,Insumos!$A:$G,2,FALSE) | E119: 140 | F119: g | G119: =E119*VLOOKUP(C119,Insumos!$A:$G,7,FALSE)
A120: 7 | B120: 4 Yemas de huevo L (80 g) | C120: YEM | D120: =VLOOKUP(C120,Insumos!$A:$G,2,FALSE) | E120: 80 | F120: g | G120: =E120*VLOOKUP(C120,Insumos!$A:$G,7,FALSE)
A121: 7 | B121: 80 g Alulosa pura cristalina | C121: ALU | D121: =VLOOKUP(C121,Insumos!$A:$G,2,FALSE) | E121: 80 | F121: g | G121: =E121*VLOOKUP(C121,Insumos!$A:$G,7,FALSE)
A122: 7 | B122: 30 g Eritritol granulado | C122: ERG | D122: =VLOOKUP(C122,Insumos!$A:$G,2,FALSE) | E122: 30 | F122: g | G122: =E122*VLOOKUP(C122,Insumos!$A:$G,7,FALSE)
A123: 7 | B123: 110 g Harina de almendra ultrafina tamizada | C123: HAL | D123: =VLOOKUP(C123,Insumos!$A:$G,2,FALSE) | E123: 110 | F123: g | G123: =E123*VLOOKUP(C123,Insumos!$A:$G,7,FALSE)
A124: 7 | B124: 20 g Fibra de bambú o almidón resistente RS4 | C124: FBA | D124: =VLOOKUP(C124,Insumos!$A:$G,2,FALSE) | E124: 20 | F124: g | G124: =E124*VLOOKUP(C124,Insumos!$A:$G,7,FALSE)
A125: 7 | B125: 2 g Goma xantana | C125: XAN | D125: =VLOOKUP(C125,Insumos!$A:$G,2,FALSE) | E125: 2 | F125: g | G125: =E125*VLOOKUP(C125,Insumos!$A:$G,7,FALSE)
A126: 7 | B126: 20 g Eritritol pulverizado (para espolvorear antes de hornear) | C126: ERP | D126: =VLOOKUP(C126,Insumos!$A:$G,2,FALSE) | E126: 20 | F126: g | G126: =E126*VLOOKUP(C126,Insumos!$A:$G,7,FALSE)
A127: 7 | B127: 250 ml Café espresso intenso recién extraído caliente | C127: CAF | D127: =VLOOKUP(C127,Insumos!$A:$G,2,FALSE) | E127: 250 | F127: ml | G127: =E127*VLOOKUP(C127,Insumos!$A:$G,7,FALSE)
A128: 7 | B128: 60 g Alulosa pura cristalina | C128: ALU | D128: =VLOOKUP(C128,Insumos!$A:$G,2,FALSE) | E128: 60 | F128: g | G128: =E128*VLOOKUP(C128,Insumos!$A:$G,7,FALSE)
A129: 7 | B129: 25 ml Extracto natural sin alcohol de vino Marsala (o 25 ml de brandy añejo destilado) | C129: EXT | D129: =VLOOKUP(C129,Insumos!$A:$G,2,FALSE) | E129: 25 | F129: ml | G129: =E129*VLOOKUP(C129,Insumos!$A:$G,7,FALSE)
A130: 7 | B130: 450 g Queso Mascarpone italiano auténtico (42 % grasa butírica, frío a 6 °C) | C130: MAS | D130: =VLOOKUP(C130,Insumos!$A:$G,2,FALSE) | E130: 450 | F130: g | G130: =E130*VLOOKUP(C130,Insumos!$A:$G,7,FALSE)
... A170: 9 | B170: 4 g Pectina de bajo metoxilo (LM Pectin) | C170: PEC | D170: =VLOOKUP(C170,Insumos!$A:$G,2,FALSE) | E170: 4 | F170: g | G170: =E170*VLOOKUP(C170,Insumos!$A:$G,7,FALSE)
A171: 9 | B171: 8 ml Zumo de limón criollo recién exprimido | C171: LIM | D171: =VLOOKUP(C171,Insumos!$A:$G,2,FALSE) | E171: 0.2 | F171: pz | G171: =E171*VLOOKUP(C171,Insumos!$A:$G,7,FALSE) | H171: Jugo convertido a piezas (limón ≈ 40 ml, naranja ≈ 80 ml)
A172: 9 | B172: 250 ml Crema para batir pasteurizada de vaca (35 % MG) muy fría | C172: CRE | D172: =VLOOKUP(C172,Insumos!$A:$G,2,FALSE) | E172: 250 | F172: ml | G172: =E172*VLOOKUP(C172,Insumos!$A:$G,7,FALSE)
A173: 9 | B173: 30 g Eritritol pulverizado con fruta del monje | C173: ERM | D173: =VLOOKUP(C173,Insumos!$A:$G,2,FALSE) | E173: 30 | F173: g | G173: =E173*VLOOKUP(C173,Insumos!$A:$G,7,FALSE)
A174: 9 | B174: 5 ml Extracto de vainilla | C174: VAE | D174: =VLOOKUP(C174,Insumos!$A:$G,2,FALSE) | E174: 5 | F174: ml | G174: =E174*VLOOKUP(C174,Insumos!$A:$G,7,FALSE)
A175: 9 | B175: 15 g Eritritol pulverizado extra para espolvorear la corona del pastel | C175: ERP | D175: =VLOOKUP(C175,Insumos!$A:$G,2,FALSE) | E175: 15 | F175: g | G175: =E175*VLOOKUP(C175,Insumos!$A:$G,7,FALSE)
A176: 10 | B176: 180 g Harina de almendra fina sin piel | C176: HAL | D176: =VLOOKUP(C176,Insumos!$A:$G,2,FALSE) | E176: 180 | F176: g | G176: =E176*VLOOKUP(C176,Insumos!$A:$G,7,FALSE)
A177: 10 | B177: 30 g Harina de coco desgrasada | C177: HCO | D177: =VLOOKUP(C177,Insumos!$A:$G,2,FALSE) | E177: 30 | F177: g | G177: =E177*VLOOKUP(C177,Insumos!$A:$G,7,FALSE)
A178: 10 | B178: 40 g Eritritol pulverizado (aporta textura crujiente que la alulosa no da) | C178: ERP | D178: =VLOOKUP(C178,Insumos!$A:$G,2,FALSE) | E178: 40 | F178: g | G178: =E178*VLOOKUP(C178,Insumos!$A:$G,7,FALSE)
A179: 10 | B179: 70 g Mantequilla sin sal cortada en cubos muy fríos (4 °C) | C179: MAN | D179: =VLOOKUP(C179,Insumos!$A:$G,2,FALSE) | E179: 70 | F179: g | G179: =E179*VLOOKUP(C179,Insumos!$A:$G,7,FALSE)
A180: 10 | B180: 1 Huevo mediano frío (50 g) | C180: HUE | D180: =VLOOKUP(C180,Insumos!$A:$G,2,FALSE) | E180: 50 | F180: g | G180: =E180*VLOOKUP(C180,Insumos!$A:$G,7,FALSE)
A181: 10 | B181: 2 g Goma xantana | C181: XAN | D181: =VLOOKUP(C181,Insumos!$A:$G,2,FALSE) | E181: 2 | F181: g | G181: =E181*VLOOKUP(C181,Insumos!$A:$G,7,FALSE)
A182: 10 | B182: 1.5 g Sal marina fina | C182: SAL | D182: =VLOOKUP(C182,Insumos!$A:$G,2,FALSE) | E182: 1.5 | F182: g | G182: =E182*VLOOKUP(C182,Insumos!$A:$G,7,FALSE)
A183: 10 | B183: 140 ml Zumo de limón amarillo Eureka o limón criollo recién exprimido y colado | C183: LIM | D183: =VLOOKUP(C183,Insumos!$A:$G,2,FALSE) | E183: 3.5 | F183: pz | G183: =E183*VLOOKUP(C183,Insumos!$A:$G,7,FALSE) | H183: Jugo convertido a piezas (limón ≈ 40 ml, naranja ≈ 80 ml)
A184: 10 | B184: Ralladura fina (solo flavedo) de 4 limones amarillos | C184: LIM | D184: =VLOOKUP(C184,Insumos!$A:$G,2,FALSE) | E184: 4 | F184: pz | G184: =E184*VLOOKUP(C184,Insumos!$A:$G,7,FALSE) | H184: Solo la ralladura; se costea la fruta completa
A185: 10 | B185: 140 g Alulosa pura cristalina | C185: ALU | D185: =VLOOKUP(C185,Insumos!$A:$G,2,FALSE) | E185: 140 | F185: g | G185: =E185*VLOOKUP(C185,Insumos!$A:$G,7,FALSE)
A186: 10 | B186: 5 Yemas de huevo fresco L (100 g) | C186: YEM | D186: =VLOOKUP(C186,Insumos!$A:$G,2,FALSE) | E186: 100 | F186: g | G186: =E186*VLOOKUP(C186,Insumos!$A:$G,7,FALSE)
A187: 10 | B187: 1 Huevo entero L (50 g) | C187: HUE | D187: =VLOOKUP(C187,Insumos!$A:$G,2,FALSE) | E187: 50 | F187: g | G187: =E187*VLOOKUP(C187,Insumos!$A:$G,7,FALSE)
A188: 10 | B188: 120 g Mantequilla de vaca sin sal fría cortada en dados de 1 cm | C188: MAN | D188: =VLOOKUP(C188,Insumos!$A:$G,2,FALSE) | E188: 120 | F188: g | G188: =E188*VLOOKUP(C188,Insumos!$A:$G,7,FALSE)
A189: 10 | B189: 2.5 g Gelatina neutra en polvo (200 Bloom, hidratada en 15 ml de agua fría, para corte perfecto) | C189: GEL | D189: =VLOOKUP(C189,Insumos!$A:$G,2,FALSE) | E189: 2.5 | F189: g | G189: =E189*VLOOKUP(C189,Insumos!$A:$G,7,FALSE)
A190: 10 | B190: 3 Claras de huevo fresco (105 g) | C190: CLA | D190: =VLOOKUP(C190,Insumos!$A:$G,2,FALSE) | E190: 105 | F190: g | G190: =E190*VLOOKUP(C190,Insumos!$A:$G,7,FALSE)
A191: 10 | B191: 120 g Alulosa pura cristalina | C191: ALU | D191: =VLOOKUP(C191,Insumos!$A:$G,2,FALSE) | E191: 120 | F191: g | G191: =E191*VLOOKUP(C191,Insumos!$A:$G,7,FALSE)
A192: 10 | B192: 30 g Eritritol pulverizado | C192: ERP | D192: =VLOOKUP(C192,Insumos!$A:$G,2,FALSE) | E192: 30 | F192: g | G192: =E192*VLOOKUP(C192,Insumos!$A:$G,7,FALSE)
A193: 10 | B193: 1.5 g Cremor tártaro o 3 gotas de zumo de limón | C193: CRT | D193: =VLOOKUP(C193,Insumos!$A:$G,2,FALSE) | E193: 1.5 | F193: g | G193: =E193*VLOOKUP(C193,Insumos!$A:$G,7,FALSE)
A194: 11 | B194: 180 g Harina de almendra fina sin piel | C194: HAL | D194: =VLOOKUP(C194,Insumos!$A:$G,2,FALSE) | E194: 180 | F194: g | G194: =E194*VLOOKUP(C194,Insumos!$A:$G,7,FALSE)
A195: 11 | B195: 40 g Eritritol pulverizado (cristaliza en frío, aportando firmeza a la base) | C195: ERP | D195: =VLOOKUP(C195,Insumos!$A:$G,2,FALSE) | E195: 40 | F195: g | G195: =E195*VLOOKUP(C195,Insumos!$A:$G,7,FALSE)
A196: 11 | B196: 60 g Mantequilla de vaca sin sal derretida | C196: MAN | D196: =VLOOKUP(C196,Insumos!$A:$G,2,FALSE) | E196: 60 | F196: g | G196: =E196*VLOOKUP(C196,Insumos!$A:$G,7,FALSE)
... A205: 11 | B205: 15 ml Extracto puro natural de vainilla de Papantla | C205: VAE | D205: =VLOOKUP(C205,Insumos!$A:$G,2,FALSE) | E205: 15 | F205: ml | G205: =E205*VLOOKUP(C205,Insumos!$A:$G,7,FALSE)
A206: 11 | B206: 15 ml Zumo de limón amarillo fresco (el ácido cítrico coagula levemente las caseínas aportando firmeza) | C206: LIM | D206: =VLOOKUP(C206,Insumos!$A:$G,2,FALSE) | E206: 0.38 | F206: pz | G206: =E206*VLOOKUP(C206,Insumos!$A:$G,7,FALSE) | H206: Jugo convertido a piezas (limón ≈ 40 ml, naranja ≈ 80 ml)
A207: 12 | B207: 250 g Cobertura de chocolate amargo sin azúcar al 70% (endulzado con eritritol/stevia) | C207: CH70 | D207: =VLOOKUP(C207,Insumos!$A:$G,2,FALSE) | E207: 250 | F207: g | G207: =E207*VLOOKUP(C207,Insumos!$A:$G,7,FALSE)
A208: 12 | B208: 100 ml Leche de almendras o leche entera muy caliente (85 °C) | C208: LAL | D208: =VLOOKUP(C208,Insumos!$A:$G,2,FALSE) | E208: 100 | F208: ml | G208: =E208*VLOOKUP(C208,Insumos!$A:$G,7,FALSE)
A209: 12 | B209: 40 ml Aceite de Oliva Virgen Extra de perfil frutado suave (variedad Arbequina) | C209: AOL | D209: =VLOOKUP(C209,Insumos!$A:$G,2,FALSE) | E209: 40 | F209: ml | G209: =E209*VLOOKUP(C209,Insumos!$A:$G,7,FALSE)
A210: 12 | B210: 1 g Sal en escamas (potenciador del cacao) | C210: SAE | D210: =VLOOKUP(C210,Insumos!$A:$G,2,FALSE) | E210: 1 | F210: g | G210: =E210*VLOOKUP(C210,Insumos!$A:$G,7,FALSE)
A211: 12 | B211: 4 Yemas de huevo fresco L (80 g) | C211: YEM | D211: =VLOOKUP(C211,Insumos!$A:$G,2,FALSE) | E211: 80 | F211: g | G211: =E211*VLOOKUP(C211,Insumos!$A:$G,7,FALSE)
A212: 12 | B212: 120 g Alulosa pura cristalina | C212: ALU | D212: =VLOOKUP(C212,Insumos!$A:$G,2,FALSE) | E212: 120 | F212: g | G212: =E212*VLOOKUP(C212,Insumos!$A:$G,7,FALSE)
A213: 12 | B213: 40 ml Agua purificada | C213: AGU | D213: =VLOOKUP(C213,Insumos!$A:$G,2,FALSE) | E213: 40 | F213: ml | G213: =E213*VLOOKUP(C213,Insumos!$A:$G,7,FALSE)
...

Sheet Mi negocio
A1: Gastos fijos mensuales | B1: 12000
A2: Piezas vendidas al mes | B2: 6000
A3: Sueldo mensual de producción | B3: 15000
A4: Horas trabajadas al mes | B4: 200
A5: % merma | B5: 0.08
A7: Overhead por pieza | B7: =B1/B2
A8: Mano de obra por minuto | B8: =B3/B4/60
A10: Canal | B10: Margen
A11: Mostrador | B11: 0.5
A12: Pedido y regalo | B12: 0.6
A13: Cafetería y restaurante | B13: 0.35
A14: Mayoreo tienda saludable | B14: 0.25

Sheet Recetas y precios
A1: # | B1: Receta | C1: Base madre | D1: Dificultad | E1: Piezas que rinde | F1: Unidad | G1: Min. activos lote | H1: Empaque/pza | I1: Energía lote | J1: Insumos lote | K1: Insumos/pza | L1: Mano de obra/pza | M1: Energía/pza | N1: Overhead/pza | O1: Costo base | P1: Costo total | Q1: Costo variable | R1: PVP Mostrador | S1: PVP Pedido y regalo | T1: PVP Cafetería y restaurante | U1: PVP Mayoreo tienda saludable | V1: Utilidad mostrador
A2: 1 | B2: Pastel Red Velvet Tradicional con Frosting de Queso Crema a la Alulosa | C2: B1 | D2: Intermedio | E2: 12 | F2: rebanada | G2: 75 | H2: 4.5 | I2: 14 | J2: =SUMIF(Ingredientes!$A$2:$A$621,A2,Ingredientes!$G$2:$G$621) | K2: =J2/E2 | L2: =G2/E2*'Mi negocio'!$B$8 | M2: =I2/E2 | N2: ='Mi negocio'!$B$7 | O2: =K2+H2+M2+L2+N2 | P2: =O2/(1-'Mi negocio'!$B$5) | Q2: =(O2-N2)/(1-'Mi negocio'!$B$5) | R2: =CEILING(ROUND(P2/(1-'Mi negocio'!$B$11),6),1) | S2: =CEILING(ROUND(P2/(1-'Mi negocio'!$B$12),6),1) | T2: =CEILING(ROUND(P2/(1-'Mi negocio'!$B$13),6),1) | U2: =CEILING(ROUND(P2/(1-'Mi negocio'!$B$14),6),1) | V2: =R2-P2
A3: 2 | B3: Tarta Selva Negra con Bizcocho de Cacao Alcalino y Mousse de Kirsch | C3: B1 | D3: Avanzado | E3: 14 | F3: rebanada | G3: 95 | H3: 4.5 | I3: 13 | J3: =SUMIF(Ingredientes!$A$2:$A$621,A3,Ingredientes!$G$2:$G$621) | K3: =J3/E3 | L3: =G3/E3*'Mi negocio'!$B$8 | M3: =I3/E3 | N3: ='Mi negocio'!$B$7 | O3: =K3+H3+M3+L3+N3 | P3: =O3/(1-'Mi negocio'!$B$5) | Q3: =(O3-N3)/(1-'Mi negocio'!$B$5) | R3: =CEILING(ROUND(P3/(1-'Mi negocio'!$B$11),6),1) | S3: =CEILING(ROUND(P3/(1-'Mi negocio'!$B$12),6),1) | T3: =CEILING(ROUND(P3/(1-'Mi negocio'!$B$13),6),1) | U3: =CEILING(ROUND(P3/(1-'Mi negocio'!$B$14),6),1) | V3: =R3-P3
A4: 3 | B4: Tarta Húmeda de Zanahoria con Nueces Pecanas y Especias de Ceilán | C4: B1 | D4: Intermedio | E4: 14 | F4: rebanada | G4: 70 | H4: 4.5 | I4: 14 | J4: =SUMIF(Ingredientes!$A$2:$A$621,A4,Ingredientes!$G$2:$G$621) | K4: =J4/E4 | L4: =G4/E4*'Mi negocio'!$B$8 | M4: =I4/E4 | N4: ='Mi negocio'!$B$7 | O4: =K4+H4+M4+L4+N4 | P4: =O4/(1-'Mi negocio'!$B$5) | Q4: =(O4-N4)/(1-'Mi negocio'!$B$5) | R4: =CEILING(ROUND(P4/(1-'Mi negocio'!$B$11),6),1) | S4: =CEILING(ROUND(P4/(1-'Mi negocio'!$B$12),6),1) | T4: =CEILING(ROUND(P4/(1-'Mi negocio'!$B$13),6),1) | U4: =CEILING(ROUND(P4/(1-'Mi negocio'!$B$14),6),1) | V4: =R4-P4
A5: 4 | B5: Tarta de Chocolate Trufado y Avellanas Piamonte | C5: B5 | D5: Intermedio | E5: 12 | F5: rebanada | G5: 60 | H5: 4.5 | I5: 12 | J5: =SUMIF(Ingredientes!$A$2:$A$621,A5,Ingredientes!$G$2:$G$621) | K5: =J5/E5 | L5: =G5/E5*'Mi negocio'!$B$8 | M5: =I5/E5 | N5: ='Mi negocio'!$B$7 | O5: =K5+H5+M5+L5+N5 | P5: =O5/(1-'Mi negocio'!$B$5) | Q5: =(O5-N5)/(1-'Mi negocio'!$B$5) | R5: =CEILING(ROUND(P5/(1-'Mi negocio'!$B$11),6),1) | S5: =CEILING(ROUND(P5/(1-'Mi negocio'!$B$12),6),1) | T5: =CEILING(ROUND(P5/(1-'Mi negocio'!$B$13),6),1) | U5: =CEILING(ROUND(P5/(1-'Mi negocio'!$B$14),6),1) | V5: =R5-P5
A6: 5 | B6: Pastel Ópera Francés con Bizcocho Joconde de Café y Crema de Mantequilla | C6: B1 | D6: Avanzado | E6: 10 | F6: porción | G6: 120 | H6: 4.5 | I6: 12 | J6: =SUMIF(Ingredientes!$A$2:$A$621,A6,Ingredientes!$G$2:$G$621) | K6: =J6/E6 | L6: =G6/E6*'Mi negocio'!$B$8 | M6: =I6/E6 | N6: ='Mi negocio'!$B$7 | O6: =K6+H6+M6+L6+N6 | P6: =O6/(1-'Mi negocio'!$B$5) | Q6: =(O6-N6)/(1-'Mi negocio'!$B$5) | R6: =CEILING(ROUND(P6/(1-'Mi negocio'!$B$11),6),1) | S6: =CEILING(ROUND(P6/(1-'Mi negocio'!$B$12),6),1) | T6: =CEILING(ROUND(P6/(1-'Mi negocio'!$B$13),6),1) | U6: =CEILING(ROUND(P6/(1-'Mi negocio'!$B$14),6),1) | V6: =R6-P6
A7: 6 | B7: Pastel Tres Leches Tradicional con Merengue Suizo a la Alulosa | C7: B1 | D7: Intermedio | E7: 12 | F7: rebanada | G7: 80 | H7: 4.5 | I7: 13 | J7: =SUMIF(Ingredientes!$A$2:$A$621,A7,Ingredientes!$G$2:$G$621) | K7: =J7/E7 | L7: =G7/E7*'Mi negocio'!$B$8 | M7: =I7/E7 | N7: ='Mi negocio'!$B$7 | O7: =K7+H7+M7+L7+N7 | P7: =O7/(1-'Mi negocio'!$B$5) | Q7: =(O7-N7)/(1-'Mi negocio'!$B$5) | R7: =CEILING(ROUND(P7/(1-'Mi negocio'!$B$11),6),1) | S7: =CEILING(ROUND(P7/(1-'Mi negocio'!$B$12),6),1) | T7: =CEILING(ROUND(P7/(1-'Mi negocio'!$B$13),6),1) | U7: =CEILING(ROUND(P7/(1-'Mi negocio'!$B$14),6),1) | V7: =R7-P7
A8: 7 | B8: Tarta Tiramisú con Savoiardi Caseros sin Gluten y Crema de Mascarpone | C8: B3 | D8: Intermedio | E8: 12 | F8: porción | G8: 70 | H8: 4.5 | I8: 8 | J8: =SUMIF(Ingredientes!$A$2:$A$621,A8,Ingredientes!$G$2:$G$621) | K8: =J8/E8 | L8: =G8/E8*'Mi negocio'!$B$8 | M8: =I8/E8 | N8: ='Mi negocio'!$B$7 | O8: =K8+H8+M8+L8+N8 | P8: =O8/(1-'Mi negocio'!$B$5) | Q8: =(O8-N8)/(1-'Mi negocio'!$B$5) | R8: =CEILING(ROUND(P8/(1-'Mi negocio'!$B$11),6),1) | S8: =CEILING(ROUND(P8/(1-'Mi negocio'!$B$12),6),1) | T8: =CEILING(ROUND(P8/(1-'Mi negocio'!$B$13),6),1) | U8: =CEILING(ROUND(P8/(1-'Mi negocio'!$B$14),6),1) | V8: =R8-P8
A9: 8 | B9: Pastel Alemán de Chocolate con Cobertura de Coco, Nueces Pecanas y Caramelo de Alulosa | C9: B1 | D9: Intermedio | E9: 14 | F9: rebanada | G9: 80 | H9: 4.5 | I9: 14 | J9: =SUMIF(Ingredientes!$A$2:$A$621,A9,Ingredientes!$G$2:$G$621) | K9: =J9/E9 | L9: =G9/E9*'Mi negocio'!$B$8 | M9: =I9/E9 | N9: ='Mi negocio'!$B$7 | O9: =K9+H9+M9+L9+N9 | P9: =O9/(1-'Mi negocio'!$B$5) | Q9: =(O9-N9)/(1-'Mi negocio'!$B$5) | R9: =CEILING(ROUND(P9/(1-'Mi negocio'!$B$11),6),1) | S9: =CEILING(ROUND(P9/(1-'Mi negocio'!$B$12),6),1) | T9: =CEILING(ROUND(P9/(1-'Mi negocio'!$B$13),6),1) | U9: =CEILING(ROUND(P9/(1-'Mi negocio'!$B$14),6),1) | V9: =R9-P9
A10: 9 | B10: Victoria Sponge Cake Clásico con Crema Chantilly y Confitura de Frambuesa | C10: B1 | D10: Fácil | E10: 10 | F10: rebanada | G10: 50 | H10: 4.5 | I10: 10 | J10: =SUMIF(Ingredientes!$A$2:$A$621,A10,Ingredientes!$G$2:$G$621) | K10: =J10/E10 | L10: =G10/E10*'Mi negocio'!$B$8 | M10: =I10/E10 | N10: ='Mi negocio'!$B$7 | O10: =K10+H10+M10+L10+N10 | P10: =O10/(1-'Mi negocio'!$B$5) | Q10: =(O10-N10)/(1-'Mi negocio'!$B$5) | R10: =CEILING(ROUND(P10/(1-'Mi negocio'!$B$11),6),1) | S10: =CEILING(ROUND(P10/(1-'Mi negocio'!$B$12),6),1) | T10: =CEILING(ROUND(P10/(1-'Mi negocio'!$B$13),6),1) | U10: =CEILING(ROUND(P10/(1-'Mi negocio'!$B$14),6),1) | V10: =R10-P10
A11: 10 | B11: Tarta de Limón Merengada con Curd Cítrico y Masa Sablée de Almendra | C11: B2 | D11: Avanzado | E11: 10 | F11: rebanada | G11: 85 | H11: 4.5 | I11: 12 | J11: =SUMIF(Ingredientes!$A$2:$A$621,A11,Ingredientes!$G$2:$G$621) | K11: =J11/E11 | L11: =G11/E11*'Mi negocio'!$B$8 | M11: =I11/E11 | N11: ='Mi negocio'!$B$7 | O11: =K11+H11+M11+L11+N11 | P11: =O11/(1-'Mi negocio'!$B$5) | Q11: =(O11-N11)/(1-'Mi negocio'!$B$5) | R11: =CEILING(ROUND(P11/(1-'Mi negocio'!$B$11),6),1) | S11: =CEILING(ROUND(P11/(1-'Mi negocio'!$B$12),6),1) | T11: =CEILING(ROUND(P11/(1-'Mi negocio'!$B$13),6),1) | U11: =CEILING(ROUND(P11/(1-'Mi negocio'!$B$14),6),1) | V11: =R11-P11
A12: 11 | B12: New York Cheesecake Clásico Horneado con Base Sablée de Almendra | C12: B4 | D12: Intermedio | E12: 12 | F12: rebanada | G12: 60 | H12: 4.5 | I12: 22 | J12: =SUMIF(Ingredientes!$A$2:$A$621,A12,Ingredientes!$G$2:$G$621) | K12: =J12/E12 | L12: =G12/E12*'Mi negocio'!$B$8 | M12: =I12/E12 | N12: ='Mi negocio'!$B$7 | O12: =K12+H12+M12+L12+N12 | P12: =O12/(1-'Mi negocio'!$B$5) | Q12: =(O12-N12)/(1-'Mi negocio'!$B$5) | R12: =CEILING(ROUND(P12/(1-'Mi negocio'!$B$11),6),1) | S12: =CEILING(ROUND(P12/(1-'Mi negocio'!$B$12),6),1) | T12: =CEILING(ROUND(P12/(1-'Mi negocio'!$B$13),6),1) | U12: =CEILING(ROUND(P12/(1-'Mi negocio'!$B$14),6),1) | V12: =R12-P12
A13: 12 | B13: Mousse de Chocolate Amargo 70% Sedosa al Aceite de Oliva | C13: B5 | D13: Fácil | E13: 10 | F13: vaso | G13: 35 | H13: 6 | I13: 3 | J13: =SUMIF(Ingredientes!$A$2:$A$621,A13,Ingredientes!$G$2:$G$621) | K13: =J13/E13 | L13: =G13/E13*'Mi negocio'!$B$8 | M13: =I13/E13 | N13: ='Mi negocio'!$B$7 | O13: =K13+H13+M13+L13+N13 | P13: =O13/(1-'Mi negocio'!$B$5) | Q13: =(O13-N13)/(1-'Mi negocio'!$B$5) | R13: =CEILING(ROUND(P13/(1-'Mi negocio'!$B$11),6),1) | S13: =CEILING(ROUND(P13/(1-'Mi negocio'!$B$12),6),1) | T13: =CEILING(ROUND(P13/(1-'Mi negocio'!$B$13),6),1) | U13: =CEILING(ROUND(P13/(1-'Mi negocio'!$B$14),6),1) | V13: =R13-P13
... A50: 49 | B50: Caramelo Salado Macchiato para Bañar | C50: B6 | D50: Fácil | E50: 1 | F50: frasco (350 g) | G50: 20 | H50: 14 | I50: 2 | J50: =SUMIF(Ingredientes!$A$2:$A$621,A50,Ingredientes!$G$2:$G$621) | K50: =J50/E50 | L50: =G50/E50*'Mi negocio'!$B$8 | M50: =I50/E50 | N50: ='Mi negocio'!$B$7 | O50: =K50+H50+M50+L50+N50 | P50: =O50/(1-'Mi negocio'!$B$5) | Q50: =(O50-N50)/(1-'Mi negocio'!$B$5) | R50: =CEILING(ROUND(P50/(1-'Mi negocio'!$B$11),6),1) | S50: =CEILING(ROUND(P50/(1-'Mi negocio'!$B$12),6),1) | T50: =CEILING(ROUND(P50/(1-'Mi negocio'!$B$13),6),1) | U50: =CEILING(ROUND(P50/(1-'Mi negocio'!$B$14),6),1) | V50: =R50-P50

Sheet Producción
A1: # | B1: Receta | C1: Piezas a producir | D1: Piezas por lote | E1: Lotes | F1: Costo insumos
A2: 1 | B2: =VLOOKUP(A2,'Recetas y precios'!$A:$B,2,FALSE) | C2: 0 | D2: =VLOOKUP(A2,'Recetas y precios'!$A:$E,5,FALSE) | E2: =IF(C2>0,CEILING(C2/D2,1),0) | F2: =E2*VLOOKUP(A2,'Recetas y precios'!$A:$J,10,FALSE)
A3: 2 | B3: =VLOOKUP(A3,'Recetas y precios'!$A:$B,2,FALSE) | C3: 0 | D3: =VLOOKUP(A3,'Recetas y precios'!$A:$E,5,FALSE) | E3: =IF(C3>0,CEILING(C3/D3,1),0) | F3: =E3*VLOOKUP(A3,'Recetas y precios'!$A:$J,10,FALSE)
A4: 3 | B4: =VLOOKUP(A4,'Recetas y precios'!$A:$B,2,FALSE) | C4: 0 | D4: =VLOOKUP(A4,'Recetas y precios'!$A:$E,5,FALSE) | E4: =IF(C4>0,CEILING(C4/D4,1),0) | F4: =E4*VLOOKUP(A4,'Recetas y precios'!$A:$J,10,FALSE)
A5: 4 | B5: =VLOOKUP(A5,'Recetas y precios'!$A:$B,2,FALSE) | C5: 0 | D5: =VLOOKUP(A5,'Recetas y precios'!$A:$E,5,FALSE) | E5: =IF(C5>0,CEILING(C5/D5,1),0) | F5: =E5*VLOOKUP(A5,'Recetas y precios'!$A:$J,10,FALSE)
A6: 5 | B6: =VLOOKUP(A6,'Recetas y precios'!$A:$B,2,FALSE) | C6: 0 | D6: =VLOOKUP(A6,'Recetas y precios'!$A:$E,5,FALSE) | E6: =IF(C6>0,CEILING(C6/D6,1),0) | F6: =E6*VLOOKUP(A6,'Recetas y precios'!$A:$J,10,FALSE)
A7: 6 | B7: =VLOOKUP(A7,'Recetas y precios'!$A:$B,2,FALSE) | C7: 0 | D7: =VLOOKUP(A7,'Recetas y precios'!$A:$E,5,FALSE) | E7: =IF(C7>0,CEILING(C7/D7,1),0) | F7: =E7*VLOOKUP(A7,'Recetas y precios'!$A:$J,10,FALSE)
A8: 7 | B8: =VLOOKUP(A8,'Recetas y precios'!$A:$B,2,FALSE) | C8: 0 | D8: =VLOOKUP(A8,'Recetas y precios'!$A:$E,5,FALSE) | E8: =IF(C8>0,CEILING(C8/D8,1),0) | F8: =E8*VLOOKUP(A8,'Recetas y precios'!$A:$J,10,FALSE)
A9: 8 | B9: =VLOOKUP(A9,'Recetas y precios'!$A:$B,2,FALSE) | C9: 0 | D9: =VLOOKUP(A9,'Recetas y precios'!$A:$E,5,FALSE) | E9: =IF(C9>0,CEILING(C9/D9,1),0) | F9: =E9*VLOOKUP(A9,'Recetas y precios'!$A:$J,10,FALSE)
A10: 9 | B10: =VLOOKUP(A10,'Recetas y precios'!$A:$B,2,FALSE) | C10: 0 | D10: =VLOOKUP(A10,'Recetas y precios'!$A:$E,5,FALSE) | E10: =IF(C10>0,CEILING(C10/D10,1),0) | F10: =E10*VLOOKUP(A10,'Recetas y precios'!$A:$J,10,FALSE)
A11: 10 | B11: =VLOOKUP(A11,'Recetas y precios'!$A:$B,2,FALSE) | C11: 0 | D11: =VLOOKUP(A11,'Recetas y precios'!$A:$E,5,FALSE) | E11: =IF(C11>0,CEILING(C11/D11,1),0) | F11: =E11*VLOOKUP(A11,'Recetas y precios'!$A:$J,10,FALSE)
A12: 11 | B12: =VLOOKUP(A12,'Recetas y precios'!$A:$B,2,FALSE) | C12: 0 | D12: =VLOOKUP(A12,'Recetas y precios'!$A:$E,5,FALSE) | E12: =IF(C12>0,CEILING(C12/D12,1),0) | F12: =E12*VLOOKUP(A12,'Recetas y precios'!$A:$J,10,FALSE)
A13: 12 | B13: =VLOOKUP(A13,'Recetas y precios'!$A:$B,2,FALSE) | C13: 0 | D13: =VLOOKUP(A13,'Recetas y precios'!$A:$E,5,FALSE) | E13: =IF(C13>0,CEILING(C13/D13,1),0) | F13: =E13*VLOOKUP(A13,'Recetas y precios'!$A:$J,10,FALSE)
... A50: 49 | B50: =VLOOKUP(A50,'Recetas y precios'!$A:$B,2,FALSE) | C50: 0 | D50: =VLOOKUP(A50,'Recetas y precios'!$A:$E,5,FALSE) | E50: =IF(C50>0,CEILING(C50/D50,1),0) | F50: =E50*VLOOKUP(A50,'Recetas y precios'!$A:$J,10,FALSE)

Sheet Ventas
A1: Fecha | B1: # | C1: Receta | D1: Canal | E1: Piezas | F1: Precio unitario | G1: Ingreso | H1: Costo | I1: Utilidad
C2: =IFERROR(VLOOKUP(B2,'Recetas y precios'!$A:$B,2,FALSE),"") | G2: =E2*F2 | H2: =IFERROR(E2*VLOOKUP(B2,'Recetas y precios'!$A:$P,16,FALSE),0) | I2: =G2-H2
C3: =IFERROR(VLOOKUP(B3,'Recetas y precios'!$A:$B,2,FALSE),"") | G3: =E3*F3 | H3: =IFERROR(E3*VLOOKUP(B3,'Recetas y precios'!$A:$P,16,FALSE),0) | I3: =G3-H3
C4: =IFERROR(VLOOKUP(B4,'Recetas y precios'!$A:$B,2,FALSE),"") | G4: =E4*F4 | H4: =IFERROR(E4*VLOOKUP(B4,'Recetas y precios'!$A:$P,16,FALSE),0) | I4: =G4-H4
C5: =IFERROR(VLOOKUP(B5,'Recetas y precios'!$A:$B,2,FALSE),"") | G5: =E5*F5 | H5: =IFERROR(E5*VLOOKUP(B5,'Recetas y precios'!$A:$P,16,FALSE),0) | I5: =G5-H5
C6: =IFERROR(VLOOKUP(B6,'Recetas y precios'!$A:$B,2,FALSE),"") | G6: =E6*F6 | H6: =IFERROR(E6*VLOOKUP(B6,'Recetas y precios'!$A:$P,16,FALSE),0) | I6: =G6-H6
C7: =IFERROR(VLOOKUP(B7,'Recetas y precios'!$A:$B,2,FALSE),"") | G7: =E7*F7 | H7: =IFERROR(E7*VLOOKUP(B7,'Recetas y precios'!$A:$P,16,FALSE),0) | I7: =G7-H7
C8: =IFERROR(VLOOKUP(B8,'Recetas y precios'!$A:$B,2,FALSE),"") | G8: =E8*F8 | H8: =IFERROR(E8*VLOOKUP(B8,'Recetas y precios'!$A:$P,16,FALSE),0) | I8: =G8-H8
C9: =IFERROR(VLOOKUP(B9,'Recetas y precios'!$A:$B,2,FALSE),"") | G9: =E9*F9 | H9: =IFERROR(E9*VLOOKUP(B9,'Recetas y precios'!$A:$P,16,FALSE),0) | I9: =G9-H9
C10: =IFERROR(VLOOKUP(B10,'Recetas y precios'!$A:$B,2,FALSE),"") | G10: =E10*F10 | H10: =IFERROR(E10*VLOOKUP(B10,'Recetas y precios'!$A:$P,16,FALSE),0) | I10: =G10-H10
C11: =IFERROR(VLOOKUP(B11,'Recetas y precios'!$A:$B,2,FALSE),"") | G11: =E11*F11 | H11: =IFERROR(E11*VLOOKUP(B11,'Recetas y precios'!$A:$P,16,FALSE),0) | I11: =G11-H11
C12: =IFERROR(VLOOKUP(B12,'Recetas y precios'!$A:$B,2,FALSE),"") | G12: =E12*F12 | H12: =IFERROR(E12*VLOOKUP(B12,'Recetas y precios'!$A:$P,16,FALSE),0) | I12: =G12-H12
C13: =IFERROR(VLOOKUP(B13,'Recetas y precios'!$A:$B,2,FALSE),"") | G13: =E13*F13 | H13: =IFERROR(E13*VLOOKUP(B13,'Recetas y precios'!$A:$P,16,FALSE),0) | I13: =G13-H13
... C201: =IFERROR(VLOOKUP(B201,'Recetas y precios'!$A:$B,2,FALSE),"") | G201: =E201*F201 | H201: =IFERROR(E201*VLOOKUP(B201,'Recetas y precios'!$A:$P,16,FALSE),0) | I201: =G201-H201

Sheet Tablero
A1: Tablero
A3: Recetas costeadas | B3: =COUNTIF('Recetas y precios'!A2:A50,">0")
A4: PVP mostrador promedio | B4: =AVERAGE('Recetas y precios'!R2:R50)
A5: Costo variable promedio | B5: =AVERAGE('Recetas y precios'!Q2:Q50)
A6: Punto de equilibrio (piezas/mes) | B6: =CEILING('Mi negocio'!B1/(B4-B5),1)
A7: Punto de equilibrio (piezas/día, 26 días) | B7: =CEILING(B6/26,1)
A8: Ingresos registrados | B8: =SUM(Ventas!G2:G201)
A9: Utilidad registrada | B9: =SUM(Ventas!I2:I201)
A10: Costo de producción planeada | B10: =SUM(Producción!F2:F50)
A13: Endulcora × Levent · Pastelería Científica para Diabéticos
