Workbook

Sheet LÉEME
A1: Tablas de Charcutería · Curación, Afinado, Composición Visual, Maridaje y 50 Tablas de Autor
A2: Anexo 1 · Costeo, merma y precios · Endulcora · Estudio Gastronómico · En colaboración con Levent
A4: • | B4: Qué es: Hoja de costeo del eBook «Tablas de Charcutería». Calcula el costo real de las 50 tablas, su costo por comensal y su precio por canal con tus propios precios de compra.
A5: • | B5: Cómo se usa: 1) Insumos: captura presentación y precio que tú pagas. 2) Preparaciones de la casa: revisa las preparaciones base; su costo alimenta a las recetas que las usan. 3) Mi negocio: gastos fijos, sueldo, horas, merma y márgenes. 4) Recetas y precios: revisa costos y precios. 5) Registra lotes en Producción y ventas en Ventas. 6) Revisa el Tablero cada semana.
A6: • | B6: Celdas amarillas: Son las únicas que debes editar. Todo lo demás es fórmula: si la borras, se rompe el cálculo.
A7: • | B7: Modelo de costeo: Costo por unidad = Precio ÷ Presentación · Las 4 preparaciones de la casa toman su costo de su propia fórmula (hoja «Preparaciones de la casa») · Insumos por tabla = Σ(cantidad × costo unitario) · Minutos por tabla = minutos de corte y mise en place ÷ tablas por tanda + minutos de montaje · Costo base = insumos + ramequines y empaque + soporte por uso + energía + mano de obra + gastos fijos · Costo total = Costo base ÷ (1 − merma) (se DIVIDE, no se suma) · Precio = Costo total ÷ (1 − margen), redondeado a $5 · Costo por comensal = Costo total ÷ comensales.
A8: • | B8: Preparaciones de la casa: La hoja «Preparaciones de la casa» costea las mermeladas, reducciones, confits y encurtidos desde su propia fórmula. Cuando cambies el precio de la fruta, del azúcar o del vino, se recalculan las preparaciones y con ellas las 50 tablas.
A9: • | B9: Hojas: Insumos (catálogo editable) · Preparaciones de la casa (las preparaciones base) · Ingredientes (cada línea del recetario normalizada, con el texto original) · Mi negocio (supuestos) · Recetas y precios (hoja principal) · Producción (bitácora de lotes y merma) · Ventas (bitácora) · Tablero (resumen).
A10: • | B10: Unidades: Las 50 tablas se costean por TABLA COMPLETA, que es como se vende. La columna «Comensales» es la de la fórmula del chef (6 en 49 tablas, 10-12 en la tabla 50) y es editable: cámbiala y el «Costo por comensal» se recalcula, que es el número con el que se cotiza un evento.
A11: • | B11: Advertencia: Los precios cargados son de referencia (mercado CDMX 2026), no cotizaciones. Los resultados son ilustrativos hasta que captures tus precios reales. No se promete ningún ingreso.
A12: • | B12: Créditos: Contenido y recetas: Chef Luis Alfonso Jiménez Cárdenas · Edición y costeo: Manuel Ramiro Justo Guzmán · Endulcora · Estudio Gastronómico, en colaboración con Levent · WhatsApp 56 6527 1901. Uso personal del comprador; prohibida su reventa o redistribución.
B14: Celda de ejemplo que sí puedes editar → | C14: 100

Sheet Insumos
A1: Insumos
A2: Captura la presentación que compras y lo que pagas. Precios de referencia CDMX 2026 (no son cotizaciones).
A4: ID | B4: Categoría | C4: Insumo | D4: Unidad | E4: Presentación | F4: Precio pagado | G4: Costo por unidad | H4: Usos | I4: Proveedor
A5: I-001 | B5: Jamones y paletas curadas | C5: Jamón 100% ibérico de bellota (loncheado a cuchillo) | D5: g | E5: 1000 | F5: 3200 | G5: =IFERROR(F5/E5,0) | H5: =COUNTIF(Ingredientes!$E:$E,C5)
A6: I-002 | B6: Jamones y paletas curadas | C6: Paleta 100% ibérica de bellota DOP | D6: g | E6: 1000 | F6: 2350 | G6: =IFERROR(F6/E6,0) | H6: =COUNTIF(Ingredientes!$E:$E,C6)
A7: I-003 | B7: Jamones y paletas curadas | C7: Jamón ibérico de cebo de campo (50-75% ibérico) | D7: g | E7: 1000 | F7: 1380 | G7: =IFERROR(F7/E7,0) | H7: =COUNTIF(Ingredientes!$E:$E,C7)
A8: I-004 | B8: Jamones y paletas curadas | C8: Jamón serrano gran reserva 18-24 meses | D8: g | E8: 1000 | F8: 620 | G8: =IFERROR(F8/E8,0) | H8: =COUNTIF(Ingredientes!$E:$E,C8)
A9: I-005 | B9: Jamones y paletas curadas | C9: Prosciutto di Parma DOP 24 meses | D9: g | E9: 1000 | F9: 1950 | G9: =IFERROR(F9/E9,0) | H9: =COUNTIF(Ingredientes!$E:$E,C9)
A10: I-006 | B10: Jamones y paletas curadas | C10: Jamón francés de cerdo negro (Bayonne IGP, Bigorre AOP) | D10: g | E10: 1000 | F10: 1780 | G10: =IFERROR(F10/E10,0) | H10: =COUNTIF(Ingredientes!$E:$E,C10)
A11: I-007 | B11: Jamones y paletas curadas | C11: Jamón ahumado de montaña (speck, schiffala, praga) | D11: g | E11: 1000 | F11: 780 | G11: =IFERROR(F11/E11,0) | H11: =COUNTIF(Ingredientes!$E:$E,C11)
A12: I-008 | B12: Jamones y paletas curadas | C12: Jamón de oveja o de cabra artesanal | D12: g | E12: 1000 | F12: 1450 | G12: =IFERROR(F12/E12,0) | H12: =COUNTIF(Ingredientes!$E:$E,C12)
A13: I-009 | B13: Jamones y paletas curadas | C13: Culatello di Zibello DOP | D13: g | E13: 1000 | F13: 3400 | G13: =IFERROR(F13/E13,0) | H13: =COUNTIF(Ingredientes!$E:$E,C13)
A14: I-010 | B14: Jamones y paletas curadas | C14: Jamón cocido fino al torchon o trufado | D14: g | E14: 1000 | F14: 520 | G14: =IFERROR(F14/E14,0) | H14: =COUNTIF(Ingredientes!$E:$E,C14)
A15: I-011 | B15: Jamones y paletas curadas | C15: Jamón criollo mexicano curado o ahumado | D15: g | E15: 1000 | F15: 520 | G15: =IFERROR(F15/E15,0) | H15: =COUNTIF(Ingredientes!$E:$E,C15)
A16: I-012 | B16: Jamones y paletas curadas | C16: Magret o jamón de pato curado | D16: g | E16: 1000 | F16: 1350 | G16: =IFERROR(F16/E16,0) | H16: =COUNTIF(Ingredientes!$E:$E,C16)
... A177: I-173 | B177: Grasas y condimentos | C177: Agua purificada | D177: ml | E177: 20000 | F177: 42 | G177: =IFERROR(F177/E177,0) | H177: =COUNTIF(Ingredientes!$E:$E,C177)
A178: I-174 | B178: Preparaciones de la casa | C178: Mermelada o compota densa de la casa (elaborada) | D178: g | E178: ='Preparaciones de la casa'!D5 | F178: ='Preparaciones de la casa'!F5 | G178: =IFERROR(F178/E178,0) | H178: =COUNTIF(Ingredientes!$E:$E,C178)
A179: I-175 | B179: Preparaciones de la casa | C179: Reducción densa de vino para tabla (elaborada) | D179: ml | E179: ='Preparaciones de la casa'!D6 | F179: ='Preparaciones de la casa'!F6 | G179: =IFERROR(F179/E179,0) | H179: =COUNTIF(Ingredientes!$E:$E,C179)
A180: I-176 | B180: Preparaciones de la casa | C180: Confit de cebolla o chalota al vino (elaborado) | D180: g | E180: ='Preparaciones de la casa'!D7 | F180: ='Preparaciones de la casa'!F7 | G180: =IFERROR(F180/E180,0) | H180: =COUNTIF(Ingredientes!$E:$E,C180)
A181: I-177 | B181: Preparaciones de la casa | C181: Encurtido rápido de la casa (elaborado) | D181: g | E181: ='Preparaciones de la casa'!D8 | F181: ='Preparaciones de la casa'!F8 | G181: =IFERROR(F181/E181,0) | H181: =COUNTIF(Ingredientes!$E:$E,C181)
C183: Las preparaciones del recetario toman su precio de la hoja «Preparaciones de la casa»: no se capturan a mano.

Sheet Preparaciones de la casa
A1: Las cuatro preparaciones de la casa
A2: Las mermeladas, reducciones, confits y encurtidos del ramequín no se compran: se elaboran. Su costo sale de su propia fórmula y alimenta a las 50 tablas. Cambia el precio de la fruta o del vino en «Insumos» y esta hoja se recalcula sola.
A4: Código | B4: Preparación base | C4: Para qué sirve | D4: Rendimiento | E4: Unidad | F4: Costo de insumos del lote | G4: Costo unitario | H4: Entra en las recetas
A5: B-1 | B5: Mermelada o compota densa de la casa | C5: La mermelada, compota, confitura o pasta densa de fruta que va en el ramequín. Es la guarnición húmeda más repetida del recetario y la que más caro se compra hecha. | D5: 600 | E5: g | F5: =SUMIF(Ingredientes!$A:$A,102,Ingredientes!$I:$I) | G5: =IFERROR(F5/D5,0) | H5: 22 de las 50 tablas · 900 g de fruta + 300 g de azúcar + vinagre y cítrico, reducidos a 600 g de pasta densa
A6: B-2 | B6: Reducción densa de vino para tabla | C6: La reducción de Pedro Ximénez, Oporto o tinto de guarda que se dibuja en hilo sobre la tabla. Se reduce a un tercio y aguanta un mes en refrigeración. | D6: 250 | E6: ml | F6: =SUMIF(Ingredientes!$A:$A,103,Ingredientes!$I:$I) | G6: =IFERROR(F6/D6,0) | H6: 5 de las 50 tablas · 750 ml de vino + azúcar y aromáticos reducidos a 250 ml de jarabe espeso
A7: B-3 | B7: Confit de cebolla o chalota al vino | C7: El confit de cebolla, chalota o cebollita caramelizada. Es la guarnición que mejor sostiene los quesos de corteza lavada y la que se puede producir en lote grande. | D7: 500 | E7: g | F7: =SUMIF(Ingredientes!$A:$A,104,Ingredientes!$I:$I) | G7: =IFERROR(F7/D7,0) | H7: 2 de las 50 tablas · 1 kg de cebolla pochada con azúcar, vino y AOVE hasta 500 g de confit
A8: B-4 | B8: Encurtido rápido de la casa | C8: El encurtido rápido de cebolla morada, chile, ajo o verdura de temporada. Sale en veinte minutos, cuesta una fracción del tarro de importación y es el contrapunto ácido de la tabla. | D8: 700 | E8: g | F8: =SUMIF(Ingredientes!$A:$A,105,Ingredientes!$I:$I) | G8: =IFERROR(F8/D8,0) | H8: 2 de las 50 tablas · 500 g de verdura + salmuera de vinagre, agua, azúcar y sal, rinde 700 g
B10: Las cuatro preparaciones tienen su propia fórmula, cargada en la hoja «Ingredientes» con los números 102 en adelante. El costo del lote incluye sólo los insumos: la mano de obra de prepararlas ya está contada en los minutos de mise en place de cada tabla.
A12: Notas técnicas
B13: El ramequín es donde está el ahorro | C13: Una mermelada artesanal de importación cuesta entre $280 y $400 el kilo. La de la casa cuesta una fracción de eso, y es la guarnición húmeda más repetida del recetario.
B14: Pésalas | C14: Hacer las guarniciones a ojo es la causa número uno de que el sabor de tus tablas cambie de una semana a otra. Estas cuatro fórmulas son la referencia.
B15: El rendimiento es editable | C15: Si tu lote rinde más o menos, cámbialo aquí y las 50 tablas se recalculan. Mide una vez y ajústalo.

Sheet Ingredientes
A1: Ingredientes
A2: Cada línea del recetario normalizada a un insumo del catálogo, con el texto original del chef al lado para auditarla.
A4: Nº | B4: Receta | C4: Bloque | D4: Texto original del chef | E4: Insumo | F4: Cantidad | G4: Unidad | H4: Costo unitario | I4: Costo
A5: 1 | B5: Tabla Ibérica Pura Bellota (Jamón 100% Ibérico de Bellota, Lomo de Bellota, Manchego DOP Viejo y Torta del Casar DOP) | C5: charcuteria | D5: 120 g Jamón 100% Ibérico de Bellota cortado a cuchillo en lonchas traslúcidas de 4 a 5 cm (aprox. 1 mm de espesor, con grasa infiltrada nacarada) | E5: Jamón 100% ibérico de bellota (loncheado a cuchillo) | F5: 120 | G5: g | H5: =IFERROR(VLOOKUP(E5,Insumos!$C$5:$G$181,5,FALSE),0) | I5: =F5*H5
A6: 1 | B6: Tabla Ibérica Pura Bellota (Jamón 100% Ibérico de Bellota, Lomo de Bellota, Manchego DOP Viejo y Torta del Casar DOP) | C6: charcuteria | D6: 80 g Caña de Lomo 100% Ibérico de Bellota curado en tripa natural, cortado al bies en láminas de 1.5 mm | E6: Caña de lomo 100% ibérico de bellota | F6: 80 | G6: g | H6: =IFERROR(VLOOKUP(E6,Insumos!$C$5:$G$181,5,FALSE),0) | I6: =F6*H6
A7: 1 | B7: Tabla Ibérica Pura Bellota (Jamón 100% Ibérico de Bellota, Lomo de Bellota, Manchego DOP Viejo y Torta del Casar DOP) | C7: queso | D7: 130 g Torta del Casar DOP (queso de leche cruda de oveja merina, coagulación con cuajo vegetal de flor de cardo Cynara cardunculus, pasta blanda untuosa fluida) | E7: Torta de cuajo vegetal DOP (Casar, La Serena) | F7: 130 | G7: g | H7: =IFERROR(VLOOKUP(E7,Insumos!$C$5:$G$181,5,FALSE),0) | I7: =F7*H7
A8: 1 | B8: Tabla Ibérica Pura Bellota (Jamón 100% Ibérico de Bellota, Lomo de Bellota, Manchego DOP Viejo y Torta del Casar DOP) | C8: queso | D8: 120 g Queso Manchego DOP Artesano Viejo (mínimo 10 a 12 meses de maduración, leche cruda de oveja manchega, pasta dura quebradiza) cortado en cuñas de 5 mm | E8: Queso manchego DOP artesano viejo o gran reserva | F8: 120 | G8: g | H8: =IFERROR(VLOOKUP(E8,Insumos!$C$5:$G$181,5,FALSE),0) | I8: =F8*H8
A9: 1 | B9: Tabla Ibérica Pura Bellota (Jamón 100% Ibérico de Bellota, Lomo de Bellota, Manchego DOP Viejo y Torta del Casar DOP) | C9: seco | D9: 60 g Picos camperos andaluces elaborados con aceite de oliva virgen extra y masa madre | E9: Picos, regañás o colines andaluces | F9: 60 | G9: g | H9: =IFERROR(VLOOKUP(E9,Insumos!$C$5:$G$181,5,FALSE),0) | I9: =F9*H9
A10: 1 | B10: Tabla Ibérica Pura Bellota (Jamón 100% Ibérico de Bellota, Lomo de Bellota, Manchego DOP Viejo y Torta del Casar DOP) | C10: seco | D10: 40 g Regañás sevillanas artesanales de ajonjolí | E10: Picos, regañás o colines andaluces | F10: 40 | G10: g | H10: =IFERROR(VLOOKUP(E10,Insumos!$C$5:$G$181,5,FALSE),0) | I10: =F10*H10
A11: 1 | B11: Tabla Ibérica Pura Bellota (Jamón 100% Ibérico de Bellota, Lomo de Bellota, Manchego DOP Viejo y Torta del Casar DOP) | C11: seco | D11: 50 g Almendras variedad Marcona tostadas y fritas en AOVE con sal marina gruesa | E11: Almendra Marcona pelada y frita en AOVE | F11: 50 | G11: g | H11: =IFERROR(VLOOKUP(E11,Insumos!$C$5:$G$181,5,FALSE),0) | I11: =F11*H11
A12: 1 | B12: Tabla Ibérica Pura Bellota (Jamón 100% Ibérico de Bellota, Lomo de Bellota, Manchego DOP Viejo y Torta del Casar DOP) | C12: humedo | D12: 80 g Uvas blancas de mesa variedad Moscatel o Thompson sin semillas (racimo pequeño seco) | E12: Uva de mesa sin semilla (blanca, roja o negra) | F12: 80 | G12: g | H12: =IFERROR(VLOOKUP(E12,Insumos!$C$5:$G$181,5,FALSE),0) | I12: =F12*H12
A13: 1 | B13: Tabla Ibérica Pura Bellota (Jamón 100% Ibérico de Bellota, Lomo de Bellota, Manchego DOP Viejo y Torta del Casar DOP) | C13: humedo | D13: 50 g Membrillo artesanal de Puente Genil cortado en dados de 1 cm | E13: Carne de membrillo, ate o dulce de fruta artesanal | F13: 50 | G13: g | H13: =IFERROR(VLOOKUP(E13,Insumos!$C$5:$G$181,5,FALSE),0) | I13: =F13*H13
A14: 1 | B14: Tabla Ibérica Pura Bellota (Jamón 100% Ibérico de Bellota, Lomo de Bellota, Manchego DOP Viejo y Torta del Casar DOP) | C14: humedo | D14: 40 g Aceitunas Gordal sevillanas marinadas con naranja y orégano (en ramequín cerámico cerrado) | E14: Aceituna de mesa aliñada (Gordal, Manzanilla, Campo Real, Gaeta) | F14: 40 | G14: g | H14: =IFERROR(VLOOKUP(E14,Insumos!$C$5:$G$181,5,FALSE),0) | I14: =F14*H14
A15: 2 | B15: Dehesa & Montanera (Salchichón Ibérico de Bellota, Chorizo Cular, Mahón Curado y Queso Idiazábal Ahumado DOP) | C15: charcuteria | D15: 90 g Chorizo Cular Ibérico de Bellota (carne de cerdo ibérico picada gruesa, pimentón de la Vera DOP dulce y agridulce, ajo y orégano) cortado al bies en láminas de 1.5 mm | E15: Chorizo cular ibérico de bellota | F15: 90 | G15: g | H15: =IFERROR(VLOOKUP(E15,Insumos!$C$5:$G$181,5,FALSE),0) | I15: =F15*H15
A16: 2 | B16: Dehesa & Montanera (Salchichón Ibérico de Bellota, Chorizo Cular, Mahón Curado y Queso Idiazábal Ahumado DOP) | C16: charcuteria | D16: 90 g Salchichón Ibérico de Bellota (carne magra de cerdo ibérico con grasa picada, pimienta negra en grano entero y nuez moscada) cortado en láminas de 1.5 mm | E16: Salchichón ibérico de bellota | F16: 90 | G16: g | H16: =IFERROR(VLOOKUP(E16,Insumos!$C$5:$G$181,5,FALSE),0) | I16: =F16*H16
... A530: 105 | B530: B-4 · Encurtido rápido de la casa | C530: humedo | D530: 5 g Especias y semillas aromáticas (comino, hinojo, anís, enebro, canela) · lote de B-4 | E530: Especias y semillas aromáticas (comino, hinojo, anís, enebro, canela) | F530: 5 | G530: g | H530: =IFERROR(VLOOKUP(E530,Insumos!$C$5:$G$181,5,FALSE),0) | I530: =F530*H530

Sheet Mi negocio
A1: Mi negocio
A2: Los supuestos que mueven todo. Si estos números están mal, todos tus precios están mal.
B4: Gasto fijo mensual | C4: Monto | D4: Nota
B5: Renta del local, obrador o cava | C5: 15000
B6: Luz, gas y cámara de frío de 2-4 °C | C6: 4600
B7: Agua y consumibles de limpieza | C7: 1100
B8: Internet, telefonía y punto de venta | C8: 800
B9: Publicidad y contenido | C9: 2800
B10: Permisos, licencias y comisiones de plataforma | C10: 2600
B11: Mantenimiento de cámara, rebanadora y cuchillería | C11: 1800
B12: Depreciación (cámara de afinado, rebanadora, tablas y soportes) | C12: 3400
B13: Análisis de laboratorio y control sanitario | C13: 900
B14: Otros gastos fijos | C14: 900
B17: Total de gastos fijos | C17: =SUM(C5:C16)
B19: Tablas producidos al mes | C19: 320 | D19: ≈ 12 tablas al día en 26 días de operación. Ajusta este número a tu venta real.
B20: Gastos fijos por tabla (overhead) | C20: =IFERROR(C17/C19,0) | D20: Se suma al costo de cada tabla.
B21: Sueldo mensual que te pagas | C21: 22000
B22: Horas de trabajo al mes | C22: 180
B23: Costo de tu hora | C23: =IFERROR(C21/C22,0) | D23: Mano de obra = minutos ÷ 60 × costo de la hora.
B24: % de merma por defecto | C24: 0.07 | D24: Cortezas, recortes, remanentes de ramequín y sobrantes de mesa. El material del taller sitúa esta merma entre 5 y 8 %. Compárala con tu merma real en el Tablero.
B25: Redondeo de precios (pesos) | C25: 5 | D25: Los precios suben al múltiplo superior de esta cifra.
B26: Márgenes objetivo por canal | C26: 6 | D26: Cortar la charcutería y los quesos y llenar los ramequines cuesta casi lo mismo con 3 tablas que con 12; montar, no. Éste es el número que más mueve tu costo de mano de obra.
B27: Margen · Salón y barra de vinos | C27: 0.58 | D27: Rango sugerido 54 – 62 %.
B28: Margen · Para llevar y reparto | C28: 0.52 | D28: Rango sugerido 48 – 56 %.
B29: Margen · Evento y catering | C29: 0.46 | D29: Rango sugerido 42 – 50 %.
B30: Margen · Mayoreo y corporativo | C30: 0.32 | D30: Rango sugerido 28 – 36 %.
B31: El soporte: el costo propio de este formato
B32: Precio de compra del soporte | C32: 850 | D32: Lo que te costó la tabla o el soporte de servicio. Se amortiza entre los usos que le saques.
B33: Usos que le sacas a cada soporte | C33: 200 | D33: Cuántas veces vas a usar ese mismo soporte antes de reponerlo. Una tabla de madera bien curada aguanta cientos de servicios.
B34: Costo del soporte por servicio | C34: =IFERROR(C32/MAX(1,C33),0) | D34: Se suma al costo de cada tabla. Es el costo propio de este formato.
B35: Alternativa desechable (referencia) | C35: 38 | D35: Base de cartón sulfatado rígido para envío. Si vendes para llevar, éste es tu costo real de soporte: cámbialo arriba.

Sheet Recetas y precios
A1: Recetas y precios
A2: Hoja principal. Cambia un precio en Insumos y los 50 precios se recalculan solos.
A4: Nº | B4: Receta | C4: Capítulo | D4: Bloque | E4: Queso | F4: Frío | G4: Unidad de venta | H4: Tablas que rinde | I4: Insumos del lote | J4: Insumos por tabla | K4: Ramequines y empaque | L4: Soporte (por uso) | M4: Energía por tabla | N4: Min. corte y mise en place (tanda) | O4: Min. montaje (tabla) | P4: Mano de obra | Q4: Gastos fijos | R4: Costo base | S4: Merma propia | T4: Merma aplicada | U4: COSTO TOTAL | V4: Comensales | W4: Costo por comensal | X4: PVP Salón y barra de vinos | Y4: PVP Para llevar y reparto | Z4: PVP Evento y catering | AA4: PVP Mayoreo y corporativo
A5: 1 | B5: Tabla Ibérica Pura Bellota (Jamón 100% Ibérico de Bellota, Lomo de Bellota, Manchego DOP Viejo y Torta del Casar DOP) | C5: Cap. 8 · España: dehesa, montaña y ovejas curadas | D5: E | E5: B | F5: E | G5: tabla | H5: 1 | I5: =SUMIF(Ingredientes!$A$5:$A$530,A5,Ingredientes!$I$5:$I$530) | J5: =IFERROR(I5/H5,0) | K5: 19.5 | L5: ='Mi negocio'!$C$34 | M5: 3.4 | N5: 75 | O5: 22 | P5: =IFERROR((N5/MAX(1,'Mi negocio'!$C$26)+O5)/60*'Mi negocio'!$C$23,0) | Q5: ='Mi negocio'!$C$20 | R5: =J5+K5+L5+M5+P5+Q5 | T5: =IF(S5="",'Mi negocio'!$C$24,S5) | U5: =IFERROR(R5/(1-T5),0) | V5: 6 | W5: =IFERROR(U5/MAX(1,V5),0) | X5: =IFERROR(CEILING(ROUND(U5/(1-'Mi negocio'!$C$27),6),'Mi negocio'!$C$25),0) | Y5: =IFERROR(CEILING(ROUND(U5/(1-'Mi negocio'!$C$28),6),'Mi negocio'!$C$25),0) | Z5: =IFERROR(CEILING(ROUND(U5/(1-'Mi negocio'!$C$29),6),'Mi negocio'!$C$25),0) | AA5: =IFERROR(CEILING(ROUND(U5/(1-'Mi negocio'!$C$30),6),'Mi negocio'!$C$25),0)
A6: 2 | B6: Dehesa & Montanera (Salchichón Ibérico de Bellota, Chorizo Cular, Mahón Curado y Queso Idiazábal Ahumado DOP) | C6: Cap. 8 · España: dehesa, montaña y ovejas curadas | D6: E | E6: D | F6: T | G6: tabla | H6: 1 | I6: =SUMIF(Ingredientes!$A$5:$A$530,A6,Ingredientes!$I$5:$I$530) | J6: =IFERROR(I6/H6,0) | K6: 19.5 | L6: ='Mi negocio'!$C$34 | M6: 2.6 | N6: 55 | O6: 18 | P6: =IFERROR((N6/MAX(1,'Mi negocio'!$C$26)+O6)/60*'Mi negocio'!$C$23,0) | Q6: ='Mi negocio'!$C$20 | R6: =J6+K6+L6+M6+P6+Q6 | T6: =IF(S6="",'Mi negocio'!$C$24,S6) | U6: =IFERROR(R6/(1-T6),0) | V6: 6 | W6: =IFERROR(U6/MAX(1,V6),0) | X6: =IFERROR(CEILING(ROUND(U6/(1-'Mi negocio'!$C$27),6),'Mi negocio'!$C$25),0) | Y6: =IFERROR(CEILING(ROUND(U6/(1-'Mi negocio'!$C$28),6),'Mi negocio'!$C$25),0) | Z6: =IFERROR(CEILING(ROUND(U6/(1-'Mi negocio'!$C$29),6),'Mi negocio'!$C$25),0) | AA6: =IFERROR(CEILING(ROUND(U6/(1-'Mi negocio'!$C$30),6),'Mi negocio'!$C$25),0)
A7: 3 | B7: Pirineos & Rastrojo (Cecina de León IGP, Fuet Artesano de Vic, Garrotxa de Cabra y Roncal DOP) | C7: Cap. 8 · España: dehesa, montaña y ovejas curadas | D7: E | E7: D | F7: T | G7: tabla | H7: 1 | I7: =SUMIF(Ingredientes!$A$5:$A$530,A7,Ingredientes!$I$5:$I$530) | J7: =IFERROR(I7/H7,0) | K7: 16 | L7: ='Mi negocio'!$C$34 | M7: 2.6 | N7: 55 | O7: 18 | P7: =IFERROR((N7/MAX(1,'Mi negocio'!$C$26)+O7)/60*'Mi negocio'!$C$23,0) | Q7: ='Mi negocio'!$C$20 | R7: =J7+K7+L7+M7+P7+Q7 | T7: =IF(S7="",'Mi negocio'!$C$24,S7) | U7: =IFERROR(R7/(1-T7),0) | V7: 6 | W7: =IFERROR(U7/MAX(1,V7),0) | X7: =IFERROR(CEILING(ROUND(U7/(1-'Mi negocio'!$C$27),6),'Mi negocio'!$C$25),0) | Y7: =IFERROR(CEILING(ROUND(U7/(1-'Mi negocio'!$C$28),6),'Mi negocio'!$C$25),0) | Z7: =IFERROR(CEILING(ROUND(U7/(1-'Mi negocio'!$C$29),6),'Mi negocio'!$C$25),0) | AA7: =IFERROR(CEILING(ROUND(U7/(1-'Mi negocio'!$C$30),6),'Mi negocio'!$C$25),0)
A8: 4 | B8: Meseta Castellana (Jamón Serrano Gran Reserva, Morcón Ibérico, Zamorano DOP y Queso Castellano Añejo) | C8: Cap. 8 · España: dehesa, montaña y ovejas curadas | D8: E | E8: D | F8: T | G8: tabla | H8: 1 | I8: =SUMIF(Ingredientes!$A$5:$A$530,A8,Ingredientes!$I$5:$I$530) | J8: =IFERROR(I8/H8,0) | K8: 19.5 | L8: ='Mi negocio'!$C$34 | M8: 2.6 | N8: 55 | O8: 18 | P8: =IFERROR((N8/MAX(1,'Mi negocio'!$C$26)+O8)/60*'Mi negocio'!$C$23,0) | Q8: ='Mi negocio'!$C$20 | R8: =J8+K8+L8+M8+P8+Q8 | T8: =IF(S8="",'Mi negocio'!$C$24,S8) | U8: =IFERROR(R8/(1-T8),0) | V8: 6 | W8: =IFERROR(U8/MAX(1,V8),0) | X8: =IFERROR(CEILING(ROUND(U8/(1-'Mi negocio'!$C$27),6),'Mi negocio'!$C$25),0) | Y8: =IFERROR(CEILING(ROUND(U8/(1-'Mi negocio'!$C$28),6),'Mi negocio'!$C$25),0) | Z8: =IFERROR(CEILING(ROUND(U8/(1-'Mi negocio'!$C$29),6),'Mi negocio'!$C$25),0) | AA8: =IFERROR(CEILING(ROUND(U8/(1-'Mi negocio'!$C$30),6),'Mi negocio'!$C$25),0)
A9: 5 | B9: Andalucía & Dehesas del Sur (Paleta Ibérica de Jabugo DOP, Caña de Lomo, Payoyo de Grazalema y Miel de Azahar) | C9: Cap. 8 · España: dehesa, montaña y ovejas curadas | D9: E | E9: P | F9: T | G9: tabla | H9: 1 | I9: =SUMIF(Ingredientes!$A$5:$A$530,A9,Ingredientes!$I$5:$I$530) | J9: =IFERROR(I9/H9,0) | K9: 16 | L9: ='Mi negocio'!$C$34 | M9: 3.4 | N9: 60 | O9: 20 | P9: =IFERROR((N9/MAX(1,'Mi negocio'!$C$26)+O9)/60*'Mi negocio'!$C$23,0) | Q9: ='Mi negocio'!$C$20 | R9: =J9+K9+L9+M9+P9+Q9 | T9: =IF(S9="",'Mi negocio'!$C$24,S9) | U9: =IFERROR(R9/(1-T9),0) | V9: 6 | W9: =IFERROR(U9/MAX(1,V9),0) | X9: =IFERROR(CEILING(ROUND(U9/(1-'Mi negocio'!$C$27),6),'Mi negocio'!$C$25),0) | Y9: =IFERROR(CEILING(ROUND(U9/(1-'Mi negocio'!$C$28),6),'Mi negocio'!$C$25),0) | Z9: =IFERROR(CEILING(ROUND(U9/(1-'Mi negocio'!$C$29),6),'Mi negocio'!$C$25),0) | AA9: =IFERROR(CEILING(ROUND(U9/(1-'Mi negocio'!$C$30),6),'Mi negocio'!$C$25),0)
A10: 6 | B10: Asturias de Cueva y Montaña (Gamonéu del Puerto, Cabrales DOP de Cueva, Chosco de Tineo IGP y Chorizo Asturiano a la Sidra) | C10: Cap. 8 · España: dehesa, montaña y ovejas curadas | D10: E | E10: P | F10: E | G10: tabla | H10: 1 | I10: =SUMIF(Ingredientes!$A$5:$A$530,A10,Ingredientes!$I$5:$I$530) | J10: =IFERROR(I10/H10,0) | K10: 19.5 | L10: ='Mi negocio'!$C$34 | M10: 2.6 | N10: 55 | O10: 18 | P10: =IFERROR((N10/MAX(1,'Mi negocio'!$C$26)+O10)/60*'Mi negocio'!$C$23,0) | Q10: ='Mi negocio'!$C$20 | R10: =J10+K10+L10+M10+P10+Q10 | T10: =IF(S10="",'Mi negocio'!$C$24,S10) | U10: =IFERROR(R10/(1-T10),0) | V10: 6 | W10: =IFERROR(U10/MAX(1,V10),0) | X10: =IFERROR(CEILING(ROUND(U10/(1-'Mi negocio'!$C$27),6),'Mi negocio'!$C$25),0) | Y10: =IFERROR(CEILING(ROUND(U10/(1-'Mi negocio'!$C$28),6),'Mi negocio'!$C$25),0) | Z10: =IFERROR(CEILING(ROUND(U10/(1-'Mi negocio'!$C$29),6),'Mi negocio'!$C$25),0) | AA10: =IFERROR(CEILING(ROUND(U10/(1-'Mi negocio'!$C$30),6),'Mi negocio'!$C$25),0)
A11: 7 | B11: Extremadura Silvestre (Lomito Ibérico de Presa, Chorizo de Pimentón de la Vera, Ibores DOP al Pimentón y Torta de la Serena DOP) | C11: Cap. 8 · España: dehesa, montaña y ovejas curadas | D11: E | E11: B | F11: E | G11: tabla | H11: 1 | I11: =SUMIF(Ingredientes!$A$5:$A$530,A11,Ingredientes!$I$5:$I$530) | J11: =IFERROR(I11/H11,0) | K11: 19.5 | L11: ='Mi negocio'!$C$34 | M11: 2.6 | N11: 55 | O11: 18 | P11: =IFERROR((N11/MAX(1,'Mi negocio'!$C$26)+O11)/60*'Mi negocio'!$C$23,0) | Q11: ='Mi negocio'!$C$20 | R11: =J11+K11+L11+M11+P11+Q11 | T11: =IF(S11="",'Mi negocio'!$C$24,S11) | U11: =IFERROR(R11/(1-T11),0) | V11: 6 | W11: =IFERROR(U11/MAX(1,V11),0) | X11: =IFERROR(CEILING(ROUND(U11/(1-'Mi negocio'!$C$27),6),'Mi negocio'!$C$25),0) | Y11: =IFERROR(CEILING(ROUND(U11/(1-'Mi negocio'!$C$28),6),'Mi negocio'!$C$25),0) | Z11: =IFERROR(CEILING(ROUND(U11/(1-'Mi negocio'!$C$29),6),'Mi negocio'!$C$25),0) | AA11: =IFERROR(CEILING(ROUND(U11/(1-'Mi negocio'!$C$30),6),'Mi negocio'!$C$25),0)
A12: 8 | B12: Islas Baleares & Salazón Marina (Sobrasada de Mallorca de Cerdo Negro, Cuixot Menorquín, Mahón Artesano Reserva y Sal de Es Trenc) | C12: Cap. 8 · España: dehesa, montaña y ovejas curadas | D12: E | E12: P | F12: M | G12: tabla | H12: 1 | I12: =SUMIF(Ingredientes!$A$5:$A$530,A12,Ingredientes!$I$5:$I$530) | J12: =IFERROR(I12/H12,0) | K12: 19.5 | L12: ='Mi negocio'!$C$34 | M12: 2.6 | N12: 50 | O12: 18 | P12: =IFERROR((N12/MAX(1,'Mi negocio'!$C$26)+O12)/60*'Mi negocio'!$C$23,0) | Q12: ='Mi negocio'!$C$20 | R12: =J12+K12+L12+M12+P12+Q12 | T12: =IF(S12="",'Mi negocio'!$C$24,S12) | U12: =IFERROR(R12/(1-T12),0) | V12: 6 | W12: =IFERROR(U12/MAX(1,V12),0) | X12: =IFERROR(CEILING(ROUND(U12/(1-'Mi negocio'!$C$27),6),'Mi negocio'!$C$25),0) | Y12: =IFERROR(CEILING(ROUND(U12/(1-'Mi negocio'!$C$28),6),'Mi negocio'!$C$25),0) | Z12: =IFERROR(CEILING(ROUND(U12/(1-'Mi negocio'!$C$29),6),'Mi negocio'!$C$25),0) | AA12: =IFERROR(CEILING(ROUND(U12/(1-'Mi negocio'!$C$30),6),'Mi negocio'!$C$25),0)
A13: 9 | B13: Galicia Rústica (Lacón Curado Tradicional, Androlla de Ourense, Queso San Simón da Costa DOP y Arzúa-Ulloa) | C13: Cap. 8 · España: dehesa, montaña y ovejas curadas | D13: E | E13: P | F13: E | G13: tabla | H13: 1 | I13: =SUMIF(Ingredientes!$A$5:$A$530,A13,Ingredientes!$I$5:$I$530) | J13: =IFERROR(I13/H13,0) | K13: 19.5 | L13: ='Mi negocio'!$C$34 | M13: 2.6 | N13: 55 | O13: 18 | P13: =IFERROR((N13/MAX(1,'Mi negocio'!$C$26)+O13)/60*'Mi negocio'!$C$23,0) | Q13: ='Mi negocio'!$C$20 | R13: =J13+K13+L13+M13+P13+Q13 | T13: =IF(S13="",'Mi negocio'!$C$24,S13) | U13: =IFERROR(R13/(1-T13),0) | V13: 6 | W13: =IFERROR(U13/MAX(1,V13),0) | X13: =IFERROR(CEILING(ROUND(U13/(1-'Mi negocio'!$C$27),6),'Mi negocio'!$C$25),0) | Y13: =IFERROR(CEILING(ROUND(U13/(1-'Mi negocio'!$C$28),6),'Mi negocio'!$C$25),0) | Z13: =IFERROR(CEILING(ROUND(U13/(1-'Mi negocio'!$C$29),6),'Mi negocio'!$C$25),0) | AA13: =IFERROR(CEILING(ROUND(U13/(1-'Mi negocio'!$C$30),6),'Mi negocio'!$C$25),0)
A14: 10 | B14: Dehesa Urbana Contemporánea (Presa Ibérica Curada al Vino Tinto, Chicharrón Ibérico Prensado, Flor de Guía DOP y Almendras Marcona Tostadas) | C14: Cap. 8 · España: dehesa, montaña y ovejas curadas | D14: E | E14: D | F14: T | G14: tabla | H14: 1 | I14: =SUMIF(Ingredientes!$A$5:$A$530,A14,Ingredientes!$I$5:$I$530) | J14: =IFERROR(I14/H14,0) | K14: 19.5 | L14: ='Mi negocio'!$C$34 | M14: 3.4 | N14: 60 | O14: 22 | P14: =IFERROR((N14/MAX(1,'Mi negocio'!$C$26)+O14)/60*'Mi negocio'!$C$23,0) | Q14: ='Mi negocio'!$C$20 | R14: =J14+K14+L14+M14+P14+Q14 | T14: =IF(S14="",'Mi negocio'!$C$24,S14) | U14: =IFERROR(R14/(1-T14),0) | V14: 6 | W14: =IFERROR(U14/MAX(1,V14),0) | X14: =IFERROR(CEILING(ROUND(U14/(1-'Mi negocio'!$C$27),6),'Mi negocio'!$C$25),0) | Y14: =IFERROR(CEILING(ROUND(U14/(1-'Mi negocio'!$C$28),6),'Mi negocio'!$C$25),0) | Z14: =IFERROR(CEILING(ROUND(U14/(1-'Mi negocio'!$C$29),6),'Mi negocio'!$C$25),0) | AA14: =IFERROR(CEILING(ROUND(U14/(1-'Mi negocio'!$C$30),6),'Mi negocio'!$C$25),0)
A15: 11 | B15: Gran Tabla Emiliana (Prosciutto di Parma DOP 24 Meses, Mortadella Bologna IGP, Parmigiano Reggiano DOP 30 Meses y Squacquerone di Romagna DOP) | C15: Cap. 9 · Italia: norcineria, alpes y mezzogiorno | D15: I | E15: D | F15: E | G15: tabla | H15: 1 | I15: =SUMIF(Ingredientes!$A$5:$A$530,A15,Ingredientes!$I$5:$I$530) | J15: =IFERROR(I15/H15,0) | K15: 19.5 | L15: ='Mi negocio'!$C$34 | M15: 3.4 | N15: 60 | O15: 20 | P15: =IFERROR((N15/MAX(1,'Mi negocio'!$C$26)+O15)/60*'Mi negocio'!$C$23,0) | Q15: ='Mi negocio'!$C$20 | R15: =J15+K15+L15+M15+P15+Q15 | T15: =IF(S15="",'Mi negocio'!$C$24,S15) | U15: =IFERROR(R15/(1-T15),0) | V15: 6 | W15: =IFERROR(U15/MAX(1,V15),0) | X15: =IFERROR(CEILING(ROUND(U15/(1-'Mi negocio'!$C$27),6),'Mi negocio'!$C$25),0) | Y15: =IFERROR(CEILING(ROUND(U15/(1-'Mi negocio'!$C$28),6),'Mi negocio'!$C$25),0) | Z15: =IFERROR(CEILING(ROUND(U15/(1-'Mi negocio'!$C$29),6),'Mi negocio'!$C$25),0) | AA15: =IFERROR(CEILING(ROUND(U15/(1-'Mi negocio'!$C$30),6),'Mi negocio'!$C$25),0)
A16: 12 | B16: Antica Norcineria Toscana (Finocchiona IGP al Hinojo Silvestre, Capocollo Toscano, Pecorino Toscano DOP Stagionato y Caciotta) | C16: Cap. 9 · Italia: norcineria, alpes y mezzogiorno | D16: I | E16: D | F16: T | G16: tabla | H16: 1 | I16: =SUMIF(Ingredientes!$A$5:$A$530,A16,Ingredientes!$I$5:$I$530) | J16: =IFERROR(I16/H16,0) | K16: 19.5 | L16: ='Mi negocio'!$C$34 | M16: 2.6 | N16: 55 | O16: 18 | P16: =IFERROR((N16/MAX(1,'Mi negocio'!$C$26)+O16)/60*'Mi negocio'!$C$23,0) | Q16: ='Mi negocio'!$C$20 | R16: =J16+K16+L16+M16+P16+Q16 | T16: =IF(S16="",'Mi negocio'!$C$24,S16) | U16: =IFERROR(R16/(1-T16),0) | V16: 6 | W16: =IFERROR(U16/MAX(1,V16),0) | X16: =IFERROR(CEILING(ROUND(U16/(1-'Mi negocio'!$C$27),6),'Mi negocio'!$C$25),0) | Y16: =IFERROR(CEILING(ROUND(U16/(1-'Mi negocio'!$C$28),6),'Mi negocio'!$C$25),0) | Z16: =IFERROR(CEILING(ROUND(U16/(1-'Mi negocio'!$C$29),6),'Mi negocio'!$C$25),0) | AA16: =IFERROR(CEILING(ROUND(U16/(1-'Mi negocio'!$C$30),6),'Mi negocio'!$C$25),0)
... A54: 50 | B54: Gran Gala Centenaria de Reyes (Cinco Jamones Nobles del Mundo, Cinco Grandes Quesos de Guarda, Néctares Nobles, Frutas de Pasión y Panes de Masa Madre) | C54: Cap. 12 · Monografías, armonías y tablas de celebración | D54: V | E54: D | F54: E | G54: tabla | H54: 1 | I54: =SUMIF(Ingredientes!$A$5:$A$530,A54,Ingredientes!$I$5:$I$530) | J54: =IFERROR(I54/H54,0) | K54: 39.1 | L54: ='Mi negocio'!$C$34 | M54: 3.4 | N54: 110 | O54: 40 | P54: =IFERROR((N54/MAX(1,'Mi negocio'!$C$26)+O54)/60*'Mi negocio'!$C$23,0) | Q54: ='Mi negocio'!$C$20 | R54: =J54+K54+L54+M54+P54+Q54 | T54: =IF(S54="",'Mi negocio'!$C$24,S54) | U54: =IFERROR(R54/(1-T54),0) | V54: 12 | W54: =IFERROR(U54/MAX(1,V54),0) | X54: =IFERROR(CEILING(ROUND(U54/(1-'Mi negocio'!$C$27),6),'Mi negocio'!$C$25),0) | Y54: =IFERROR(CEILING(ROUND(U54/(1-'Mi negocio'!$C$28),6),'Mi negocio'!$C$25),0) | Z54: =IFERROR(CEILING(ROUND(U54/(1-'Mi negocio'!$C$29),6),'Mi negocio'!$C$25),0) | AA54: =IFERROR(CEILING(ROUND(U54/(1-'Mi negocio'!$C$30),6),'Mi negocio'!$C$25),0)
B56: Los minutos de corte y mise en place son por tanda completa y se reparten entre las tablas por tanda de Mi negocio; los de montaje son por tabla y no bajan con la escala. Deja «Merma propia» vacía para usar la merma por defecto de Mi negocio. Bloque: E España · I Italia · F Francia · M México · V monografías y celebración. Queso: D pasta dura · P prensada · B blanda · A azul · H hilada. Frío: E estricta · M media · T tolerante. IMPORTANTE: el precio real de tu charcutería y de tus quesos es el de compra dividido entre tu rendimiento real de corte. Captura ese número en «Insumos», no el de la factura.

Sheet Producción
A1: Producción y merma
A2: Una fila por lote o tanda. La primera fila es un ejemplo: sobrescríbela.
A4: Fecha | B4: Lote | C4: Nº receta | D4: Receta | E4: Planeadas | F4: Buenas | G4: Falladas | H4: % merma | I4: Costo total unitario | J4: Costo de la merma | K4: Causa principal | L4: Notas
A5: 46298 | B5: L-2610-01 | C5: 11 | D5: =IF(C5="","",IFERROR(VLOOKUP(C5,'Recetas y precios'!$A$5:$B$54,2,FALSE),"")) | E5: 12 | F5: 11 | G5: 1 | H5: =IF((F5+G5)>0,G5/(F5+G5),"") | I5: =IF(C5="",0,IFERROR(VLOOKUP(C5,'Recetas y precios'!$A$5:$U$54,21,FALSE),0)) | J5: =G5*I5 | K5: Queso o charcutería fuera de punto al abrir | L5: Fila de ejemplo
D6: =IF(C6="","",IFERROR(VLOOKUP(C6,'Recetas y precios'!$A$5:$B$54,2,FALSE),"")) | H6: =IF((F6+G6)>0,G6/(F6+G6),"") | I6: =IF(C6="",0,IFERROR(VLOOKUP(C6,'Recetas y precios'!$A$5:$U$54,21,FALSE),0)) | J6: =G6*I6
D7: =IF(C7="","",IFERROR(VLOOKUP(C7,'Recetas y precios'!$A$5:$B$54,2,FALSE),"")) | H7: =IF((F7+G7)>0,G7/(F7+G7),"") | I7: =IF(C7="",0,IFERROR(VLOOKUP(C7,'Recetas y precios'!$A$5:$U$54,21,FALSE),0)) | J7: =G7*I7
D8: =IF(C8="","",IFERROR(VLOOKUP(C8,'Recetas y precios'!$A$5:$B$54,2,FALSE),"")) | H8: =IF((F8+G8)>0,G8/(F8+G8),"") | I8: =IF(C8="",0,IFERROR(VLOOKUP(C8,'Recetas y precios'!$A$5:$U$54,21,FALSE),0)) | J8: =G8*I8
D9: =IF(C9="","",IFERROR(VLOOKUP(C9,'Recetas y precios'!$A$5:$B$54,2,FALSE),"")) | H9: =IF((F9+G9)>0,G9/(F9+G9),"") | I9: =IF(C9="",0,IFERROR(VLOOKUP(C9,'Recetas y precios'!$A$5:$U$54,21,FALSE),0)) | J9: =G9*I9
D10: =IF(C10="","",IFERROR(VLOOKUP(C10,'Recetas y precios'!$A$5:$B$54,2,FALSE),"")) | H10: =IF((F10+G10)>0,G10/(F10+G10),"") | I10: =IF(C10="",0,IFERROR(VLOOKUP(C10,'Recetas y precios'!$A$5:$U$54,21,FALSE),0)) | J10: =G10*I10
D11: =IF(C11="","",IFERROR(VLOOKUP(C11,'Recetas y precios'!$A$5:$B$54,2,FALSE),"")) | H11: =IF((F11+G11)>0,G11/(F11+G11),"") | I11: =IF(C11="",0,IFERROR(VLOOKUP(C11,'Recetas y precios'!$A$5:$U$54,21,FALSE),0)) | J11: =G11*I11
D12: =IF(C12="","",IFERROR(VLOOKUP(C12,'Recetas y precios'!$A$5:$B$54,2,FALSE),"")) | H12: =IF((F12+G12)>0,G12/(F12+G12),"") | I12: =IF(C12="",0,IFERROR(VLOOKUP(C12,'Recetas y precios'!$A$5:$U$54,21,FALSE),0)) | J12: =G12*I12
D13: =IF(C13="","",IFERROR(VLOOKUP(C13,'Recetas y precios'!$A$5:$B$54,2,FALSE),"")) | H13: =IF((F13+G13)>0,G13/(F13+G13),"") | I13: =IF(C13="",0,IFERROR(VLOOKUP(C13,'Recetas y precios'!$A$5:$U$54,21,FALSE),0)) | J13: =G13*I13
D14: =IF(C14="","",IFERROR(VLOOKUP(C14,'Recetas y precios'!$A$5:$B$54,2,FALSE),"")) | H14: =IF((F14+G14)>0,G14/(F14+G14),"") | I14: =IF(C14="",0,IFERROR(VLOOKUP(C14,'Recetas y precios'!$A$5:$U$54,21,FALSE),0)) | J14: =G14*I14
D15: =IF(C15="","",IFERROR(VLOOKUP(C15,'Recetas y precios'!$A$5:$B$54,2,FALSE),"")) | H15: =IF((F15+G15)>0,G15/(F15+G15),"") | I15: =IF(C15="",0,IFERROR(VLOOKUP(C15,'Recetas y precios'!$A$5:$U$54,21,FALSE),0)) | J15: =G15*I15
D16: =IF(C16="","",IFERROR(VLOOKUP(C16,'Recetas y precios'!$A$5:$B$54,2,FALSE),"")) | H16: =IF((F16+G16)>0,G16/(F16+G16),"") | I16: =IF(C16="",0,IFERROR(VLOOKUP(C16,'Recetas y precios'!$A$5:$U$54,21,FALSE),0)) | J16: =G16*I16
D17: =IF(C17="","",IFERROR(VLOOKUP(C17,'Recetas y precios'!$A$5:$B$54,2,FALSE),"")) | H17: =IF((F17+G17)>0,G17/(F17+G17),"") | I17: =IF(C17="",0,IFERROR(VLOOKUP(C17,'Recetas y precios'!$A$5:$U$54,21,FALSE),0)) | J17: =G17*I17
... D304: =IF(C304="","",IFERROR(VLOOKUP(C304,'Recetas y precios'!$A$5:$B$54,2,FALSE),"")) | H304: =IF((F304+G304)>0,G304/(F304+G304),"") | I304: =IF(C304="",0,IFERROR(VLOOKUP(C304,'Recetas y precios'!$A$5:$U$54,21,FALSE),0)) | J304: =G304*I304

Sheet Ventas
A1: Ventas
A2: Una fila por venta. La primera fila es un ejemplo: sobrescríbela.
A4: Fecha | B4: Nº receta | C4: Receta | D4: Canal | E4: Tablas | F4: Precio unitario | G4: Ingreso | H4: Costo total | I4: Comisión % | J4: Comisión $ | K4: Utilidad neta | L4: Margen | M4: Cliente o nota
A5: 46298 | B5: 11 | C5: =IF(B5="","",IFERROR(VLOOKUP(B5,'Recetas y precios'!$A$5:$B$54,2,FALSE),"")) | D5: Salón y barra de vinos | E5: 2 | F5: 1520 | G5: =E5*F5 | H5: =IF(B5="",0,E5*IFERROR(VLOOKUP(B5,'Recetas y precios'!$A$5:$U$54,21,FALSE),0)) | I5: 0 | J5: =G5*I5 | K5: =G5-H5-J5 | L5: =IF(G5>0,K5/G5,"") | M5: Fila de ejemplo
C6: =IF(B6="","",IFERROR(VLOOKUP(B6,'Recetas y precios'!$A$5:$B$54,2,FALSE),"")) | G6: =E6*F6 | H6: =IF(B6="",0,E6*IFERROR(VLOOKUP(B6,'Recetas y precios'!$A$5:$U$54,21,FALSE),0)) | J6: =G6*I6 | K6: =G6-H6-J6 | L6: =IF(G6>0,K6/G6,"")
C7: =IF(B7="","",IFERROR(VLOOKUP(B7,'Recetas y precios'!$A$5:$B$54,2,FALSE),"")) | G7: =E7*F7 | H7: =IF(B7="",0,E7*IFERROR(VLOOKUP(B7,'Recetas y precios'!$A$5:$U$54,21,FALSE),0)) | J7: =G7*I7 | K7: =G7-H7-J7 | L7: =IF(G7>0,K7/G7,"")
C8: =IF(B8="","",IFERROR(VLOOKUP(B8,'Recetas y precios'!$A$5:$B$54,2,FALSE),"")) | G8: =E8*F8 | H8: =IF(B8="",0,E8*IFERROR(VLOOKUP(B8,'Recetas y precios'!$A$5:$U$54,21,FALSE),0)) | J8: =G8*I8 | K8: =G8-H8-J8 | L8: =IF(G8>0,K8/G8,"")
C9: =IF(B9="","",IFERROR(VLOOKUP(B9,'Recetas y precios'!$A$5:$B$54,2,FALSE),"")) | G9: =E9*F9 | H9: =IF(B9="",0,E9*IFERROR(VLOOKUP(B9,'Recetas y precios'!$A$5:$U$54,21,FALSE),0)) | J9: =G9*I9 | K9: =G9-H9-J9 | L9: =IF(G9>0,K9/G9,"")
C10: =IF(B10="","",IFERROR(VLOOKUP(B10,'Recetas y precios'!$A$5:$B$54,2,FALSE),"")) | G10: =E10*F10 | H10: =IF(B10="",0,E10*IFERROR(VLOOKUP(B10,'Recetas y precios'!$A$5:$U$54,21,FALSE),0)) | J10: =G10*I10 | K10: =G10-H10-J10 | L10: =IF(G10>0,K10/G10,"")
C11: =IF(B11="","",IFERROR(VLOOKUP(B11,'Recetas y precios'!$A$5:$B$54,2,FALSE),"")) | G11: =E11*F11 | H11: =IF(B11="",0,E11*IFERROR(VLOOKUP(B11,'Recetas y precios'!$A$5:$U$54,21,FALSE),0)) | J11: =G11*I11 | K11: =G11-H11-J11 | L11: =IF(G11>0,K11/G11,"")
C12: =IF(B12="","",IFERROR(VLOOKUP(B12,'Recetas y precios'!$A$5:$B$54,2,FALSE),"")) | G12: =E12*F12 | H12: =IF(B12="",0,E12*IFERROR(VLOOKUP(B12,'Recetas y precios'!$A$5:$U$54,21,FALSE),0)) | J12: =G12*I12 | K12: =G12-H12-J12 | L12: =IF(G12>0,K12/G12,"")
C13: =IF(B13="","",IFERROR(VLOOKUP(B13,'Recetas y precios'!$A$5:$B$54,2,FALSE),"")) | G13: =E13*F13 | H13: =IF(B13="",0,E13*IFERROR(VLOOKUP(B13,'Recetas y precios'!$A$5:$U$54,21,FALSE),0)) | J13: =G13*I13 | K13: =G13-H13-J13 | L13: =IF(G13>0,K13/G13,"")
C14: =IF(B14="","",IFERROR(VLOOKUP(B14,'Recetas y precios'!$A$5:$B$54,2,FALSE),"")) | G14: =E14*F14 | H14: =IF(B14="",0,E14*IFERROR(VLOOKUP(B14,'Recetas y precios'!$A$5:$U$54,21,FALSE),0)) | J14: =G14*I14 | K14: =G14-H14-J14 | L14: =IF(G14>0,K14/G14,"")
C15: =IF(B15="","",IFERROR(VLOOKUP(B15,'Recetas y precios'!$A$5:$B$54,2,FALSE),"")) | G15: =E15*F15 | H15: =IF(B15="",0,E15*IFERROR(VLOOKUP(B15,'Recetas y precios'!$A$5:$U$54,21,FALSE),0)) | J15: =G15*I15 | K15: =G15-H15-J15 | L15: =IF(G15>0,K15/G15,"")
C16: =IF(B16="","",IFERROR(VLOOKUP(B16,'Recetas y precios'!$A$5:$B$54,2,FALSE),"")) | G16: =E16*F16 | H16: =IF(B16="",0,E16*IFERROR(VLOOKUP(B16,'Recetas y precios'!$A$5:$U$54,21,FALSE),0)) | J16: =G16*I16 | K16: =G16-H16-J16 | L16: =IF(G16>0,K16/G16,"")
C17: =IF(B17="","",IFERROR(VLOOKUP(B17,'Recetas y precios'!$A$5:$B$54,2,FALSE),"")) | G17: =E17*F17 | H17: =IF(B17="",0,E17*IFERROR(VLOOKUP(B17,'Recetas y precios'!$A$5:$U$54,21,FALSE),0)) | J17: =G17*I17 | K17: =G17-H17-J17 | L17: =IF(G17>0,K17/G17,"")
... C504: =IF(B504="","",IFERROR(VLOOKUP(B504,'Recetas y precios'!$A$5:$B$54,2,FALSE),"")) | G504: =E504*F504 | H504: =IF(B504="",0,E504*IFERROR(VLOOKUP(B504,'Recetas y precios'!$A$5:$U$54,21,FALSE),0)) | J504: =G504*I504 | K504: =G504-H504-J504 | L504: =IF(G504>0,K504/G504,"")

Sheet Tablero
A1: Tablero
A2: Resumen automático de Ventas y Producción. No se edita.
B3: Ventas | E3: Canal | F3: Ingreso | G3: Tablas
B4: Ingreso acumulado | C4: =SUM(Ventas!G5:G504) | E4: Salón y barra de vinos | F4: =SUMIF(Ventas!$D$5:$D$504,E4,Ventas!$G$5:$G$504) | G4: =SUMIF(Ventas!$D$5:$D$504,E4,Ventas!$E$5:$E$504)
B5: Tablas vendidos | C5: =SUM(Ventas!E5:E504) | E5: Para llevar y reparto | F5: =SUMIF(Ventas!$D$5:$D$504,E5,Ventas!$G$5:$G$504) | G5: =SUMIF(Ventas!$D$5:$D$504,E5,Ventas!$E$5:$E$504)
B6: Costo de lo vendido | C6: =SUM(Ventas!H5:H504) | E6: Evento y catering | F6: =SUMIF(Ventas!$D$5:$D$504,E6,Ventas!$G$5:$G$504) | G6: =SUMIF(Ventas!$D$5:$D$504,E6,Ventas!$E$5:$E$504)
B7: Comisiones | C7: =SUM(Ventas!J5:J504) | E7: Mayoreo y corporativo | F7: =SUMIF(Ventas!$D$5:$D$504,E7,Ventas!$G$5:$G$504) | G7: =SUMIF(Ventas!$D$5:$D$504,E7,Ventas!$E$5:$E$504)
B8: Utilidad neta (antes de gastos fijos) | C8: =SUM(Ventas!K5:K504) | E8: Degustación o cortesía | F8: =SUMIF(Ventas!$D$5:$D$504,E8,Ventas!$G$5:$G$504) | G8: =SUMIF(Ventas!$D$5:$D$504,E8,Ventas!$E$5:$E$504)
B9: Margen neto | C9: =IFERROR(C8/C4,0)
B10: Utilidad después de gastos fijos | C10: =C8-'Mi negocio'!C17
B11: Producción y merma | E11: Preparación base | F11: Costo del lote | G11: Costo unitario
B12: Tablas buenos producidos | C12: =SUM(Producción!F5:F304) | E12: B-1 · Mermelada o compota densa de la casa | F12: ='Preparaciones de la casa'!F5 | G12: ='Preparaciones de la casa'!G5
B13: Tablas fallados | C13: =SUM(Producción!G5:G304) | E13: B-2 · Reducción densa de vino para tabla | F13: ='Preparaciones de la casa'!F6 | G13: ='Preparaciones de la casa'!G6
B14: Merma real | C14: =IFERROR(C13/(C12+C13),0) | E14: B-3 · Confit de cebolla o chalota al vino | F14: ='Preparaciones de la casa'!F7 | G14: ='Preparaciones de la casa'!G7
B15: Merma supuesta | C15: ='Mi negocio'!$C$24 | E15: B-4 · Encurtido rápido de la casa | F15: ='Preparaciones de la casa'!F8 | G15: ='Preparaciones de la casa'!G8
B16: Dinero perdido en merma | C16: =SUM(Producción!J5:J304)
B17: Punto de equilibrio
B18: Precio promedio · Salón y barra de vinos | C18: =AVERAGE('Recetas y precios'!$X$5:$X$54)
B19: Costo total promedio (recetario) | C19: =AVERAGE('Recetas y precios'!$U$5:$U$54)
B20: Margen de contribución promedio | C20: =C18-C19
B21: Margen de contribución real de tus ventas | C21: =IFERROR((C4-C6-C7)/C5,0) | D21: ← | E21: En cuanto registres ventas reales, el equilibrio usa tu margen real, no el promedio del recetario.
B22: Gastos fijos del mes | C22: ='Mi negocio'!C17
B23: PUNTO DE EQUILIBRIO (tablas al mes) | C23: =IFERROR(ROUNDUP(C22/IF(C21>0,C21,C20),0),0)
B24: Avance contra el punto de equilibrio | C24: =IFERROR(C5/C23,0)
B28: Endulcora · Estudio Gastronómico · En colaboración con Levent · Tablas de Charcutería · Anexo 1
