Workbook

Sheet LÉEME
A1: ANEXO 1 · CALCULADORA DE COSTOS, MERMA Y PRECIOS
A2: Panqués y Pound Cakes Gourmet de Autor · 51 recetas · Oficios Dulces vol. 5
A3: Endulcora · Estudio Gastronómico · en colaboración con Levent
A6: QUÉ ES ESTO
B7: Un modelo de costeo vivo para las 51 recetas del libro. Todas las hojas están enlazadas con fórmulas reales: si cambias un precio de compra, las 51 recetas, sus cuatro canales de venta y el punto de equilibrio se recalculan solos.
A9: CÓMO SE USA
A10: 1 | B10: Ve a la hoja «Mi negocio» y pon tus datos reales: renta, sueldo, producción mensual, empaque, energía y merma. Son ocho celdas.
A11: 2 | B11: Ve a la hoja «Insumos» y sustituye los precios de referencia por los que tú pagas. Solo la columna «Precio de compra» (celdas en amarillo).
A12: 3 | B12: Abre «Recetas y precios». Ahí están las 51 piezas costeadas con tus números y sus precios sugeridos en los cuatro canales.
A13: 4 | B13: Usa «Producción» para planear el mes y «Ventas» para registrar lo que vendes. El «Tablero» resume todo.
A15: LA REGLA DE ORO
B16: SOLO SE EDITAN LAS CELDAS AMARILLAS. Todo lo demás son fórmulas: si escribes encima, rompes el modelo.
A18: EL MODELO DE COSTEO
B19: Costo por unidad = Precio de compra ÷ Cantidad comprada
B20: Costo insumos lote = Σ (cantidad × costo por unidad)
B21: Costo base = Insumos + Empaque + Energía + Mano de obra + Overhead
B22: Costo total unitario = Costo base ÷ (1 − % merma) ← se DIVIDE, no se suma
B23: PVP = Costo total ÷ (1 − margen)
B24: Costo por rebanada = Costo total ÷ rebanadas del molde
B25: Punto de equilibrio = Gastos fijos ÷ (PVP − costo variable unitario)
A27: LAS NUEVE HOJAS
A28: LÉEME | B28: Esta página.
A29: Insumos | B29: 135 insumos con presentación, precio de compra (editable) y costo por gramo o mililitro.
A30: Bases madre | B30: Los 6 métodos de emulsión y las 6 preparaciones transversales, con cuántas recetas usa cada uno y su costo promedio.
A31: Ingredientes | B31: Las 773 líneas del recetario normalizadas contra el catálogo, con el texto original del chef al lado para poder auditarlas.
A32: Mi negocio | B32: Tus parámetros. Es la hoja que hay que llenar primero.
A33: Recetas y precios | B33: La hoja principal: las 51 piezas con su costo y sus 4 precios.
A34: Producción | B34: Plan mensual: cuántas piezas de cada receta y qué cuesta producirlas.
A35: Ventas | B35: Registro de ventas con cálculo automático de utilidad.
A36: Tablero | B36: Resumen, punto de equilibrio y ranking de rentabilidad.
A38: ADVERTENCIAS
B39: Los precios precargados son REFERENCIAS de mercado CDMX 2026, no cotizaciones. Sustitúyelos.
B40: Endulcora no garantiza ingresos ni resultados de negocio. Este archivo es una herramienta de cálculo, no una promesa.
B41: Las líneas marcadas en la hoja «Ingredientes» con una nota en la columna «Equivalencia asumida» llevan un supuesto editorial (piezas a gramos, ralladuras, subpreparaciones ya costeadas). Están declaradas una por una para que puedas revisarlas y cambiarlas.

Sheet Insumos
A1: INSUMOS
A2: Sustituye la columna «Precio de compra» (amarillo) por tus precios reales.
A3: Endulcora · Estudio Gastronómico · en colaboración con Levent
A5: Clave | B5: Insumo | C5: Categoría | D5: Cantidad comprada | E5: Unidad | F5: Precio de compra | G5: Costo por unidad | H5: Recetas que lo usan | I5: Consumo total (g/ml)
A6: I-001 | B6: Mantequilla sin sal 82% grasa | C6: Lácteos y grasas | D6: 1000 | E6: g | F6: 245 | G6: =IFERROR(F6/D6,0) -> 0.245 | H6: =COUNTIF(Ingredientes!$E:$E,A6) -> 71 | I6: =SUMIF(Ingredientes!$E:$E,A6,Ingredientes!$F:$F) -> 8763
A7: I-002 | B7: Mantequilla de rancho sin sal | C7: Lácteos y grasas | D7: 1000 | E7: g | F7: 290 | G7: =IFERROR(F7/D7,0) -> 0.29 | H7: =COUNTIF(Ingredientes!$E:$E,A7) -> 1 | I7: =SUMIF(Ingredientes!$E:$E,A7,Ingredientes!$F:$F) -> 220
A8: I-003 | B8: Mantequilla con sal | C8: Lácteos y grasas | D8: 1000 | E8: g | F8: 240 | G8: =IFERROR(F8/D8,0) -> 0.24 | H8: =COUNTIF(Ingredientes!$E:$E,A8) -> 1 | I8: =SUMIF(Ingredientes!$E:$E,A8,Ingredientes!$F:$F) -> 40
A9: I-004 | B9: Huevo entero (sin cascarón) | C9: Lácteos y grasas | D9: 1000 | E9: g | F9: 62 | G9: =IFERROR(F9/D9,0) -> 0.062 | H9: =COUNTIF(Ingredientes!$E:$E,A9) -> 51 | I9: =SUMIF(Ingredientes!$E:$E,A9,Ingredientes!$F:$F) -> 9800
A10: I-005 | B10: Yema de huevo | C10: Lácteos y grasas | D10: 1000 | E10: g | F10: 118 | G10: =IFERROR(F10/D10,0) -> 0.118 | H10: =COUNTIF(Ingredientes!$E:$E,A10) -> 1 | I10: =SUMIF(Ingredientes!$E:$E,A10,Ingredientes!$F:$F) -> 60
A11: I-006 | B11: Clara de huevo | C11: Lácteos y grasas | D11: 1000 | E11: g | F11: 48 | G11: =IFERROR(F11/D11,0) -> 0.048 | H11: =COUNTIF(Ingredientes!$E:$E,A11) -> 2 | I11: =SUMIF(Ingredientes!$E:$E,A11,Ingredientes!$F:$F) -> 180
A12: I-007 | B12: Leche entera | C12: Lácteos y grasas | D12: 1000 | E12: ml | F12: 27 | G12: =IFERROR(F12/D12,0) -> 0.027 | H12: =COUNTIF(Ingredientes!$E:$E,A12) -> 19 | I12: =SUMIF(Ingredientes!$E:$E,A12,Ingredientes!$F:$F) -> 682
A13: I-008 | B13: Crema para batir 35% | C13: Lácteos y grasas | D13: 1000 | E13: ml | F13: 118 | G13: =IFERROR(F13/D13,0) -> 0.118 | H13: =COUNTIF(Ingredientes!$E:$E,A13) -> 19 | I13: =SUMIF(Ingredientes!$E:$E,A13,Ingredientes!$F:$F) -> 945
A14: I-009 | B14: Crema ácida / crema de rancho | C14: Lácteos y grasas | D14: 900 | E14: g | F14: 92 | G14: =IFERROR(F14/D14,0) -> 0.10222222 | H14: =COUNTIF(Ingredientes!$E:$E,A14) -> 9 | I14: =SUMIF(Ingredientes!$E:$E,A14,Ingredientes!$F:$F) -> 380
A15: I-010 | B15: Nata fresca de rancho | C15: Lácteos y grasas | D15: 500 | E15: g | F15: 95 | G15: =IFERROR(F15/D15,0) -> 0.19 | H15: =COUNTIF(Ingredientes!$E:$E,A15) -> 2 | I15: =SUMIF(Ingredientes!$E:$E,A15,Ingredientes!$F:$F) -> 350
A16: I-011 | B16: Yogur griego natural sin azúcar | C16: Lácteos y grasas | D16: 900 | E16: g | F16: 98 | G16: =IFERROR(F16/D16,0) -> 0.10888889 | H16: =COUNTIF(Ingredientes!$E:$E,A16) -> 1 | I16: =SUMIF(Ingredientes!$E:$E,A16,Ingredientes!$F:$F) -> 40
A17: I-012 | B17: Queso crema entero (bloque) | C17: Lácteos y grasas | D17: 1000 | E17: g | F17: 168 | G17: =IFERROR(F17/D17,0) -> 0.168 | H17: =COUNTIF(Ingredientes!$E:$E,A17) -> 3 | I17: =SUMIF(Ingredientes!$E:$E,A17,Ingredientes!$F:$F) -> 420
... A140: I-167 | B140: Licor amaretto | C140: Licores | D140: 700 | E140: ml | F140: 395 | G140: =IFERROR(F140/D140,0) -> 0.56428571 | H140: =COUNTIF(Ingredientes!$E:$E,A140) -> 1 | I140: =SUMIF(Ingredientes!$E:$E,A140,Ingredientes!$F:$F) -> 15
A142: Precios de referencia CDMX 2026. Ilustrativos, no cotizaciones.

Sheet Bases madre
A1: BASES MADRE
A2: Los seis métodos de emulsión y las seis preparaciones transversales.
A3: Endulcora · Estudio Gastronómico · en colaboración con Levent
A5: Clave | B5: Método base | C5: Qué es | D5: Recetas | E5: Costo promedio de insumos | F5: Costo mínimo | G5: Costo máximo
A6: M-1 | B6: Cremado clásico (mantequilla pomada + azúcar) | C6: La mantequilla en pomada a 18 °C se bate con el azúcar hasta blanquear e incorporar aire; el huevo entra en emulsión y la harina se integra al mínimo. | D6: =COUNTIF('Recetas y precios'!$C:$C,A6) -> 37 | E6: =IFERROR(AVERAGEIF('Recetas y precios'!$C:$C,A6,'Recetas y precios'!$E:$E),0) -> 149.82116 | F6: =IFERROR(minifs('Recetas y precios'!$E$6:$E$56,'Recetas y precios'!$C$6:$C$56,A6),0) -> 0 | G6: =IFERROR(maxifs('Recetas y precios'!$E$6:$E$56,'Recetas y precios'!$C$6:$C$56,A6),0) -> 0
A7: M-2 | B7: Cremado inverso / arenado (mantequilla fría sobre harina) | C7: La mantequilla fría se corta sobre la harina antes de que entre el líquido: recubre el gluten y da una miga corta, apretada y de corte limpio. | D7: =COUNTIF('Recetas y precios'!$C:$C,A7) -> 1 | E7: =IFERROR(AVERAGEIF('Recetas y precios'!$C:$C,A7,'Recetas y precios'!$E:$E),0) -> 278.122 | F7: =IFERROR(minifs('Recetas y precios'!$E$6:$E$56,'Recetas y precios'!$C$6:$C$56,A7),0) -> 0 | G7: =IFERROR(maxifs('Recetas y precios'!$E$6:$E$56,'Recetas y precios'!$C$6:$C$56,A7),0) -> 0
A8: M-3 | B8: Emulsión en caliente / beurre noisette | C8: La mantequilla se funde y se tuesta hasta avellanar; se emulsiona en caliente con azúcares y huevo. Rinde 75 % del peso de la mantequilla cruda. | D8: =COUNTIF('Recetas y precios'!$C:$C,A8) -> 3 | E8: =IFERROR(AVERAGEIF('Recetas y precios'!$C:$C,A8,'Recetas y precios'!$E:$E),0) -> 142.58317 | F8: =IFERROR(minifs('Recetas y precios'!$E$6:$E$56,'Recetas y precios'!$C$6:$C$56,A8),0) -> 0 | G8: =IFERROR(maxifs('Recetas y precios'!$E$6:$E$56,'Recetas y precios'!$C$6:$C$56,A8),0) -> 0
A9: M-4 | B9: Base de aceite y lácteo ácido (tipo chiffon) | C9: El aceite no cristaliza en frío: la miga queda húmeda por más días. El lácteo ácido estabiliza la proteína del huevo frente a los cítricos. | D9: =COUNTIF('Recetas y precios'!$C:$C,A9) -> 3 | E9: =IFERROR(AVERAGEIF('Recetas y precios'!$C:$C,A9,'Recetas y precios'!$E:$E),0) -> 164.80719 | F9: =IFERROR(minifs('Recetas y precios'!$E$6:$E$56,'Recetas y precios'!$C$6:$C$56,A9),0) -> 0 | G9: =IFERROR(maxifs('Recetas y precios'!$E$6:$E$56,'Recetas y precios'!$C$6:$C$56,A9),0) -> 0
A10: M-5 | B10: Base financiera y de pasta de fruto seco | C10: Clara de huevo sin montar, harina de fruto seco y mantequilla avellanada o pasta pura: estructura densa, húmeda y de larga vida útil. | D10: =COUNTIF('Recetas y precios'!$C:$C,A10) -> 6 | E10: =IFERROR(AVERAGEIF('Recetas y precios'!$C:$C,A10,'Recetas y precios'!$E:$E),0) -> 231.82051 | F10: =IFERROR(minifs('Recetas y precios'!$E$6:$E$56,'Recetas y precios'!$C$6:$C$56,A10),0) -> 0 | G10: =IFERROR(maxifs('Recetas y precios'!$E$6:$E$56,'Recetas y precios'!$C$6:$C$56,A10),0) -> 0
A11: M-6 | B11: Masa enriquecida con yemas y aromáticos | C11: Yemas adicionales y pastas aromáticas maceradas: color, aroma y suavidad de masa fermentada sin fermentación. | D11: =COUNTIF('Recetas y precios'!$C:$C,A11) -> 1 | E11: =IFERROR(AVERAGEIF('Recetas y precios'!$C:$C,A11,'Recetas y precios'!$E:$E),0) -> 194.78117 | F11: =IFERROR(minifs('Recetas y precios'!$E$6:$E$56,'Recetas y precios'!$C$6:$C$56,A11),0) -> 0 | G11: =IFERROR(maxifs('Recetas y precios'!$E$6:$E$56,'Recetas y precios'!$C$6:$C$56,A11),0) -> 0
A14: PREPARACIONES TRANSVERSALES
A15: Clave | B15: Preparación | C15: Qué es
A16: P-1 | B16: Jarabe de imbibage (calado) | C16: Agua o jugo + azúcar a partes desiguales, hervido 2 min y aplicado en caliente sobre la pieza tibia. Aporta de 60 a 110 g de humedad viva y es lo que separa un panqué de vitrina de uno seco.
A17: P-2 | B17: Glaseado traslúcido y glaseado opaco | C17: Azúcar glas + líquido ácido o lácteo. Traslúcido con 15-18 % de líquido; opaco con 20-25 % y aplicado sobre la pieza fría. Seca en 20-25 min y forma costra.
A18: P-3 | B18: Ganache y cobertura | C18: Chocolate + crema caliente en emulsión (1:0.7 para cobertura, 1:1.4 para ganache montada). Se usa como baño, veteado o decoración.
A19: P-4 | B19: Streusel y costra superior | C19: Mantequilla fría, azúcar, harina y fruto seco en proporción 1:1:1.5. Se hornea sobre la masa cruda y da contraste de mordida.
A20: P-5 | B20: Núcleo e inserción | C20: Toffee, cremino, cheesecake o gianduja en manga, colocado en el centro de la masa antes del horno o inyectado en frío. Sube el ticket sin subir mucho el costo.
A21: P-6 | B21: Fruta y fruto seco tratado | C21: Salteado, caramelizado, macerado, garapiñado, confitado o reducido a puré. Siempre escurrido y frío antes de entrar a la masa, y rebozado en harina si va en suspensión.

Sheet Ingredientes
A1: INGREDIENTES
A2: Cada línea del recetario normalizada contra el catálogo de insumos. La columna «Texto original del chef» permite auditar la equivalencia.
A3: Endulcora · Estudio Gastronómico · en colaboración con Levent
A5: # | B5: Receta | C5: Componente | D5: Texto original del chef | E5: Clave insumo | F5: Cantidad | G5: Unidad | H5: Costo de la línea | I5: Equivalencia asumida
A6: 1 | B6: Panqué Cuatro Cuartos Perfecto a la Vainilla de Papantla y Mantequilla de Rancho | C6: la Masa | D6: 220 g Mantequilla de rancho sin sal (mínimo 82% materia grasa), a 18°C (pomada) | E6: I-002 | F6: 220 | G6: g | H6: =IFERROR(F6*VLOOKUP(E6,Insumos!$A:$G,7,FALSE()),0) -> 63.8
A7: 1 | B7: Panqué Cuatro Cuartos Perfecto a la Vainilla de Papantla y Mantequilla de Rancho | C7: la Masa | D7: 220 g Azúcar refinada blanca | E7: I-040 | F7: 220 | G7: g | H7: =IFERROR(F7*VLOOKUP(E7,Insumos!$A:$G,7,FALSE()),0) -> 6.16
A8: 1 | B8: Panqué Cuatro Cuartos Perfecto a la Vainilla de Papantla y Mantequilla de Rancho | C8: la Masa | D8: 220 g Huevos enteros pasteurizados (aprox. 4 piezas grandes), a temperatura ambiente | E8: I-004 | F8: 220 | G8: g | H8: =IFERROR(F8*VLOOKUP(E8,Insumos!$A:$G,7,FALSE()),0) -> 13.64
A9: 1 | B9: Panqué Cuatro Cuartos Perfecto a la Vainilla de Papantla y Mantequilla de Rancho | C9: la Masa | D9: 220 g Harina de trigo repostera (baja en proteína, 8-9%) | E9: I-030 | F9: 220 | G9: g | H9: =IFERROR(F9*VLOOKUP(E9,Insumos!$A:$G,7,FALSE()),0) -> 5.72
A10: 1 | B10: Panqué Cuatro Cuartos Perfecto a la Vainilla de Papantla y Mantequilla de Rancho | C10: la Masa | D10: 4 g Polvo para hornear de doble acción | E10: I-033 | F10: 4 | G10: g | H10: =IFERROR(F10*VLOOKUP(E10,Insumos!$A:$G,7,FALSE()),0) -> 0.544
A11: 1 | B11: Panqué Cuatro Cuartos Perfecto a la Vainilla de Papantla y Mantequilla de Rancho | C11: la Masa | D11: 2 g Flor de sal fina | E11: I-037 | F11: 2 | G11: g | H11: =IFERROR(F11*VLOOKUP(E11,Insumos!$A:$G,7,FALSE()),0) -> 1.56
A12: 1 | B12: Panqué Cuatro Cuartos Perfecto a la Vainilla de Papantla y Mantequilla de Rancho | C12: la Masa | D12: 12 g Pasta concentrada de vainilla natural de Papantla (o las semillas de 1 vaina madura) | E12: I-130 | F12: 12 | G12: g | H12: =IFERROR(F12*VLOOKUP(E12,Insumos!$A:$G,7,FALSE()),0) -> 20.16
A13: 1 | B13: Panqué Cuatro Cuartos Perfecto a la Vainilla de Papantla y Mantequilla de Rancho | C13: la Masa | D13: 20 ml Leche entera a temperatura ambiente | E13: I-007 | F13: 20 | G13: ml | H13: =IFERROR(F13*VLOOKUP(E13,Insumos!$A:$G,7,FALSE()),0) -> 0.54
A14: 1 | B14: Panqué Cuatro Cuartos Perfecto a la Vainilla de Papantla y Mantequilla de Rancho | C14: el Jarabe de Imbibage | D14: 50 ml Agua purificada | E14: I-052 | F14: 50 | G14: ml | H14: =IFERROR(F14*VLOOKUP(E14,Insumos!$A:$G,7,FALSE()),0) -> 0.1125
A15: 1 | B15: Panqué Cuatro Cuartos Perfecto a la Vainilla de Papantla y Mantequilla de Rancho | C15: el Jarabe de Imbibage | D15: 40 g Azúcar blanca | E15: I-040 | F15: 40 | G15: g | H15: =IFERROR(F15*VLOOKUP(E15,Insumos!$A:$G,7,FALSE()),0) -> 1.12
A16: 1 | B16: Panqué Cuatro Cuartos Perfecto a la Vainilla de Papantla y Mantequilla de Rancho | C16: el Jarabe de Imbibage | D16: 5 ml Extracto puro de vainilla de Papantla | E16: I-130 | F16: 5 | G16: ml | H16: =IFERROR(F16*VLOOKUP(E16,Insumos!$A:$G,7,FALSE()),0) -> 8.4
A17: 1 | B17: Panqué Cuatro Cuartos Perfecto a la Vainilla de Papantla y Mantequilla de Rancho | C17: el Glaseado Traslúcido | D17: 70 g Azúcar glas micropulverizada | E17: I-042 | F17: 70 | G17: g | H17: =IFERROR(F17*VLOOKUP(E17,Insumos!$A:$G,7,FALSE()),0) -> 2.94
... A20: 2 | B20: Panqué de Mantequilla Avellanada (Beurre Noisette) y Flor de Sal | C20: la Mantequilla Avellanada | D20: 280 g Mantequilla sin sal (al evaporar agua y tostar sólidos lácteos rendirá 210 g netos de beurre noisette) | E20: I-001 | F20: 280 | G20: g | H20: =IFERROR(F20*VLOOKUP(E20,Insumos!$A:$G,7,FALSE()),0) -> 68.6
A21: 2 | B21: Panqué de Mantequilla Avellanada (Beurre Noisette) y Flor de Sal | C21: la Masa | D21: 210 g Mantequilla avellanada (beurre noisette) colada pero con sus posos tostados, templada a 28°C | E21: I-001 | F21: 0 | G21: g | H21: =IFERROR(F21*VLOOKUP(E21,Insumos!$A:$G,7,FALSE()),0) -> 0 | I21: cubierta por «Para la Mantequilla Avellanada» (280 g → 210 g netos)
A22: 2 | B22: Panqué de Mantequilla Avellanada (Beurre Noisette) y Flor de Sal | C22: la Masa | D22: 190 g Azúcar mascabado fino | E22: I-043 | F22: 190 | G22: g | H22: =IFERROR(F22*VLOOKUP(E22,Insumos!$A:$G,7,FALSE()),0) -> 9.88
A23: 2 | B23: Panqué de Mantequilla Avellanada (Beurre Noisette) y Flor de Sal | C23: la Masa | D23: 40 g Miel de abeja de azahar | E23: I-046 | F23: 40 | G23: g | H23: =IFERROR(F23*VLOOKUP(E23,Insumos!$A:$G,7,FALSE()),0) -> 7.8
A24: 2 | B24: Panqué de Mantequilla Avellanada (Beurre Noisette) y Flor de Sal | C24: la Masa | D24: 200 g Huevos enteros (4 piezas) | E24: I-004 | F24: 200 | G24: g | H24: =IFERROR(F24*VLOOKUP(E24,Insumos!$A:$G,7,FALSE()),0) -> 12.4
A25: 2 | B25: Panqué de Mantequilla Avellanada (Beurre Noisette) y Flor de Sal | C25: la Masa | D25: 200 g Harina de trigo repostera | E25: I-030 | F25: 200 | G25: g | H25: =IFERROR(F25*VLOOKUP(E25,Insumos!$A:$G,7,FALSE()),0) -> 5.2
A26: 2 | B26: Panqué de Mantequilla Avellanada (Beurre Noisette) y Flor de Sal | C26: la Masa | D26: 40 g Harina de almendra extrafina | E26: I-070 | F26: 40 | G26: g | H26: =IFERROR(F26*VLOOKUP(E26,Insumos!$A:$G,7,FALSE()),0) -> 17
A27: 2 | B27: Panqué de Mantequilla Avellanada (Beurre Noisette) y Flor de Sal | C27: la Masa | D27: 5 g Polvo para hornear | E27: I-033 | F27: 5 | G27: g | H27: =IFERROR(F27*VLOOKUP(E27,Insumos!$A:$G,7,FALSE()),0) -> 0.68
A28: 2 | B28: Panqué de Mantequilla Avellanada (Beurre Noisette) y Flor de Sal | C28: la Masa | D28: 3 g Flor de sal molida | E28: I-037 | F28: 3 | G28: g | H28: =IFERROR(F28*VLOOKUP(E28,Insumos!$A:$G,7,FALSE()),0) -> 2.34
A29: 2 | B29: Panqué de Mantequilla Avellanada (Beurre Noisette) y Flor de Sal | C29: la Masa | D29: 40 ml Crema para batir (35% materia grasa) a temperatura ambiente | E29: I-008 | F29: 40 | G29: ml | H29: =IFERROR(F29*VLOOKUP(E29,Insumos!$A:$G,7,FALSE()),0) -> 4.72
A30: 2 | B30: Panqué de Mantequilla Avellanada (Beurre Noisette) y Flor de Sal | C30: el Acabado Salino | D30: 40 g Mantequilla avellanada fundida líquida | E30: I-001 | F30: 53 | G30: g | H30: =IFERROR(F30*VLOOKUP(E30,Insumos!$A:$G,7,FALSE()),0) -> 12.985 | I30: beurre noisette: 280 g → 210 g netos (rend. 75 %)
A31: 2 | B31: Panqué de Mantequilla Avellanada (Beurre Noisette) y Flor de Sal | C31: el Acabado Salino | D31: 20 g Jarabe simple (50% agua / 50% azúcar) | E31: I-040 | F31: 20 | G31: g | H31: =IFERROR(F31*VLOOKUP(E31,Insumos!$A:$G,7,FALSE()),0) -> 0.56
A32: 2 | B32: Panqué de Mantequilla Avellanada (Beurre Noisette) y Flor de Sal | C32: el Acabado Salino | D32: 2 g Flor de sal en escamas | E32: I-037 | F32: 2 | G32: g | H32: =IFERROR(F32*VLOOKUP(E32,Insumos!$A:$G,7,FALSE()),0) -> 1.56
A33: 3 | B33: Panqué Marble / Jaspeado Suizo de Chocolate Oscuro y Vainilla Bourbon | C33: la Masa Base | D33: 240 g Mantequilla sin sal a 18°C | E33: I-001 | F33: 240 | G33: g | H33: =IFERROR(F33*VLOOKUP(E33,Insumos!$A:$G,7,FALSE()),0) -> 58.8
A34: 3 | B34: Panqué Marble / Jaspeado Suizo de Chocolate Oscuro y Vainilla Bourbon | C34: la Masa Base | D34: 220 g Azúcar blanca extrafina | E34: I-041 | F34: 220 | G34: g | H34: =IFERROR(F34*VLOOKUP(E34,Insumos!$A:$G,7,FALSE()),0) -> 7.48
A35: 3 | B35: Panqué Marble / Jaspeado Suizo de Chocolate Oscuro y Vainilla Bourbon | C35: la Masa Base | D35: 200 g Huevos enteros | E35: I-004 | F35: 200 | G35: g | H35: =IFERROR(F35*VLOOKUP(E35,Insumos!$A:$G,7,FALSE()),0) -> 12.4
A36: 3 | B36: Panqué Marble / Jaspeado Suizo de Chocolate Oscuro y Vainilla Bourbon | C36: la Masa Base | D36: 240 g Harina de trigo repostera | E36: I-030 | F36: 240 | G36: g | H36: =IFERROR(F36*VLOOKUP(E36,Insumos!$A:$G,7,FALSE()),0) -> 6.24
A37: 3 | B37: Panqué Marble / Jaspeado Suizo de Chocolate Oscuro y Vainilla Bourbon | C37: la Masa Base | D37: 5 g Polvo para hornear | E37: I-033 | F37: 5 | G37: g | H37: =IFERROR(F37*VLOOKUP(E37,Insumos!$A:$G,7,FALSE()),0) -> 0.68
A38: 3 | B38: Panqué Marble / Jaspeado Suizo de Chocolate Oscuro y Vainilla Bourbon | C38: la Masa Base | D38: 3 g Sal fina | E38: I-035 | F38: 3 | G38: g | H38: =IFERROR(F38*VLOOKUP(E38,Insumos!$A:$G,7,FALSE()),0) -> 0.048
A39: 3 | B39: Panqué Marble / Jaspeado Suizo de Chocolate Oscuro y Vainilla Bourbon | C39: la Masa Base | D39: 60 ml Crema ácida espesa (o crème fraîche) | E39: I-009 | F39: 60 | G39: ml | H39: =IFERROR(F39*VLOOKUP(E39,Insumos!$A:$G,7,FALSE()),0) -> 6.1333333
A40: 3 | B40: Panqué Marble / Jaspeado Suizo de Chocolate Oscuro y Vainilla Bourbon | C40: la Fase Vainilla | D40: 10 ml Extracto concentrado de vainilla Bourbon | E40: I-130 | F40: 10 | G40: ml | H40: =IFERROR(F40*VLOOKUP(E40,Insumos!$A:$G,7,FALSE()),0) -> 16.8
A41: 3 | B41: Panqué Marble / Jaspeado Suizo de Chocolate Oscuro y Vainilla Bourbon | C41: la Fase Vainilla | D41: 15 ml Leche entera | E41: I-007 | F41: 15 | G41: ml | H41: =IFERROR(F41*VLOOKUP(E41,Insumos!$A:$G,7,FALSE()),0) -> 0.405
A42: 3 | B42: Panqué Marble / Jaspeado Suizo de Chocolate Oscuro y Vainilla Bourbon | C42: la Fase Chocolate Suizo | D42: 60 g Chocolate amargo 70% cacao, fundido a 45°C | E42: I-060 | F42: 60 | G42: g | H42: =IFERROR(F42*VLOOKUP(E42,Insumos!$A:$G,7,FALSE()),0) -> 23.1
... A51: 4 | B51: Panqué Bretón de Caramelo Salado con Ganache Montada | C51: la Masa Bretón | D51: 130 g Azúcar mascabado claro | E51: I-043 | F51: 130 | G51: g | H51: =IFERROR(F51*VLOOKUP(E51,Insumos!$A:$G,7,FALSE()),0) -> 6.76
A52: 4 | B52: Panqué Bretón de Caramelo Salado con Ganache Montada | C52: la Masa Bretón | D52: 60 g Caramelo salado preparado (frío) | E52: I-051 | F52: 0 | G52: g | H52: =IFERROR(F52*VLOOKUP(E52,Insumos!$A:$G,7,FALSE()),0) -> 0 | I52: cubierto por «Para el Toffee / Caramelo Salado»
A53: 4 | B53: Panqué Bretón de Caramelo Salado con Ganache Montada | C53: la Masa Bretón | D53: 180 g Huevos enteros (3 grandes) | E53: I-004 | F53: 180 | G53: g | H53: =IFERROR(F53*VLOOKUP(E53,Insumos!$A:$G,7,FALSE()),0) -> 11.16
A54: 4 | B54: Panqué Bretón de Caramelo Salado con Ganache Montada | C54: la Masa Bretón | D54: 210 g Harina de trigo | E54: I-030 | F54: 210 | G54: g | H54: =IFERROR(F54*VLOOKUP(E54,Insumos!$A:$G,7,FALSE()),0) -> 5.46
A55: 4 | B55: Panqué Bretón de Caramelo Salado con Ganache Montada | C55: la Masa Bretón | D55: 5 g Polvo de hornear | E55: I-033 | F55: 5 | G55: g | H55: =IFERROR(F55*VLOOKUP(E55,Insumos!$A:$G,7,FALSE()),0) -> 0.68
A56: 4 | B56: Panqué Bretón de Caramelo Salado con Ganache Montada | C56: la Masa Bretón | D56: 2 g Sal fina | E56: I-035 | F56: 2 | G56: g | H56: =IFERROR(F56*VLOOKUP(E56,Insumos!$A:$G,7,FALSE()),0) -> 0.032
A57: 4 | B57: Panqué Bretón de Caramelo Salado con Ganache Montada | C57: la Masa Bretón | D57: 30 ml Leche entera | E57: I-007 | F57: 30 | G57: ml | H57: =IFERROR(F57*VLOOKUP(E57,Insumos!$A:$G,7,FALSE()),0) -> 0.81
A58: 4 | B58: Panqué Bretón de Caramelo Salado con Ganache Montada | C58: la Ganache Montada de Caramelo (decoración) | D58: 100 g Chocolate blanco 32% manteca de cacao | E58: I-063 | F58: 100 | G58: g | H58: =IFERROR(F58*VLOOKUP(E58,Insumos!$A:$G,7,FALSE()),0) -> 36.5
A59: 4 | B59: Panqué Bretón de Caramelo Salado con Ganache Montada | C59: la Ganache Montada de Caramelo (decoración) | D59: 40 g Caramelo salado preparado | E59: I-051 | F59: 0 | G59: g | H59: =IFERROR(F59*VLOOKUP(E59,Insumos!$A:$G,7,FALSE()),0) -> 0 | I59: cubierto por «Para el Toffee / Caramelo Salado»
A60: 4 | B60: Panqué Bretón de Caramelo Salado con Ganache Montada | C60: la Ganache Montada de Caramelo (decoración) | D60: 140 ml Crema para batir (muy fría) | E60: I-008 | F60: 140 | G60: ml | H60: =IFERROR(F60*VLOOKUP(E60,Insumos!$A:$G,7,FALSE()),0) -> 16.52
A61: 5 | B61: Panqué Financiero de Pera Caramelizada y Harina de Almendra | C61: las Peras Caramelizadas | D61: 2 Peras Bosc o Anjou firmes (peladas y descorazonadas) | E61: I-111 | F61: 360 | G61: g | H61: =IFERROR(F61*VLOOKUP(E61,Insumos!$A:$G,7,FALSE()),0) -> 22.32 | I61: 2 peras × 180 g
A62: 5 | B62: Panqué Financiero de Pera Caramelizada y Harina de Almendra | C62: las Peras Caramelizadas | D62: 25 g Mantequilla sin sal | E62: I-001 | F62: 25 | G62: g | H62: =IFERROR(F62*VLOOKUP(E62,Insumos!$A:$G,7,FALSE()),0) -> 6.125
A63: 5 | B63: Panqué Financiero de Pera Caramelizada y Harina de Almendra | C63: las Peras Caramelizadas | D63: 30 g Azúcar mascabado | E63: I-043 | F63: 30 | G63: g | H63: =IFERROR(F63*VLOOKUP(E63,Insumos!$A:$G,7,FALSE()),0) -> 1.56
A64: 5 | B64: Panqué Financiero de Pera Caramelizada y Harina de Almendra | C64: las Peras Caramelizadas | D64: 1 Pizca de canela molida | E64: I-132 | F64: 0.5 | G64: g | H64: =IFERROR(F64*VLOOKUP(E64,Insumos!$A:$G,7,FALSE()),0) -> 0.37 | I64: pizca ≈ 0.5 g
A65: 5 | B65: Panqué Financiero de Pera Caramelizada y Harina de Almendra | C65: la Masa Financiera | D65: 160 g Claras de huevo frescas (aprox. 5 claras), sin batir a punto de nieve | E65: I-006 | F65: 160 | G65: g | H65: =IFERROR(F65*VLOOKUP(E65,Insumos!$A:$G,7,FALSE()),0) -> 7.68
A66: 5 | B66: Panqué Financiero de Pera Caramelizada y Harina de Almendra | C66: la Masa Financiera | D66: 150 g Mantequilla avellanada (beurre noisette caliente filtrado a 50°C) | E66: I-001 | F66: 200 | G66: g | H66: =IFERROR(F66*VLOOKUP(E66,Insumos!$A:$G,7,FALSE()),0) -> 49 | I66: beurre noisette: rendimiento 75 % (declarado en receta 2)
A67: 5 | B67: Panqué Financiero de Pera Caramelizada y Harina de Almendra | C67: la Masa Financiera | D67: 150 g Azúcar glas tamizada | E67: I-042 | F67: 150 | G67: g | H67: =IFERROR(F67*VLOOKUP(E67,Insumos!$A:$G,7,FALSE()),0) -> 6.3
A68: 5 | B68: Panqué Financiero de Pera Caramelizada y Harina de Almendra | C68: la Masa Financiera | D68: 90 g Harina de almendra pelada extrafina | E68: I-070 | F68: 90 | G68: g | H68: =IFERROR(F68*VLOOKUP(E68,Insumos!$A:$G,7,FALSE()),0) -> 38.25
A69: 5 | B69: Panqué Financiero de Pera Caramelizada y Harina de Almendra | C69: la Masa Financiera | D69: 70 g Harina de trigo repostera | E69: I-030 | F69: 70 | G69: g | H69: =IFERROR(F69*VLOOKUP(E69,Insumos!$A:$G,7,FALSE()),0) -> 1.82
A70: 5 | B70: Panqué Financiero de Pera Caramelizada y Harina de Almendra | C70: la Masa Financiera | D70: 4 g Polvo para hornear | E70: I-033 | F70: 4 | G70: g | H70: =IFERROR(F70*VLOOKUP(E70,Insumos!$A:$G,7,FALSE()),0) -> 0.544
A71: 5 | B71: Panqué Financiero de Pera Caramelizada y Harina de Almendra | C71: la Masa Financiera | D71: 2 g Sal marina fina | E71: I-036 | F71: 2 | G71: g | H71: =IFERROR(F71*VLOOKUP(E71,Insumos!$A:$G,7,FALSE()),0) -> 0.168
A72: 5 | B72: Panqué Financiero de Pera Caramelizada y Harina de Almendra | C72: la Masa Financiera | D72: 5 ml Extracto de almendra amarga o licor de pera (opcional) | E72: I-149 | F72: 5 | G72: ml | H72: =IFERROR(F72*VLOOKUP(E72,Insumos!$A:$G,7,FALSE()),0) -> 9.5833333
A73: 6 | B73: Panqué de Queso Crema y Nuez Pecán Tostada al Jarabe de Maple | C73: las Nueces Pecán al Maple | D73: 140 g Nueces pecán en mitades y trozos gruesos | E73: I-075 | F73: 140 | G73: g | H73: =IFERROR(F73*VLOOKUP(E73,Insumos!$A:$G,7,FALSE()),0) -> 67.2
A74: 6 | B74: Panqué de Queso Crema y Nuez Pecán Tostada al Jarabe de Maple | C74: las Nueces Pecán al Maple | D74: 40 ml Jarabe puro de maple (Grado A oscuro) | E74: I-048 | F74: 40 | G74: ml | H74: =IFERROR(F74*VLOOKUP(E74,Insumos!$A:$G,7,FALSE()),0) -> 33.6
A75: 6 | B75: Panqué de Queso Crema y Nuez Pecán Tostada al Jarabe de Maple | C75: las Nueces Pecán al Maple | D75: 10 g Mantequilla sin sal | E75: I-001 | F75: 10 | G75: g | H75: =IFERROR(F75*VLOOKUP(E75,Insumos!$A:$G,7,FALSE()),0) -> 2.45
A76: 6 | B76: Panqué de Queso Crema y Nuez Pecán Tostada al Jarabe de Maple | C76: las Nueces Pecán al Maple | D76: 2 g Flor de sal | E76: I-037 | F76: 2 | G76: g | H76: =IFERROR(F76*VLOOKUP(E76,Insumos!$A:$G,7,FALSE()),0) -> 1.56
A77: 6 | B77: Panqué de Queso Crema y Nuez Pecán Tostada al Jarabe de Maple | C77: la Masa | D77: 180 g Mantequilla sin sal a 18°C | E77: I-001 | F77: 180 | G77: g | H77: =IFERROR(F77*VLOOKUP(E77,Insumos!$A:$G,7,FALSE()),0) -> 44.1
A78: 6 | B78: Panqué de Queso Crema y Nuez Pecán Tostada al Jarabe de Maple | C78: la Masa | D78: 140 g Queso crema entero tipo bloque (25°C, maleable) | E78: I-012 | F78: 140 | G78: g | H78: =IFERROR(F78*VLOOKUP(E78,Insumos!$A:$G,7,FALSE()),0) -> 23.52
... A99: 7 | B99: Panqué de Nata Artesanal de Rancho y Cardamomo Verde Molido | C99: el Jarabe de Cardamomo (Imbibage) | D99: 30 g Azúcar blanca | E99: I-040 | F99: 30 | G99: g | H99: =IFERROR(F99*VLOOKUP(E99,Insumos!$A:$G,7,FALSE()),0) -> 0.84
A100: 7 | B100: Panqué de Nata Artesanal de Rancho y Cardamomo Verde Molido | C100: el Jarabe de Cardamomo (Imbibage) | D100: 2 Cápsulas de cardamomo verde abiertas | E100: I-134 | F100: 1 | G100: g | H100: =IFERROR(F100*VLOOKUP(E100,Insumos!$A:$G,7,FALSE()),0) -> 1.65 | I100: 2 cápsulas ≈ 1 g
A101: 8 | B101: Panqué Red Velvet de Autor con Núcleo Horneado de Cheesecake | C101: el Núcleo de Cheesecake | D101: 200 g Queso crema entero a 20°C | E101: I-012 | F101: 200 | G101: g | H101: =IFERROR(F101*VLOOKUP(E101,Insumos!$A:$G,7,FALSE()),0) -> 33.6
A102: 8 | B102: Panqué Red Velvet de Autor con Núcleo Horneado de Cheesecake | C102: el Núcleo de Cheesecake | D102: 50 g Azúcar refinada | E102: I-040 | F102: 50 | G102: g | H102: =IFERROR(F102*VLOOKUP(E102,Insumos!$A:$G,7,FALSE()),0) -> 1.4
A103: 8 | B103: Panqué Red Velvet de Autor con Núcleo Horneado de Cheesecake | C103: el Núcleo de Cheesecake | D103: 1 Huevo mediano (50 g) | E103: I-004 | F103: 50 | G103: g | H103: =IFERROR(F103*VLOOKUP(E103,Insumos!$A:$G,7,FALSE()),0) -> 3.1 | I103: declarado en la receta
A104: 8 | B104: Panqué Red Velvet de Autor con Núcleo Horneado de Cheesecake | C104: el Núcleo de Cheesecake | D104: 15 g Harina de trigo (para dar soporte estructural en el horneado) | E104: I-030 | F104: 15 | G104: g | H104: =IFERROR(F104*VLOOKUP(E104,Insumos!$A:$G,7,FALSE()),0) -> 0.39
A105: 8 | B105: Panqué Red Velvet de Autor con Núcleo Horneado de Cheesecake | C105: el Núcleo de Cheesecake | D105: 5 ml Extracto de vainilla | E105: I-130 | F105: 5 | G105: ml | H105: =IFERROR(F105*VLOOKUP(E105,Insumos!$A:$G,7,FALSE()),0) -> 8.4
A106: 8 | B106: Panqué Red Velvet de Autor con Núcleo Horneado de Cheesecake | C106: la Masa Red Velvet | D106: 140 g Mantequilla sin sal pomada | E106: I-001 | F106: 140 | G106: g | H106: =IFERROR(F106*VLOOKUP(E106,Insumos!$A:$G,7,FALSE()),0) -> 34.3
A107: 8 | B107: Panqué Red Velvet de Autor con Núcleo Horneado de Cheesecake | C107: la Masa Red Velvet | D107: 180 g Azúcar blanca | E107: I-040 | F107: 180 | G107: g | H107: =IFERROR(F107*VLOOKUP(E107,Insumos!$A:$G,7,FALSE()),0) -> 5.04
A108: 8 | B108: Panqué Red Velvet de Autor con Núcleo Horneado de Cheesecake | C108: la Masa Red Velvet | D108: 150 g Huevos enteros (3 piezas) | E108: I-004 | F108: 150 | G108: g | H108: =IFERROR(F108*VLOOKUP(E108,Insumos!$A:$G,7,FALSE()),0) -> 9.3
A109: 8 | B109: Panqué Red Velvet de Autor con Núcleo Horneado de Cheesecake | C109: la Masa Red Velvet | D109: 200 g Harina de trigo repostera | E109: I-030 | F109: 200 | G109: g | H109: =IFERROR(F109*VLOOKUP(E109,Insumos!$A:$G,7,FALSE()),0) -> 5.2
A110: 8 | B110: Panqué Red Velvet de Autor con Núcleo Horneado de Cheesecake | C110: la Masa Red Velvet | D110: 18 g Cacao puro en polvo alcalinizado (sin azúcar) | E110: I-065 | F110: 18 | G110: g | H110: =IFERROR(F110*VLOOKUP(E110,Insumos!$A:$G,7,FALSE()),0) -> 5.13
A111: 8 | B111: Panqué Red Velvet de Autor con Núcleo Horneado de Cheesecake | C111: la Masa Red Velvet | D111: 4 g Polvo para hornear | E111: I-033 | F111: 4 | G111: g | H111: =IFERROR(F111*VLOOKUP(E111,Insumos!$A:$G,7,FALSE()),0) -> 0.544
A112: 8 | B112: Panqué Red Velvet de Autor con Núcleo Horneado de Cheesecake | C112: la Masa Red Velvet | D112: 3 g Bicarbonato de sodio | E112: I-034 | F112: 3 | G112: g | H112: =IFERROR(F112*VLOOKUP(E112,Insumos!$A:$G,7,FALSE()),0) -> 0.228
A113: 8 | B113: Panqué Red Velvet de Autor con Núcleo Horneado de Cheesecake | C113: la Masa Red Velvet | D113: 6 ml Vinagre de manzana o blanco | E113: I-152 | F113: 6 | G113: ml | H113: =IFERROR(F113*VLOOKUP(E113,Insumos!$A:$G,7,FALSE()),0) -> 0.456
A114: 8 | B114: Panqué Red Velvet de Autor con Núcleo Horneado de Cheesecake | C114: la Masa Red Velvet | D114: 120 ml Suero de leche casero (buttermilk: 115 ml leche entera + 5 ml jugo de limón reposado 10 min) | E114: I-019 | F114: 120 | G114: ml | H114: =IFERROR(F114*VLOOKUP(E114,Insumos!$A:$G,7,FALSE()),0) -> 5.4
A115: 8 | B115: Panqué Red Velvet de Autor con Núcleo Horneado de Cheesecake | C115: la Masa Red Velvet | D115: 5 ml Colorante hidrosoluble rojo intenso en gel | E115: I-151 | F115: 5 | G115: ml | H115: =IFERROR(F115*VLOOKUP(E115,Insumos!$A:$G,7,FALSE()),0) -> 6.25
... A118: 9 | B118: Panqué Imperial de Vainilla Tahití con Glaseado Traslúcido de Mantequilla | C118: la Masa | D118: 200 g Azúcar blanca extrafina | E118: I-041 | F118: 200 | G118: g | H118: =IFERROR(F118*VLOOKUP(E118,Insumos!$A:$G,7,FALSE()),0) -> 6.8
A119: 9 | B119: Panqué Imperial de Vainilla Tahití con Glaseado Traslúcido de Mantequilla | C119: la Masa | D119: 2 Vainas de vainilla de Tahití (abiertas y raspadas) | E119: I-131 | F119: 6 | G119: g | H119: =IFERROR(F119*VLOOKUP(E119,Insumos!$A:$G,7,FALSE()),0) -> 57 | I119: 2 vainas × 3 g
A120: 9 | B120: Panqué Imperial de Vainilla Tahití con Glaseado Traslúcido de Mantequilla | C120: la Masa | D120: 220 g Huevos enteros | E120: I-004 | F120: 220 | G120: g | H120: =IFERROR(F120*VLOOKUP(E120,Insumos!$A:$G,7,FALSE()),0) -> 13.64
A121: 9 | B121: Panqué Imperial de Vainilla Tahití con Glaseado Traslúcido de Mantequilla | C121: la Masa | D121: 220 g Harina de trigo repostera | E121: I-030 | F121: 220 | G121: g | H121: =IFERROR(F121*VLOOKUP(E121,Insumos!$A:$G,7,FALSE()),0) -> 5.72
A122: 9 | B122: Panqué Imperial de Vainilla Tahití con Glaseado Traslúcido de Mantequilla | C122: la Masa | D122: 40 ml Crema para batir (35% M.G.) a temperatura ambiente | E122: I-008 | F122: 40 | G122: ml | H122: =IFERROR(F122*VLOOKUP(E122,Insumos!$A:$G,7,FALSE()),0) -> 4.72
A123: 9 | B123: Panqué Imperial de Vainilla Tahití con Glaseado Traslúcido de Mantequilla | C123: la Masa | D123: 5 g Polvo para hornear | E123: I-033 | F123: 5 | G123: g | H123: =IFERROR(F123*VLOOKUP(E123,Insumos!$A:$G,7,FALSE()),0) -> 0.68
A124: 9 | B124: Panqué Imperial de Vainilla Tahití con Glaseado Traslúcido de Mantequilla | C124: la Masa | D124: 2 g Flor de sal | E124: I-037 | F124: 2 | G124: g | H124: =IFERROR(F124*VLOOKUP(E124,Insumos!$A:$G,7,FALSE()),0) -> 1.56
A125: 9 | B125: Panqué Imperial de Vainilla Tahití con Glaseado Traslúcido de Mantequilla | C125: el Jarabe de Vainilla | D125: 50 ml Agua | E125: I-052 | F125: 50 | G125: ml | H125: =IFERROR(F125*VLOOKUP(E125,Insumos!$A:$G,7,FALSE()),0) -> 0.1125
A126: 9 | B126: Panqué Imperial de Vainilla Tahití con Glaseado Traslúcido de Mantequilla | C126: el Jarabe de Vainilla | D126: 40 g Azúcar | E126: I-040 | F126: 40 | G126: g | H126: =IFERROR(F126*VLOOKUP(E126,Insumos!$A:$G,7,FALSE()),0) -> 1.12
A127: 9 | B127: Panqué Imperial de Vainilla Tahití con Glaseado Traslúcido de Mantequilla | C127: el Jarabe de Vainilla | D127: Vainas vacías de vainilla de Tahití (para infusionar) | E127: — | F127: 0 | G127: g | H127: =IFERROR(F127*VLOOKUP(E127,Insumos!$A:$G,7,FALSE()),0) -> 0 | I127: reutiliza las vainas ya costeadas
A128: 9 | B128: Panqué Imperial de Vainilla Tahití con Glaseado Traslúcido de Mantequilla | C128: el Glaseado Traslúcido | D128: 80 g Azúcar glas | E128: I-042 | F128: 80 | G128: g | H128: =IFERROR(F128*VLOOKUP(E128,Insumos!$A:$G,7,FALSE()),0) -> 3.36
A129: 9 | B129: Panqué Imperial de Vainilla Tahití con Glaseado Traslúcido de Mantequilla | C129: el Glaseado Traslúcido | D129: 15 g Mantequilla fundida avellanada muy clara | E129: I-001 | F129: 15 | G129: g | H129: =IFERROR(F129*VLOOKUP(E129,Insumos!$A:$G,7,FALSE()),0) -> 3.675
A130: 9 | B130: Panqué Imperial de Vainilla Tahití con Glaseado Traslúcido de Mantequilla | C130: el Glaseado Traslúcido | D130: 15 ml Leche entera tibia | E130: I-007 | F130: 15 | G130: ml | H130: =IFERROR(F130*VLOOKUP(E130,Insumos!$A:$G,7,FALSE()),0) -> 0.405
A131: 10 | B131: Panqué Glaseado de Limón Amarillo Eureka y Semillas de Amapola | C131: la Masa | D131: 180 g Mantequilla sin sal pomada | E131: I-001 | F131: 180 | G131: g | H131: =IFERROR(F131*VLOOKUP(E131,Insumos!$A:$G,7,FALSE()),0) -> 44.1
A132: 10 | B132: Panqué Glaseado de Limón Amarillo Eureka y Semillas de Amapola | C132: la Masa | D132: 200 g Azúcar refinada | E132: I-040 | F132: 200 | G132: g | H132: =IFERROR(F132*VLOOKUP(E132,Insumos!$A:$G,7,FALSE()),0) -> 5.6
A133: 10 | B133: Panqué Glaseado de Limón Amarillo Eureka y Semillas de Amapola | C133: la Masa | D133: Ralladura fina de 3 limones amarillos Eureka (solo corteza amarilla) | E133: I-101 | F133: 82.5 | G133: g | H133: =IFERROR(F133*VLOOKUP(E133,Insumos!$A:$G,7,FALSE()),0) -> 4.785 | I133: 3 × 110 g × 25 % cáscara
...

Sheet Mi negocio
A1: MI NEGOCIO
A2: Empieza aquí. Solo las celdas amarillas. Todo el archivo depende de estas.
A3: Endulcora · Estudio Gastronómico · en colaboración con Levent
A5: Parámetro | B5: Valor | D5: Qué es
A6: Gastos fijos mensuales | B6: 18000 | D6: Renta, luz, agua, internet, suscripciones, contador
A7: Producción mensual estimada (moldes) | B7: 500 | D7: Cuántas piezas planeas producir al mes
A8: Sueldo mensual del pastelero | B8: 18000 | D8: Tu sueldo o el de quien produce
A9: Horas trabajadas al mes | B9: 200 | D9: 200 h ≈ jornada completa
A10: Minutos extra de acabado por molde | B10: 15 | D10: Calado, glaseado, limpieza y empaque
A11: Empaque · panqué entero | B11: 18 | D11: Caja rígida y etiqueta
A12: Empaque · rebanada | B12: 2.5 | D12: Bolsa de celofán y etiqueta
A13: Energía por hornada | B13: 48 | D13: Gas y electricidad de una hornada
A14: Moldes por hornada | B14: 4 | D14: Cuántos moldes caben en tu horno a la vez
A15: Merma comercial | B15: 0.06 | D15: Producto no vendido, caído o devuelto. 10 % si empiezas, 4 % con demanda medida
A17: CALCULADO AUTOMÁTICAMENTE
A18: Overhead por molde | B18: =IFERROR(B6/B7,0) -> 36 | D18: Gastos fijos ÷ producción mensual
A19: Costo de mano de obra por hora | B19: =IFERROR(B8/B9,0) -> 90 | D19: Sueldo ÷ horas
A20: Energía por molde | B20: =IFERROR(B13/B14,0) -> 12 | D20: Energía por hornada ÷ moldes por hornada
A23: MÁRGENES POR CANAL
A24: Canal | B24: Margen | D24: Unidad de venta
A25: Rebanada en mostrador | B25: 0.6 | D25: Rebanada individual
A26: Panqué entero | B26: 0.55 | D26: Molde completo
A27: Caja de regalo / temporada | B27: 0.72 | D27: Molde completo
A28: Cafetería y mayoreo | B28: 0.32 | D28: Molde completo
A30: Un ejemplo: si pagas $290 por el kilo de mantequilla en vez de $245, cámbialo en «Insumos» y las 51 recetas se recalculan al instante.

Sheet Recetas y precios
A1: RECETAS Y PRECIOS
A2: La hoja principal. Todo se recalcula desde «Insumos» y «Mi negocio». Aquí no se edita nada.
A3: Endulcora · Estudio Gastronómico · en colaboración con Levent
A5: # | B5: Receta | C5: Método | D5: Cap. | E5: Costo insumos | F5: Empaque | G5: Energía | H5: Min. prep | I5: Mano de obra | J5: Overhead | K5: Costo base | L5: Merma | M5: COSTO TOTAL | N5: Rebanadas | O5: Costo/rebanada | P5: Rebanada mostrador | Q5: Panqué entero | R5: Caja de regalo | S5: Cafetería/mayoreo | T5: Utilidad entero | U5: Margen real
A6: 1 | B6: Panqué Cuatro Cuartos Perfecto a la Vainilla de Papantla y Mantequilla de Rancho | C6: M-1 | D6: 6 | E6: =SUMIF(Ingredientes!$A:$A,$A6,Ingredientes!$H:$H) -> 125.7555 | F6: ='Mi negocio'!$B$11 -> 18 | G6: ='Mi negocio'!$B$20 -> 12 | H6: 25 | I6: =(H6+'Mi negocio'!$B$10)/60*'Mi negocio'!$B$19 -> 60 | J6: ='Mi negocio'!$B$18 -> 36 | K6: =E6+F6+G6+I6+J6 -> 251.7555 | L6: ='Mi negocio'!$B$15 -> 0.06 | M6: =IFERROR(K6/(1-L6),0) -> 267.825 | N6: 10 | O6: =IFERROR(M6/N6,0) -> 26.7825 | P6: =IFERROR(CEILING((M6/N6+'Mi negocio'!$B$12)/(1-'Mi negocio'!$B$25),1),0) -> 74 | Q6: =IFERROR(CEILING(M6/(1-'Mi negocio'!$B$26),5),0) -> 600 | R6: =IFERROR(CEILING(M6/(1-'Mi negocio'!$B$27),5),0) -> 960 | S6: =IFERROR(CEILING(M6/(1-'Mi negocio'!$B$28),5),0) -> 395 | T6: =Q6-M6 -> 332.175 | U6: =IFERROR(T6/Q6,0) -> 0.553625
A7: 2 | B7: Panqué de Mantequilla Avellanada (Beurre Noisette) y Flor de Sal | C7: M-3 | D7: 6 | E7: =SUMIF(Ingredientes!$A:$A,$A7,Ingredientes!$H:$H) -> 143.725 | F7: ='Mi negocio'!$B$11 -> 18 | G7: ='Mi negocio'!$B$20 -> 12 | H7: 35 | I7: =(H7+'Mi negocio'!$B$10)/60*'Mi negocio'!$B$19 -> 75 | J7: ='Mi negocio'!$B$18 -> 36 | K7: =E7+F7+G7+I7+J7 -> 284.725 | L7: ='Mi negocio'!$B$15 -> 0.06 | M7: =IFERROR(K7/(1-L7),0) -> 302.89894 | N7: 10 | O7: =IFERROR(M7/N7,0) -> 30.289894 | P7: =IFERROR(CEILING((M7/N7+'Mi negocio'!$B$12)/(1-'Mi negocio'!$B$25),1),0) -> 82 | Q7: =IFERROR(CEILING(M7/(1-'Mi negocio'!$B$26),5),0) -> 675 | R7: =IFERROR(CEILING(M7/(1-'Mi negocio'!$B$27),5),0) -> 1085 | S7: =IFERROR(CEILING(M7/(1-'Mi negocio'!$B$28),5),0) -> 450 | T7: =Q7-M7 -> 372.10106 | U7: =IFERROR(T7/Q7,0) -> 0.55126084
A8: 3 | B8: Panqué Marble / Jaspeado Suizo de Chocolate Oscuro y Vainilla Bourbon | C8: M-1 | D8: 6 | E8: =SUMIF(Ingredientes!$A:$A,$A8,Ingredientes!$H:$H) -> 140.71133 | F8: ='Mi negocio'!$B$11 -> 18 | G8: ='Mi negocio'!$B$20 -> 12 | H8: 30 | I8: =(H8+'Mi negocio'!$B$10)/60*'Mi negocio'!$B$19 -> 67.5 | J8: ='Mi negocio'!$B$18 -> 36 | K8: =E8+F8+G8+I8+J8 -> 274.21133 | L8: ='Mi negocio'!$B$15 -> 0.06 | M8: =IFERROR(K8/(1-L8),0) -> 291.71418 | N8: 12 | O8: =IFERROR(M8/N8,0) -> 24.309515 | P8: =IFERROR(CEILING((M8/N8+'Mi negocio'!$B$12)/(1-'Mi negocio'!$B$25),1),0) -> 68 | Q8: =IFERROR(CEILING(M8/(1-'Mi negocio'!$B$26),5),0) -> 650 | R8: =IFERROR(CEILING(M8/(1-'Mi negocio'!$B$27),5),0) -> 1045 | S8: =IFERROR(CEILING(M8/(1-'Mi negocio'!$B$28),5),0) -> 430 | T8: =Q8-M8 -> 358.28582 | U8: =IFERROR(T8/Q8,0) -> 0.55120895
A9: 4 | B9: Panqué Bretón de Caramelo Salado con Ganache Montada | C9: M-1 | D9: 6 | E9: =SUMIF(Ingredientes!$A:$A,$A9,Ingredientes!$H:$H) -> 143.91 | F9: ='Mi negocio'!$B$11 -> 18 | G9: ='Mi negocio'!$B$20 -> 12 | H9: 40 | I9: =(H9+'Mi negocio'!$B$10)/60*'Mi negocio'!$B$19 -> 82.5 | J9: ='Mi negocio'!$B$18 -> 36 | K9: =E9+F9+G9+I9+J9 -> 292.41 | L9: ='Mi negocio'!$B$15 -> 0.06 | M9: =IFERROR(K9/(1-L9),0) -> 311.07447 | N9: 10 | O9: =IFERROR(M9/N9,0) -> 31.107447 | P9: =IFERROR(CEILING((M9/N9+'Mi negocio'!$B$12)/(1-'Mi negocio'!$B$25),1),0) -> 85 | Q9: =IFERROR(CEILING(M9/(1-'Mi negocio'!$B$26),5),0) -> 695 | R9: =IFERROR(CEILING(M9/(1-'Mi negocio'!$B$27),5),0) -> 1115 | S9: =IFERROR(CEILING(M9/(1-'Mi negocio'!$B$28),5),0) -> 460 | T9: =Q9-M9 -> 383.92553 | U9: =IFERROR(T9/Q9,0) -> 0.55241084
A10: 5 | B10: Panqué Financiero de Pera Caramelizada y Harina de Almendra | C10: M-5 | D10: 6 | E10: =SUMIF(Ingredientes!$A:$A,$A10,Ingredientes!$H:$H) -> 143.72033 | F10: ='Mi negocio'!$B$11 -> 18 | G10: ='Mi negocio'!$B$20 -> 12 | H10: 35 | I10: =(H10+'Mi negocio'!$B$10)/60*'Mi negocio'!$B$19 -> 75 | J10: ='Mi negocio'!$B$18 -> 36 | K10: =E10+F10+G10+I10+J10 -> 284.72033 | L10: ='Mi negocio'!$B$15 -> 0.06 | M10: =IFERROR(K10/(1-L10),0) -> 302.89397 | N10: 10 | O10: =IFERROR(M10/N10,0) -> 30.289397 | P10: =IFERROR(CEILING((M10/N10+'Mi negocio'!$B$12)/(1-'Mi negocio'!$B$25),1),0) -> 82 | Q10: =IFERROR(CEILING(M10/(1-'Mi negocio'!$B$26),5),0) -> 675 | R10: =IFERROR(CEILING(M10/(1-'Mi negocio'!$B$27),5),0) -> 1085 | S10: =IFERROR(CEILING(M10/(1-'Mi negocio'!$B$28),5),0) -> 450 | T10: =Q10-M10 -> 372.10603 | U10: =IFERROR(T10/Q10,0) -> 0.55126819
A11: 6 | B11: Panqué de Queso Crema y Nuez Pecán Tostada al Jarabe de Maple | C11: M-1 | D11: 6 | E11: =SUMIF(Ingredientes!$A:$A,$A11,Ingredientes!$H:$H) -> 261.452 | F11: ='Mi negocio'!$B$11 -> 18 | G11: ='Mi negocio'!$B$20 -> 12 | H11: 30 | I11: =(H11+'Mi negocio'!$B$10)/60*'Mi negocio'!$B$19 -> 67.5 | J11: ='Mi negocio'!$B$18 -> 36 | K11: =E11+F11+G11+I11+J11 -> 394.952 | L11: ='Mi negocio'!$B$15 -> 0.06 | M11: =IFERROR(K11/(1-L11),0) -> 420.1617 | N11: 10 | O11: =IFERROR(M11/N11,0) -> 42.01617 | P11: =IFERROR(CEILING((M11/N11+'Mi negocio'!$B$12)/(1-'Mi negocio'!$B$25),1),0) -> 112 | Q11: =IFERROR(CEILING(M11/(1-'Mi negocio'!$B$26),5),0) -> 935 | R11: =IFERROR(CEILING(M11/(1-'Mi negocio'!$B$27),5),0) -> 1505 | S11: =IFERROR(CEILING(M11/(1-'Mi negocio'!$B$28),5),0) -> 620 | T11: =Q11-M11 -> 514.8383 | U11: =IFERROR(T11/Q11,0) -> 0.5506292
A12: 7 | B12: Panqué de Nata Artesanal de Rancho y Cardamomo Verde Molido | C12: M-1 | D12: 6 | E12: =SUMIF(Ingredientes!$A:$A,$A12,Ingredientes!$H:$H) -> 92.678 | F12: ='Mi negocio'!$B$11 -> 18 | G12: ='Mi negocio'!$B$20 -> 12 | H12: 25 | I12: =(H12+'Mi negocio'!$B$10)/60*'Mi negocio'!$B$19 -> 60 | J12: ='Mi negocio'!$B$18 -> 36 | K12: =E12+F12+G12+I12+J12 -> 218.678 | L12: ='Mi negocio'!$B$15 -> 0.06 | M12: =IFERROR(K12/(1-L12),0) -> 232.63617 | N12: 10 | O12: =IFERROR(M12/N12,0) -> 23.263617 | P12: =IFERROR(CEILING((M12/N12+'Mi negocio'!$B$12)/(1-'Mi negocio'!$B$25),1),0) -> 65 | Q12: =IFERROR(CEILING(M12/(1-'Mi negocio'!$B$26),5),0) -> 520 | R12: =IFERROR(CEILING(M12/(1-'Mi negocio'!$B$27),5),0) -> 835 | S12: =IFERROR(CEILING(M12/(1-'Mi negocio'!$B$28),5),0) -> 345 | T12: =Q12-M12 -> 287.36383 | U12: =IFERROR(T12/Q12,0) -> 0.55262275
A13: 8 | B13: Panqué Red Velvet de Autor con Núcleo Horneado de Cheesecake | C13: M-1 | D13: 6 | E13: =SUMIF(Ingredientes!$A:$A,$A13,Ingredientes!$H:$H) -> 118.77 | F13: ='Mi negocio'!$B$11 -> 18 | G13: ='Mi negocio'!$B$20 -> 12 | H13: 40 | I13: =(H13+'Mi negocio'!$B$10)/60*'Mi negocio'!$B$19 -> 82.5 | J13: ='Mi negocio'!$B$18 -> 36 | K13: =E13+F13+G13+I13+J13 -> 267.27 | L13: ='Mi negocio'!$B$15 -> 0.06 | M13: =IFERROR(K13/(1-L13),0) -> 284.32979 | N13: 12 | O13: =IFERROR(M13/N13,0) -> 23.694149 | P13: =IFERROR(CEILING((M13/N13+'Mi negocio'!$B$12)/(1-'Mi negocio'!$B$25),1),0) -> 66 | Q13: =IFERROR(CEILING(M13/(1-'Mi negocio'!$B$26),5),0) -> 635 | R13: =IFERROR(CEILING(M13/(1-'Mi negocio'!$B$27),5),0) -> 1020 | S13: =IFERROR(CEILING(M13/(1-'Mi negocio'!$B$28),5),0) -> 420 | T13: =Q13-M13 -> 350.67021 | U13: =IFERROR(T13/Q13,0) -> 0.55223656
A14: 9 | B14: Panqué Imperial de Vainilla Tahití con Glaseado Traslúcido de Mantequilla | C14: M-3 | D14: 6 | E14: =SUMIF(Ingredientes!$A:$A,$A14,Ingredientes!$H:$H) -> 152.6925 | F14: ='Mi negocio'!$B$11 -> 18 | G14: ='Mi negocio'!$B$20 -> 12 | H14: 30 | I14: =(H14+'Mi negocio'!$B$10)/60*'Mi negocio'!$B$19 -> 67.5 | J14: ='Mi negocio'!$B$18 -> 36 | K14: =E14+F14+G14+I14+J14 -> 286.1925 | L14: ='Mi negocio'!$B$15 -> 0.06 | M14: =IFERROR(K14/(1-L14),0) -> 304.46011 | N14: 10 | O14: =IFERROR(M14/N14,0) -> 30.446011 | P14: =IFERROR(CEILING((M14/N14+'Mi negocio'!$B$12)/(1-'Mi negocio'!$B$25),1),0) -> 83 | Q14: =IFERROR(CEILING(M14/(1-'Mi negocio'!$B$26),5),0) -> 680 | R14: =IFERROR(CEILING(M14/(1-'Mi negocio'!$B$27),5),0) -> 1090 | S14: =IFERROR(CEILING(M14/(1-'Mi negocio'!$B$28),5),0) -> 450 | T14: =Q14-M14 -> 375.53989 | U14: =IFERROR(T14/Q14,0) -> 0.55226455
A15: 10 | B15: Panqué Glaseado de Limón Amarillo Eureka y Semillas de Amapola | C15: M-1 | D15: 7 | E15: =SUMIF(Ingredientes!$A:$A,$A15,Ingredientes!$H:$H) -> 108.17711 | F15: ='Mi negocio'!$B$11 -> 18 | G15: ='Mi negocio'!$B$20 -> 12 | H15: 25 | I15: =(H15+'Mi negocio'!$B$10)/60*'Mi negocio'!$B$19 -> 60 | J15: ='Mi negocio'!$B$18 -> 36 | K15: =E15+F15+G15+I15+J15 -> 234.17711 | L15: ='Mi negocio'!$B$15 -> 0.06 | M15: =IFERROR(K15/(1-L15),0) -> 249.12459 | N15: 10 | O15: =IFERROR(M15/N15,0) -> 24.912459 | P15: =IFERROR(CEILING((M15/N15+'Mi negocio'!$B$12)/(1-'Mi negocio'!$B$25),1),0) -> 69 | Q15: =IFERROR(CEILING(M15/(1-'Mi negocio'!$B$26),5),0) -> 555 | R15: =IFERROR(CEILING(M15/(1-'Mi negocio'!$B$27),5),0) -> 890 | S15: =IFERROR(CEILING(M15/(1-'Mi negocio'!$B$28),5),0) -> 370 | T15: =Q15-M15 -> 305.87541 | U15: =IFERROR(T15/Q15,0) -> 0.55112687
A16: 11 | B16: Panqué de Naranja Valencia, Romero Fresco y Aceite de Oliva Extra Virgen | C16: M-4 | D16: 7 | E16: =SUMIF(Ingredientes!$A:$A,$A16,Ingredientes!$H:$H) -> 111.03156 | F16: ='Mi negocio'!$B$11 -> 18 | G16: ='Mi negocio'!$B$20 -> 12 | H16: 30 | I16: =(H16+'Mi negocio'!$B$10)/60*'Mi negocio'!$B$19 -> 67.5 | J16: ='Mi negocio'!$B$18 -> 36 | K16: =E16+F16+G16+I16+J16 -> 244.53156 | L16: ='Mi negocio'!$B$15 -> 0.06 | M16: =IFERROR(K16/(1-L16),0) -> 260.13995 | N16: 10 | O16: =IFERROR(M16/N16,0) -> 26.013995 | P16: =IFERROR(CEILING((M16/N16+'Mi negocio'!$B$12)/(1-'Mi negocio'!$B$25),1),0) -> 72 | Q16: =IFERROR(CEILING(M16/(1-'Mi negocio'!$B$26),5),0) -> 580 | R16: =IFERROR(CEILING(M16/(1-'Mi negocio'!$B$27),5),0) -> 930 | S16: =IFERROR(CEILING(M16/(1-'Mi negocio'!$B$28),5),0) -> 385 | T16: =Q16-M16 -> 319.86005 | U16: =IFERROR(T16/Q16,0) -> 0.55148284
A17: 12 | B17: Panqué de Toronja Rosa y Campari con Embebiendo Cítrico Amargo | C17: M-1 | D17: 7 | E17: =SUMIF(Ingredientes!$A:$A,$A17,Ingredientes!$H:$H) -> 105.59533 | F17: ='Mi negocio'!$B$11 -> 18 | G17: ='Mi negocio'!$B$20 -> 12 | H17: 30 | I17: =(H17+'Mi negocio'!$B$10)/60*'Mi negocio'!$B$19 -> 67.5 | J17: ='Mi negocio'!$B$18 -> 36 | K17: =E17+F17+G17+I17+J17 -> 239.09533 | L17: ='Mi negocio'!$B$15 -> 0.06 | M17: =IFERROR(K17/(1-L17),0) -> 254.35674 | N17: 10 | O17: =IFERROR(M17/N17,0) -> 25.435674 | P17: =IFERROR(CEILING((M17/N17+'Mi negocio'!$B$12)/(1-'Mi negocio'!$B$25),1),0) -> 70 | Q17: =IFERROR(CEILING(M17/(1-'Mi negocio'!$B$26),5),0) -> 570 | R17: =IFERROR(CEILING(M17/(1-'Mi negocio'!$B$27),5),0) -> 910 | S17: =IFERROR(CEILING(M17/(1-'Mi negocio'!$B$28),5),0) -> 375 | T17: =Q17-M17 -> 315.64326 | U17: =IFERROR(T17/Q17,0) -> 0.55376011
... A56: 51 | B56: Panqué Panettone de Masa Enriquecida con Naranja Confitada y Chocolate | C56: M-6 | D56: 11 | E56: =SUMIF(Ingredientes!$A:$A,$A56,Ingredientes!$H:$H) -> 194.78117 | F56: ='Mi negocio'!$B$11 -> 18 | G56: ='Mi negocio'!$B$20 -> 12 | H56: 45 | I56: =(H56+'Mi negocio'!$B$10)/60*'Mi negocio'!$B$19 -> 90 | J56: ='Mi negocio'!$B$18 -> 36 | K56: =E56+F56+G56+I56+J56 -> 350.78117 | L56: ='Mi negocio'!$B$15 -> 0.06 | M56: =IFERROR(K56/(1-L56),0) -> 373.17146 | N56: 12 | O56: =IFERROR(M56/N56,0) -> 31.097622 | P56: =IFERROR(CEILING((M56/N56+'Mi negocio'!$B$12)/(1-'Mi negocio'!$B$25),1),0) -> 84 | Q56: =IFERROR(CEILING(M56/(1-'Mi negocio'!$B$26),5),0) -> 830 | R56: =IFERROR(CEILING(M56/(1-'Mi negocio'!$B$27),5),0) -> 1335 | S56: =IFERROR(CEILING(M56/(1-'Mi negocio'!$B$28),5),0) -> 550 | T56: =Q56-M56 -> 456.82854 | U56: =IFERROR(T56/Q56,0) -> 0.55039583
B58: PROMEDIO | E58: =AVERAGE(E6:E56) -> 163.32118 | M58: =AVERAGE(M6:M56) -> 321.24281 | O58: =AVERAGE(O6:O56) -> 31.685583 | P58: =AVERAGE(P6:P56) -> 85.960784 | Q58: =AVERAGE(Q6:Q56) -> 716.27451 | R58: =AVERAGE(R6:R56) -> 1149.6078 | S58: =AVERAGE(S6:S56) -> 474.90196 | T58: =AVERAGE(T6:T56) -> 395.0317
B60: Precios redondeados: al peso en rebanada, a $5 en pieza entera. Cifras ilustrativas, no cotizaciones.

Sheet Producción
A1: PRODUCCIÓN
A2: Plan del mes. Escribe cuántos moldes de cada receta vas a hacer (columna amarilla) y el resto se calcula.
A3: Endulcora · Estudio Gastronómico · en colaboración con Levent
A5: # | B5: Receta | C5: Moldes a producir | D5: Hornadas necesarias | E5: Costo insumos | F5: Costo total | G5: Minutos de trabajo | H5: Horas | I5: Ingreso si se vende entero | J5: Ingreso si se vende en rebanada | K5: Utilidad estimada
A6: 1 | B6: Panqué Cuatro Cuartos Perfecto a la Vainilla de Papantla y Mantequilla de Rancho | C6: 0 | D6: =IFERROR(CEILING(C6/'Mi negocio'!$B$14,1),0) -> 0 | E6: =C6*'Recetas y precios'!E6 -> 0 | F6: =C6*'Recetas y precios'!M6 -> 0 | G6: =C6*('Recetas y precios'!H6+'Mi negocio'!$B$10) -> 0 | H6: =G6/60 -> 0 | I6: =C6*'Recetas y precios'!Q6 -> 0 | J6: =C6*'Recetas y precios'!N6*'Recetas y precios'!P6 -> 0 | K6: =I6-F6 -> 0
A7: 2 | B7: Panqué de Mantequilla Avellanada (Beurre Noisette) y Flor de Sal | C7: 0 | D7: =IFERROR(CEILING(C7/'Mi negocio'!$B$14,1),0) -> 0 | E7: =C7*'Recetas y precios'!E7 -> 0 | F7: =C7*'Recetas y precios'!M7 -> 0 | G7: =C7*('Recetas y precios'!H7+'Mi negocio'!$B$10) -> 0 | H7: =G7/60 -> 0 | I7: =C7*'Recetas y precios'!Q7 -> 0 | J7: =C7*'Recetas y precios'!N7*'Recetas y precios'!P7 -> 0 | K7: =I7-F7 -> 0
A8: 3 | B8: Panqué Marble / Jaspeado Suizo de Chocolate Oscuro y Vainilla Bourbon | C8: 0 | D8: =IFERROR(CEILING(C8/'Mi negocio'!$B$14,1),0) -> 0 | E8: =C8*'Recetas y precios'!E8 -> 0 | F8: =C8*'Recetas y precios'!M8 -> 0 | G8: =C8*('Recetas y precios'!H8+'Mi negocio'!$B$10) -> 0 | H8: =G8/60 -> 0 | I8: =C8*'Recetas y precios'!Q8 -> 0 | J8: =C8*'Recetas y precios'!N8*'Recetas y precios'!P8 -> 0 | K8: =I8-F8 -> 0
A9: 4 | B9: Panqué Bretón de Caramelo Salado con Ganache Montada | C9: 0 | D9: =IFERROR(CEILING(C9/'Mi negocio'!$B$14,1),0) -> 0 | E9: =C9*'Recetas y precios'!E9 -> 0 | F9: =C9*'Recetas y precios'!M9 -> 0 | G9: =C9*('Recetas y precios'!H9+'Mi negocio'!$B$10) -> 0 | H9: =G9/60 -> 0 | I9: =C9*'Recetas y precios'!Q9 -> 0 | J9: =C9*'Recetas y precios'!N9*'Recetas y precios'!P9 -> 0 | K9: =I9-F9 -> 0
A10: 5 | B10: Panqué Financiero de Pera Caramelizada y Harina de Almendra | C10: 0 | D10: =IFERROR(CEILING(C10/'Mi negocio'!$B$14,1),0) -> 0 | E10: =C10*'Recetas y precios'!E10 -> 0 | F10: =C10*'Recetas y precios'!M10 -> 0 | G10: =C10*('Recetas y precios'!H10+'Mi negocio'!$B$10) -> 0 | H10: =G10/60 -> 0 | I10: =C10*'Recetas y precios'!Q10 -> 0 | J10: =C10*'Recetas y precios'!N10*'Recetas y precios'!P10 -> 0 | K10: =I10-F10 -> 0
A11: 6 | B11: Panqué de Queso Crema y Nuez Pecán Tostada al Jarabe de Maple | C11: 0 | D11: =IFERROR(CEILING(C11/'Mi negocio'!$B$14,1),0) -> 0 | E11: =C11*'Recetas y precios'!E11 -> 0 | F11: =C11*'Recetas y precios'!M11 -> 0 | G11: =C11*('Recetas y precios'!H11+'Mi negocio'!$B$10) -> 0 | H11: =G11/60 -> 0 | I11: =C11*'Recetas y precios'!Q11 -> 0 | J11: =C11*'Recetas y precios'!N11*'Recetas y precios'!P11 -> 0 | K11: =I11-F11 -> 0
A12: 7 | B12: Panqué de Nata Artesanal de Rancho y Cardamomo Verde Molido | C12: 0 | D12: =IFERROR(CEILING(C12/'Mi negocio'!$B$14,1),0) -> 0 | E12: =C12*'Recetas y precios'!E12 -> 0 | F12: =C12*'Recetas y precios'!M12 -> 0 | G12: =C12*('Recetas y precios'!H12+'Mi negocio'!$B$10) -> 0 | H12: =G12/60 -> 0 | I12: =C12*'Recetas y precios'!Q12 -> 0 | J12: =C12*'Recetas y precios'!N12*'Recetas y precios'!P12 -> 0 | K12: =I12-F12 -> 0
A13: 8 | B13: Panqué Red Velvet de Autor con Núcleo Horneado de Cheesecake | C13: 0 | D13: =IFERROR(CEILING(C13/'Mi negocio'!$B$14,1),0) -> 0 | E13: =C13*'Recetas y precios'!E13 -> 0 | F13: =C13*'Recetas y precios'!M13 -> 0 | G13: =C13*('Recetas y precios'!H13+'Mi negocio'!$B$10) -> 0 | H13: =G13/60 -> 0 | I13: =C13*'Recetas y precios'!Q13 -> 0 | J13: =C13*'Recetas y precios'!N13*'Recetas y precios'!P13 -> 0 | K13: =I13-F13 -> 0
A14: 9 | B14: Panqué Imperial de Vainilla Tahití con Glaseado Traslúcido de Mantequilla | C14: 0 | D14: =IFERROR(CEILING(C14/'Mi negocio'!$B$14,1),0) -> 0 | E14: =C14*'Recetas y precios'!E14 -> 0 | F14: =C14*'Recetas y precios'!M14 -> 0 | G14: =C14*('Recetas y precios'!H14+'Mi negocio'!$B$10) -> 0 | H14: =G14/60 -> 0 | I14: =C14*'Recetas y precios'!Q14 -> 0 | J14: =C14*'Recetas y precios'!N14*'Recetas y precios'!P14 -> 0 | K14: =I14-F14 -> 0
A15: 10 | B15: Panqué Glaseado de Limón Amarillo Eureka y Semillas de Amapola | C15: 0 | D15: =IFERROR(CEILING(C15/'Mi negocio'!$B$14,1),0) -> 0 | E15: =C15*'Recetas y precios'!E15 -> 0 | F15: =C15*'Recetas y precios'!M15 -> 0 | G15: =C15*('Recetas y precios'!H15+'Mi negocio'!$B$10) -> 0 | H15: =G15/60 -> 0 | I15: =C15*'Recetas y precios'!Q15 -> 0 | J15: =C15*'Recetas y precios'!N15*'Recetas y precios'!P15 -> 0 | K15: =I15-F15 -> 0
A16: 11 | B16: Panqué de Naranja Valencia, Romero Fresco y Aceite de Oliva Extra Virgen | C16: 0 | D16: =IFERROR(CEILING(C16/'Mi negocio'!$B$14,1),0) -> 0 | E16: =C16*'Recetas y precios'!E16 -> 0 | F16: =C16*'Recetas y precios'!M16 -> 0 | G16: =C16*('Recetas y precios'!H16+'Mi negocio'!$B$10) -> 0 | H16: =G16/60 -> 0 | I16: =C16*'Recetas y precios'!Q16 -> 0 | J16: =C16*'Recetas y precios'!N16*'Recetas y precios'!P16 -> 0 | K16: =I16-F16 -> 0
A17: 12 | B17: Panqué de Toronja Rosa y Campari con Embebiendo Cítrico Amargo | C17: 0 | D17: =IFERROR(CEILING(C17/'Mi negocio'!$B$14,1),0) -> 0 | E17: =C17*'Recetas y precios'!E17 -> 0 | F17: =C17*'Recetas y precios'!M17 -> 0 | G17: =C17*('Recetas y precios'!H17+'Mi negocio'!$B$10) -> 0 | H17: =G17/60 -> 0 | I17: =C17*'Recetas y precios'!Q17 -> 0 | J17: =C17*'Recetas y precios'!N17*'Recetas y precios'!P17 -> 0 | K17: =I17-F17 -> 0
... A56: 51 | B56: Panqué Panettone de Masa Enriquecida con Naranja Confitada y Chocolate | C56: 0 | D56: =IFERROR(CEILING(C56/'Mi negocio'!$B$14,1),0) -> 0 | E56: =C56*'Recetas y precios'!E56 -> 0 | F56: =C56*'Recetas y precios'!M56 -> 0 | G56: =C56*('Recetas y precios'!H56+'Mi negocio'!$B$10) -> 0 | H56: =G56/60 -> 0 | I56: =C56*'Recetas y precios'!Q56 -> 0 | J56: =C56*'Recetas y precios'!N56*'Recetas y precios'!P56 -> 0 | K56: =I56-F56 -> 0
B57: TOTAL DEL MES | C57: =SUM(C6:C56) -> 0 | D57: =SUM(D6:D56) -> 0 | E57: =SUM(E6:E56) -> 0 | F57: =SUM(F6:F56) -> 0 | G57: =SUM(G6:G56) -> 0 | H57: =SUM(H6:H56) -> 0 | I57: =SUM(I6:I56) -> 0 | J57: =SUM(J6:J56) -> 0 | K57: =SUM(K6:K56) -> 0
B59: La columna «Hornadas necesarias» usa los moldes por hornada de «Mi negocio».

Sheet Ventas
A1: VENTAS
A2: Registra cada venta. Elige la receta por número y el canal de la lista; el precio y la utilidad salen solos.
A3: Endulcora · Estudio Gastronómico · en colaboración con Levent | H3: TOTALES
G4: =SUM(G6:G305) -> 0 | I4: =SUM(I6:I305) -> 0 | J4: =SUM(J6:J305) -> 0
A5: Fecha | B5: # receta | C5: Receta | D5: Canal | E5: Unidades | F5: Precio unitario | G5: Ingreso | H5: Costo unitario | I5: Costo total | J5: Utilidad | K5: Margen | L5: Nota
C6: =IF($B6="","",IFERROR(VLOOKUP($B6,'Recetas y precios'!$A:$B,2,FALSE()),"")) | F6: =IF(OR($B6="",$D6=""),"",IFERROR(INDEX('Recetas y precios'!$P:$S,MATCH($B6,'Recetas y precios'!$A:$A,0),MATCH($D6,'Recetas y precios'!$P$5:$S$5,0)),"")) | G6: =IFERROR($E6*$F6,"") | H6: =IF($B6="","",IF($D6="Rebanada en mostrador",IFERROR(VLOOKUP($B6,'Recetas y precios'!$A:$O,15,FALSE()),""),IFERROR(VLOOKUP($B6,'Recetas y precios'!$A:$M,13,FALSE()),""))) | I6: =IFERROR($E6*$H6,"") | J6: =IFERROR($G6-$I6,"") | K6: =IFERROR($J6/$G6,"")
C7: =IF($B7="","",IFERROR(VLOOKUP($B7,'Recetas y precios'!$A:$B,2,FALSE()),"")) | F7: =IF(OR($B7="",$D7=""),"",IFERROR(INDEX('Recetas y precios'!$P:$S,MATCH($B7,'Recetas y precios'!$A:$A,0),MATCH($D7,'Recetas y precios'!$P$5:$S$5,0)),"")) | G7: =IFERROR($E7*$F7,"") | H7: =IF($B7="","",IF($D7="Rebanada en mostrador",IFERROR(VLOOKUP($B7,'Recetas y precios'!$A:$O,15,FALSE()),""),IFERROR(VLOOKUP($B7,'Recetas y precios'!$A:$M,13,FALSE()),""))) | I7: =IFERROR($E7*$H7,"") | J7: =IFERROR($G7-$I7,"") | K7: =IFERROR($J7/$G7,"")
C8: =IF($B8="","",IFERROR(VLOOKUP($B8,'Recetas y precios'!$A:$B,2,FALSE()),"")) | F8: =IF(OR($B8="",$D8=""),"",IFERROR(INDEX('Recetas y precios'!$P:$S,MATCH($B8,'Recetas y precios'!$A:$A,0),MATCH($D8,'Recetas y precios'!$P$5:$S$5,0)),"")) | G8: =IFERROR($E8*$F8,"") | H8: =IF($B8="","",IF($D8="Rebanada en mostrador",IFERROR(VLOOKUP($B8,'Recetas y precios'!$A:$O,15,FALSE()),""),IFERROR(VLOOKUP($B8,'Recetas y precios'!$A:$M,13,FALSE()),""))) | I8: =IFERROR($E8*$H8,"") | J8: =IFERROR($G8-$I8,"") | K8: =IFERROR($J8/$G8,"")
C9: =IF($B9="","",IFERROR(VLOOKUP($B9,'Recetas y precios'!$A:$B,2,FALSE()),"")) | F9: =IF(OR($B9="",$D9=""),"",IFERROR(INDEX('Recetas y precios'!$P:$S,MATCH($B9,'Recetas y precios'!$A:$A,0),MATCH($D9,'Recetas y precios'!$P$5:$S$5,0)),"")) | G9: =IFERROR($E9*$F9,"") | H9: =IF($B9="","",IF($D9="Rebanada en mostrador",IFERROR(VLOOKUP($B9,'Recetas y precios'!$A:$O,15,FALSE()),""),IFERROR(VLOOKUP($B9,'Recetas y precios'!$A:$M,13,FALSE()),""))) | I9: =IFERROR($E9*$H9,"") | J9: =IFERROR($G9-$I9,"") | K9: =IFERROR($J9/$G9,"")
C10: =IF($B10="","",IFERROR(VLOOKUP($B10,'Recetas y precios'!$A:$B,2,FALSE()),"")) | F10: =IF(OR($B10="",$D10=""),"",IFERROR(INDEX('Recetas y precios'!$P:$S,MATCH($B10,'Recetas y precios'!$A:$A,0),MATCH($D10,'Recetas y precios'!$P$5:$S$5,0)),"")) | G10: =IFERROR($E10*$F10,"") | H10: =IF($B10="","",IF($D10="Rebanada en mostrador",IFERROR(VLOOKUP($B10,'Recetas y precios'!$A:$O,15,FALSE()),""),IFERROR(VLOOKUP($B10,'Recetas y precios'!$A:$M,13,FALSE()),""))) | I10: =IFERROR($E10*$H10,"") | J10: =IFERROR($G10-$I10,"") | K10: =IFERROR($J10/$G10,"")
C11: =IF($B11="","",IFERROR(VLOOKUP($B11,'Recetas y precios'!$A:$B,2,FALSE()),"")) | F11: =IF(OR($B11="",$D11=""),"",IFERROR(INDEX('Recetas y precios'!$P:$S,MATCH($B11,'Recetas y precios'!$A:$A,0),MATCH($D11,'Recetas y precios'!$P$5:$S$5,0)),"")) | G11: =IFERROR($E11*$F11,"") | H11: =IF($B11="","",IF($D11="Rebanada en mostrador",IFERROR(VLOOKUP($B11,'Recetas y precios'!$A:$O,15,FALSE()),""),IFERROR(VLOOKUP($B11,'Recetas y precios'!$A:$M,13,FALSE()),""))) | I11: =IFERROR($E11*$H11,"") | J11: =IFERROR($G11-$I11,"") | K11: =IFERROR($J11/$G11,"")
C12: =IF($B12="","",IFERROR(VLOOKUP($B12,'Recetas y precios'!$A:$B,2,FALSE()),"")) | F12: =IF(OR($B12="",$D12=""),"",IFERROR(INDEX('Recetas y precios'!$P:$S,MATCH($B12,'Recetas y precios'!$A:$A,0),MATCH($D12,'Recetas y precios'!$P$5:$S$5,0)),"")) | G12: =IFERROR($E12*$F12,"") | H12: =IF($B12="","",IF($D12="Rebanada en mostrador",IFERROR(VLOOKUP($B12,'Recetas y precios'!$A:$O,15,FALSE()),""),IFERROR(VLOOKUP($B12,'Recetas y precios'!$A:$M,13,FALSE()),""))) | I12: =IFERROR($E12*$H12,"") | J12: =IFERROR($G12-$I12,"") | K12: =IFERROR($J12/$G12,"")
C13: =IF($B13="","",IFERROR(VLOOKUP($B13,'Recetas y precios'!$A:$B,2,FALSE()),"")) | F13: =IF(OR($B13="",$D13=""),"",IFERROR(INDEX('Recetas y precios'!$P:$S,MATCH($B13,'Recetas y precios'!$A:$A,0),MATCH($D13,'Recetas y precios'!$P$5:$S$5,0)),"")) | G13: =IFERROR($E13*$F13,"") | H13: =IF($B13="","",IF($D13="Rebanada en mostrador",IFERROR(VLOOKUP($B13,'Recetas y precios'!$A:$O,15,FALSE()),""),IFERROR(VLOOKUP($B13,'Recetas y precios'!$A:$M,13,FALSE()),""))) | I13: =IFERROR($E13*$H13,"") | J13: =IFERROR($G13-$I13,"") | K13: =IFERROR($J13/$G13,"")
C14: =IF($B14="","",IFERROR(VLOOKUP($B14,'Recetas y precios'!$A:$B,2,FALSE()),"")) | F14: =IF(OR($B14="",$D14=""),"",IFERROR(INDEX('Recetas y precios'!$P:$S,MATCH($B14,'Recetas y precios'!$A:$A,0),MATCH($D14,'Recetas y precios'!$P$5:$S$5,0)),"")) | G14: =IFERROR($E14*$F14,"") | H14: =IF($B14="","",IF($D14="Rebanada en mostrador",IFERROR(VLOOKUP($B14,'Recetas y precios'!$A:$O,15,FALSE()),""),IFERROR(VLOOKUP($B14,'Recetas y precios'!$A:$M,13,FALSE()),""))) | I14: =IFERROR($E14*$H14,"") | J14: =IFERROR($G14-$I14,"") | K14: =IFERROR($J14/$G14,"")
C15: =IF($B15="","",IFERROR(VLOOKUP($B15,'Recetas y precios'!$A:$B,2,FALSE()),"")) | F15: =IF(OR($B15="",$D15=""),"",IFERROR(INDEX('Recetas y precios'!$P:$S,MATCH($B15,'Recetas y precios'!$A:$A,0),MATCH($D15,'Recetas y precios'!$P$5:$S$5,0)),"")) | G15: =IFERROR($E15*$F15,"") | H15: =IF($B15="","",IF($D15="Rebanada en mostrador",IFERROR(VLOOKUP($B15,'Recetas y precios'!$A:$O,15,FALSE()),""),IFERROR(VLOOKUP($B15,'Recetas y precios'!$A:$M,13,FALSE()),""))) | I15: =IFERROR($E15*$H15,"") | J15: =IFERROR($G15-$I15,"") | K15: =IFERROR($J15/$G15,"")
C16: =IF($B16="","",IFERROR(VLOOKUP($B16,'Recetas y precios'!$A:$B,2,FALSE()),"")) | F16: =IF(OR($B16="",$D16=""),"",IFERROR(INDEX('Recetas y precios'!$P:$S,MATCH($B16,'Recetas y precios'!$A:$A,0),MATCH($D16,'Recetas y precios'!$P$5:$S$5,0)),"")) | G16: =IFERROR($E16*$F16,"") | H16: =IF($B16="","",IF($D16="Rebanada en mostrador",IFERROR(VLOOKUP($B16,'Recetas y precios'!$A:$O,15,FALSE()),""),IFERROR(VLOOKUP($B16,'Recetas y precios'!$A:$M,13,FALSE()),""))) | I16: =IFERROR($E16*$H16,"") | J16: =IFERROR($G16-$I16,"") | K16: =IFERROR($J16/$G16,"")
C17: =IF($B17="","",IFERROR(VLOOKUP($B17,'Recetas y precios'!$A:$B,2,FALSE()),"")) | F17: =IF(OR($B17="",$D17=""),"",IFERROR(INDEX('Recetas y precios'!$P:$S,MATCH($B17,'Recetas y precios'!$A:$A,0),MATCH($D17,'Recetas y precios'!$P$5:$S$5,0)),"")) | G17: =IFERROR($E17*$F17,"") | H17: =IF($B17="","",IF($D17="Rebanada en mostrador",IFERROR(VLOOKUP($B17,'Recetas y precios'!$A:$O,15,FALSE()),""),IFERROR(VLOOKUP($B17,'Recetas y precios'!$A:$M,13,FALSE()),""))) | I17: =IFERROR($E17*$H17,"") | J17: =IFERROR($G17-$I17,"") | K17: =IFERROR($J17/$G17,"")
... C305: =IF($B305="","",IFERROR(VLOOKUP($B305,'Recetas y precios'!$A:$B,2,FALSE()),"")) | F305: =IF(OR($B305="",$D305=""),"",IFERROR(INDEX('Recetas y precios'!$P:$S,MATCH($B305,'Recetas y precios'!$A:$A,0),MATCH($D305,'Recetas y precios'!$P$5:$S$5,0)),"")) | G305: =IFERROR($E305*$F305,"") | H305: =IF($B305="","",IF($D305="Rebanada en mostrador",IFERROR(VLOOKUP($B305,'Recetas y precios'!$A:$O,15,FALSE()),""),IFERROR(VLOOKUP($B305,'Recetas y precios'!$A:$M,13,FALSE()),""))) | I305: =IFERROR($E305*$H305,"") | J305: =IFERROR($G305-$I305,"") | K305: =IFERROR($J305/$G305,"")

Sheet Tablero
A1: TABLERO
A2: Resumen del modelo con tus números.
A3: Endulcora · Estudio Gastronómico · en colaboración con Levent | D3: LAS 51 RECETAS ORDENADAS POR COSTO DE INSUMOS
A5: Recetas costeadas | B5: =COUNT('Recetas y precios'!$A$6:$A$56) -> 51
A6: Insumos en catálogo | B6: =COUNTA(Insumos!$A$6:$A$140) -> 135 | D6: # | E6: Receta | F6: Costo insumos | G6: Costo total | H6: Entero
A7: Líneas de receta normalizadas | B7: =COUNTA(Ingredientes!$A$6:$A$778) -> 773 | D7: 28 | E7: Panqué de Pistache Siciliano Puro con Costra Crocante de Frambuesa | F7: ='Recetas y precios'!E33 -> 445.239 | G7: ='Recetas y precios'!M33 -> 623.65851 | H7: ='Recetas y precios'!Q33 -> 1390
D8: 30 | E8: Panqué de Castañas Glaseadas (Marrons Glacés) y Vainilla | F8: ='Recetas y precios'!E35 -> 390.47883 | G8: ='Recetas y precios'!M35 -> 565.40301 | H8: ='Recetas y precios'!Q35 -> 1260
A9: Costo de insumos promedio por molde | B9: =AVERAGE('Recetas y precios'!$E$6:$E$56) -> 163.32118 | D9: 23 | E9: Panqué de Gianduja Casera y Avellanas del Piamonte Tostadas | F9: ='Recetas y precios'!E28 -> 288.282 | G9: ='Recetas y precios'!M28 -> 464.6617 | H9: ='Recetas y precios'!Q28 -> 1035
A10: Costo total promedio por molde | B10: =AVERAGE('Recetas y precios'!$M$6:$M$56) -> 321.24281 | D10: 17 | E10: Panqué de Yuzu y Té Matcha Ceremonial con Streusel Crujiente | F10: ='Recetas y precios'!E22 -> 278.122 | G10: ='Recetas y precios'!M22 -> 445.87447 | H10: ='Recetas y precios'!Q22 -> 995
A11: Costo total promedio por rebanada | B11: =AVERAGE('Recetas y precios'!$O$6:$O$56) -> 31.685583 | D11: 6 | E11: Panqué de Queso Crema y Nuez Pecán Tostada al Jarabe de Maple | F11: ='Recetas y precios'!E11 -> 261.452 | G11: ='Recetas y precios'!M11 -> 420.1617 | H11: ='Recetas y precios'!Q11 -> 935
A12: Precio promedio · panqué entero | B12: =AVERAGE('Recetas y precios'!$Q$6:$Q$56) -> 716.27451 | D12: 22 | E12: Panqué Selva Negra con Cerezas Amarenas y Licor Kirsch | F12: ='Recetas y precios'!E27 -> 260.4365 | G12: ='Recetas y precios'!M27 -> 427.06011 | H12: ='Recetas y precios'!Q27 -> 950
A13: Precio promedio · rebanada | B13: =AVERAGE('Recetas y precios'!$P$6:$P$56) -> 85.960784 | D13: 32 | E13: Panqué Praliné de Almendras Tostadas con Núcleo Cremino | F13: ='Recetas y precios'!E37 -> 256.992 | G13: ='Recetas y precios'!M37 -> 431.37447 | H13: ='Recetas y precios'!Q37 -> 960
A14: Utilidad promedio por pieza entera | B14: =AVERAGE('Recetas y precios'!$T$6:$T$56) -> 395.0317 | D14: 19 | E14: Panqué Fudge de Chocolate Amargo 70% con Glaseado Rocher de Avellana | F14: ='Recetas y precios'!E24 -> 228.606 | G14: ='Recetas y precios'!M24 -> 393.19787 | H14: ='Recetas y precios'!Q24 -> 875
D15: 21 | E15: Panqué de Chocolate Blanco, Nuez de Macadamia y Maracuyá | F15: ='Recetas y precios'!E26 -> 215.208 | G15: ='Recetas y precios'!M26 -> 378.94468 | H15: ='Recetas y precios'!Q26 -> 845
A16: Costo variable promedio por molde | B16: =AVERAGE('Recetas y precios'!$E$6:$E$56)+'Mi negocio'!$B$11+'Mi negocio'!$B$20 -> 193.32118 | D16: 20 | E16: Panqué Doble Chocolate y Frambuesa Liofilizada con Ganache Brillante | F16: ='Recetas y precios'!E25 -> 199.328 | G16: ='Recetas y precios'!M25 -> 362.05106 | H16: ='Recetas y precios'!Q25 -> 805
A17: Contribución marginal por molde | B17: =B12-B16 -> 522.95333 | D17: 51 | E17: Panqué Panettone de Masa Enriquecida con Naranja Confitada y Chocolate | F17: ='Recetas y precios'!E56 -> 194.78117 | G17: ='Recetas y precios'!M56 -> 373.17146 | H17: ='Recetas y precios'!Q56 -> 830
A18: PUNTO DE EQUILIBRIO (moldes al mes) | B18: =IFERROR(CEILING('Mi negocio'!$B$6/B17,1),0) -> 35 | D18: 33 | E18: Panqué de Nuez de Castilla, Higo Fresco y Miel de Bosque | F18: ='Recetas y precios'!E38 -> 193.033 | G18: ='Recetas y precios'!M38 -> 355.35426 | H18: ='Recetas y precios'!Q38 -> 790
A19: Punto de equilibrio (moldes al día, 26 días) | B19: =IFERROR(CEILING(B18/26,1),0) -> 2 | D19: 35 | E19: Panqué de Dátil Medjool, Nuez Pecán y Toffee Líquido (Sticky Toffee Cake) | F19: ='Recetas y precios'!E40 -> 189.7275 | G19: ='Recetas y precios'!M40 -> 351.83777 | H19: ='Recetas y precios'!Q40 -> 785
D20: 45 | E20: Panqué de Maíz Dulce y Nata con Queso Parmesano Reggiano | F20: ='Recetas y precios'!E50 -> 169.048 | G20: ='Recetas y precios'!M50 -> 321.85957 | H20: ='Recetas y precios'!Q50 -> 720
A21: Producción planeada en «Producción» | B21: =Producción!C57 -> 0 | D21: 50 | E21: Panqué de Carajillo (Licor 43 y Café Espresso) con Cobertura Cremosa | F21: ='Recetas y precios'!E55 -> 167.24557 | G21: ='Recetas y precios'!M55 -> 327.92082 | H21: ='Recetas y precios'!Q55 -> 730
A22: Costo total de esa producción | B22: =Producción!F57 -> 0 | D22: 38 | E22: Panqué Húmedo de Zanahoria Especiada con Piña Confitada y Mascarpone | F22: ='Recetas y precios'!E43 -> 154.784 | G22: ='Recetas y precios'!M43 -> 322.64255 | H22: ='Recetas y precios'!Q43 -> 720
A23: Ingreso estimado (pieza entera) | B23: =Producción!I57 -> 0 | D23: 9 | E23: Panqué Imperial de Vainilla Tahití con Glaseado Traslúcido de Mantequilla | F23: ='Recetas y precios'!E14 -> 152.6925 | G23: ='Recetas y precios'!M14 -> 304.46011 | H23: ='Recetas y precios'!Q14 -> 680
A24: Utilidad estimada | B24: =Producción!K57 -> 0 | D24: 41 | E24: Panqué de Maracuyá y Frambuesas con Almíbar de Fruta de la Pasión | F24: ='Recetas y precios'!E46 -> 150.91161 | G24: ='Recetas y precios'!M46 -> 302.56554 | H24: ='Recetas y precios'!Q46 -> 675
A25: Horas de trabajo del plan | B25: =Producción!H57 -> 0 | D25: 24 | E25: Panqué de Chocolate Oscuro, Nibs de Cacao y Flor de Sal Maldon | F25: ='Recetas y precios'!E29 -> 150.465 | G25: ='Recetas y precios'!M29 -> 302.09043 | H25: ='Recetas y precios'!Q29 -> 675
D26: 48 | E26: Panqué Selva Lacandona de Cardamomo, Café y Chocolate Chiapaneco | F26: ='Recetas y precios'!E53 -> 148.357 | G26: ='Recetas y precios'!M53 -> 307.8266 | H26: ='Recetas y precios'!Q53 -> 685
A27: Ventas registradas · ingreso | B27: =Ventas!G4 -> 0 | D27: 27 | E27: Panqué Mole y Cacao Oaxaqueño con Ajonjolí y Especias Cálidas | F27: ='Recetas y precios'!E32 -> 145.5875 | G27: ='Recetas y precios'!M32 -> 304.88032 | H27: ='Recetas y precios'!Q32 -> 680
A28: Ventas registradas · utilidad | B28: =Ventas!J4 -> 0 | D28: 46 | E28: Panqué de Té Chai Especiado con Glaseado de Chocolate Blanco y Anís | F28: ='Recetas y precios'!E51 -> 144.368 | G28: ='Recetas y precios'!M51 -> 303.58298 | H28: ='Recetas y precios'!Q51 -> 675
D29: 4 | E29: Panqué Bretón de Caramelo Salado con Ganache Montada | F29: ='Recetas y precios'!E9 -> 143.91 | G29: ='Recetas y precios'!M9 -> 311.07447 | H29: ='Recetas y precios'!Q9 -> 695
D30: 2 | E30: Panqué de Mantequilla Avellanada (Beurre Noisette) y Flor de Sal | F30: ='Recetas y precios'!E7 -> 143.725 | G30: ='Recetas y precios'!M7 -> 302.89894 | H30: ='Recetas y precios'!Q7 -> 675
D31: 5 | E31: Panqué Financiero de Pera Caramelizada y Harina de Almendra | F31: ='Recetas y precios'!E10 -> 143.72033 | G31: ='Recetas y precios'!M10 -> 302.89397 | H31: ='Recetas y precios'!Q10 -> 675
D32: 25 | E32: Panqué de Café Espresso Arábica y Dulce de Leche Repostero | F32: ='Recetas y precios'!E30 -> 141.233 | G32: ='Recetas y precios'!M30 -> 300.24787 | H32: ='Recetas y precios'!Q30 -> 670
D33: 3 | E33: Panqué Marble / Jaspeado Suizo de Chocolate Oscuro y Vainilla Bourbon | F33: ='Recetas y precios'!E8 -> 140.71133 | G33: ='Recetas y precios'!M8 -> 291.71418 | H33: ='Recetas y precios'!Q8 -> 650
D34: 42 | E34: Panqué de Ciruela Pasa al Brandy y Canela con Baño de Azúcar Moreno | F34: ='Recetas y precios'!E47 -> 139.802 | G34: ='Recetas y precios'!M47 -> 298.72553 | H34: ='Recetas y precios'!Q47 -> 665
D35: 29 | E35: Panqué de Mazapán Artesanal de Cacahuate con Cobertura de Chocolate con Leche | F35: ='Recetas y precios'!E34 -> 139.543 | G35: ='Recetas y precios'!M34 -> 290.47128 | H35: ='Recetas y precios'!Q34 -> 650
D36: 14 | E36: Panqué de Lima Kaffir y Coco Tostado con Ganache de Chocolate Blanco | F36: ='Recetas y precios'!E19 -> 137.81113 | G36: ='Recetas y precios'!M19 -> 296.60759 | H36: ='Recetas y precios'!Q19 -> 660
D37: 36 | E37: Panqué de Plátano Asado, Dulce de Leche y Nueces Glaseadas | F37: ='Recetas y precios'!E41 -> 135.27389 | G37: ='Recetas y precios'!M41 -> 293.90839 | H37: ='Recetas y precios'!Q41 -> 655
D38: 18 | E38: Panqué de Moras Silvestres y Limón Meyer con Costra de Azúcar Glas | F38: ='Recetas y precios'!E23 -> 132.59389 | G38: ='Recetas y precios'!M23 -> 275.09988 | H38: ='Recetas y precios'!Q23 -> 615
D39: 37 | E39: Panqué de Manzana Reineta, Mantequilla Tostada y Canela de Ceilán | F39: ='Recetas y precios'!E42 -> 131.332 | G39: ='Recetas y precios'!M42 -> 289.71489 | H39: ='Recetas y precios'!Q42 -> 645
D40: 43 | E40: Panqué de Guayaba Rosa con Relleno de Ate Artesanal y Queso de Rancho | F40: ='Recetas y precios'!E48 -> 130.08089 | G40: ='Recetas y precios'!M48 -> 288.38392 | H40: ='Recetas y precios'!Q48 -> 645
D41: 1 | E41: Panqué Cuatro Cuartos Perfecto a la Vainilla de Papantla y Mantequilla de Rancho | F41: ='Recetas y precios'!E6 -> 125.7555 | G41: ='Recetas y precios'!M6 -> 267.825 | H41: ='Recetas y precios'!Q6 -> 600
D42: 31 | E42: Panqué de Semillas de Girasol, Pepitas de Calabaza y Miel de Azahar | F42: ='Recetas y precios'!E36 -> 123.59175 | G42: ='Recetas y precios'!M36 -> 273.50186 | H42: ='Recetas y precios'!Q36 -> 610
D43: 40 | E43: Panqué de Mango Manila Caramelizado y Jengibre Confitado | F43: ='Recetas y precios'!E45 -> 122.99367 | G43: ='Recetas y precios'!M45 -> 280.84433 | H43: ='Recetas y precios'!Q45 -> 625
D44: 47 | E44: Panqué de Mezcal Espadín, Naranja Asada y Sal de Gusano Dulce | F44: ='Recetas y precios'!E52 -> 122.882 | G44: ='Recetas y precios'!M52 -> 280.72553 | H44: ='Recetas y precios'!Q52 -> 625
D45: 49 | E45: Panqué Tres Leches Horneado con Compota de Frutos del Bosque | F45: ='Recetas y precios'!E54 -> 120.23107 | G45: ='Recetas y precios'!M54 -> 285.88412 | H45: ='Recetas y precios'!Q54 -> 640
D46: 44 | E46: Panqué de Churro y Dulce de Leche con Costra de Azúcar y Canela | F46: ='Recetas y precios'!E49 -> 119.517 | G46: ='Recetas y precios'!M49 -> 269.16702 | H46: ='Recetas y precios'!Q49 -> 600
D47: 8 | E47: Panqué Red Velvet de Autor con Núcleo Horneado de Cheesecake | F47: ='Recetas y precios'!E13 -> 118.77 | G47: ='Recetas y precios'!M13 -> 284.32979 | H47: ='Recetas y precios'!Q13 -> 635
D48: 34 | E48: Panqué de Tahini Tostado (Ajonjolí) con Glaseado de Miel y Sésamo Negro | F48: ='Recetas y precios'!E39 -> 117.14675 | G48: ='Recetas y precios'!M39 -> 266.64548 | H48: ='Recetas y precios'!Q39 -> 595
D49: 26 | E49: Panqué de Cacao Alcalinizado, Menta Piperita y Chispas Semiamargas | F49: ='Recetas y precios'!E31 -> 113.40075 | G49: ='Recetas y precios'!M31 -> 262.66037 | H49: ='Recetas y precios'!Q31 -> 585
D50: 11 | E50: Panqué de Naranja Valencia, Romero Fresco y Aceite de Oliva Extra Virgen | F50: ='Recetas y precios'!E16 -> 111.03156 | G50: ='Recetas y precios'!M16 -> 260.13995 | H50: ='Recetas y precios'!Q16 -> 580
D51: 10 | E51: Panqué Glaseado de Limón Amarillo Eureka y Semillas de Amapola | F51: ='Recetas y precios'!E15 -> 108.17711 | G51: ='Recetas y precios'!M15 -> 249.12459 | H51: ='Recetas y precios'!Q15 -> 555
D52: 12 | E52: Panqué de Toronja Rosa y Campari con Embebiendo Cítrico Amargo | F52: ='Recetas y precios'!E17 -> 105.59533 | G52: ='Recetas y precios'!M17 -> 254.35674 | H52: ='Recetas y precios'!Q17 -> 570
D53: 15 | E53: Panqué de Earl Grey y Bergamota con Glaseado de Lavanda | F53: ='Recetas y precios'!E20 -> 102.822 | G53: ='Recetas y precios'!M20 -> 259.38511 | H53: ='Recetas y precios'!Q20 -> 580
D54: 39 | E54: Panqué de Calabaza de Castilla en Tacha con Especias de Otoño | F54: ='Recetas y precios'!E44 -> 99.152 | G54: ='Recetas y precios'!M44 -> 255.48085 | H54: ='Recetas y precios'!Q44 -> 570
D55: 16 | E55: Panqué de Limón Real y Albahaca Genovesa con Glaseado Ácido | F55: ='Recetas y precios'!E21 -> 97.706 | G55: ='Recetas y precios'!M21 -> 245.96383 | H55: ='Recetas y precios'!Q21 -> 550
D56: 7 | E56: Panqué de Nata Artesanal de Rancho y Cardamomo Verde Molido | F56: ='Recetas y precios'!E12 -> 92.678 | G56: ='Recetas y precios'!M12 -> 232.63617 | H56: ='Recetas y precios'!Q12 -> 520
D57: 13 | E57: Panqué de Mandarina Criolla y Tomillo con Costra de Azúcar Mascabado | F57: ='Recetas y precios'!E18 -> 83.048 | G57: ='Recetas y precios'!M18 -> 222.39149 | H57: ='Recetas y precios'!Q18 -> 495
D59: Endulcora · Estudio Gastronómico · en colaboración con Levent
D60: Cifras ilustrativas. Endulcora no garantiza ingresos ni resultados.
