Workbook

Sheet LÉEME
A1: Masa Madre · Fermentaciones Salvajes, Reología y 50 Formulaciones Técnicas
A2: Anexo 1 · Costeo, merma y precios · Endulcora · Estudio Gastronómico · En colaboración con Levent
A4: • | B4: Qué es: Hoja de costeo del eBook «Masa Madre». Calcula el costo real de las 50 formulaciones y su precio por canal con tus propios precios de compra.
A5: • | B5: Cómo se usa: 1) Insumos: captura presentación y precio que tú pagas. 2) Cultivos: revisa las preparaciones base; su costo alimenta a las recetas que las usan. 3) Mi negocio: gastos fijos, sueldo, horas, merma y márgenes. 4) Recetas y precios: revisa costos y precios. 5) Registra lotes en Producción y ventas en Ventas. 6) Revisa el Tablero cada semana.
A6: • | B6: Celdas amarillas: Son las únicas que debes editar. Todo lo demás es fórmula: si la borras, se rompe el cálculo.
A7: • | B7: Modelo de costeo: Costo por unidad = Precio ÷ Presentación · Los tres cultivos toman su costo de su fórmula de refresco (hoja «Cultivos») · Insumos por pieza = Σ(cantidad × costo unitario) ÷ piezas que rinde la fórmula · Minutos por pieza = minutos de amasado y manejo ÷ piezas por tanda + minutos de formado · Costo base = insumos + empaque + energía + mano de obra + gastos fijos · Costo total = Costo base ÷ (1 − merma) (se DIVIDE, no se suma) · Precio = Costo total ÷ (1 − margen), redondeado a $5.
A8: • | B8: Cultivos: La hoja «Cultivos» costea las tres masas madre del libro desde su propia fórmula de refresco. Es la hoja que hace que este anexo sea distinto a los demás: cuando cambies el precio de la harina, los tres cultivos y las 50 recetas se recalculan solos.
A9: • | B9: Hojas: Insumos (catálogo editable) · Cultivos (las preparaciones base) · Ingredientes (cada línea del recetario normalizada, con el texto original) · Mi negocio (supuestos) · Recetas y precios (hoja principal) · Producción (bitácora de lotes y merma) · Ventas (bitácora) · Tablero (resumen).
A10: • | B10: Unidades: Las 50 recetas se costean por pieza. La columna «Piezas que rinde» es la de la fórmula del chef (500 g de harina); la escala real de producción se ajusta con «Piezas por tanda real de obrador» en Mi negocio.
A11: • | B11: Advertencia: Los precios cargados son de referencia (mercado CDMX 2026), no cotizaciones. Los resultados son ilustrativos hasta que captures tus precios reales. No se promete ningún ingreso.
A12: • | B12: Créditos: Contenido y recetas: Chef Luis Alfonso Jiménez Cárdenas · Edición y costeo: Manuel Ramiro Justo Guzmán · Endulcora · Estudio Gastronómico, en colaboración con Levent · WhatsApp 56 6527 1901. Uso personal del comprador; prohibida su reventa o redistribución.
B14: Celda de ejemplo que sí puedes editar → | C14: 100

Sheet Insumos
A1: Insumos
A2: Captura la presentación que compras y lo que pagas. Precios de referencia CDMX 2026 (no son cotizaciones).
A4: ID | B4: Categoría | C4: Insumo | D4: Unidad | E4: Presentación | F4: Precio pagado | G4: Costo por unidad | H4: Usos | I4: Proveedor
A5: I-001 | B5: Harinas de trigo | C5: Harina panificable de fuerza (W 280-300) | D5: g | E5: 1000 | F5: 32 | G5: =IFERROR(F5/E5,0) | H5: =COUNTIF(Ingredientes!$E:$E,C5)
A6: I-002 | B6: Harinas de trigo | C6: Harina de gran fuerza (W 350+) o de panettone | D6: g | E6: 1000 | F6: 48 | G6: =IFERROR(F6/E6,0) | H6: =COUNTIF(Ingredientes!$E:$E,C6)
A7: I-003 | B7: Harinas de trigo | C7: Harina francesa T65 o tipo 00 | D7: g | E7: 1000 | F7: 42 | G7: =IFERROR(F7/E7,0) | H7: =COUNTIF(Ingredientes!$E:$E,C7)
A8: I-004 | B8: Harinas de trigo | C8: Harina de trigo integral de molienda a la piedra | D8: g | E8: 1000 | F8: 38 | G8: =IFERROR(F8/E8,0) | H8: =COUNTIF(Ingredientes!$E:$E,C8)
A9: I-005 | B9: Harinas de trigo | C9: Harina semi-integral T80 o T110 | D9: g | E9: 1000 | F9: 40 | G9: =IFERROR(F9/E9,0) | H9: =COUNTIF(Ingredientes!$E:$E,C9)
A10: I-006 | B10: Harinas de trigo | C10: Sémola rimacinata de trigo duro | D10: g | E10: 1000 | F10: 55 | G10: =IFERROR(F10/E10,0) | H10: =COUNTIF(Ingredientes!$E:$E,C10)
A11: I-007 | B11: Harinas de trigo | C11: Germen de trigo | D11: g | E11: 500 | F11: 60 | G11: =IFERROR(F11/E11,0) | H11: =COUNTIF(Ingredientes!$E:$E,C11)
A12: I-008 | B12: Harinas de trigo | C12: Leche en polvo entera | D12: g | E12: 500 | F12: 95 | G12: =IFERROR(F12/E12,0) | H12: =COUNTIF(Ingredientes!$E:$E,C12)
A13: I-009 | B13: Granos antiguos | C13: Harina de centeno integral o T130 | D13: g | E13: 1000 | F13: 52 | G13: =IFERROR(F13/E13,0) | H13: =COUNTIF(Ingredientes!$E:$E,C13)
A14: I-010 | B14: Granos antiguos | C14: Harina de centeno blanca T70 | D14: g | E14: 1000 | F14: 48 | G14: =IFERROR(F14/E14,0) | H14: =COUNTIF(Ingredientes!$E:$E,C14)
A15: I-011 | B15: Granos antiguos | C15: Harina de espelta integral | D15: g | E15: 1000 | F15: 78 | G15: =IFERROR(F15/E15,0) | H15: =COUNTIF(Ingredientes!$E:$E,C15)
A16: I-012 | B16: Granos antiguos | C16: Harina de kamut o khorasan | D16: g | E16: 1000 | F16: 95 | G16: =IFERROR(F16/E16,0) | H16: =COUNTIF(Ingredientes!$E:$E,C16)
... A21: I-017 | B21: Granos antiguos | C21: Sémola de maíz | D21: g | E21: 1000 | F21: 32 | G21: =IFERROR(F21/E21,0) | H21: =COUNTIF(Ingredientes!$E:$E,C21)
A22: I-018 | B22: Cultivos vivos | C22: Masa madre blanca activa 100% (cultivada) | D22: g | E22: ='Cultivos'!D5 | F22: ='Cultivos'!F5 | G22: =IFERROR(F22/E22,0) | H22: =COUNTIF(Ingredientes!$E:$E,C22)
A23: I-019 | B23: Cultivos vivos | C23: Masa madre de centeno o integral 100% (cultivada) | D23: g | E23: ='Cultivos'!D6 | F23: ='Cultivos'!F6 | G23: =IFERROR(F23/E23,0) | H23: =COUNTIF(Ingredientes!$E:$E,C23)
A24: I-020 | B24: Cultivos vivos | C24: Pasta madre sólida 50% (cultivada) | D24: g | E24: ='Cultivos'!D7 | F24: ='Cultivos'!F7 | G24: =IFERROR(F24/E24,0) | H24: =COUNTIF(Ingredientes!$E:$E,C24)
A25: I-021 | B25: Líquidos y grasas | C25: Agua purificada | D25: ml | E25: 20000 | F25: 40 | G25: =IFERROR(F25/E25,0) | H25: =COUNTIF(Ingredientes!$E:$E,C25)
A26: I-022 | B26: Líquidos y grasas | C26: Leche entera pasteurizada | D26: ml | E26: 1000 | F26: 28 | G26: =IFERROR(F26/E26,0) | H26: =COUNTIF(Ingredientes!$E:$E,C26)
A27: I-023 | B27: Líquidos y grasas | C27: Yogur natural entero | D27: g | E27: 1000 | F27: 65 | G27: =IFERROR(F27/E27,0) | H27: =COUNTIF(Ingredientes!$E:$E,C27)
A28: I-024 | B28: Líquidos y grasas | C28: Pulque blanco fresco | D28: ml | E28: 1000 | F28: 60 | G28: =IFERROR(F28/E28,0) | H28: =COUNTIF(Ingredientes!$E:$E,C28)
A29: I-025 | B29: Líquidos y grasas | C29: Aceite de oliva virgen extra | D29: ml | E29: 1000 | F29: 230 | G29: =IFERROR(F29/E29,0) | H29: =COUNTIF(Ingredientes!$E:$E,C29)
A30: I-026 | B30: Líquidos y grasas | C30: Aceite vegetal neutro | D30: ml | E30: 1000 | F30: 45 | G30: =IFERROR(F30/E30,0) | H30: =COUNTIF(Ingredientes!$E:$E,C30)
A31: I-027 | B31: Líquidos y grasas | C31: Mantequilla sin sal 82% M.G. | D31: g | E31: 1000 | F31: 330 | G31: =IFERROR(F31/E31,0) | H31: =COUNTIF(Ingredientes!$E:$E,C31)
A32: I-028 | B32: Líquidos y grasas | C32: Mantequilla clarificada o manteca de cerdo | D32: g | E32: 1000 | F32: 190 | G32: =IFERROR(F32/E32,0) | H32: =COUNTIF(Ingredientes!$E:$E,C32)
A33: I-029 | B33: Huevo, azúcares y sal | C33: Huevo campero | D33: pz | E33: 1 | F33: 6 | G33: =IFERROR(F33/E33,0) | H33: =COUNTIF(Ingredientes!$E:$E,C33)
A34: I-030 | B34: Huevo, azúcares y sal | C34: Yema de huevo | D34: g | E34: 1000 | F34: 130 | G34: =IFERROR(F34/E34,0) | H34: =COUNTIF(Ingredientes!$E:$E,C34)
A35: I-031 | B35: Huevo, azúcares y sal | C35: Azúcar blanco refinado | D35: g | E35: 1000 | F35: 28 | G35: =IFERROR(F35/E35,0) | H35: =COUNTIF(Ingredientes!$E:$E,C35)
A36: I-032 | B36: Huevo, azúcares y sal | C36: Miel de abeja | D36: g | E36: 500 | F36: 130 | G36: =IFERROR(F36/E36,0) | H36: =COUNTIF(Ingredientes!$E:$E,C36)
... A64: I-060 | B64: Inclusiones y aromáticos | C64: Naranja o limón | D64: g | E64: 1000 | F64: 30 | G64: =IFERROR(F64/E64,0) | H64: =COUNTIF(Ingredientes!$E:$E,C64)
C66: Las preparaciones del recetario toman su precio de la hoja «Cultivos»: no se capturan a mano.

Sheet Cultivos
A1: Los tres cultivos vivos
A2: Un cultivo no se compra: se refresca. Su costo sale de su propia fórmula de refresco y alimenta a las 50 recetas. Cambia el precio de la harina en «Insumos» y esta hoja se recalcula sola.
A4: Código | B4: Preparación base | C4: Para qué sirve | D4: Rendimiento | E4: Unidad | F4: Costo de insumos del lote | G4: Costo unitario | H4: Entra en las recetas
A5: C-1 | B5: Masa madre blanca activa 100% | C5: El cultivo de casi todo el recetario. Refresco cada 12 h a 26 °C o cada 24 h a 4 °C. | D5: 300 | E5: g | F5: =SUMIF(Ingredientes!$A:$A,101,Ingredientes!$I:$I) | G5: =IFERROR(F5/D5,0) | H5: 42 de las 50 recetas · Refresco 1:1:1 · 100 g de madre + 100 g de harina + 100 ml de agua
A6: C-2 | B6: Masa madre de centeno o integral 100% | C6: Cultivo más ácido y activo para los panes de centeno y los integrales puros. | D6: 300 | E6: g | F6: =SUMIF(Ingredientes!$A:$A,102,Ingredientes!$I:$I) | G6: =IFERROR(F6/D6,0) | H6: 6 de las 50 recetas · Refresco 1:1:1 con harina de centeno integral
A7: C-3 | B7: Pasta madre sólida 50% | C7: El lievito madre del panettone: sólido, atado en tela y con tres refrescos el día del amasado. | D7: 250 | E7: g | F7: =SUMIF(Ingredientes!$A:$A,103,Ingredientes!$I:$I) | G7: =IFERROR(F7/D7,0) | H7: 2 de las 50 recetas · Refresco 1:1:0.5 · 100 g de madre + 100 g de harina de gran fuerza + 50 ml de agua
B9: El «Costo de insumos del lote» suma la harina y el agua que se AÑADEN en cada refresco (no la madre que ya tenías). El rendimiento es el cultivo listo que sale de ese refresco. La harina del descarte no entra aquí: es gasto fijo, y está en «Mi negocio».
A11: Notas técnicas
B12: Punto pico | C12: Usa el cultivo cuando la cúpula está alta y los bordes empiezan a ceder. Antes hay poca población activa; después, demasiado ácido.
B13: Láctico contra acético | C13: Más calor y más agua dan acidez suave tipo yogur; más frío, menos agua y más hambre dan la punta avinagrada. El sabor es una decisión, no un accidente.
B14: Mantenimiento | C14: La harina de los refrescos que nunca llega a una pieza vendida es gasto fijo: está como línea propia en «Mi negocio». Si vendes crackers o pizza de descarte, ese gasto deja de serlo.

Sheet Ingredientes
A1: Ingredientes
A2: Cada línea del recetario normalizada a un insumo del catálogo, con el texto original del chef al lado para auditarla.
A4: Nº | B4: Receta | C4: Bloque | D4: Texto original del chef | E4: Insumo | F4: Cantidad | G4: Unidad | H4: Costo unitario | I4: Costo
A5: 1 | B5: Hogaza Rústica Blanca Campestre (Country Loaf 75% Hidratación) | C5: masa | D5: 450 g Harina de trigo panificable de fuerza (W 280-300, 12.5% proteína, P/L 0.5-0.6) (90%) | E5: Harina panificable de fuerza (W 280-300) | F5: 450 | G5: g | H5: =IFERROR(VLOOKUP(E5,Insumos!$C$5:$G$64,5,FALSE),0) | I5: =F5*H5
A6: 1 | B6: Hogaza Rústica Blanca Campestre (Country Loaf 75% Hidratación) | C6: masa | D6: 50 g Harina de trigo integral de molienda gruesa a la piedra (10%) | E6: Harina de trigo integral de molienda a la piedra | F6: 50 | G6: g | H6: =IFERROR(VLOOKUP(E6,Insumos!$C$5:$G$64,5,FALSE),0) | I6: =F6*H6
A7: 1 | B7: Hogaza Rústica Blanca Campestre (Country Loaf 75% Hidratación) | C7: masa | D7: 355 ml Agua purificada limpia (330 ml iniciales para autólisis + 25 ml para bassinage) (71% de agua añadida; 75% hidratación total sumando la masa madre) | E7: Agua purificada | F7: 355 | G7: ml | H7: =IFERROR(VLOOKUP(E7,Insumos!$C$5:$G$64,5,FALSE),0) | I7: =F7*H7
A8: 1 | B8: Hogaza Rústica Blanca Campestre (Country Loaf 75% Hidratación) | C8: masa | D8: 100 g Masa madre activa al 100% de hidratación refrescada 4 h antes (20%) | E8: Masa madre blanca activa 100% (cultivada) | F8: 100 | G8: g | H8: =IFERROR(VLOOKUP(E8,Insumos!$C$5:$G$64,5,FALSE),0) | I8: =F8*H8
A9: 1 | B9: Hogaza Rústica Blanca Campestre (Country Loaf 75% Hidratación) | C9: masa | D9: 10 g Sal marina fina no refinada (2%) | E9: Sal marina fina no refinada | F9: 10 | G9: g | H9: =IFERROR(VLOOKUP(E9,Insumos!$C$5:$G$64,5,FALSE),0) | I9: =F9*H9
A10: 2 | B10: Pan Campesino Tradicional con Centeno y Trigo Integral (Pain de Campagne) | C10: masa | D10: 375 g Harina de trigo panificable blanca (W 260-280, 12% proteína) (75%) | E10: Harina panificable de fuerza (W 280-300) | F10: 375 | G10: g | H10: =IFERROR(VLOOKUP(E10,Insumos!$C$5:$G$64,5,FALSE),0) | I10: =F10*H10
A11: 2 | B11: Pan Campesino Tradicional con Centeno y Trigo Integral (Pain de Campagne) | C11: masa | D11: 75 g Harina de trigo integral de molienda a la piedra (15%) | E11: Harina de trigo integral de molienda a la piedra | F11: 75 | G11: g | H11: =IFERROR(VLOOKUP(E11,Insumos!$C$5:$G$64,5,FALSE),0) | I11: =F11*H11
A12: 2 | B12: Pan Campesino Tradicional con Centeno y Trigo Integral (Pain de Campagne) | C12: masa | D12: 50 g Harina de centeno integral pura (10%) | E12: Harina de centeno integral o T130 | F12: 50 | G12: g | H12: =IFERROR(VLOOKUP(E12,Insumos!$C$5:$G$64,5,FALSE),0) | I12: =F12*H12
A13: 2 | B13: Pan Campesino Tradicional con Centeno y Trigo Integral (Pain de Campagne) | C13: masa | D13: 340 ml Agua purificada limpia (320 ml para autólisis + 20 ml para disolver la sal) (68% agua añadida; 72% hidratación total) | E13: Agua purificada | F13: 340 | G13: ml | H13: =IFERROR(VLOOKUP(E13,Insumos!$C$5:$G$64,5,FALSE),0) | I13: =F13*H13
A14: 2 | B14: Pan Campesino Tradicional con Centeno y Trigo Integral (Pain de Campagne) | C14: masa | D14: 100 g Masa madre activa (alimentada con harina blanca y centeno integral al 100% de hidratación) (20%) | E14: Masa madre blanca activa 100% (cultivada) | F14: 100 | G14: g | H14: =IFERROR(VLOOKUP(E14,Insumos!$C$5:$G$64,5,FALSE),0) | I14: =F14*H14
A15: 2 | B15: Pan Campesino Tradicional con Centeno y Trigo Integral (Pain de Campagne) | C15: masa | D15: 10 g Sal marina fina (2%) | E15: Sal marina fina no refinada | F15: 10 | G15: g | H15: =IFERROR(VLOOKUP(E15,Insumos!$C$5:$G$64,5,FALSE),0) | I15: =F15*H15
A16: 3 | B16: Barra Tradicional Rústica de Masa Madre (Formato Batard) | C16: masa | D16: 450 g Harina de trigo panificable (W 260, 12% proteína) (90%) | E16: Harina panificable de fuerza (W 280-300) | F16: 450 | G16: g | H16: =IFERROR(VLOOKUP(E16,Insumos!$C$5:$G$64,5,FALSE),0) | I16: =F16*H16
... A397: 103 | B397: C-3 · Pasta madre sólida 50% | C397: cultivo | D397: 50 ml Agua purificada · refresco de C-3 | E397: Agua purificada | F397: 50 | G397: ml | H397: =IFERROR(VLOOKUP(E397,Insumos!$C$5:$G$64,5,FALSE),0) | I397: =F397*H397

Sheet Mi negocio
A1: Mi negocio
A2: Los supuestos que mueven todo. Si estos números están mal, todos tus precios están mal.
B4: Gasto fijo mensual | C4: Monto | D4: Nota
B5: Renta del obrador | C5: 9000
B6: Luz, gas y cámara de frío | C6: 3400
B7: Agua y consumibles de limpieza | C7: 800
B8: Internet, telefonía y punto de venta | C8: 600
B9: Publicidad y contenido | C9: 1800
B10: Permisos, licencias y comisiones de plataforma | C10: 1200
B11: Mantenimiento de horno de vapor y amasadora | C11: 1400
B12: Depreciación (horno, amasadora, cámara, bannetons) | C12: 2600
B13: Mantenimiento del cultivo (harina de los refrescos) | C13: 450
B14: Otros gastos fijos | C14: 750
B17: Total de gastos fijos | C17: =SUM(C5:C16)
B19: Piezas producidos al mes | C19: 2400 | D19: ≈ 92 piezas al día en 26 días de operación. Ajusta este número a tu producción real.
B20: Gastos fijos por pieza (overhead) | C20: =IFERROR(C17/C19,0) | D20: Se suma al costo de cada pieza.
B21: Sueldo mensual que te pagas | C21: 19800
B22: Horas de trabajo al mes | C22: 180
B23: Costo de tu hora | C23: =IFERROR(C21/C22,0) | D23: Mano de obra = minutos ÷ 60 × costo de la hora.
B24: % de merma por defecto | C24: 0.05 | D24: Piezas planas, quemadas y sobrante del día. Compárala con tu merma real en el Tablero.
B25: Redondeo de precios (pesos) | C25: 5 | D25: Los precios suben al múltiplo superior de esta cifra.
B26: Márgenes objetivo por canal | C26: 24 | D26: Refrescar, amasar y plegar cuesta lo mismo con 4 piezas que con 40; formar, no. Éste es el número que más mueve tu costo de mano de obra.
B27: Margen · Mostrador y vitrina | C27: 0.58 | D27: Rango sugerido 55 – 65 %.
B28: Margen · Suscripción y preventa | C28: 0.52 | D28: Rango sugerido 48 – 58 %.
B29: Margen · Restaurante y hotel | C29: 0.4 | D29: Rango sugerido 35 – 45 %.
B30: Margen · Mayoreo a cafeterías | C30: 0.32 | D30: Rango sugerido 28 – 38 %.

Sheet Recetas y precios
A1: Recetas y precios
A2: Hoja principal. Cambia un precio en Insumos y los 50 precios se recalculan solos.
A4: Nº | B4: Receta | C4: Capítulo | D4: Bloque | E4: Hidrat. | F4: Proceso | G4: Unidad de venta | H4: Piezas que rinde | I4: Insumos del lote | J4: Insumos por pieza | K4: Empaque | L4: Energía por pieza | M4: Min. amasado (tanda) | N4: Min. formado (pieza) | O4: Mano de obra | P4: Gastos fijos | Q4: Costo base | R4: Merma propia | S4: Merma aplicada | T4: COSTO TOTAL | U4: PVP Mostrador y vitrina | V4: PVP Suscripción y preventa | W4: PVP Restaurante y hotel | X4: PVP Mayoreo a cafeterías
A5: 1 | B5: Hogaza Rústica Blanca Campestre (Country Loaf 75% Hidratación) | C5: Cap. 8 · Panes fundamentales de corteza noble | D5: F | E5: A | F5: L | G5: pieza | H5: 1 | I5: =SUMIF(Ingredientes!$A$5:$A$397,A5,Ingredientes!$I$5:$I$397) | J5: =IFERROR(I5/H5,0) | K5: 5 | L5: 2 | M5: 45 | N5: 6 | O5: =IFERROR((M5/MAX(1,'Mi negocio'!$C$26)+N5)/60*'Mi negocio'!$C$23,0) | P5: ='Mi negocio'!$C$20 | Q5: =J5+K5+L5+O5+P5 | S5: =IF(R5="",'Mi negocio'!$C$24,R5) | T5: =IFERROR(Q5/(1-S5),0) | U5: =IFERROR(CEILING(ROUND(T5/(1-'Mi negocio'!$C$27),6),'Mi negocio'!$C$25),0) | V5: =IFERROR(CEILING(ROUND(T5/(1-'Mi negocio'!$C$28),6),'Mi negocio'!$C$25),0) | W5: =IFERROR(CEILING(ROUND(T5/(1-'Mi negocio'!$C$29),6),'Mi negocio'!$C$25),0) | X5: =IFERROR(CEILING(ROUND(T5/(1-'Mi negocio'!$C$30),6),'Mi negocio'!$C$25),0)
A6: 2 | B6: Pan Campesino Tradicional con Centeno y Trigo Integral (Pain de Campagne) | C6: Cap. 8 · Panes fundamentales de corteza noble | D6: F | E6: M | F6: L | G6: pieza | H6: 1 | I6: =SUMIF(Ingredientes!$A$5:$A$397,A6,Ingredientes!$I$5:$I$397) | J6: =IFERROR(I6/H6,0) | K6: 5 | L6: 2 | M6: 45 | N6: 6 | O6: =IFERROR((M6/MAX(1,'Mi negocio'!$C$26)+N6)/60*'Mi negocio'!$C$23,0) | P6: ='Mi negocio'!$C$20 | Q6: =J6+K6+L6+O6+P6 | S6: =IF(R6="",'Mi negocio'!$C$24,R6) | T6: =IFERROR(Q6/(1-S6),0) | U6: =IFERROR(CEILING(ROUND(T6/(1-'Mi negocio'!$C$27),6),'Mi negocio'!$C$25),0) | V6: =IFERROR(CEILING(ROUND(T6/(1-'Mi negocio'!$C$28),6),'Mi negocio'!$C$25),0) | W6: =IFERROR(CEILING(ROUND(T6/(1-'Mi negocio'!$C$29),6),'Mi negocio'!$C$25),0) | X6: =IFERROR(CEILING(ROUND(T6/(1-'Mi negocio'!$C$30),6),'Mi negocio'!$C$25),0)
A7: 3 | B7: Barra Tradicional Rústica de Masa Madre (Formato Batard) | C7: Cap. 8 · Panes fundamentales de corteza noble | D7: F | E7: M | F7: L | G7: pieza | H7: 2 | I7: =SUMIF(Ingredientes!$A$5:$A$397,A7,Ingredientes!$I$5:$I$397) | J7: =IFERROR(I7/H7,0) | K7: 5 | L7: 2 | M7: 45 | N7: 5 | O7: =IFERROR((M7/MAX(1,'Mi negocio'!$C$26)+N7)/60*'Mi negocio'!$C$23,0) | P7: ='Mi negocio'!$C$20 | Q7: =J7+K7+L7+O7+P7 | S7: =IF(R7="",'Mi negocio'!$C$24,R7) | T7: =IFERROR(Q7/(1-S7),0) | U7: =IFERROR(CEILING(ROUND(T7/(1-'Mi negocio'!$C$27),6),'Mi negocio'!$C$25),0) | V7: =IFERROR(CEILING(ROUND(T7/(1-'Mi negocio'!$C$28),6),'Mi negocio'!$C$25),0) | W7: =IFERROR(CEILING(ROUND(T7/(1-'Mi negocio'!$C$29),6),'Mi negocio'!$C$25),0) | X7: =IFERROR(CEILING(ROUND(T7/(1-'Mi negocio'!$C$30),6),'Mi negocio'!$C$25),0)
A8: 4 | B8: Baguetín Clásico de Fermentación Lenta en Frío | C8: Cap. 8 · Panes fundamentales de corteza noble | D8: F | E8: M | F8: L | G8: pieza | H8: 4 | I8: =SUMIF(Ingredientes!$A$5:$A$397,A8,Ingredientes!$I$5:$I$397) | J8: =IFERROR(I8/H8,0) | K8: 5 | L8: 3 | M8: 50 | N8: 4 | O8: =IFERROR((M8/MAX(1,'Mi negocio'!$C$26)+N8)/60*'Mi negocio'!$C$23,0) | P8: ='Mi negocio'!$C$20 | Q8: =J8+K8+L8+O8+P8 | S8: =IF(R8="",'Mi negocio'!$C$24,R8) | T8: =IFERROR(Q8/(1-S8),0) | U8: =IFERROR(CEILING(ROUND(T8/(1-'Mi negocio'!$C$27),6),'Mi negocio'!$C$25),0) | V8: =IFERROR(CEILING(ROUND(T8/(1-'Mi negocio'!$C$28),6),'Mi negocio'!$C$25),0) | W8: =IFERROR(CEILING(ROUND(T8/(1-'Mi negocio'!$C$29),6),'Mi negocio'!$C$25),0) | X8: =IFERROR(CEILING(ROUND(T8/(1-'Mi negocio'!$C$30),6),'Mi negocio'!$C$25),0)
A9: 5 | B9: Chapatas Tradicionales de Alta Hidratación al 85% con Masa Madre (Ciabatta) | C9: Cap. 8 · Panes fundamentales de corteza noble | D9: F | E9: X | F9: L | G9: pieza | H9: 4 | I9: =SUMIF(Ingredientes!$A$5:$A$397,A9,Ingredientes!$I$5:$I$397) | J9: =IFERROR(I9/H9,0) | K9: 5 | L9: 3 | M9: 40 | N9: 3 | O9: =IFERROR((M9/MAX(1,'Mi negocio'!$C$26)+N9)/60*'Mi negocio'!$C$23,0) | P9: ='Mi negocio'!$C$20 | Q9: =J9+K9+L9+O9+P9 | S9: =IF(R9="",'Mi negocio'!$C$24,R9) | T9: =IFERROR(Q9/(1-S9),0) | U9: =IFERROR(CEILING(ROUND(T9/(1-'Mi negocio'!$C$27),6),'Mi negocio'!$C$25),0) | V9: =IFERROR(CEILING(ROUND(T9/(1-'Mi negocio'!$C$28),6),'Mi negocio'!$C$25),0) | W9: =IFERROR(CEILING(ROUND(T9/(1-'Mi negocio'!$C$29),6),'Mi negocio'!$C$25),0) | X9: =IFERROR(CEILING(ROUND(T9/(1-'Mi negocio'!$C$30),6),'Mi negocio'!$C$25),0)
A10: 6 | B10: Góndolas Venecianas de Corteza Crujiente (Pan de Formato Naval Alargado) | C10: Cap. 8 · Panes fundamentales de corteza noble | D10: F | E10: M | F10: L | G10: pieza | H10: 4 | I10: =SUMIF(Ingredientes!$A$5:$A$397,A10,Ingredientes!$I$5:$I$397) | J10: =IFERROR(I10/H10,0) | K10: 5 | L10: 2 | M10: 45 | N10: 4 | O10: =IFERROR((M10/MAX(1,'Mi negocio'!$C$26)+N10)/60*'Mi negocio'!$C$23,0) | P10: ='Mi negocio'!$C$20 | Q10: =J10+K10+L10+O10+P10 | S10: =IF(R10="",'Mi negocio'!$C$24,R10) | T10: =IFERROR(Q10/(1-S10),0) | U10: =IFERROR(CEILING(ROUND(T10/(1-'Mi negocio'!$C$27),6),'Mi negocio'!$C$25),0) | V10: =IFERROR(CEILING(ROUND(T10/(1-'Mi negocio'!$C$28),6),'Mi negocio'!$C$25),0) | W10: =IFERROR(CEILING(ROUND(T10/(1-'Mi negocio'!$C$29),6),'Mi negocio'!$C$25),0) | X10: =IFERROR(CEILING(ROUND(T10/(1-'Mi negocio'!$C$30),6),'Mi negocio'!$C$25),0)
A11: 7 | B11: Trenza Rústica de Tres Cabos de Masa Madre con Semillas Tostadas | C11: Cap. 8 · Panes fundamentales de corteza noble | D11: F | E11: M | F11: L | G11: pieza | H11: 2 | I11: =SUMIF(Ingredientes!$A$5:$A$397,A11,Ingredientes!$I$5:$I$397) | J11: =IFERROR(I11/H11,0) | K11: 5 | L11: 2 | M11: 50 | N11: 8 | O11: =IFERROR((M11/MAX(1,'Mi negocio'!$C$26)+N11)/60*'Mi negocio'!$C$23,0) | P11: ='Mi negocio'!$C$20 | Q11: =J11+K11+L11+O11+P11 | S11: =IF(R11="",'Mi negocio'!$C$24,R11) | T11: =IFERROR(Q11/(1-S11),0) | U11: =IFERROR(CEILING(ROUND(T11/(1-'Mi negocio'!$C$27),6),'Mi negocio'!$C$25),0) | V11: =IFERROR(CEILING(ROUND(T11/(1-'Mi negocio'!$C$28),6),'Mi negocio'!$C$25),0) | W11: =IFERROR(CEILING(ROUND(T11/(1-'Mi negocio'!$C$29),6),'Mi negocio'!$C$25),0) | X11: =IFERROR(CEILING(ROUND(T11/(1-'Mi negocio'!$C$30),6),'Mi negocio'!$C$25),0)
A12: 8 | B12: Baguette Tradicional Francesa 100% Levain (Sin Levadura Comercial) | C12: Cap. 8 · Panes fundamentales de corteza noble | D12: F | E12: M | F12: L | G12: pieza | H12: 3 | I12: =SUMIF(Ingredientes!$A$5:$A$397,A12,Ingredientes!$I$5:$I$397) | J12: =IFERROR(I12/H12,0) | K12: 5 | L12: 3 | M12: 55 | N12: 7 | O12: =IFERROR((M12/MAX(1,'Mi negocio'!$C$26)+N12)/60*'Mi negocio'!$C$23,0) | P12: ='Mi negocio'!$C$20 | Q12: =J12+K12+L12+O12+P12 | S12: =IF(R12="",'Mi negocio'!$C$24,R12) | T12: =IFERROR(Q12/(1-S12),0) | U12: =IFERROR(CEILING(ROUND(T12/(1-'Mi negocio'!$C$27),6),'Mi negocio'!$C$25),0) | V12: =IFERROR(CEILING(ROUND(T12/(1-'Mi negocio'!$C$28),6),'Mi negocio'!$C$25),0) | W12: =IFERROR(CEILING(ROUND(T12/(1-'Mi negocio'!$C$29),6),'Mi negocio'!$C$25),0) | X12: =IFERROR(CEILING(ROUND(T12/(1-'Mi negocio'!$C$30),6),'Mi negocio'!$C$25),0)
A13: 9 | B13: Hogaza Miche Tradicional de Molienda a la Piedra (Pain de Seigle et Blé) | C13: Cap. 8 · Panes fundamentales de corteza noble | D13: F | E13: A | F13: L | G13: pieza | H13: 1 | I13: =SUMIF(Ingredientes!$A$5:$A$397,A13,Ingredientes!$I$5:$I$397) | J13: =IFERROR(I13/H13,0) | K13: 5 | L13: 3 | M13: 50 | N13: 10 | O13: =IFERROR((M13/MAX(1,'Mi negocio'!$C$26)+N13)/60*'Mi negocio'!$C$23,0) | P13: ='Mi negocio'!$C$20 | Q13: =J13+K13+L13+O13+P13 | S13: =IF(R13="",'Mi negocio'!$C$24,R13) | T13: =IFERROR(Q13/(1-S13),0) | U13: =IFERROR(CEILING(ROUND(T13/(1-'Mi negocio'!$C$27),6),'Mi negocio'!$C$25),0) | V13: =IFERROR(CEILING(ROUND(T13/(1-'Mi negocio'!$C$28),6),'Mi negocio'!$C$25),0) | W13: =IFERROR(CEILING(ROUND(T13/(1-'Mi negocio'!$C$29),6),'Mi negocio'!$C$25),0) | X13: =IFERROR(CEILING(ROUND(T13/(1-'Mi negocio'!$C$30),6),'Mi negocio'!$C$25),0)
A14: 10 | B14: Fougasse Provenzal de Masa Madre con Aceite de Oliva y Hierbas | C14: Cap. 8 · Panes fundamentales de corteza noble | D14: F | E14: A | F14: L | G14: pieza | H14: 3 | I14: =SUMIF(Ingredientes!$A$5:$A$397,A14,Ingredientes!$I$5:$I$397) | J14: =IFERROR(I14/H14,0) | K14: 5 | L14: 2 | M14: 40 | N14: 6 | O14: =IFERROR((M14/MAX(1,'Mi negocio'!$C$26)+N14)/60*'Mi negocio'!$C$23,0) | P14: ='Mi negocio'!$C$20 | Q14: =J14+K14+L14+O14+P14 | S14: =IF(R14="",'Mi negocio'!$C$24,R14) | T14: =IFERROR(Q14/(1-S14),0) | U14: =IFERROR(CEILING(ROUND(T14/(1-'Mi negocio'!$C$27),6),'Mi negocio'!$C$25),0) | V14: =IFERROR(CEILING(ROUND(T14/(1-'Mi negocio'!$C$28),6),'Mi negocio'!$C$25),0) | W14: =IFERROR(CEILING(ROUND(T14/(1-'Mi negocio'!$C$29),6),'Mi negocio'!$C$25),0) | X14: =IFERROR(CEILING(ROUND(T14/(1-'Mi negocio'!$C$30),6),'Mi negocio'!$C$25),0)
A15: 11 | B15: Hogaza de Trigo Espelta 100% Integral de Molienda Fina (Triticum spelta) | C15: Cap. 9 · Cereales ancestrales e integrales puros | D15: A | E15: M | F15: L | G15: pieza | H15: 1 | I15: =SUMIF(Ingredientes!$A$5:$A$397,A15,Ingredientes!$I$5:$I$397) | J15: =IFERROR(I15/H15,0) | K15: 5 | L15: 2 | M15: 45 | N15: 6 | O15: =IFERROR((M15/MAX(1,'Mi negocio'!$C$26)+N15)/60*'Mi negocio'!$C$23,0) | P15: ='Mi negocio'!$C$20 | Q15: =J15+K15+L15+O15+P15 | S15: =IF(R15="",'Mi negocio'!$C$24,R15) | T15: =IFERROR(Q15/(1-S15),0) | U15: =IFERROR(CEILING(ROUND(T15/(1-'Mi negocio'!$C$27),6),'Mi negocio'!$C$25),0) | V15: =IFERROR(CEILING(ROUND(T15/(1-'Mi negocio'!$C$28),6),'Mi negocio'!$C$25),0) | W15: =IFERROR(CEILING(ROUND(T15/(1-'Mi negocio'!$C$29),6),'Mi negocio'!$C$25),0) | X15: =IFERROR(CEILING(ROUND(T15/(1-'Mi negocio'!$C$30),6),'Mi negocio'!$C$25),0)
A16: 12 | B16: Pan de Centeno Puro Tradicional del Norte (Rugbrød / Vollkornbrot 100% Centeno) | C16: Cap. 9 · Cereales ancestrales e integrales puros | D16: A | E16: X | F16: L | G16: pieza | H16: 1 | I16: =SUMIF(Ingredientes!$A$5:$A$397,A16,Ingredientes!$I$5:$I$397) | J16: =IFERROR(I16/H16,0) | K16: 5 | L16: 3 | M16: 55 | N16: 6 | O16: =IFERROR((M16/MAX(1,'Mi negocio'!$C$26)+N16)/60*'Mi negocio'!$C$23,0) | P16: ='Mi negocio'!$C$20 | Q16: =J16+K16+L16+O16+P16 | S16: =IF(R16="",'Mi negocio'!$C$24,R16) | T16: =IFERROR(Q16/(1-S16),0) | U16: =IFERROR(CEILING(ROUND(T16/(1-'Mi negocio'!$C$27),6),'Mi negocio'!$C$25),0) | V16: =IFERROR(CEILING(ROUND(T16/(1-'Mi negocio'!$C$28),6),'Mi negocio'!$C$25),0) | W16: =IFERROR(CEILING(ROUND(T16/(1-'Mi negocio'!$C$29),6),'Mi negocio'!$C$25),0) | X16: =IFERROR(CEILING(ROUND(T16/(1-'Mi negocio'!$C$30),6),'Mi negocio'!$C$25),0)
... A54: 50 | B54: Panettone de Chocolate Negro con Fermentación Biológica Pura (Sin Levadura Comercial) | C54: Cap. 12 · Panes del mundo y masas planas | D54: W | E54: B | F54: D | G54: pieza | H54: 2 | I54: =SUMIF(Ingredientes!$A$5:$A$397,A54,Ingredientes!$I$5:$I$397) | J54: =IFERROR(I54/H54,0) | K54: 38 | L54: 3 | M54: 90 | N54: 18 | O54: =IFERROR((M54/MAX(1,'Mi negocio'!$C$26)+N54)/60*'Mi negocio'!$C$23,0) | P54: ='Mi negocio'!$C$20 | Q54: =J54+K54+L54+O54+P54 | S54: =IF(R54="",'Mi negocio'!$C$24,R54) | T54: =IFERROR(Q54/(1-S54),0) | U54: =IFERROR(CEILING(ROUND(T54/(1-'Mi negocio'!$C$27),6),'Mi negocio'!$C$25),0) | V54: =IFERROR(CEILING(ROUND(T54/(1-'Mi negocio'!$C$28),6),'Mi negocio'!$C$25),0) | W54: =IFERROR(CEILING(ROUND(T54/(1-'Mi negocio'!$C$29),6),'Mi negocio'!$C$25),0) | X54: =IFERROR(CEILING(ROUND(T54/(1-'Mi negocio'!$C$30),6),'Mi negocio'!$C$25),0)
B56: Los minutos de amasado y manejo son por tanda completa y se reparten entre las piezas por tanda de Mi negocio; los de formado son por pieza y no bajan con la escala. Deja «Merma propia» vacía para usar la merma por defecto de Mi negocio. Bloque: F fundamentales · A ancestrales · E enriquecidos · M molde · W del mundo. Hidratación: B baja · M media · A alta · X muy alta. Proceso: L levain directo · D doble empaste · S con escaldado · P masa plana.

Sheet Producción
A1: Producción y merma
A2: Una fila por lote o tanda. La primera fila es un ejemplo: sobrescríbela.
A4: Fecha | B4: Lote | C4: Nº receta | D4: Receta | E4: Planeadas | F4: Buenas | G4: Falladas | H4: % merma | I4: Costo total unitario | J4: Costo de la merma | K4: Causa principal | L4: Notas
A5: 46298 | B5: L-2610-01 | C5: 1 | D5: =IF(C5="","",IFERROR(VLOOKUP(C5,'Recetas y precios'!$A$5:$B$54,2,FALSE),"")) | E5: 24 | F5: 23 | G5: 1 | H5: =IF((F5+G5)>0,G5/(F5+G5),"") | I5: =IF(C5="",0,IFERROR(VLOOKUP(C5,'Recetas y precios'!$A$5:$T$54,20,FALSE),0)) | J5: =G5*I5 | K5: Cultivo débil o sin punto pico | L5: Fila de ejemplo
D6: =IF(C6="","",IFERROR(VLOOKUP(C6,'Recetas y precios'!$A$5:$B$54,2,FALSE),"")) | H6: =IF((F6+G6)>0,G6/(F6+G6),"") | I6: =IF(C6="",0,IFERROR(VLOOKUP(C6,'Recetas y precios'!$A$5:$T$54,20,FALSE),0)) | J6: =G6*I6
D7: =IF(C7="","",IFERROR(VLOOKUP(C7,'Recetas y precios'!$A$5:$B$54,2,FALSE),"")) | H7: =IF((F7+G7)>0,G7/(F7+G7),"") | I7: =IF(C7="",0,IFERROR(VLOOKUP(C7,'Recetas y precios'!$A$5:$T$54,20,FALSE),0)) | J7: =G7*I7
D8: =IF(C8="","",IFERROR(VLOOKUP(C8,'Recetas y precios'!$A$5:$B$54,2,FALSE),"")) | H8: =IF((F8+G8)>0,G8/(F8+G8),"") | I8: =IF(C8="",0,IFERROR(VLOOKUP(C8,'Recetas y precios'!$A$5:$T$54,20,FALSE),0)) | J8: =G8*I8
D9: =IF(C9="","",IFERROR(VLOOKUP(C9,'Recetas y precios'!$A$5:$B$54,2,FALSE),"")) | H9: =IF((F9+G9)>0,G9/(F9+G9),"") | I9: =IF(C9="",0,IFERROR(VLOOKUP(C9,'Recetas y precios'!$A$5:$T$54,20,FALSE),0)) | J9: =G9*I9
D10: =IF(C10="","",IFERROR(VLOOKUP(C10,'Recetas y precios'!$A$5:$B$54,2,FALSE),"")) | H10: =IF((F10+G10)>0,G10/(F10+G10),"") | I10: =IF(C10="",0,IFERROR(VLOOKUP(C10,'Recetas y precios'!$A$5:$T$54,20,FALSE),0)) | J10: =G10*I10
D11: =IF(C11="","",IFERROR(VLOOKUP(C11,'Recetas y precios'!$A$5:$B$54,2,FALSE),"")) | H11: =IF((F11+G11)>0,G11/(F11+G11),"") | I11: =IF(C11="",0,IFERROR(VLOOKUP(C11,'Recetas y precios'!$A$5:$T$54,20,FALSE),0)) | J11: =G11*I11
D12: =IF(C12="","",IFERROR(VLOOKUP(C12,'Recetas y precios'!$A$5:$B$54,2,FALSE),"")) | H12: =IF((F12+G12)>0,G12/(F12+G12),"") | I12: =IF(C12="",0,IFERROR(VLOOKUP(C12,'Recetas y precios'!$A$5:$T$54,20,FALSE),0)) | J12: =G12*I12
D13: =IF(C13="","",IFERROR(VLOOKUP(C13,'Recetas y precios'!$A$5:$B$54,2,FALSE),"")) | H13: =IF((F13+G13)>0,G13/(F13+G13),"") | I13: =IF(C13="",0,IFERROR(VLOOKUP(C13,'Recetas y precios'!$A$5:$T$54,20,FALSE),0)) | J13: =G13*I13
D14: =IF(C14="","",IFERROR(VLOOKUP(C14,'Recetas y precios'!$A$5:$B$54,2,FALSE),"")) | H14: =IF((F14+G14)>0,G14/(F14+G14),"") | I14: =IF(C14="",0,IFERROR(VLOOKUP(C14,'Recetas y precios'!$A$5:$T$54,20,FALSE),0)) | J14: =G14*I14
D15: =IF(C15="","",IFERROR(VLOOKUP(C15,'Recetas y precios'!$A$5:$B$54,2,FALSE),"")) | H15: =IF((F15+G15)>0,G15/(F15+G15),"") | I15: =IF(C15="",0,IFERROR(VLOOKUP(C15,'Recetas y precios'!$A$5:$T$54,20,FALSE),0)) | J15: =G15*I15
D16: =IF(C16="","",IFERROR(VLOOKUP(C16,'Recetas y precios'!$A$5:$B$54,2,FALSE),"")) | H16: =IF((F16+G16)>0,G16/(F16+G16),"") | I16: =IF(C16="",0,IFERROR(VLOOKUP(C16,'Recetas y precios'!$A$5:$T$54,20,FALSE),0)) | J16: =G16*I16
D17: =IF(C17="","",IFERROR(VLOOKUP(C17,'Recetas y precios'!$A$5:$B$54,2,FALSE),"")) | H17: =IF((F17+G17)>0,G17/(F17+G17),"") | I17: =IF(C17="",0,IFERROR(VLOOKUP(C17,'Recetas y precios'!$A$5:$T$54,20,FALSE),0)) | J17: =G17*I17
... D304: =IF(C304="","",IFERROR(VLOOKUP(C304,'Recetas y precios'!$A$5:$B$54,2,FALSE),"")) | H304: =IF((F304+G304)>0,G304/(F304+G304),"") | I304: =IF(C304="",0,IFERROR(VLOOKUP(C304,'Recetas y precios'!$A$5:$T$54,20,FALSE),0)) | J304: =G304*I304

Sheet Ventas
A1: Ventas
A2: Una fila por venta. La primera fila es un ejemplo: sobrescríbela.
A4: Fecha | B4: Nº receta | C4: Receta | D4: Canal | E4: Piezas | F4: Precio unitario | G4: Ingreso | H4: Costo total | I4: Comisión % | J4: Comisión $ | K4: Utilidad neta | L4: Margen | M4: Cliente o nota
A5: 46298 | B5: 1 | C5: =IF(B5="","",IFERROR(VLOOKUP(B5,'Recetas y precios'!$A$5:$B$54,2,FALSE),"")) | D5: Mostrador y vitrina | E5: 6 | F5: 125 | G5: =E5*F5 | H5: =IF(B5="",0,E5*IFERROR(VLOOKUP(B5,'Recetas y precios'!$A$5:$T$54,20,FALSE),0)) | I5: 0 | J5: =G5*I5 | K5: =G5-H5-J5 | L5: =IF(G5>0,K5/G5,"") | M5: Fila de ejemplo
C6: =IF(B6="","",IFERROR(VLOOKUP(B6,'Recetas y precios'!$A$5:$B$54,2,FALSE),"")) | G6: =E6*F6 | H6: =IF(B6="",0,E6*IFERROR(VLOOKUP(B6,'Recetas y precios'!$A$5:$T$54,20,FALSE),0)) | J6: =G6*I6 | K6: =G6-H6-J6 | L6: =IF(G6>0,K6/G6,"")
C7: =IF(B7="","",IFERROR(VLOOKUP(B7,'Recetas y precios'!$A$5:$B$54,2,FALSE),"")) | G7: =E7*F7 | H7: =IF(B7="",0,E7*IFERROR(VLOOKUP(B7,'Recetas y precios'!$A$5:$T$54,20,FALSE),0)) | J7: =G7*I7 | K7: =G7-H7-J7 | L7: =IF(G7>0,K7/G7,"")
C8: =IF(B8="","",IFERROR(VLOOKUP(B8,'Recetas y precios'!$A$5:$B$54,2,FALSE),"")) | G8: =E8*F8 | H8: =IF(B8="",0,E8*IFERROR(VLOOKUP(B8,'Recetas y precios'!$A$5:$T$54,20,FALSE),0)) | J8: =G8*I8 | K8: =G8-H8-J8 | L8: =IF(G8>0,K8/G8,"")
C9: =IF(B9="","",IFERROR(VLOOKUP(B9,'Recetas y precios'!$A$5:$B$54,2,FALSE),"")) | G9: =E9*F9 | H9: =IF(B9="",0,E9*IFERROR(VLOOKUP(B9,'Recetas y precios'!$A$5:$T$54,20,FALSE),0)) | J9: =G9*I9 | K9: =G9-H9-J9 | L9: =IF(G9>0,K9/G9,"")
C10: =IF(B10="","",IFERROR(VLOOKUP(B10,'Recetas y precios'!$A$5:$B$54,2,FALSE),"")) | G10: =E10*F10 | H10: =IF(B10="",0,E10*IFERROR(VLOOKUP(B10,'Recetas y precios'!$A$5:$T$54,20,FALSE),0)) | J10: =G10*I10 | K10: =G10-H10-J10 | L10: =IF(G10>0,K10/G10,"")
C11: =IF(B11="","",IFERROR(VLOOKUP(B11,'Recetas y precios'!$A$5:$B$54,2,FALSE),"")) | G11: =E11*F11 | H11: =IF(B11="",0,E11*IFERROR(VLOOKUP(B11,'Recetas y precios'!$A$5:$T$54,20,FALSE),0)) | J11: =G11*I11 | K11: =G11-H11-J11 | L11: =IF(G11>0,K11/G11,"")
C12: =IF(B12="","",IFERROR(VLOOKUP(B12,'Recetas y precios'!$A$5:$B$54,2,FALSE),"")) | G12: =E12*F12 | H12: =IF(B12="",0,E12*IFERROR(VLOOKUP(B12,'Recetas y precios'!$A$5:$T$54,20,FALSE),0)) | J12: =G12*I12 | K12: =G12-H12-J12 | L12: =IF(G12>0,K12/G12,"")
C13: =IF(B13="","",IFERROR(VLOOKUP(B13,'Recetas y precios'!$A$5:$B$54,2,FALSE),"")) | G13: =E13*F13 | H13: =IF(B13="",0,E13*IFERROR(VLOOKUP(B13,'Recetas y precios'!$A$5:$T$54,20,FALSE),0)) | J13: =G13*I13 | K13: =G13-H13-J13 | L13: =IF(G13>0,K13/G13,"")
C14: =IF(B14="","",IFERROR(VLOOKUP(B14,'Recetas y precios'!$A$5:$B$54,2,FALSE),"")) | G14: =E14*F14 | H14: =IF(B14="",0,E14*IFERROR(VLOOKUP(B14,'Recetas y precios'!$A$5:$T$54,20,FALSE),0)) | J14: =G14*I14 | K14: =G14-H14-J14 | L14: =IF(G14>0,K14/G14,"")
C15: =IF(B15="","",IFERROR(VLOOKUP(B15,'Recetas y precios'!$A$5:$B$54,2,FALSE),"")) | G15: =E15*F15 | H15: =IF(B15="",0,E15*IFERROR(VLOOKUP(B15,'Recetas y precios'!$A$5:$T$54,20,FALSE),0)) | J15: =G15*I15 | K15: =G15-H15-J15 | L15: =IF(G15>0,K15/G15,"")
C16: =IF(B16="","",IFERROR(VLOOKUP(B16,'Recetas y precios'!$A$5:$B$54,2,FALSE),"")) | G16: =E16*F16 | H16: =IF(B16="",0,E16*IFERROR(VLOOKUP(B16,'Recetas y precios'!$A$5:$T$54,20,FALSE),0)) | J16: =G16*I16 | K16: =G16-H16-J16 | L16: =IF(G16>0,K16/G16,"")
C17: =IF(B17="","",IFERROR(VLOOKUP(B17,'Recetas y precios'!$A$5:$B$54,2,FALSE),"")) | G17: =E17*F17 | H17: =IF(B17="",0,E17*IFERROR(VLOOKUP(B17,'Recetas y precios'!$A$5:$T$54,20,FALSE),0)) | J17: =G17*I17 | K17: =G17-H17-J17 | L17: =IF(G17>0,K17/G17,"")
... C504: =IF(B504="","",IFERROR(VLOOKUP(B504,'Recetas y precios'!$A$5:$B$54,2,FALSE),"")) | G504: =E504*F504 | H504: =IF(B504="",0,E504*IFERROR(VLOOKUP(B504,'Recetas y precios'!$A$5:$T$54,20,FALSE),0)) | J504: =G504*I504 | K504: =G504-H504-J504 | L504: =IF(G504>0,K504/G504,"")

Sheet Tablero
A1: Tablero
A2: Resumen automático de Ventas y Producción. No se edita.
B3: Ventas | E3: Canal | F3: Ingreso | G3: Piezas
B4: Ingreso acumulado | C4: =SUM(Ventas!G5:G504) | E4: Mostrador y vitrina | F4: =SUMIF(Ventas!$D$5:$D$504,E4,Ventas!$G$5:$G$504) | G4: =SUMIF(Ventas!$D$5:$D$504,E4,Ventas!$E$5:$E$504)
B5: Piezas vendidos | C5: =SUM(Ventas!E5:E504) | E5: Suscripción y preventa | F5: =SUMIF(Ventas!$D$5:$D$504,E5,Ventas!$G$5:$G$504) | G5: =SUMIF(Ventas!$D$5:$D$504,E5,Ventas!$E$5:$E$504)
B6: Costo de lo vendido | C6: =SUM(Ventas!H5:H504) | E6: Restaurante y hotel | F6: =SUMIF(Ventas!$D$5:$D$504,E6,Ventas!$G$5:$G$504) | G6: =SUMIF(Ventas!$D$5:$D$504,E6,Ventas!$E$5:$E$504)
B7: Comisiones | C7: =SUM(Ventas!J5:J504) | E7: Mayoreo a cafeterías | F7: =SUMIF(Ventas!$D$5:$D$504,E7,Ventas!$G$5:$G$504) | G7: =SUMIF(Ventas!$D$5:$D$504,E7,Ventas!$E$5:$E$504)
B8: Utilidad neta (antes de gastos fijos) | C8: =SUM(Ventas!K5:K504) | E8: Degustación o cortesía | F8: =SUMIF(Ventas!$D$5:$D$504,E8,Ventas!$G$5:$G$504) | G8: =SUMIF(Ventas!$D$5:$D$504,E8,Ventas!$E$5:$E$504)
B9: Margen neto | C9: =IFERROR(C8/C4,0)
B10: Utilidad después de gastos fijos | C10: =C8-'Mi negocio'!C17
B11: Producción y merma | E11: Preparación base | F11: Costo del lote | G11: Costo unitario
B12: Piezas buenos producidos | C12: =SUM(Producción!F5:F304) | E12: C-1 · Masa madre blanca activa 100% | F12: ='Cultivos'!F5 | G12: ='Cultivos'!G5
B13: Piezas fallados | C13: =SUM(Producción!G5:G304) | E13: C-2 · Masa madre de centeno o integral 100% | F13: ='Cultivos'!F6 | G13: ='Cultivos'!G6
B14: Merma real | C14: =IFERROR(C13/(C12+C13),0) | E14: C-3 · Pasta madre sólida 50% | F14: ='Cultivos'!F7 | G14: ='Cultivos'!G7
B15: Merma supuesta | C15: ='Mi negocio'!$C$24
B16: Dinero perdido en merma | C16: =SUM(Producción!J5:J304)
B17: Punto de equilibrio
B18: Precio promedio · Mostrador y vitrina | C18: =AVERAGE('Recetas y precios'!$U$5:$U$54)
B19: Costo total promedio (recetario) | C19: =AVERAGE('Recetas y precios'!$T$5:$T$54)
B20: Margen de contribución promedio | C20: =C18-C19
B21: Margen de contribución real de tus ventas | C21: =IFERROR((C4-C6-C7)/C5,0) | D21: ← | E21: En cuanto registres ventas reales, el equilibrio usa tu margen real, no el promedio del recetario.
B22: Gastos fijos del mes | C22: ='Mi negocio'!C17
B23: PUNTO DE EQUILIBRIO (piezas al mes) | C23: =IFERROR(ROUNDUP(C22/IF(C21>0,C21,C20),0),0)
B24: Avance contra el punto de equilibrio | C24: =IFERROR(C5/C23,0)
B28: Endulcora · Estudio Gastronómico · En colaboración con Levent · Masa Madre · Anexo 1
