Workbook

Sheet LÉEME
A1: Tiramisú Douyin · Ingeniería de Cremas Fluidas, Texturas de Lava y Formatos Virales
A2: Anexo 1 · Costeo, merma y precios · Endulcora · Estudio Gastronómico · En colaboración con Levent
A4: • | B4: Qué es: Hoja de costeo del eBook «Tiramisú Douyin». Calcula el costo real de las 51 recetas y su precio por canal con tus propios precios.
A5: • | B5: Cómo se usa: 1) Insumos: captura presentación y precio que tú pagas (empieza por mascarpone y crema para batir: son el 70 % del costo). 2) Mi negocio: gastos fijos, sueldo, horas, merma y márgenes. 3) Recetas y precios: revisa costos y precios (se recalculan solos). 4) Registra lotes en Producción y ventas en Ventas. 5) Revisa el Tablero cada semana.
A6: • | B6: Celdas amarillas: Son las únicas que debes editar. Todo lo demás es fórmula: si la borras, se rompe el cálculo.
A7: • | B7: Modelo de costeo: Costo por unidad = Precio ÷ Presentación · Costo del componente = Σ(cantidad × costo unitario) × factor de uso · Insumos por porción = lote ÷ porciones · Costo base = insumos + empaque + energía + mano de obra + gastos fijos · Costo total = Costo base ÷ (1 − merma) (se DIVIDE, no se suma) · Precio = Costo total ÷ (1 − margen), redondeado a los $5 superiores.
A8: • | B8: Factor de uso: Un molde de chiffon rinde 4 discos y la receta usa 2; un jarabe rinde más de lo que el postre absorbe. Por eso el bizcocho y el jarabe se cargan solo en la fracción que entra al postre (columnas amarillas en Recetas y precios). La crema y los acabados se elaboran a la medida: factor 1.
A9: • | B9: Hojas: Insumos (catálogo editable) · Componentes (fórmulas maestras y formatos de ensamble) · Ingredientes (cada línea del recetario normalizada, con el texto original del chef) · Mi negocio (supuestos) · Recetas y precios (hoja principal) · Producción (bitácora de lotes y merma) · Ventas (bitácora) · Tablero (resumen).
A10: • | B10: Unidades: Todas las recetas rinden 2 porciones individuales de 330 a 390 g. El costeo es por porción.
A11: • | B11: Advertencia: Los precios cargados son de referencia (mercado CDMX 2026), no cotizaciones. Los resultados son ilustrativos hasta que captures tus precios reales. No se promete ningún ingreso.
A12: • | B12: Créditos: Contenido y recetas: Chef Luis Alfonso Jiménez Cárdenas · Edición y costeo: Manuel Ramiro Justo Guzmán · Endulcora · Estudio Gastronómico, en colaboración con Levent · WhatsApp 56 6527 1901. Uso personal del comprador; prohibida su reventa o redistribución.
B14: Celda de ejemplo que sí puedes editar → | C14: 100

Sheet Insumos
A1: Insumos
A2: Captura la presentación que compras y lo que pagas. Precios de referencia CDMX 2026 (no son cotizaciones).
A4: ID | B4: Categoría | C4: Insumo | D4: Unidad | E4: Presentación | F4: Precio pagado | G4: Costo por unidad | H4: Usos | I4: Proveedor
A5: I-001 | B5: Lácteos y huevo | C5: Queso mascarpone | D5: g | E5: 1000 | F5: 380 | G5: =IFERROR(F5/E5,0) -> 0.38 | H5: =COUNTIF(Ingredientes!$F:$F,C5) -> 51
A6: I-002 | B6: Lácteos y huevo | C6: Queso crema tipo Philadelphia | D6: g | E6: 1000 | F6: 195 | G6: =IFERROR(F6/E6,0) -> 0.195 | H6: =COUNTIF(Ingredientes!$F:$F,C6) -> 3
A7: I-003 | B7: Lácteos y huevo | C7: Queso crema artesanal de rancho | D7: g | E7: 1000 | F7: 150 | G7: =IFERROR(F7/E7,0) -> 0.15 | H7: =COUNTIF(Ingredientes!$F:$F,C7) -> 1
A8: I-004 | B8: Lácteos y huevo | C8: Crema para batir 35% M.G. | D8: ml | E8: 1000 | F8: 78 | G8: =IFERROR(F8/E8,0) -> 0.078 | H8: =COUNTIF(Ingredientes!$F:$F,C8) -> 56
A9: I-005 | B9: Lácteos y huevo | C9: Leche condensada | D9: g | E9: 1000 | F9: 85 | G9: =IFERROR(F9/E9,0) -> 0.085 | H9: =COUNTIF(Ingredientes!$F:$F,C9) -> 54
A10: I-006 | B10: Lácteos y huevo | C10: Leche evaporada | D10: ml | E10: 1000 | F10: 60 | G10: =IFERROR(F10/E10,0) -> 0.06 | H10: =COUNTIF(Ingredientes!$F:$F,C10) -> 2
A11: I-007 | B11: Lácteos y huevo | C11: Leche entera | D11: ml | E11: 1000 | F11: 28 | G11: =IFERROR(F11/E11,0) -> 0.028 | H11: =COUNTIF(Ingredientes!$F:$F,C11) -> 18
A12: I-008 | B12: Lácteos y huevo | C12: Leche entera en polvo | D12: g | E12: 1000 | F12: 190 | G12: =IFERROR(F12/E12,0) -> 0.19 | H12: =COUNTIF(Ingredientes!$F:$F,C12) -> 1
A13: I-009 | B13: Lácteos y huevo | C13: Polvo de leche malteada | D13: g | E13: 1000 | F13: 260 | G13: =IFERROR(F13/E13,0) -> 0.26 | H13: =COUNTIF(Ingredientes!$F:$F,C13) -> 2
A14: I-010 | B14: Lácteos y huevo | C14: Mantequilla sin sal | D14: g | E14: 1000 | F14: 330 | G14: =IFERROR(F14/E14,0) -> 0.33 | H14: =COUNTIF(Ingredientes!$F:$F,C14) -> 5
A15: I-011 | B15: Lácteos y huevo | C15: Yemas de huevo pasteurizadas | D15: g | E15: 1000 | F15: 130 | G15: =IFERROR(F15/E15,0) -> 0.13 | H15: =COUNTIF(Ingredientes!$F:$F,C15) -> 32
A16: I-012 | B16: Lácteos y huevo | C16: Claras de huevo pasteurizadas | D16: g | E16: 1000 | F16: 75 | G16: =IFERROR(F16/E16,0) -> 0.075 | H16: =COUNTIF(Ingredientes!$F:$F,C16) -> 32
... A143: I-139 | B143: Licores | C143: Vinagre balsámico de Módena IGP | D143: ml | E143: 250 | F143: 180 | G143: =IFERROR(F143/E143,0) -> 0.72 | H143: =COUNTIF(Ingredientes!$F:$F,C143) -> 2

Sheet Componentes
A1: Componentes madre y formatos de ensamble
A2: Las cuatro fórmulas maestras del Capítulo 3 y el empaque de cada formato. El empaque alimenta la hoja Recetas y precios.
A4: Código | B4: Componente madre | C4: Qué controla | D4: Costo medio por porción | E4: % del costo de insumos
A5: B | B5: Bizcocho chiffon asiático | C5: Bizcocho de aceite y agua, sin mantequilla: merengue francés flexible, miga elástica que absorbe jarabe sin desmoronarse. | D5: =IFERROR(SUMIF(Ingredientes!$C:$C,"bizcocho",Ingredientes!$K:$K)/SUM('Recetas y precios'!$E$5:$E$55),0) -> 2.9075197 | E5: =IFERROR(D5/SUM($D$5:$D$8),0) -> 0.04194796
A6: J | B6: Jarabe de imbibición (punch) | C6: Líquido aromático azucarado que hidrata el bizcocho en proporción 1:1 en peso, sin dejar charco en el fondo. | D6: =IFERROR(SUMIF(Ingredientes!$C:$C,"jarabe",Ingredientes!$K:$K)/SUM('Recetas y precios'!$E$5:$E$55),0) -> 5.5755027 | E6: =IFERROR(D6/SUM($D$5:$D$8),0) -> 0.080440028
A7: C | B7: Crema fluida de mascarpone | C7: Emulsión de mascarpone, crema al 35 % y leche condensada montada solo al 50–60 %: la textura de lava. | D7: =IFERROR(SUMIF(Ingredientes!$C:$C,"crema",Ingredientes!$K:$K)/SUM('Recetas y precios'!$E$5:$E$55),0) -> 48.491201 | E7: =IFERROR(D7/SUM($D$5:$D$8),0) -> 0.69960213
A8: A | B8: Acabados y texturas | C8: Polvos micronizados, crujientes, craquelados y coberturas que rematan y dan el contraste de textura. | D8: =IFERROR(SUMIF(Ingredientes!$C:$C,"acabado",Ingredientes!$K:$K)/SUM('Recetas y precios'!$E$5:$E$55),0) -> 12.338317 | E8: =IFERROR(D8/SUM($D$5:$D$8),0) -> 0.17800988
A10: Código | B10: Formato de ensamble | C10: Descripción | D10: Empaque por porción | E10: Nº recetas
A11: F-1 | B11: Aro de acetato · cascada | C11: Cilindro de acetato de 10 × 10 cm que se retira frente al comensal: el efecto Liú Xīn. | D11: 9 | E11: =COUNTIF('Recetas y precios'!$D:$D,A11) -> 26
A12: F-2 | B12: Caja bento acrílica | C12: Caja transparente de 10 × 10 cm; se rompe la cubierta craquelada o se sirve con cuchara desde la tapa. | D12: 16 | E12: =COUNTIF('Recetas y precios'!$D:$D,A12) -> 14
A13: F-3 | B13: Vaso o copa domo | C13: Montaje por capas visibles a través del vidrio; no se desmolda, se come directo. | D13: 12 | E13: =COUNTIF('Recetas y precios'!$D:$D,A13) -> 10
A14: F-4 | B14: Molde, tarta o formato especial | C14: Piezas horneadas o cortadas que se presentan en plato o molde desmontable. | D14: 11 | E14: =COUNTIF('Recetas y precios'!$D:$D,A14) -> 1
A17: Fórmula maestra · Chiffon base (molde 18 cm, 4 discos)
B18: Insumo | C18: Cantidad | D18: Unidad | E18: Costo unitario | F18: Costo | G18: Nota
B19: Harina baja en proteína (pastelera) | C19: 50 | D19: g | E19: =IFERROR(VLOOKUP(B19,Insumos!$C$5:$G$143,5,FALSE()),0) -> 0.032 | F19: =C19*E19 -> 1.6
B20: Yemas de huevo pasteurizadas | C20: 35 | D20: g | E20: =IFERROR(VLOOKUP(B20,Insumos!$C$5:$G$143,5,FALSE()),0) -> 0.13 | F20: =C20*E20 -> 4.55
B21: Claras de huevo pasteurizadas | C21: 75 | D21: g | E21: =IFERROR(VLOOKUP(B21,Insumos!$C$5:$G$143,5,FALSE()),0) -> 0.075 | F21: =C21*E21 -> 5.625
B22: Azúcar refinada | C22: 40 | D22: g | E22: =IFERROR(VLOOKUP(B22,Insumos!$C$5:$G$143,5,FALSE()),0) -> 0.028 | F22: =C22*E22 -> 1.12
B23: Aceite vegetal neutro | C23: 25 | D23: ml | E23: =IFERROR(VLOOKUP(B23,Insumos!$C$5:$G$143,5,FALSE()),0) -> 0.045 | F23: =C23*E23 -> 1.125
B24: Leche entera | C24: 35 | D24: ml | E24: =IFERROR(VLOOKUP(B24,Insumos!$C$5:$G$143,5,FALSE()),0) -> 0.028 | F24: =C24*E24 -> 0.98
B25: Sal fina | C25: 1 | D25: g | E25: =IFERROR(VLOOKUP(B25,Insumos!$C$5:$G$143,5,FALSE()),0) -> 0.025 | F25: =C25*E25 -> 0.025
B26: Crémor tártaro | C26: 1 | D26: g | E26: =IFERROR(VLOOKUP(B26,Insumos!$C$5:$G$143,5,FALSE()),0) -> 0.48 | F26: =C26*E26 -> 0.48
B27: Costo de la tanda | F27: =SUM(F19:F26) -> 15.505 | G27: Horno 150 °C, 30–35 min · enfriar boca abajo · discos de 9 cm
A29: Fórmula maestra · Crema fluida Douyin (2 porciones)
B30: Insumo | C30: Cantidad | D30: Unidad | E30: Costo unitario | F30: Costo | G30: Nota
B31: Queso mascarpone | C31: 180 | D31: g | E31: =IFERROR(VLOOKUP(B31,Insumos!$C$5:$G$143,5,FALSE()),0) -> 0.38 | F31: =C31*E31 -> 68.4
B32: Crema para batir 35% M.G. | C32: 180 | D32: ml | E32: =IFERROR(VLOOKUP(B32,Insumos!$C$5:$G$143,5,FALSE()),0) -> 0.078 | F32: =C32*E32 -> 14.04
B33: Leche condensada | C33: 45 | D33: g | E33: =IFERROR(VLOOKUP(B33,Insumos!$C$5:$G$143,5,FALSE()),0) -> 0.085 | F33: =C33*E33 -> 3.825
B34: Azúcar glas | C34: 20 | D34: g | E34: =IFERROR(VLOOKUP(B34,Insumos!$C$5:$G$143,5,FALSE()),0) -> 0.045 | F34: =C34*E34 -> 0.9
B35: Sal fina | C35: 1 | D35: g | E35: =IFERROR(VLOOKUP(B35,Insumos!$C$5:$G$143,5,FALSE()),0) -> 0.025 | F35: =C35*E35 -> 0.025
B36: Costo de la tanda | F36: =SUM(F31:F35) -> 87.19 | G36: Montar a 50–60 % · prueba de la cinta continua
A38: Fórmula maestra · Jarabe de imbibición (2 porciones)
B39: Insumo | C39: Cantidad | D39: Unidad | E39: Costo unitario | F39: Costo | G39: Nota
B40: Café espresso o filtrado preparado | C40: 50 | D40: ml | E40: =IFERROR(VLOOKUP(B40,Insumos!$C$5:$G$143,5,FALSE()),0) -> 0.145 | F40: =C40*E40 -> 7.25
B41: Jarabe simple 50/50 (elaborado) | C41: 20 | D41: ml | E41: =IFERROR(VLOOKUP(B41,Insumos!$C$5:$G$143,5,FALSE()),0) -> 0.018 | F41: =C41*E41 -> 0.36
B42: Licor de café (Kahlúa) | C42: 5 | D42: ml | E42: =IFERROR(VLOOKUP(B42,Insumos!$C$5:$G$143,5,FALSE()),0) -> 0.42666667 | F42: =C42*E42 -> 2.1333333
B43: Costo de la tanda | F43: =SUM(F40:F42) -> 9.7433333 | G43: Templar a 15–20 °C · imbibición 1:1 en peso
A45: Las fórmulas maestras son la mediana de las 51 fichas del chef, calculada por la edición: sirven como base para crear recetas nuevas.

Sheet Ingredientes
A1: Ingredientes
A2: Cada línea del recetario normalizada a un insumo del catálogo, con el texto original del chef al lado para auditarla.
A4: Nº | B4: Receta | C4: Componente | D4: Grupo del chef | E4: Texto original del chef | F4: Insumo | G4: Cantidad | H4: Unidad | I4: Costo unitario | J4: Factor de uso | K4: Costo
A5: 1 | B5: Tiramisú Clásico de Cascada Douyin (Pull-Me-Up Lava Tiramisu) | C5: bizcocho | D5: Para el Bizcocho Chiffon de Vainilla (molde 18 cm, rinde para 4 discos) | E5: 60 g Harina de trigo baja en proteína (harina para repostería o pastelera) | F5: Harina baja en proteína (pastelera) | G5: 60 | H5: g | I5: =IFERROR(VLOOKUP(F5,Insumos!$C$5:$G$143,5,FALSE()),0) -> 0.032 | J5: =IF(C5="bizcocho",VLOOKUP(A5,'Recetas y precios'!$A$5:$G$55,6,FALSE()),IF(C5="jarabe",VLOOKUP(A5,'Recetas y precios'!$A$5:$G$55,7,FALSE()),1)) -> 0.309 | K5: =G5*I5*J5 -> 0.59328
A6: 1 | B6: Tiramisú Clásico de Cascada Douyin (Pull-Me-Up Lava Tiramisu) | C6: bizcocho | D6: Para el Bizcocho Chiffon de Vainilla (molde 18 cm, rinde para 4 discos) | E6: 40 g Yemas de huevo pasteurizadas | F6: Yemas de huevo pasteurizadas | G6: 40 | H6: g | I6: =IFERROR(VLOOKUP(F6,Insumos!$C$5:$G$143,5,FALSE()),0) -> 0.13 | J6: =IF(C6="bizcocho",VLOOKUP(A6,'Recetas y precios'!$A$5:$G$55,6,FALSE()),IF(C6="jarabe",VLOOKUP(A6,'Recetas y precios'!$A$5:$G$55,7,FALSE()),1)) -> 0.309 | K6: =G6*I6*J6 -> 1.6068
A7: 1 | B7: Tiramisú Clásico de Cascada Douyin (Pull-Me-Up Lava Tiramisu) | C7: bizcocho | D7: Para el Bizcocho Chiffon de Vainilla (molde 18 cm, rinde para 4 discos) | E7: 80 g Claras de huevo a 4 °C | F7: Claras de huevo pasteurizadas | G7: 80 | H7: g | I7: =IFERROR(VLOOKUP(F7,Insumos!$C$5:$G$143,5,FALSE()),0) -> 0.075 | J7: =IF(C7="bizcocho",VLOOKUP(A7,'Recetas y precios'!$A$5:$G$55,6,FALSE()),IF(C7="jarabe",VLOOKUP(A7,'Recetas y precios'!$A$5:$G$55,7,FALSE()),1)) -> 0.309 | K7: =G7*I7*J7 -> 1.854
A8: 1 | B8: Tiramisú Clásico de Cascada Douyin (Pull-Me-Up Lava Tiramisu) | C8: bizcocho | D8: Para el Bizcocho Chiffon de Vainilla (molde 18 cm, rinde para 4 discos) | E8: 40 g Azúcar refinada (para el merengue) | F8: Azúcar refinada | G8: 40 | H8: g | I8: =IFERROR(VLOOKUP(F8,Insumos!$C$5:$G$143,5,FALSE()),0) -> 0.028 | J8: =IF(C8="bizcocho",VLOOKUP(A8,'Recetas y precios'!$A$5:$G$55,6,FALSE()),IF(C8="jarabe",VLOOKUP(A8,'Recetas y precios'!$A$5:$G$55,7,FALSE()),1)) -> 0.309 | K8: =G8*I8*J8 -> 0.34608
A9: 1 | B9: Tiramisú Clásico de Cascada Douyin (Pull-Me-Up Lava Tiramisu) | C9: bizcocho | D9: Para el Bizcocho Chiffon de Vainilla (molde 18 cm, rinde para 4 discos) | E9: 30 ml Aceite vegetal de maíz o girasol | F9: Aceite vegetal neutro | G9: 30 | H9: ml | I9: =IFERROR(VLOOKUP(F9,Insumos!$C$5:$G$143,5,FALSE()),0) -> 0.045 | J9: =IF(C9="bizcocho",VLOOKUP(A9,'Recetas y precios'!$A$5:$G$55,6,FALSE()),IF(C9="jarabe",VLOOKUP(A9,'Recetas y precios'!$A$5:$G$55,7,FALSE()),1)) -> 0.309 | K9: =G9*I9*J9 -> 0.41715
A10: 1 | B10: Tiramisú Clásico de Cascada Douyin (Pull-Me-Up Lava Tiramisu) | C10: bizcocho | D10: Para el Bizcocho Chiffon de Vainilla (molde 18 cm, rinde para 4 discos) | E10: 35 ml Leche entera | F10: Leche entera | G10: 35 | H10: ml | I10: =IFERROR(VLOOKUP(F10,Insumos!$C$5:$G$143,5,FALSE()),0) -> 0.028 | J10: =IF(C10="bizcocho",VLOOKUP(A10,'Recetas y precios'!$A$5:$G$55,6,FALSE()),IF(C10="jarabe",VLOOKUP(A10,'Recetas y precios'!$A$5:$G$55,7,FALSE()),1)) -> 0.309 | K10: =G10*I10*J10 -> 0.30282
A11: 1 | B11: Tiramisú Clásico de Cascada Douyin (Pull-Me-Up Lava Tiramisu) | C11: bizcocho | D11: Para el Bizcocho Chiffon de Vainilla (molde 18 cm, rinde para 4 discos) | E11: 4 ml Extracto puro de vainilla | F11: Extracto de vainilla | G11: 4 | H11: ml | I11: =IFERROR(VLOOKUP(F11,Insumos!$C$5:$G$143,5,FALSE()),0) -> 0.45 | J11: =IF(C11="bizcocho",VLOOKUP(A11,'Recetas y precios'!$A$5:$G$55,6,FALSE()),IF(C11="jarabe",VLOOKUP(A11,'Recetas y precios'!$A$5:$G$55,7,FALSE()),1)) -> 0.309 | K11: =G11*I11*J11 -> 0.5562
A12: 1 | B12: Tiramisú Clásico de Cascada Douyin (Pull-Me-Up Lava Tiramisu) | C12: bizcocho | D12: Para el Bizcocho Chiffon de Vainilla (molde 18 cm, rinde para 4 discos) | E12: 1 g Sal fina | F12: Sal fina | G12: 1 | H12: g | I12: =IFERROR(VLOOKUP(F12,Insumos!$C$5:$G$143,5,FALSE()),0) -> 0.025 | J12: =IF(C12="bizcocho",VLOOKUP(A12,'Recetas y precios'!$A$5:$G$55,6,FALSE()),IF(C12="jarabe",VLOOKUP(A12,'Recetas y precios'!$A$5:$G$55,7,FALSE()),1)) -> 0.309 | K12: =G12*I12*J12 -> 0.007725
A13: 1 | B13: Tiramisú Clásico de Cascada Douyin (Pull-Me-Up Lava Tiramisu) | C13: bizcocho | D13: Para el Bizcocho Chiffon de Vainilla (molde 18 cm, rinde para 4 discos) | E13: 1 g Crémor tártaro | F13: Crémor tártaro | G13: 1 | H13: g | I13: =IFERROR(VLOOKUP(F13,Insumos!$C$5:$G$143,5,FALSE()),0) -> 0.48 | J13: =IF(C13="bizcocho",VLOOKUP(A13,'Recetas y precios'!$A$5:$G$55,6,FALSE()),IF(C13="jarabe",VLOOKUP(A13,'Recetas y precios'!$A$5:$G$55,7,FALSE()),1)) -> 0.309 | K13: =G13*I13*J13 -> 0.14832
A14: 1 | B14: Tiramisú Clásico de Cascada Douyin (Pull-Me-Up Lava Tiramisu) | C14: jarabe | D14: Para el Jarabe de Café Espresso (Punch) | E14: 60 ml Café espresso doble recién extraído (tueste medio-oscuro) | F14: Café espresso o filtrado preparado | G14: 60 | H14: ml | I14: =IFERROR(VLOOKUP(F14,Insumos!$C$5:$G$143,5,FALSE()),0) -> 0.145 | J14: =IF(C14="bizcocho",VLOOKUP(A14,'Recetas y precios'!$A$5:$G$55,6,FALSE()),IF(C14="jarabe",VLOOKUP(A14,'Recetas y precios'!$A$5:$G$55,7,FALSE()),1)) -> 0.762 | K14: =G14*I14*J14 -> 6.6294
A15: 1 | B15: Tiramisú Clásico de Cascada Douyin (Pull-Me-Up Lava Tiramisu) | C15: jarabe | D15: Para el Jarabe de Café Espresso (Punch) | E15: 20 ml Agua purificada | F15: Agua purificada | G15: 20 | H15: ml | I15: =IFERROR(VLOOKUP(F15,Insumos!$C$5:$G$143,5,FALSE()),0) -> 0.002 | J15: =IF(C15="bizcocho",VLOOKUP(A15,'Recetas y precios'!$A$5:$G$55,6,FALSE()),IF(C15="jarabe",VLOOKUP(A15,'Recetas y precios'!$A$5:$G$55,7,FALSE()),1)) -> 0.762 | K15: =G15*I15*J15 -> 0.03048
A16: 1 | B16: Tiramisú Clásico de Cascada Douyin (Pull-Me-Up Lava Tiramisu) | C16: jarabe | D16: Para el Jarabe de Café Espresso (Punch) | E16: 15 g Azúcar refinada | F16: Azúcar refinada | G16: 15 | H16: g | I16: =IFERROR(VLOOKUP(F16,Insumos!$C$5:$G$143,5,FALSE()),0) -> 0.028 | J16: =IF(C16="bizcocho",VLOOKUP(A16,'Recetas y precios'!$A$5:$G$55,6,FALSE()),IF(C16="jarabe",VLOOKUP(A16,'Recetas y precios'!$A$5:$G$55,7,FALSE()),1)) -> 0.762 | K16: =G16*I16*J16 -> 0.32004
... A859: 51 | B859: Tiramisú Imperial de Hoja de Oro 24K con Vainilla Bourbon de Madagascar | C859: acabado | D859: Para el Núcleo y Acabado | E859: 2 Hojas completas de oro puro comestible de 24 quilates (transferible con pinza de repostería) | F859: Hoja de oro comestible 24K | G859: 2 | H859: pz | I859: =IFERROR(VLOOKUP(F859,Insumos!$C$5:$G$143,5,FALSE()),0) -> 90 | J859: =IF(C859="bizcocho",VLOOKUP(A859,'Recetas y precios'!$A$5:$G$55,6,FALSE()),IF(C859="jarabe",VLOOKUP(A859,'Recetas y precios'!$A$5:$G$55,7,FALSE()),1)) -> 1 | K859: =G859*I859*J859 -> 180

Sheet Mi negocio
A1: Mi negocio
A2: Los supuestos que mueven todo. Si estos números están mal, todos tus precios están mal.
B4: Gasto fijo mensual | C4: Monto | D4: Nota
B5: Renta de la cocina de producción | C5: 5500
B6: Luz (refrigeración y horno) | C6: 1600
B7: Agua y gas | C7: 600
B8: Internet y telefonía | C8: 450
B9: Publicidad y contenido para redes | C9: 1800
B10: Permisos, cuotas y comisiones de plataforma | C10: 900
B11: Mantenimiento de equipo | C11: 500
B12: Depreciación de equipo (batidora, abatidor, refrigeración) | C12: 1200
B13: Limpieza y consumibles generales | C13: 600
B14: Otros gastos fijos | C14: 700
B17: Total de gastos fijos | C17: =SUM(C5:C16) -> 13850
B19: Porciones producidas al mes | C19: 800 | D19: ≈ 33 al día, 24 días.
B20: Gastos fijos por porción (overhead) | C20: =IFERROR(C17/C19,0) -> 17.3125 | D20: Se suma al costo de cada porción.
B21: Sueldo mensual que te pagas | C21: 16000
B22: Horas de trabajo al mes | C22: 200
B23: Costo de tu hora | C23: =IFERROR(C21/C22,0) -> 80 | D23: Mano de obra = minutos ÷ 60 × costo de la hora.
B24: % de merma por defecto | C24: 0.05 | D24: Piezas falladas, cremas cortadas y sobrantes. Compárala con tu merma real en el Tablero.
B25: Redondeo de precios (pesos) | C25: 5 | D25: Los precios suben al múltiplo superior de esta cifra.
B26: Márgenes objetivo por canal
B27: Margen · Mostrador y pedido directo | C27: 0.55 | D27: Rango sugerido 50–60 %.
B28: Margen · Domicilio y venta por redes | C28: 0.6 | D28: Rango sugerido 55–65 %.
B29: Margen · Evento y pedido especial | C29: 0.66 | D29: Rango sugerido 60–70 %.
B30: Margen · Mayoreo a cafeterías | C30: 0.32 | D30: Rango sugerido 28–38 %.

Sheet Recetas y precios
A1: Recetas y precios
A2: Hoja principal. Cambia un precio en Insumos y los 51 precios se recalculan solos.
A4: Nº | B4: Receta | C4: Capítulo | D4: Formato | E4: Porciones | F4: Factor bizcocho | G4: Factor jarabe | H4: Insumos del lote | I4: Insumos por porción | J4: Empaque | K4: Energía | L4: Minutos | M4: Mano de obra | N4: Gastos fijos | O4: Costo base | P4: Merma propia | Q4: Merma aplicada | R4: COSTO TOTAL | S4: PVP mostrador | T4: PVP domicilio | U4: PVP evento | V4: PVP mayoreo | W4: Utilidad mostrador | X4: Margen real
A5: 1 | B5: Tiramisú Clásico de Cascada Douyin (Pull-Me-Up Lava Tiramisu) | C5: Cap. 6 · Flujo clásico y cafetería asiática | D5: F-1 | E5: 2 | F5: 0.309 | G5: 0.762 | H5: =SUMIF(Ingredientes!$A$5:$A$859,A5,Ingredientes!$K$5:$K$859) -> 127.72349 | I5: =IFERROR(H5/E5,0) -> 63.861747 | J5: =IFERROR(VLOOKUP(D5,Componentes!$A$11:$D$14,4,FALSE()),0) -> 9 | K5: 3 | L5: 17 | M5: =L5/60*'Mi negocio'!$C$23 -> 22.666667 | N5: ='Mi negocio'!$C$20 -> 17.3125 | O5: =I5+J5+K5+M5+N5 -> 115.84091 | Q5: =IF(P5="",'Mi negocio'!$C$24,P5) -> 0.05 | R5: =IFERROR(O5/(1-Q5),0) -> 121.9378 | S5: =IFERROR(CEILING(ROUND(R5/(1-'Mi negocio'!$C$27),6),'Mi negocio'!$C$25),0) -> 275 | T5: =IFERROR(CEILING(ROUND(R5/(1-'Mi negocio'!$C$28),6),'Mi negocio'!$C$25),0) -> 305 | U5: =IFERROR(CEILING(ROUND(R5/(1-'Mi negocio'!$C$29),6),'Mi negocio'!$C$25),0) -> 360 | V5: =IFERROR(CEILING(ROUND(R5/(1-'Mi negocio'!$C$30),6),'Mi negocio'!$C$25),0) -> 180 | W5: =S5-R5 -> 153.0622 | X5: =IFERROR(W5/S5,0) -> 0.5565898
A6: 2 | B6: Espresso Doble con Cubierta Craquelada de Chocolate (Smash Tiramisu Box) | C6: Cap. 6 · Flujo clásico y cafetería asiática | D6: F-2 | E6: 2 | F6: 0.333 | G6: 0.933 | H6: =SUMIF(Ingredientes!$A$5:$A$859,A6,Ingredientes!$K$5:$K$859) -> 90.082044 | I6: =IFERROR(H6/E6,0) -> 45.041022 | J6: =IFERROR(VLOOKUP(D6,Componentes!$A$11:$D$14,4,FALSE()),0) -> 16 | K6: 3 | L6: 17 | M6: =L6/60*'Mi negocio'!$C$23 -> 22.666667 | N6: ='Mi negocio'!$C$20 -> 17.3125 | O6: =I6+J6+K6+M6+N6 -> 104.02019 | Q6: =IF(P6="",'Mi negocio'!$C$24,P6) -> 0.05 | R6: =IFERROR(O6/(1-Q6),0) -> 109.49494 | S6: =IFERROR(CEILING(ROUND(R6/(1-'Mi negocio'!$C$27),6),'Mi negocio'!$C$25),0) -> 245 | T6: =IFERROR(CEILING(ROUND(R6/(1-'Mi negocio'!$C$28),6),'Mi negocio'!$C$25),0) -> 275 | U6: =IFERROR(CEILING(ROUND(R6/(1-'Mi negocio'!$C$29),6),'Mi negocio'!$C$25),0) -> 325 | V6: =IFERROR(CEILING(ROUND(R6/(1-'Mi negocio'!$C$30),6),'Mi negocio'!$C$25),0) -> 165 | W6: =S6-R6 -> 135.50506 | X6: =IFERROR(W6/S6,0) -> 0.5530819
A7: 3 | B7: Hojicha Tostado de Kioto con Crema de Leche Fluida | C7: Cap. 6 · Flujo clásico y cafetería asiática | D7: F-3 | E7: 2 | F7: 0.407 | G7: 1 | H7: =SUMIF(Ingredientes!$A$5:$A$859,A7,Ingredientes!$K$5:$K$859) -> 138.78638 | I7: =IFERROR(H7/E7,0) -> 69.393192 | J7: =IFERROR(VLOOKUP(D7,Componentes!$A$11:$D$14,4,FALSE()),0) -> 12 | K7: 3 | L7: 17 | M7: =L7/60*'Mi negocio'!$C$23 -> 22.666667 | N7: ='Mi negocio'!$C$20 -> 17.3125 | O7: =I7+J7+K7+M7+N7 -> 124.37236 | Q7: =IF(P7="",'Mi negocio'!$C$24,P7) -> 0.05 | R7: =IFERROR(O7/(1-Q7),0) -> 130.91827 | S7: =IFERROR(CEILING(ROUND(R7/(1-'Mi negocio'!$C$27),6),'Mi negocio'!$C$25),0) -> 295 | T7: =IFERROR(CEILING(ROUND(R7/(1-'Mi negocio'!$C$28),6),'Mi negocio'!$C$25),0) -> 330 | U7: =IFERROR(CEILING(ROUND(R7/(1-'Mi negocio'!$C$29),6),'Mi negocio'!$C$25),0) -> 390 | V7: =IFERROR(CEILING(ROUND(R7/(1-'Mi negocio'!$C$30),6),'Mi negocio'!$C$25),0) -> 195 | W7: =S7-R7 -> 164.08173 | X7: =IFERROR(W7/S7,0) -> 0.55620924
A8: 4 | B8: Café Dalgona Caramelizado con Toffee Crunch | C8: Cap. 6 · Flujo clásico y cafetería asiática | D8: F-3 | E8: 2 | F8: 0.552 | G8: 1 | H8: =SUMIF(Ingredientes!$A$5:$A$859,A8,Ingredientes!$K$5:$K$859) -> 103.39816 | I8: =IFERROR(H8/E8,0) -> 51.69908 | J8: =IFERROR(VLOOKUP(D8,Componentes!$A$11:$D$14,4,FALSE()),0) -> 12 | K8: 3 | L8: 17 | M8: =L8/60*'Mi negocio'!$C$23 -> 22.666667 | N8: ='Mi negocio'!$C$20 -> 17.3125 | O8: =I8+J8+K8+M8+N8 -> 106.67825 | Q8: =IF(P8="",'Mi negocio'!$C$24,P8) -> 0.05 | R8: =IFERROR(O8/(1-Q8),0) -> 112.29289 | S8: =IFERROR(CEILING(ROUND(R8/(1-'Mi negocio'!$C$27),6),'Mi negocio'!$C$25),0) -> 250 | T8: =IFERROR(CEILING(ROUND(R8/(1-'Mi negocio'!$C$28),6),'Mi negocio'!$C$25),0) -> 285 | U8: =IFERROR(CEILING(ROUND(R8/(1-'Mi negocio'!$C$29),6),'Mi negocio'!$C$25),0) -> 335 | V8: =IFERROR(CEILING(ROUND(R8/(1-'Mi negocio'!$C$30),6),'Mi negocio'!$C$25),0) -> 170 | W8: =S8-R8 -> 137.70711 | X8: =IFERROR(W8/S8,0) -> 0.55082844
A9: 5 | B9: Mocha Profundo con Sal Marina de Maldon y Nibs de Cacao Mocha Profundo con Sal Marina de Maldon y Nibs de Cacao | C9: Cap. 6 · Flujo clásico y cafetería asiática | D9: F-1 | E9: 2 | F9: 0.282 | G9: 0.737 | H9: =SUMIF(Ingredientes!$A$5:$A$859,A9,Ingredientes!$K$5:$K$859) -> 135.78668 | I9: =IFERROR(H9/E9,0) -> 67.893338 | J9: =IFERROR(VLOOKUP(D9,Componentes!$A$11:$D$14,4,FALSE()),0) -> 9 | K9: 3 | L9: 17 | M9: =L9/60*'Mi negocio'!$C$23 -> 22.666667 | N9: ='Mi negocio'!$C$20 -> 17.3125 | O9: =I9+J9+K9+M9+N9 -> 119.87251 | Q9: =IF(P9="",'Mi negocio'!$C$24,P9) -> 0.05 | R9: =IFERROR(O9/(1-Q9),0) -> 126.18158 | S9: =IFERROR(CEILING(ROUND(R9/(1-'Mi negocio'!$C$27),6),'Mi negocio'!$C$25),0) -> 285 | T9: =IFERROR(CEILING(ROUND(R9/(1-'Mi negocio'!$C$28),6),'Mi negocio'!$C$25),0) -> 320 | U9: =IFERROR(CEILING(ROUND(R9/(1-'Mi negocio'!$C$29),6),'Mi negocio'!$C$25),0) -> 375 | V9: =IFERROR(CEILING(ROUND(R9/(1-'Mi negocio'!$C$30),6),'Mi negocio'!$C$25),0) -> 190 | W9: =S9-R9 -> 158.81842 | X9: =IFERROR(W9/S9,0) -> 0.5572576
A10: 6 | B10: Tiramisú de Caramelo Salado con Mantequilla Tostada (Beurre Noisette) | C10: Cap. 6 · Flujo clásico y cafetería asiática | D10: F-1 | E10: 2 | F10: 0.309 | G10: 0.789 | H10: =SUMIF(Ingredientes!$A$5:$A$859,A10,Ingredientes!$K$5:$K$859) -> 129.97868 | I10: =IFERROR(H10/E10,0) -> 64.989338 | J10: =IFERROR(VLOOKUP(D10,Componentes!$A$11:$D$14,4,FALSE()),0) -> 9 | K10: 4 | L10: 24 | M10: =L10/60*'Mi negocio'!$C$23 -> 32 | N10: ='Mi negocio'!$C$20 -> 17.3125 | O10: =I10+J10+K10+M10+N10 -> 127.30184 | Q10: =IF(P10="",'Mi negocio'!$C$24,P10) -> 0.05 | R10: =IFERROR(O10/(1-Q10),0) -> 134.00193 | S10: =IFERROR(CEILING(ROUND(R10/(1-'Mi negocio'!$C$27),6),'Mi negocio'!$C$25),0) -> 300 | T10: =IFERROR(CEILING(ROUND(R10/(1-'Mi negocio'!$C$28),6),'Mi negocio'!$C$25),0) -> 340 | U10: =IFERROR(CEILING(ROUND(R10/(1-'Mi negocio'!$C$29),6),'Mi negocio'!$C$25),0) -> 395 | V10: =IFERROR(CEILING(ROUND(R10/(1-'Mi negocio'!$C$30),6),'Mi negocio'!$C$25),0) -> 200 | W10: =S10-R10 -> 165.99807 | X10: =IFERROR(W10/S10,0) -> 0.55332689
A11: 7 | B11: Café con Leche Condensada estilo Vietnamita (Cà Phê Trứng Tiramisu) | C11: Cap. 6 · Flujo clásico y cafetería asiática | D11: F-3 | E11: 2 | F11: 0.364 | G11: 1 | H11: =SUMIF(Ingredientes!$A$5:$A$859,A11,Ingredientes!$K$5:$K$859) -> 99.655967 | I11: =IFERROR(H11/E11,0) -> 49.827983 | J11: =IFERROR(VLOOKUP(D11,Componentes!$A$11:$D$14,4,FALSE()),0) -> 12 | K11: 3 | L11: 17 | M11: =L11/60*'Mi negocio'!$C$23 -> 22.666667 | N11: ='Mi negocio'!$C$20 -> 17.3125 | O11: =I11+J11+K11+M11+N11 -> 104.80715 | Q11: =IF(P11="",'Mi negocio'!$C$24,P11) -> 0.05 | R11: =IFERROR(O11/(1-Q11),0) -> 110.32332 | S11: =IFERROR(CEILING(ROUND(R11/(1-'Mi negocio'!$C$27),6),'Mi negocio'!$C$25),0) -> 250 | T11: =IFERROR(CEILING(ROUND(R11/(1-'Mi negocio'!$C$28),6),'Mi negocio'!$C$25),0) -> 280 | U11: =IFERROR(CEILING(ROUND(R11/(1-'Mi negocio'!$C$29),6),'Mi negocio'!$C$25),0) -> 325 | V11: =IFERROR(CEILING(ROUND(R11/(1-'Mi negocio'!$C$30),6),'Mi negocio'!$C$25),0) -> 165 | W11: =S11-R11 -> 139.67668 | X11: =IFERROR(W11/S11,0) -> 0.55870674
A12: 8 | B12: Tiramisú de Té Negro Asamés con Leche Tostada y Boba de Azúcar Morena | C12: Cap. 6 · Flujo clásico y cafetería asiática | D12: F-2 | E12: 2 | F12: 0.352 | G12: 1 | H12: =SUMIF(Ingredientes!$A$5:$A$859,A12,Ingredientes!$K$5:$K$859) -> 107.48227 | I12: =IFERROR(H12/E12,0) -> 53.741133 | J12: =IFERROR(VLOOKUP(D12,Componentes!$A$11:$D$14,4,FALSE()),0) -> 16 | K12: 3 | L12: 17 | M12: =L12/60*'Mi negocio'!$C$23 -> 22.666667 | N12: ='Mi negocio'!$C$20 -> 17.3125 | O12: =I12+J12+K12+M12+N12 -> 112.7203 | Q12: =IF(P12="",'Mi negocio'!$C$24,P12) -> 0.05 | R12: =IFERROR(O12/(1-Q12),0) -> 118.65295 | S12: =IFERROR(CEILING(ROUND(R12/(1-'Mi negocio'!$C$27),6),'Mi negocio'!$C$25),0) -> 265 | T12: =IFERROR(CEILING(ROUND(R12/(1-'Mi negocio'!$C$28),6),'Mi negocio'!$C$25),0) -> 300 | U12: =IFERROR(CEILING(ROUND(R12/(1-'Mi negocio'!$C$29),6),'Mi negocio'!$C$25),0) -> 350 | V12: =IFERROR(CEILING(ROUND(R12/(1-'Mi negocio'!$C$30),6),'Mi negocio'!$C$25),0) -> 175 | W12: =S12-R12 -> 146.34705 | X12: =IFERROR(W12/S12,0) -> 0.55225303
A13: 9 | B13: Capuchino Frappé con Crema de Queso Salado y Canela Ceilán | C13: Cap. 6 · Flujo clásico y cafetería asiática | D13: F-3 | E13: 2 | F13: 0.583 | G13: 1 | H13: =SUMIF(Ingredientes!$A$5:$A$859,A13,Ingredientes!$K$5:$K$859) -> 104.57017 | I13: =IFERROR(H13/E13,0) -> 52.285085 | J13: =IFERROR(VLOOKUP(D13,Componentes!$A$11:$D$14,4,FALSE()),0) -> 12 | K13: 2.5 | L13: 12 | M13: =L13/60*'Mi negocio'!$C$23 -> 16 | N13: ='Mi negocio'!$C$20 -> 17.3125 | O13: =I13+J13+K13+M13+N13 -> 100.09758 | Q13: =IF(P13="",'Mi negocio'!$C$24,P13) -> 0.05 | R13: =IFERROR(O13/(1-Q13),0) -> 105.36588 | S13: =IFERROR(CEILING(ROUND(R13/(1-'Mi negocio'!$C$27),6),'Mi negocio'!$C$25),0) -> 235 | T13: =IFERROR(CEILING(ROUND(R13/(1-'Mi negocio'!$C$28),6),'Mi negocio'!$C$25),0) -> 265 | U13: =IFERROR(CEILING(ROUND(R13/(1-'Mi negocio'!$C$29),6),'Mi negocio'!$C$25),0) -> 310 | V13: =IFERROR(CEILING(ROUND(R13/(1-'Mi negocio'!$C$30),6),'Mi negocio'!$C$25),0) -> 155 | W13: =S13-R13 -> 129.63412 | X13: =IFERROR(W13/S13,0) -> 0.55163456
A14: 10 | B14: Tiramisú de Avellana Tostada Gianduja con Craquelado de Chocolate con Leche | C14: Cap. 6 · Flujo clásico y cafetería asiática | D14: F-2 | E14: 2 | F14: 0.516 | G14: 1 | H14: =SUMIF(Ingredientes!$A$5:$A$859,A14,Ingredientes!$K$5:$K$859) -> 123.898 | I14: =IFERROR(H14/E14,0) -> 61.949001 | J14: =IFERROR(VLOOKUP(D14,Componentes!$A$11:$D$14,4,FALSE()),0) -> 16 | K14: 3 | L14: 17 | M14: =L14/60*'Mi negocio'!$C$23 -> 22.666667 | N14: ='Mi negocio'!$C$20 -> 17.3125 | O14: =I14+J14+K14+M14+N14 -> 120.92817 | Q14: =IF(P14="",'Mi negocio'!$C$24,P14) -> 0.05 | R14: =IFERROR(O14/(1-Q14),0) -> 127.29281 | S14: =IFERROR(CEILING(ROUND(R14/(1-'Mi negocio'!$C$27),6),'Mi negocio'!$C$25),0) -> 285 | T14: =IFERROR(CEILING(ROUND(R14/(1-'Mi negocio'!$C$28),6),'Mi negocio'!$C$25),0) -> 320 | U14: =IFERROR(CEILING(ROUND(R14/(1-'Mi negocio'!$C$29),6),'Mi negocio'!$C$25),0) -> 375 | V14: =IFERROR(CEILING(ROUND(R14/(1-'Mi negocio'!$C$30),6),'Mi negocio'!$C$25),0) -> 190 | W14: =S14-R14 -> 157.70719 | X14: =IFERROR(W14/S14,0) -> 0.55335857
A15: 11 | B15: Tiramisú de Matcha Ceremonial de Uji con Frijol Rojo Dulce (Ogura) | C15: Cap. 7 · Tés orientales, flores y herbolaria | D15: F-1 | E15: 2 | F15: 0.27 | G15: 0.769 | H15: =SUMIF(Ingredientes!$A$5:$A$859,A15,Ingredientes!$K$5:$K$859) -> 219.52564 | I15: =IFERROR(H15/E15,0) -> 109.76282 | J15: =IFERROR(VLOOKUP(D15,Componentes!$A$11:$D$14,4,FALSE()),0) -> 9 | K15: 3 | L15: 17 | M15: =L15/60*'Mi negocio'!$C$23 -> 22.666667 | N15: ='Mi negocio'!$C$20 -> 17.3125 | O15: =I15+J15+K15+M15+N15 -> 161.74198 | Q15: =IF(P15="",'Mi negocio'!$C$24,P15) -> 0.05 | R15: =IFERROR(O15/(1-Q15),0) -> 170.25472 | S15: =IFERROR(CEILING(ROUND(R15/(1-'Mi negocio'!$C$27),6),'Mi negocio'!$C$25),0) -> 380 | T15: =IFERROR(CEILING(ROUND(R15/(1-'Mi negocio'!$C$28),6),'Mi negocio'!$C$25),0) -> 430 | U15: =IFERROR(CEILING(ROUND(R15/(1-'Mi negocio'!$C$29),6),'Mi negocio'!$C$25),0) -> 505 | V15: =IFERROR(CEILING(ROUND(R15/(1-'Mi negocio'!$C$30),6),'Mi negocio'!$C$25),0) -> 255 | W15: =S15-R15 -> 209.74528 | X15: =IFERROR(W15/S15,0) -> 0.55196126
A16: 12 | B16: Té Oolong Tostado de Montaña Alta (Tieguanyin) con Durazno Blanco | C16: Cap. 7 · Tés orientales, flores y herbolaria | D16: F-2 | E16: 2 | F16: 0.352 | G16: 1 | H16: =SUMIF(Ingredientes!$A$5:$A$859,A16,Ingredientes!$K$5:$K$859) -> 110.20405 | I16: =IFERROR(H16/E16,0) -> 55.102027 | J16: =IFERROR(VLOOKUP(D16,Componentes!$A$11:$D$14,4,FALSE()),0) -> 16 | K16: 4 | L16: 24 | M16: =L16/60*'Mi negocio'!$C$23 -> 32 | N16: ='Mi negocio'!$C$20 -> 17.3125 | O16: =I16+J16+K16+M16+N16 -> 124.41453 | Q16: =IF(P16="",'Mi negocio'!$C$24,P16) -> 0.05 | R16: =IFERROR(O16/(1-Q16),0) -> 130.96266 | S16: =IFERROR(CEILING(ROUND(R16/(1-'Mi negocio'!$C$27),6),'Mi negocio'!$C$25),0) -> 295 | T16: =IFERROR(CEILING(ROUND(R16/(1-'Mi negocio'!$C$28),6),'Mi negocio'!$C$25),0) -> 330 | U16: =IFERROR(CEILING(ROUND(R16/(1-'Mi negocio'!$C$29),6),'Mi negocio'!$C$25),0) -> 390 | V16: =IFERROR(CEILING(ROUND(R16/(1-'Mi negocio'!$C$30),6),'Mi negocio'!$C$25),0) -> 195 | W16: =S16-R16 -> 164.03734 | X16: =IFERROR(W16/S16,0) -> 0.55605878
... A55: 51 | B55: Tiramisú Imperial de Hoja de Oro 24K con Vainilla Bourbon de Madagascar | C55: Cap. 10 · Chocolatería viral, galletas y alta técnica | D55: F-1 | E55: 2 | F55: 0.29 | G55: 0.933 | H55: =SUMIF(Ingredientes!$A$5:$A$859,A55,Ingredientes!$K$5:$K$859) -> 509.47823 | I55: =IFERROR(H55/E55,0) -> 254.73911 | J55: =IFERROR(VLOOKUP(D55,Componentes!$A$11:$D$14,4,FALSE()),0) -> 9 | K55: 4 | L55: 24 | M55: =L55/60*'Mi negocio'!$C$23 -> 32 | N55: ='Mi negocio'!$C$20 -> 17.3125 | O55: =I55+J55+K55+M55+N55 -> 317.05162 | Q55: =IF(P55="",'Mi negocio'!$C$24,P55) -> 0.05 | R55: =IFERROR(O55/(1-Q55),0) -> 333.73854 | S55: =IFERROR(CEILING(ROUND(R55/(1-'Mi negocio'!$C$27),6),'Mi negocio'!$C$25),0) -> 745 | T55: =IFERROR(CEILING(ROUND(R55/(1-'Mi negocio'!$C$28),6),'Mi negocio'!$C$25),0) -> 835 | U55: =IFERROR(CEILING(ROUND(R55/(1-'Mi negocio'!$C$29),6),'Mi negocio'!$C$25),0) -> 985 | V55: =IFERROR(CEILING(ROUND(R55/(1-'Mi negocio'!$C$30),6),'Mi negocio'!$C$25),0) -> 495 | W55: =S55-R55 -> 411.26146 | X55: =IFERROR(W55/S55,0) -> 0.5520288
B57: Todas las recetas rinden 2 porciones de 330–390 g. Los factores de bizcocho y jarabe cargan solo la parte que entra al postre (Capítulo 13); deja «Merma propia» vacía para usar la merma por defecto de Mi negocio.

Sheet Producción
A1: Producción y merma
A2: Una fila por lote. La primera fila es un ejemplo: sobrescríbela.
A4: Fecha | B4: Lote | C4: Nº receta | D4: Receta | E4: Planeadas | F4: Buenas | G4: Falladas | H4: % merma | I4: Costo total unitario | J4: Costo de la merma | K4: Causa principal | L4: Notas
A5: 46298 | B5: L-2610-01 | C5: 1 | D5: =IF(C5="","",IFERROR(VLOOKUP(C5,'Recetas y precios'!$A$5:$B$55,2,FALSE()),"")) -> Tiramisú Clásico de Cascada Douyin (Pull-Me-Up Lava Tiramisu) | E5: 10 | F5: 9 | G5: 1 | H5: =IF((F5+G5)>0,G5/(F5+G5),"") -> 0.1 | I5: =IF(C5="",0,IFERROR(VLOOKUP(C5,'Recetas y precios'!$A$5:$R$55,18,FALSE()),0)) -> 121.9378 | J5: =G5*I5 -> 121.9378 | K5: Crema cortada o sobrebatida | L5: Fila de ejemplo
D6: =IF(C6="","",IFERROR(VLOOKUP(C6,'Recetas y precios'!$A$5:$B$55,2,FALSE()),"")) | H6: =IF((F6+G6)>0,G6/(F6+G6),"") | I6: =IF(C6="",0,IFERROR(VLOOKUP(C6,'Recetas y precios'!$A$5:$R$55,18,FALSE()),0)) -> 0 | J6: =G6*I6 -> 0
D7: =IF(C7="","",IFERROR(VLOOKUP(C7,'Recetas y precios'!$A$5:$B$55,2,FALSE()),"")) | H7: =IF((F7+G7)>0,G7/(F7+G7),"") | I7: =IF(C7="",0,IFERROR(VLOOKUP(C7,'Recetas y precios'!$A$5:$R$55,18,FALSE()),0)) -> 0 | J7: =G7*I7 -> 0
D8: =IF(C8="","",IFERROR(VLOOKUP(C8,'Recetas y precios'!$A$5:$B$55,2,FALSE()),"")) | H8: =IF((F8+G8)>0,G8/(F8+G8),"") | I8: =IF(C8="",0,IFERROR(VLOOKUP(C8,'Recetas y precios'!$A$5:$R$55,18,FALSE()),0)) -> 0 | J8: =G8*I8 -> 0
D9: =IF(C9="","",IFERROR(VLOOKUP(C9,'Recetas y precios'!$A$5:$B$55,2,FALSE()),"")) | H9: =IF((F9+G9)>0,G9/(F9+G9),"") | I9: =IF(C9="",0,IFERROR(VLOOKUP(C9,'Recetas y precios'!$A$5:$R$55,18,FALSE()),0)) -> 0 | J9: =G9*I9 -> 0
D10: =IF(C10="","",IFERROR(VLOOKUP(C10,'Recetas y precios'!$A$5:$B$55,2,FALSE()),"")) | H10: =IF((F10+G10)>0,G10/(F10+G10),"") | I10: =IF(C10="",0,IFERROR(VLOOKUP(C10,'Recetas y precios'!$A$5:$R$55,18,FALSE()),0)) -> 0 | J10: =G10*I10 -> 0
D11: =IF(C11="","",IFERROR(VLOOKUP(C11,'Recetas y precios'!$A$5:$B$55,2,FALSE()),"")) | H11: =IF((F11+G11)>0,G11/(F11+G11),"") | I11: =IF(C11="",0,IFERROR(VLOOKUP(C11,'Recetas y precios'!$A$5:$R$55,18,FALSE()),0)) -> 0 | J11: =G11*I11 -> 0
D12: =IF(C12="","",IFERROR(VLOOKUP(C12,'Recetas y precios'!$A$5:$B$55,2,FALSE()),"")) | H12: =IF((F12+G12)>0,G12/(F12+G12),"") | I12: =IF(C12="",0,IFERROR(VLOOKUP(C12,'Recetas y precios'!$A$5:$R$55,18,FALSE()),0)) -> 0 | J12: =G12*I12 -> 0
D13: =IF(C13="","",IFERROR(VLOOKUP(C13,'Recetas y precios'!$A$5:$B$55,2,FALSE()),"")) | H13: =IF((F13+G13)>0,G13/(F13+G13),"") | I13: =IF(C13="",0,IFERROR(VLOOKUP(C13,'Recetas y precios'!$A$5:$R$55,18,FALSE()),0)) -> 0 | J13: =G13*I13 -> 0
D14: =IF(C14="","",IFERROR(VLOOKUP(C14,'Recetas y precios'!$A$5:$B$55,2,FALSE()),"")) | H14: =IF((F14+G14)>0,G14/(F14+G14),"") | I14: =IF(C14="",0,IFERROR(VLOOKUP(C14,'Recetas y precios'!$A$5:$R$55,18,FALSE()),0)) -> 0 | J14: =G14*I14 -> 0
D15: =IF(C15="","",IFERROR(VLOOKUP(C15,'Recetas y precios'!$A$5:$B$55,2,FALSE()),"")) | H15: =IF((F15+G15)>0,G15/(F15+G15),"") | I15: =IF(C15="",0,IFERROR(VLOOKUP(C15,'Recetas y precios'!$A$5:$R$55,18,FALSE()),0)) -> 0 | J15: =G15*I15 -> 0
D16: =IF(C16="","",IFERROR(VLOOKUP(C16,'Recetas y precios'!$A$5:$B$55,2,FALSE()),"")) | H16: =IF((F16+G16)>0,G16/(F16+G16),"") | I16: =IF(C16="",0,IFERROR(VLOOKUP(C16,'Recetas y precios'!$A$5:$R$55,18,FALSE()),0)) -> 0 | J16: =G16*I16 -> 0
D17: =IF(C17="","",IFERROR(VLOOKUP(C17,'Recetas y precios'!$A$5:$B$55,2,FALSE()),"")) | H17: =IF((F17+G17)>0,G17/(F17+G17),"") | I17: =IF(C17="",0,IFERROR(VLOOKUP(C17,'Recetas y precios'!$A$5:$R$55,18,FALSE()),0)) -> 0 | J17: =G17*I17 -> 0
... D304: =IF(C304="","",IFERROR(VLOOKUP(C304,'Recetas y precios'!$A$5:$B$55,2,FALSE()),"")) | H304: =IF((F304+G304)>0,G304/(F304+G304),"") | I304: =IF(C304="",0,IFERROR(VLOOKUP(C304,'Recetas y precios'!$A$5:$R$55,18,FALSE()),0)) -> 0 | J304: =G304*I304 -> 0

Sheet Ventas
A1: Ventas
A2: Una fila por venta. La primera fila es un ejemplo: sobrescríbela.
A4: Fecha | B4: Nº receta | C4: Receta | D4: Canal | E4: Porciones | F4: Precio unitario | G4: Ingreso | H4: Costo total | I4: Comisión % | J4: Comisión $ | K4: Utilidad neta | L4: Margen | M4: Cliente o nota
A5: 46298 | B5: 1 | C5: =IF(B5="","",IFERROR(VLOOKUP(B5,'Recetas y precios'!$A$5:$B$55,2,FALSE()),"")) -> Tiramisú Clásico de Cascada Douyin (Pull-Me-Up Lava Tiramisu) | D5: Mostrador y pedido directo | E5: 4 | F5: 275 | G5: =E5*F5 -> 1100 | H5: =IF(B5="",0,E5*IFERROR(VLOOKUP(B5,'Recetas y precios'!$A$5:$R$55,18,FALSE()),0)) -> 487.75122 | I5: 0 | J5: =G5*I5 -> 0 | K5: =G5-H5-J5 -> 612.24878 | L5: =IF(G5>0,K5/G5,"") -> 0.5565898 | M5: Fila de ejemplo
C6: =IF(B6="","",IFERROR(VLOOKUP(B6,'Recetas y precios'!$A$5:$B$55,2,FALSE()),"")) | G6: =E6*F6 -> 0 | H6: =IF(B6="",0,E6*IFERROR(VLOOKUP(B6,'Recetas y precios'!$A$5:$R$55,18,FALSE()),0)) -> 0 | J6: =G6*I6 -> 0 | K6: =G6-H6-J6 -> 0 | L6: =IF(G6>0,K6/G6,"")
C7: =IF(B7="","",IFERROR(VLOOKUP(B7,'Recetas y precios'!$A$5:$B$55,2,FALSE()),"")) | G7: =E7*F7 -> 0 | H7: =IF(B7="",0,E7*IFERROR(VLOOKUP(B7,'Recetas y precios'!$A$5:$R$55,18,FALSE()),0)) -> 0 | J7: =G7*I7 -> 0 | K7: =G7-H7-J7 -> 0 | L7: =IF(G7>0,K7/G7,"")
C8: =IF(B8="","",IFERROR(VLOOKUP(B8,'Recetas y precios'!$A$5:$B$55,2,FALSE()),"")) | G8: =E8*F8 -> 0 | H8: =IF(B8="",0,E8*IFERROR(VLOOKUP(B8,'Recetas y precios'!$A$5:$R$55,18,FALSE()),0)) -> 0 | J8: =G8*I8 -> 0 | K8: =G8-H8-J8 -> 0 | L8: =IF(G8>0,K8/G8,"")
C9: =IF(B9="","",IFERROR(VLOOKUP(B9,'Recetas y precios'!$A$5:$B$55,2,FALSE()),"")) | G9: =E9*F9 -> 0 | H9: =IF(B9="",0,E9*IFERROR(VLOOKUP(B9,'Recetas y precios'!$A$5:$R$55,18,FALSE()),0)) -> 0 | J9: =G9*I9 -> 0 | K9: =G9-H9-J9 -> 0 | L9: =IF(G9>0,K9/G9,"")
C10: =IF(B10="","",IFERROR(VLOOKUP(B10,'Recetas y precios'!$A$5:$B$55,2,FALSE()),"")) | G10: =E10*F10 -> 0 | H10: =IF(B10="",0,E10*IFERROR(VLOOKUP(B10,'Recetas y precios'!$A$5:$R$55,18,FALSE()),0)) -> 0 | J10: =G10*I10 -> 0 | K10: =G10-H10-J10 -> 0 | L10: =IF(G10>0,K10/G10,"")
C11: =IF(B11="","",IFERROR(VLOOKUP(B11,'Recetas y precios'!$A$5:$B$55,2,FALSE()),"")) | G11: =E11*F11 -> 0 | H11: =IF(B11="",0,E11*IFERROR(VLOOKUP(B11,'Recetas y precios'!$A$5:$R$55,18,FALSE()),0)) -> 0 | J11: =G11*I11 -> 0 | K11: =G11-H11-J11 -> 0 | L11: =IF(G11>0,K11/G11,"")
C12: =IF(B12="","",IFERROR(VLOOKUP(B12,'Recetas y precios'!$A$5:$B$55,2,FALSE()),"")) | G12: =E12*F12 -> 0 | H12: =IF(B12="",0,E12*IFERROR(VLOOKUP(B12,'Recetas y precios'!$A$5:$R$55,18,FALSE()),0)) -> 0 | J12: =G12*I12 -> 0 | K12: =G12-H12-J12 -> 0 | L12: =IF(G12>0,K12/G12,"")
C13: =IF(B13="","",IFERROR(VLOOKUP(B13,'Recetas y precios'!$A$5:$B$55,2,FALSE()),"")) | G13: =E13*F13 -> 0 | H13: =IF(B13="",0,E13*IFERROR(VLOOKUP(B13,'Recetas y precios'!$A$5:$R$55,18,FALSE()),0)) -> 0 | J13: =G13*I13 -> 0 | K13: =G13-H13-J13 -> 0 | L13: =IF(G13>0,K13/G13,"")
C14: =IF(B14="","",IFERROR(VLOOKUP(B14,'Recetas y precios'!$A$5:$B$55,2,FALSE()),"")) | G14: =E14*F14 -> 0 | H14: =IF(B14="",0,E14*IFERROR(VLOOKUP(B14,'Recetas y precios'!$A$5:$R$55,18,FALSE()),0)) -> 0 | J14: =G14*I14 -> 0 | K14: =G14-H14-J14 -> 0 | L14: =IF(G14>0,K14/G14,"")
C15: =IF(B15="","",IFERROR(VLOOKUP(B15,'Recetas y precios'!$A$5:$B$55,2,FALSE()),"")) | G15: =E15*F15 -> 0 | H15: =IF(B15="",0,E15*IFERROR(VLOOKUP(B15,'Recetas y precios'!$A$5:$R$55,18,FALSE()),0)) -> 0 | J15: =G15*I15 -> 0 | K15: =G15-H15-J15 -> 0 | L15: =IF(G15>0,K15/G15,"")
C16: =IF(B16="","",IFERROR(VLOOKUP(B16,'Recetas y precios'!$A$5:$B$55,2,FALSE()),"")) | G16: =E16*F16 -> 0 | H16: =IF(B16="",0,E16*IFERROR(VLOOKUP(B16,'Recetas y precios'!$A$5:$R$55,18,FALSE()),0)) -> 0 | J16: =G16*I16 -> 0 | K16: =G16-H16-J16 -> 0 | L16: =IF(G16>0,K16/G16,"")
C17: =IF(B17="","",IFERROR(VLOOKUP(B17,'Recetas y precios'!$A$5:$B$55,2,FALSE()),"")) | G17: =E17*F17 -> 0 | H17: =IF(B17="",0,E17*IFERROR(VLOOKUP(B17,'Recetas y precios'!$A$5:$R$55,18,FALSE()),0)) -> 0 | J17: =G17*I17 -> 0 | K17: =G17-H17-J17 -> 0 | L17: =IF(G17>0,K17/G17,"")
... C504: =IF(B504="","",IFERROR(VLOOKUP(B504,'Recetas y precios'!$A$5:$B$55,2,FALSE()),"")) | G504: =E504*F504 -> 0 | H504: =IF(B504="",0,E504*IFERROR(VLOOKUP(B504,'Recetas y precios'!$A$5:$R$55,18,FALSE()),0)) -> 0 | J504: =G504*I504 -> 0 | K504: =G504-H504-J504 -> 0 | L504: =IF(G504>0,K504/G504,"")

Sheet Tablero
A1: Tablero
A2: Resumen automático de Ventas y Producción. No se edita.
B3: Ventas | E3: Canal | F3: Ingreso | G3: Porciones
B4: Ingreso acumulado | C4: =SUM(Ventas!G5:G504) -> 1100 | E4: Mostrador y pedido directo | F4: =SUMIF(Ventas!$D$5:$D$504,E4,Ventas!$G$5:$G$504) -> 1100 | G4: =SUMIF(Ventas!$D$5:$D$504,E4,Ventas!$E$5:$E$504) -> 4
B5: Porciones vendidas | C5: =SUM(Ventas!E5:E504) -> 4 | E5: Domicilio y venta por redes | F5: =SUMIF(Ventas!$D$5:$D$504,E5,Ventas!$G$5:$G$504) -> 0 | G5: =SUMIF(Ventas!$D$5:$D$504,E5,Ventas!$E$5:$E$504) -> 0
B6: Costo de lo vendido | C6: =SUM(Ventas!H5:H504) -> 487.75122 | E6: Evento y pedido especial | F6: =SUMIF(Ventas!$D$5:$D$504,E6,Ventas!$G$5:$G$504) -> 0 | G6: =SUMIF(Ventas!$D$5:$D$504,E6,Ventas!$E$5:$E$504) -> 0
B7: Comisiones | C7: =SUM(Ventas!J5:J504) -> 0 | E7: Mayoreo a cafeterías | F7: =SUMIF(Ventas!$D$5:$D$504,E7,Ventas!$G$5:$G$504) -> 0 | G7: =SUMIF(Ventas!$D$5:$D$504,E7,Ventas!$E$5:$E$504) -> 0
B8: Utilidad neta (antes de gastos fijos) | C8: =SUM(Ventas!K5:K504) -> 612.24878 | E8: Degustación o cortesía | F8: =SUMIF(Ventas!$D$5:$D$504,E8,Ventas!$G$5:$G$504) -> 0 | G8: =SUMIF(Ventas!$D$5:$D$504,E8,Ventas!$E$5:$E$504) -> 0
B9: Margen neto | C9: =IFERROR(C8/C4,0) -> 0.5565898
B10: Utilidad después de gastos fijos | C10: =C8-'Mi negocio'!C17 -> -13237.751
B11: Producción y merma | E11: Componente madre | F11: Costo medio | G11: % del costo
B12: Porciones buenas producidas | C12: =SUM(Producción!F5:F304) -> 9 | E12: B · Bizcocho chiffon asiático | F12: =Componentes!D5 -> 2.9075197 | G12: =Componentes!E5 -> 0.04194796
B13: Porciones falladas | C13: =SUM(Producción!G5:G304) -> 1 | E13: J · Jarabe de imbibición (punch) | F13: =Componentes!D6 -> 5.5755027 | G13: =Componentes!E6 -> 0.080440028
B14: Merma real | C14: =IFERROR(C13/(C12+C13),0) -> 0.1 | E14: C · Crema fluida de mascarpone | F14: =Componentes!D7 -> 48.491201 | G14: =Componentes!E7 -> 0.69960213
B15: Merma supuesta | C15: ='Mi negocio'!$C$24 -> 0.05 | E15: A · Acabados y texturas | F15: =Componentes!D8 -> 12.338317 | G15: =Componentes!E8 -> 0.17800988
B16: Dinero perdido en merma | C16: =SUM(Producción!J5:J304) -> 121.9378
B17: Punto de equilibrio
B18: Precio promedio de mostrador | C18: =AVERAGE('Recetas y precios'!$S$5:$S$55) -> 297.54902
B19: Costo total promedio | C19: =AVERAGE('Recetas y precios'!$R$5:$R$55) -> 132.75288
B20: Margen de contribución por porción | C20: =C18-C19 -> 164.79614
B21: Gastos fijos del mes | C21: ='Mi negocio'!C17 -> 13850
B22: PUNTO DE EQUILIBRIO (porciones al mes) | C22: =IFERROR(ROUNDUP(C21/C20,0),0) -> 85
B23: Avance contra el punto de equilibrio | C23: =IFERROR(C5/C22,0) -> 0.047058824
B26: Endulcora · Estudio Gastronómico · En colaboración con Levent · Tiramisú Douyin · Anexo 1
