Workbook

Sheet Léeme
B2: ANEXO 1 · PLANTILLA DE COSTEO
B3: Palomitas Gourmet de Autor & Confitería Técnica — Oficios Dulces · Endulcora Estudio Gastronómico · En colaboración con Levent
B5: CÓMO USAR ESTA PLANTILLA
B6: 1. Hoja «Catálogo»: escribe TU precio real de compra (columna E) y la cantidad de la presentación (columna C). El costo por gramo/ml se calcula solo.
B7: 2. Hoja «Parámetros»: ajusta empaque por porción, energía, tarifa de mano de obra, overhead, % de merma y márgenes por canal.
B8: 3. Hoja «Costeo»: ajusta las horas por lote de cada receta (columna G). Todo lo demás se recalcula: costo del lote, costo por porción y precio de venta por canal.
B9: 4. Hoja «Recetas»: contiene las 51 fórmulas línea por línea, tal como aparecen en el ebook. No necesitas editarla; si cambias una cantidad, el costeo se actualiza.
B11: CÓDIGO DE COLORES
B12: Texto AZUL sobre fondo AMARILLO = dato que tú capturas (precio, parámetro, horas).
B13: Texto negro = fórmula. No la sobrescribas.
B15: FÓRMULAS (idénticas en el ebook, en esta hoja y en la app HTML)
B16: Costo por gramo = Precio de compra ÷ Cantidad comprada
... B28: Esta plantilla es orientativa y no sustituye asesoría contable o fiscal. El IVA no es utilidad.

Sheet Costeo
A1: # | B1: Receta | C1: Técnica | D1: Rendimiento (g) | E1: Porciones | F1: Porción (g) | G1: Horas por lote | H1: Insumos | I1: Empaque | J1: Energía | K1: Mano de obra | L1: Overhead | M1: Costo base | N1: Costo total (con merma) | O1: Costo por porción | P1: PVP Menudeo | Q1: PVP Mayoreo | R1: PVP Corporativo | S1: Utilidad por porción (menudeo)
A2: 1 | B2: Toffee Clásico de Caramelo Salado con Mantequilla Avellanada y Sal de Colima | C2: Toffee aireado | D2: 550 | E2: 10 | F2: 55 | G2: 1.5 | H2: =SUMIF(Recetas!$A$2:$A$468,A2,Recetas!$I$2:$I$468) -> 69.335 | I2: =E2*Parámetros!$B$2 -> 90 | J2: =Parámetros!$B$3 -> 25 | K2: =G2*Parámetros!$B$4 -> 135 | L2: =Parámetros!$B$5 -> 30 | M2: =SUM(H2:L2) -> 349.335 | N2: =M2/(1-Parámetros!$B$6) -> 388.15 | O2: =N2/E2 -> 38.815 | P2: =O2/(1-Parámetros!$B$7) -> 97.0375 | Q2: =O2/(1-Parámetros!$B$8) -> 64.691667 | R2: =O2/(1-Parámetros!$B$9) -> 110.9 | S2: =P2-O2 -> 58.2225
A3: 2 | B3: Caramelo Dorado con Bourbon Añejo y Nueces Pecán Tostadas | C3: Toffee aireado | D3: 620 | E3: 10 | F3: 60 | G3: 1.5 | H3: =SUMIF(Recetas!$A$2:$A$468,A3,Recetas!$I$2:$I$468) -> 127.535 | I3: =E3*Parámetros!$B$2 -> 90 | J3: =Parámetros!$B$3 -> 25 | K3: =G3*Parámetros!$B$4 -> 135 | L3: =Parámetros!$B$5 -> 30 | M3: =SUM(H3:L3) -> 407.535 | N3: =M3/(1-Parámetros!$B$6) -> 452.81667 | O3: =N3/E3 -> 45.281667 | P3: =O3/(1-Parámetros!$B$7) -> 113.20417 | Q3: =O3/(1-Parámetros!$B$8) -> 75.469444 | R3: =O3/(1-Parámetros!$B$9) -> 129.37619 | S3: =P3-O3 -> 67.9225
A4: 3 | B4: Toffee de Maple Puro Grado A y Tocino Ahumado Crujiente | C4: Toffee aireado | D4: 580 | E4: 10 | F4: 58 | G4: 1.5 | H4: =SUMIF(Recetas!$A$2:$A$468,A4,Recetas!$I$2:$I$468) -> 155.14 | I4: =E4*Parámetros!$B$2 -> 90 | J4: =Parámetros!$B$3 -> 25 | K4: =G4*Parámetros!$B$4 -> 135 | L4: =Parámetros!$B$5 -> 30 | M4: =SUM(H4:L4) -> 435.14 | N4: =M4/(1-Parámetros!$B$6) -> 483.48889 | O4: =N4/E4 -> 48.348889 | P4: =O4/(1-Parámetros!$B$7) -> 120.87222 | Q4: =O4/(1-Parámetros!$B$8) -> 80.581481 | R4: =O4/(1-Parámetros!$B$9) -> 138.13968 | S4: =P4-O4 -> 72.523333
A5: 4 | B5: Caramelo al Cardamomo Verde y Café Arábica Tostado | C5: Toffee aireado | D5: 540 | E5: 10 | F5: 54 | G5: 1.5 | H5: =SUMIF(Recetas!$A$2:$A$468,A5,Recetas!$I$2:$I$468) -> 65.85 | I5: =E5*Parámetros!$B$2 -> 90 | J5: =Parámetros!$B$3 -> 25 | K5: =G5*Parámetros!$B$4 -> 135 | L5: =Parámetros!$B$5 -> 30 | M5: =SUM(H5:L5) -> 345.85 | N5: =M5/(1-Parámetros!$B$6) -> 384.27778 | O5: =N5/E5 -> 38.427778 | P5: =O5/(1-Parámetros!$B$7) -> 96.069444 | Q5: =O5/(1-Parámetros!$B$8) -> 64.046296 | R5: =O5/(1-Parámetros!$B$9) -> 109.79365 | S5: =P5-O5 -> 57.641667
A6: 5 | B6: Dulce de Leche y Sal Marina con Almendras Fileteadas | C6: Toffee aireado | D6: 590 | E6: 10 | F6: 59 | G6: 1.5 | H6: =SUMIF(Recetas!$A$2:$A$468,A6,Recetas!$I$2:$I$468) -> 88.75 | I6: =E6*Parámetros!$B$2 -> 90 | J6: =Parámetros!$B$3 -> 25 | K6: =G6*Parámetros!$B$4 -> 135 | L6: =Parámetros!$B$5 -> 30 | M6: =SUM(H6:L6) -> 368.75 | N6: =M6/(1-Parámetros!$B$6) -> 409.72222 | O6: =N6/E6 -> 40.972222 | P6: =O6/(1-Parámetros!$B$7) -> 102.43056 | Q6: =O6/(1-Parámetros!$B$8) -> 68.287037 | R6: =O6/(1-Parámetros!$B$9) -> 117.06349 | S6: =P6-O6 -> 61.458333
A7: 6 | B7: Mantequilla de Trufa Negra y Parmesano Reggiano de 24 Meses | C7: Nebulización / adhesión | D7: 270 | E7: 10 | F7: 27 | G7: 1 | H7: =SUMIF(Recetas!$A$2:$A$468,A7,Recetas!$I$2:$I$468) -> 110.7 | I7: =E7*Parámetros!$B$2 -> 90 | J7: =Parámetros!$B$3 -> 25 | K7: =G7*Parámetros!$B$4 -> 90 | L7: =Parámetros!$B$5 -> 30 | M7: =SUM(H7:L7) -> 345.7 | N7: =M7/(1-Parámetros!$B$6) -> 384.11111 | O7: =N7/E7 -> 38.411111 | P7: =O7/(1-Parámetros!$B$7) -> 96.027778 | Q7: =O7/(1-Parámetros!$B$8) -> 64.018519 | R7: =O7/(1-Parámetros!$B$9) -> 109.74603 | S7: =P7-O7 -> 57.616667
A8: 7 | B8: Mantequilla Morena (Beurre Noisette) con Romero Crispy y Sal en Escamas | C8: Nebulización / adhesión | D8: 240 | E8: 10 | F8: 24 | G8: 1 | H8: =SUMIF(Recetas!$A$2:$A$468,A8,Recetas!$I$2:$I$468) -> 47.124 | I8: =E8*Parámetros!$B$2 -> 90 | J8: =Parámetros!$B$3 -> 25 | K8: =G8*Parámetros!$B$4 -> 90 | L8: =Parámetros!$B$5 -> 30 | M8: =SUM(H8:L8) -> 282.124 | N8: =M8/(1-Parámetros!$B$6) -> 313.47111 | O8: =N8/E8 -> 31.347111 | P8: =O8/(1-Parámetros!$B$7) -> 78.367778 | Q8: =O8/(1-Parámetros!$B$8) -> 52.245185 | R8: =O8/(1-Parámetros!$B$9) -> 89.563175 | S8: =P8-O8 -> 47.020667
A9: 8 | B9: Caramelo Especiado Masala Chai con Vainilla Tahití | C9: Toffee aireado | D9: 560 | E9: 10 | F9: 56 | G9: 1.5 | H9: =SUMIF(Recetas!$A$2:$A$468,A9,Recetas!$I$2:$I$468) -> 112.19 | I9: =E9*Parámetros!$B$2 -> 90 | J9: =Parámetros!$B$3 -> 25 | K9: =G9*Parámetros!$B$4 -> 135 | L9: =Parámetros!$B$5 -> 30 | M9: =SUM(H9:L9) -> 392.19 | N9: =M9/(1-Parámetros!$B$6) -> 435.76667 | O9: =N9/E9 -> 43.576667 | P9: =O9/(1-Parámetros!$B$7) -> 108.94167 | Q9: =O9/(1-Parámetros!$B$8) -> 72.627778 | R9: =O9/(1-Parámetros!$B$9) -> 124.50476 | S9: =P9-O9 -> 65.365
A10: 9 | B10: Toffee Crunch de Melaza de Piloncillo y Ajonjolí Tostado al Comal | C10: Toffee aireado | D10: 580 | E10: 10 | F10: 58 | G10: 1.5 | H10: =SUMIF(Recetas!$A$2:$A$468,A10,Recetas!$I$2:$I$468) -> 59.94 | I10: =E10*Parámetros!$B$2 -> 90 | J10: =Parámetros!$B$3 -> 25 | K10: =G10*Parámetros!$B$4 -> 135 | L10: =Parámetros!$B$5 -> 30 | M10: =SUM(H10:L10) -> 339.94 | N10: =M10/(1-Parámetros!$B$6) -> 377.71111 | O10: =N10/E10 -> 37.771111 | P10: =O10/(1-Parámetros!$B$7) -> 94.427778 | Q10: =O10/(1-Parámetros!$B$8) -> 62.951852 | R10: =O10/(1-Parámetros!$B$9) -> 107.91746 | S10: =P10-O10 -> 56.656667
A11: 10 | B11: Caramelo de Maracuyá Ácido con Contraste de Sal Rosa del Himalaya | C11: Toffee aireado | D11: 540 | E11: 10 | F11: 54 | G11: 1.5 | H11: =SUMIF(Recetas!$A$2:$A$468,A11,Recetas!$I$2:$I$468) -> 63.31 | I11: =E11*Parámetros!$B$2 -> 90 | J11: =Parámetros!$B$3 -> 25 | K11: =G11*Parámetros!$B$4 -> 135 | L11: =Parámetros!$B$5 -> 30 | M11: =SUM(H11:L11) -> 343.31 | N11: =M11/(1-Parámetros!$B$6) -> 381.45556 | O11: =N11/E11 -> 38.145556 | P11: =O11/(1-Parámetros!$B$7) -> 95.363889 | Q11: =O11/(1-Parámetros!$B$8) -> 63.575926 | R11: =O11/(1-Parámetros!$B$9) -> 108.9873 | S11: =P11-O11 -> 57.218333
A12: 11 | B12: Chocolate Oscuro 70% con Nibs de Cacao y Flor de Sal Maldon | C12: Pre-sellado + chocolate | D12: 570 | E12: 10 | F12: 57 | G12: 2 | H12: =SUMIF(Recetas!$A$2:$A$468,A12,Recetas!$I$2:$I$468) -> 161.51 | I12: =E12*Parámetros!$B$2 -> 90 | J12: =Parámetros!$B$3 -> 25 | K12: =G12*Parámetros!$B$4 -> 180 | L12: =Parámetros!$B$5 -> 30 | M12: =SUM(H12:L12) -> 486.51 | N12: =M12/(1-Parámetros!$B$6) -> 540.56667 | O12: =N12/E12 -> 54.056667 | P12: =O12/(1-Parámetros!$B$7) -> 135.14167 | Q12: =O12/(1-Parámetros!$B$8) -> 90.094444 | R12: =O12/(1-Parámetros!$B$9) -> 154.44762 | S12: =P12-O12 -> 81.085
A13: 12 | B13: Chocolate Blanco, Frambuesa Liofilizada y Nuez de Macadamia | C13: Pre-sellado + chocolate | D13: 590 | E13: 10 | F13: 59 | G13: 2 | H13: =SUMIF(Recetas!$A$2:$A$468,A13,Recetas!$I$2:$I$468) -> 239.98 | I13: =E13*Parámetros!$B$2 -> 90 | J13: =Parámetros!$B$3 -> 25 | K13: =G13*Parámetros!$B$4 -> 180 | L13: =Parámetros!$B$5 -> 30 | M13: =SUM(H13:L13) -> 564.98 | N13: =M13/(1-Parámetros!$B$6) -> 627.75556 | O13: =N13/E13 -> 62.775556 | P13: =O13/(1-Parámetros!$B$7) -> 156.93889 | Q13: =O13/(1-Parámetros!$B$8) -> 104.62593 | R13: =O13/(1-Parámetros!$B$9) -> 179.35873 | S13: =P13-O13 -> 94.163333
... A52: 51 | B52: Tres Leches con Canela y Horchata de Arroz Concentrada | C52: Toffee aireado | D52: 580 | E52: 10 | F52: 58 | G52: 1.5 | H52: =SUMIF(Recetas!$A$2:$A$468,A52,Recetas!$I$2:$I$468) -> 71.432907 | I52: =E52*Parámetros!$B$2 -> 90 | J52: =Parámetros!$B$3 -> 25 | K52: =G52*Parámetros!$B$4 -> 135 | L52: =Parámetros!$B$5 -> 30 | M52: =SUM(H52:L52) -> 351.43291 | N52: =M52/(1-Parámetros!$B$6) -> 390.48101 | O52: =N52/E52 -> 39.048101 | P52: =O52/(1-Parámetros!$B$7) -> 97.620252 | Q52: =O52/(1-Parámetros!$B$8) -> 65.080168 | R52: =O52/(1-Parámetros!$B$9) -> 111.566 | S52: =P52-O52 -> 58.572151
B54: Promedio de las 51 recetas | H54: =AVERAGE(H2:H52) -> 116.44162 | M54: =AVERAGE(M2:M52) -> 396.44162 | N54: =AVERAGE(N2:N52) -> 440.49069 | O54: =AVERAGE(O2:O52) -> 44.049069 | P54: =AVERAGE(P2:P52) -> 110.12267 | Q54: =AVERAGE(Q2:Q52) -> 73.415115 | R54: =AVERAGE(R2:R52) -> 125.85448 | S54: =AVERAGE(S2:S52) -> 66.073603
B56: Todos los montos dependen de precios y parámetros ESTIMADOS. Sustitúyelos por los tuyos antes de publicar precios.

Sheet Parámetros
A1: Parámetro | B1: Valor | C1: Unidad | D1: Nota
A2: Empaque por porción (bolsa tricapa + desecante + etiqueta) | B2: 9 | C2: MXN / porción | D2: Estimado. Sustituye por tu costo real de empaque.
A3: Energía y consumibles por lote | B3: 25 | C3: MXN / lote | D3: Estimado: estufa + horno de secado + papel, guantes.
A4: Tarifa de mano de obra | B4: 90 | C4: MXN / hora | D4: Tu hora vale aunque produzcas tú. Estimado.
A5: Overhead prorrateado por lote | B5: 30 | C5: MXN / lote | D5: Renta, servicios, publicidad ÷ lotes al mes. Estimado.
A6: % de merma | B6: 0.1 | C6: % | D6: Principiante 15–25 %, intermedio 8–15 %, estandarizado 3–8 %.
A7: Margen · Menudeo (bolsa individual) | B7: 0.6 | C7: % sobre venta | D7: Sugerencia editable; decisión de cada negocio.
A8: Margen · Mayoreo / reventa | B8: 0.4 | C8: % sobre venta | D8: Sugerencia editable; decisión de cada negocio.
A9: Margen · Regalo corporativo / eventos | B9: 0.65 | C9: % sobre venta | D9: Sugerencia editable; decisión de cada negocio.

Sheet Catálogo
A1: ID | B1: Insumo | C1: Cantidad de compra | D1: Unidad | E1: Precio de compra (MXN) | F1: Costo por unidad (MXN) | G1: Nota
A2: MAIZ_M | B2: Maíz palomero Mushroom (costo por g reventado) | C2: 1000 | D2: g | E2: 110 | F2: =IF(C2=0,0,E2/C2) -> 0.11 | G2: Precio de referencia ESTIMADO — sustituir
A3: MAIZ_B | B3: Maíz palomero Butterfly (costo por g reventado) | C3: 1000 | D3: g | E3: 70 | F3: =IF(C3=0,0,E3/C3) -> 0.07 | G3: Precio de referencia ESTIMADO — sustituir
A4: PRESELL | B4: Palomitas pre-selladas (sellado base de la Receta 11) | C4: 1000 | D4: g | E4: 150 | F4: =IF(C4=0,0,E4/C4) -> 0.15 | G4: Precio de referencia ESTIMADO — sustituir
A5: MANTEQ | B5: Mantequilla sin sal (82–84 % M.G.) | C5: 1000 | D5: g | E5: 260 | F5: =IF(C5=0,0,E5/C5) -> 0.26 | G5: Precio de referencia ESTIMADO — sustituir
A6: GHEE | B6: Ghee / mantequilla clarificada | C6: 1000 | D6: g | E6: 420 | F6: =IF(C6=0,0,E6/C6) -> 0.42 | G6: Precio de referencia ESTIMADO — sustituir
A7: AZ_REF | B7: Azúcar refinada | C7: 1000 | D7: g | E7: 32 | F7: =IF(C7=0,0,E7/C7) -> 0.032 | G7: Precio de referencia ESTIMADO — sustituir
A8: AZ_GLAS | B8: Azúcar glas | C8: 1000 | D8: g | E8: 40 | F8: =IF(C8=0,0,E8/C8) -> 0.04 | G8: Precio de referencia ESTIMADO — sustituir
A9: AZ_MASC | B9: Azúcar mascabado | C9: 1000 | D9: g | E9: 45 | F9: =IF(C9=0,0,E9/C9) -> 0.045 | G9: Precio de referencia ESTIMADO — sustituir
A10: PILON | B10: Piloncillo | C10: 1000 | D10: g | E10: 45 | F10: =IF(C10=0,0,E10/C10) -> 0.045 | G10: Precio de referencia ESTIMADO — sustituir
A11: GLUC | B11: Jarabe de glucosa / jarabe de maíz | C11: 1000 | D11: g | E11: 70 | F11: =IF(C11=0,0,E11/C11) -> 0.07 | G11: Precio de referencia ESTIMADO — sustituir
A12: AGUA | B12: Agua purificada | C12: 1000 | D12: ml | E12: 2 | F12: =IF(C12=0,0,E12/C12) -> 0.002 | G12: Precio de referencia ESTIMADO — sustituir
A13: BICARB | B13: Bicarbonato de sodio | C13: 1000 | D13: g | E13: 60 | F13: =IF(C13=0,0,E13/C13) -> 0.06 | G13: Precio de referencia ESTIMADO — sustituir
... A140: INT | B140: (Preparación intermedia ya costeada en la misma receta) | C140: 1 | D140: g | E140: 0 | F140: =IF(C140=0,0,E140/C140) -> 0 | G140: Preparación intermedia: costo 0

Sheet Recetas
A1: Receta | B1: Nombre de la receta | C1: Componente | D1: Ingrediente (tal como aparece en la fórmula) | E1: ID insumo | F1: Cantidad | G1: Unidad | H1: Costo unitario | I1: Costo de la línea
A2: 1 | B2: Toffee Clásico de Caramelo Salado con Mantequilla Avellanada y Sal de Colima | C2: la Base | D2: 150 g Maíz palomero Mushroom reventado por aire caliente (sin aceite, tibio y sin granos sin abrir) | E2: MAIZ_M | F2: 150 | G2: g | H2: =IFERROR(INDEX(Catálogo!$F$2:$F$140,MATCH(E2,Catálogo!$A$2:$A$140,0)),0) -> 0.11 | I2: =F2*H2 -> 16.5
A3: 1 | B3: Toffee Clásico de Caramelo Salado con Mantequilla Avellanada y Sal de Colima | C3: el Toffee Avellanado | D3: 120 g Mantequilla sin sal de alta calidad (84% M.G.) | E3: MANTEQ | F3: 120 | G3: g | H3: =IFERROR(INDEX(Catálogo!$F$2:$F$140,MATCH(E3,Catálogo!$A$2:$A$140,0)),0) -> 0.26 | I3: =F3*H3 -> 31.2
A4: 1 | B4: Toffee Clásico de Caramelo Salado con Mantequilla Avellanada y Sal de Colima | C4: el Toffee Avellanado | D4: 180 g Azúcar mascabado claro | E4: AZ_MASC | F4: 180 | G4: g | H4: =IFERROR(INDEX(Catálogo!$F$2:$F$140,MATCH(E4,Catálogo!$A$2:$A$140,0)),0) -> 0.045 | I4: =F4*H4 -> 8.1
A5: 1 | B5: Toffee Clásico de Caramelo Salado con Mantequilla Avellanada y Sal de Colima | C5: el Toffee Avellanado | D5: 60 g Jarabe de glucosa o miel de maíz clara | E5: GLUC | F5: 60 | G5: g | H5: =IFERROR(INDEX(Catálogo!$F$2:$F$140,MATCH(E5,Catálogo!$A$2:$A$140,0)),0) -> 0.07 | I5: =F5*H5 -> 4.2
A6: 1 | B6: Toffee Clásico de Caramelo Salado con Mantequilla Avellanada y Sal de Colima | C6: el Toffee Avellanado | D6: 40 ml Agua purificada | E6: AGUA | F6: 40 | G6: ml | H6: =IFERROR(INDEX(Catálogo!$F$2:$F$140,MATCH(E6,Catálogo!$A$2:$A$140,0)),0) -> 0.002 | I6: =F6*H6 -> 0.08
A7: 1 | B7: Toffee Clásico de Caramelo Salado con Mantequilla Avellanada y Sal de Colima | C7: el Toffee Avellanado | D7: 4 g Bicarbonato de sodio tamizado (aerador y microcristalizador) | E7: BICARB | F7: 4 | G7: g | H7: =IFERROR(INDEX(Catálogo!$F$2:$F$140,MATCH(E7,Catálogo!$A$2:$A$140,0)),0) -> 0.06 | I7: =F7*H7 -> 0.24
A8: 1 | B8: Toffee Clásico de Caramelo Salado con Mantequilla Avellanada y Sal de Colima | C8: el Toffee Avellanado | D8: 3 g Sal marina fina | E8: SAL_FINA | F8: 3 | G8: g | H8: =IFERROR(INDEX(Catálogo!$F$2:$F$140,MATCH(E8,Catálogo!$A$2:$A$140,0)),0) -> 0.025 | I8: =F8*H8 -> 0.075
A9: 1 | B9: Toffee Clásico de Caramelo Salado con Mantequilla Avellanada y Sal de Colima | C9: el Toffee Avellanado | D9: 5 ml Extracto concentrado de vainilla Bourbon | E9: VAIN_EXT | F9: 5 | G9: ml | H9: =IFERROR(INDEX(Catálogo!$F$2:$F$140,MATCH(E9,Catálogo!$A$2:$A$140,0)),0) -> 1.5 | I9: =F9*H9 -> 7.5
A10: 1 | B10: Toffee Clásico de Caramelo Salado con Mantequilla Avellanada y Sal de Colima | C10: el Acabado Salino | D10: 6 g Flor de sal de Colima en grano medio | E10: FLOR_SAL | F10: 6 | G10: g | H10: =IFERROR(INDEX(Catálogo!$F$2:$F$140,MATCH(E10,Catálogo!$A$2:$A$140,0)),0) -> 0.24 | I10: =F10*H10 -> 1.44
A11: 2 | B11: Caramelo Dorado con Bourbon Añejo y Nueces Pecán Tostadas | C11: la Base e Inclusiones | D11: 140 g Maíz palomero Mushroom reventado | E11: MAIZ_M | F11: 140 | G11: g | H11: =IFERROR(INDEX(Catálogo!$F$2:$F$140,MATCH(E11,Catálogo!$A$2:$A$140,0)),0) -> 0.11 | I11: =F11*H11 -> 15.4
A12: 2 | B12: Caramelo Dorado con Bourbon Añejo y Nueces Pecán Tostadas | C12: la Base e Inclusiones | D12: 120 g Nueces pecán seleccionadas (tostadas a 150°C por 10 min y templadas) | E12: PECAN | F12: 120 | G12: g | H12: =IFERROR(INDEX(Catálogo!$F$2:$F$140,MATCH(E12,Catálogo!$A$2:$A$140,0)),0) -> 0.38 | I12: =F12*H12 -> 45.6
A13: 2 | B13: Caramelo Dorado con Bourbon Añejo y Nueces Pecán Tostadas | C13: el Caramelo al Bourbon | D13: 110 g Mantequilla sin sal a 18°C | E13: MANTEQ | F13: 110 | G13: g | H13: =IFERROR(INDEX(Catálogo!$F$2:$F$140,MATCH(E13,Catálogo!$A$2:$A$140,0)),0) -> 0.26 | I13: =F13*H13 -> 28.6
... A468: 51 | B468: Tres Leches con Canela y Horchata de Arroz Concentrada | C468: el Rebozado Aterciopelado Exterior | D468: 2 g Flor de sal marina fina | E468: FLOR_SAL | F468: 2 | G468: g | H468: =IFERROR(INDEX(Catálogo!$F$2:$F$140,MATCH(E468,Catálogo!$A$2:$A$140,0)),0) -> 0.24 | I468: =F468*H468 -> 0.48
